Workbook
Name Beg_Bal: #REF!
Name Beg_Bal: #REF!
Name Cum_Int: #REF!
Name Data: #REF!
Name DisbursementType: #REF!
Name DisbursementType: #REF!
Name End_Bal: #REF!
Name End_Bal: #REF!
Name EXPENSES: #REF!
Name EXPENSES: #REF!
Name Extra_Pay: #REF!
Name Extra_Pay: #REF!
Name Full_Print: #REF!
Name Full_Print: #REF!
Name Header_Row: ROW(#REF!)
Name Header_Row: ROW(#REF!)
Name Int: #REF!
Name Int: #REF!
Name Interest_Rate: #REF!
Name Interest_Rate: #REF!
Name Last_Row: IF('504-Hybrid'!Values_Entered,Header_Row+'504-Hybrid'!Number_of_Payments,Header_Row)
Name Last_Row: IF(Scores!Values_Entered,Scores!Header_Row+Scores!Number_of_Payments,Scores!Header_Row)
Name Last_Row: IF(Values_Entered,Header_Row+Number_of_Payments,Header_Row)
Name Loan_Amount: #REF!
Name Loan_Amount: #REF!
Name Loan_Start: #REF!
Name Loan_Start: #REF!
Name Loan_Years: #REF!
Name Loan_Years: #REF!
Name MajorExpensesList: #REF!
Name MajorExpensesList: #REF!
Name Num_Pmt_Per_Year: #REF!
Name Num_Pmt_Per_Year: #REF!
Name Number_of_Payments: MATCH(0.01,End_Bal,-1)+1
Name Number_of_Payments: MATCH(0.01,Scores!End_Bal,-1)+1
Name Number_of_Payments: MATCH(0.01,End_Bal,-1)+1
Name Pay_Date: #REF!
Name Pay_Num: #REF!
Name Pay_Num: #REF!
Name Payment_Date: DATE(YEAR(Scores!Loan_Start),MONTH(Scores!Loan_Start)+Payment_Number,DAY(Scores!Loan_Start))
Name Payment_Date: DATE(YEAR(Loan_Start),MONTH(Loan_Start)+Payment_Number,DAY(Loan_Start))
Name Periodic_rate: Annual_interest_rate/Payments_per_year
Name Periodic_rate: Annual_interest_rate/Payments_per_year
Name Periodic_rate: Annual_interest_rate/Payments_per_year
Name Princ: #REF!
Name Princ: #REF!
Name Print_Area_Reset: OFFSET(Full_Print,0,0,[0]!Last_Row)
Name Print_Area_Reset: OFFSET(Scores!Full_Print,0,0,Scores!Last_Row)
Name Print_Area_Reset: OFFSET(Full_Print,0,0,Last_Row)
Name Sched_Pay: #REF!
Name Sched_Pay: #REF!
Name Scheduled_Extra_Payments: #REF!
Name Scheduled_Extra_Payments: #REF!
Name Scheduled_Interest_Rate: #REF!
Name Scheduled_Monthly_Payment: #REF!
Name Scheduled_Monthly_Payment: #REF!
Name Total_Interest: #REF!
Name Total_Pay: #REF!
Name Total_Pay: #REF!
Name Total_Payment: Scheduled_Payment+Extra_Payment

Sheet Financial Spreads
B1: Financing Structure
C2: ='BDO Prequal'!C31 -> T Bank Loan | D2: ='BDO Prequal'!D31 -> T Bank Loan | E2: ='BDO Prequal'!E31 -> CDC Debenture | F2: ='BDO Prequal'!F31 -> T Bank Loan | G2: ='BDO Prequal'!G31 -> T Bank Loan | H2: ='BDO Prequal'!H31 -> Equity | I2: ='BDO Prequal'!I31 -> Seller Note | J2: ='BDO Prequal'!J31 -> 3rd Party
B3: Financing Source | C3: =IF('BDO Prequal'!C32=0,"", 'BDO Prequal'!C32) -> P&E | D3: =IF('BDO Prequal'!D32=0,"", 'BDO Prequal'!D32) -> USDA | E3: =IF('BDO Prequal'!E32=0,"", 'BDO Prequal'!E32) -> Conventional | F3: =IF('BDO Prequal'!F32=0,"", 'BDO Prequal'!F32) -> 7A Express | G3: =IF('BDO Prequal'!G32=0,"", 'BDO Prequal'!G32) -> CAPLine | H3: ='BDO Prequal'!H31 -> Equity | I3: ='BDO Prequal'!I31 -> Seller Note | J3: ='BDO Prequal'!J31 -> 3rd Party
B4: Guarantee % | C4: 0.75 | D4: 0 | E4: 0.5 | F4: 0.24 | G4: 0.6 | H4: 0.54 | I4: 0.02 | J4: 0.03
B5: Amount | C5: ='BDO Prequal'!C33 -> 1000 | D5: ='BDO Prequal'!D33 -> 20000 | E5: ='BDO Prequal'!E33 -> 30000 | F5: ='BDO Prequal'!F33 -> 4 | G5: ='BDO Prequal'!G33 -> 5 | H5: ='BDO Prequal'!H33 -> 6 | I5: ='BDO Prequal'!I33 -> 7 | J5: ='BDO Prequal'!J33 -> 8
B6: Rate Type | C6: Variable | D6: Variable | E6: Fixed | F6: Fixed | G6: Fixed | H6: Fixed | I6: Fixed | J6: N/A
B7: Term Yrs | C7: ='BDO Prequal'!C38 -> 10 | D7: ='BDO Prequal'!D38 -> 10 | E7: ='BDO Prequal'!E38 -> 10 | F7: ='BDO Prequal'!F38 -> 10 | G7: ='BDO Prequal'!G38 -> 0 | H7: ='BDO Prequal'!H38 -> 0 | I7: ='BDO Prequal'!I38 -> 10 | J7: ='BDO Prequal'!J38 -> 25
B8: Amortization (Months) | C8: ='BDO Prequal'!C39 -> 120 | D8: ='BDO Prequal'!D39 -> 120 | E8: ='BDO Prequal'!E39 -> 120 | F8: ='BDO Prequal'!F39 -> 120 | G8: ='BDO Prequal'!G39 -> 0 | H8: ='BDO Prequal'!H39 -> 0 | I8: ='BDO Prequal'!I39 -> 120 | J8: ='BDO Prequal'!J39 -> 300
B9: Base Rate | C9: ='BDO Prequal'!C34 -> 0.075 | D9: ='BDO Prequal'!D34 -> 0.075 | E9: ='BDO Prequal'!E34 -> 0.075 | F9: ='BDO Prequal'!F34 -> 0.075 | G9: ='BDO Prequal'!G34 -> 0 | H9: ='BDO Prequal'!H34 -> 0 | I9: ='BDO Prequal'!I34 -> 0.08 | J9: ='BDO Prequal'!J34 -> 0.0624
B10: Spread | C10: ='BDO Prequal'!C35 -> 0.015 | D10: ='BDO Prequal'!D35 -> 0.015 | E10: ='BDO Prequal'!E35 -> 0.015 | F10: ='BDO Prequal'!F35 -> 0.015 | G10: ='BDO Prequal'!G35 -> 0 | H10: ='BDO Prequal'!H35 -> 0 | I10: ='BDO Prequal'!I35 -> 0 | J10: ='BDO Prequal'!J35 -> 0
B11: Total Rate | C11: =C9+C10 -> 0.09 | D11: =D9+D10 -> 0.09 | E11: =E9+E10 -> 0.09 | F11: =F9+F10 -> 0.09 | G11: =G9+G10 -> 0 | H11: =H9+H10 -> 0 | I11: =I9+I10 -> 0.08 | J11: =J9+J10 -> 0.0624
B13: Sources and Uses of Proceeds
C14: ='BDO Prequal'!C47 -> P&E | D14: ='BDO Prequal'!D47 -> USDA | E14: ='BDO Prequal'!E47 -> Conventional | F14: ='BDO Prequal'!F47 -> 7A Express | G14: ='BDO Prequal'!G47 -> CAPLine | H14: ='BDO Prequal'!H47 -> Equity | I14: ='BDO Prequal'!I47 -> Seller Note | J14: ='BDO Prequal'!J47 -> 3rd Party | K14: ='BDO Prequal'!K47 -> Total
B15: Real Estate Acquisition | C15: ='BDO Prequal'!C49 -> 896000 | D15: ='BDO Prequal'!D49 -> 896000 | E15: ='BDO Prequal'!E49 -> 896000 | F15: ='BDO Prequal'!F49 -> 896000 | G15: ='BDO Prequal'!G49 -> 896000 | H15: ='BDO Prequal'!H49 -> 8000 | I15: ='BDO Prequal'!I49 -> 80000 | J15: ='BDO Prequal'!J49 -> 16000 | K15: ='BDO Prequal'!K49 -> 1000000
B16: Debt Refi - CRE | C16: ='BDO Prequal'!C50 -> 5387 | D16: ='BDO Prequal'!D50 -> 5387 | E16: ='BDO Prequal'!E50 -> 5387 | F16: ='BDO Prequal'!F50 -> 5387 | G16: ='BDO Prequal'!G50 -> 5387 | H16: ='BDO Prequal'!H50 -> 10 | I16: ='BDO Prequal'!I50 -> 1 | J16: ='BDO Prequal'!J50 -> 2 | K16: ='BDO Prequal'!K50 -> 5400
B17: Debt Refi - Non-CRE | C17: ='BDO Prequal'!C51 -> 55987 | D17: ='BDO Prequal'!D51 -> 55987 | E17: ='BDO Prequal'!E51 -> 55987 | F17: ='BDO Prequal'!F51 -> 55987 | G17: ='BDO Prequal'!G51 -> 55987 | H17: ='BDO Prequal'!H51 -> 10 | I17: ='BDO Prequal'!I51 -> 1 | J17: ='BDO Prequal'!J51 -> 2 | K17: ='BDO Prequal'!K51 -> 56000
B18: Machinery & Equipment | C18: ='BDO Prequal'!C52 -> 4499 | D18: ='BDO Prequal'!D52 -> 4499 | E18: ='BDO Prequal'!E52 -> 4499 | F18: ='BDO Prequal'!F52 -> 4499 | G18: ='BDO Prequal'!G52 -> 4499 | H18: ='BDO Prequal'!H52 -> 10 | I18: ='BDO Prequal'!I52 -> 1 | J18: ='BDO Prequal'!J52 -> 2 | K18: ='BDO Prequal'!K52 -> 4512
B19: Furniture & Fixtures (TIs) | C19: ='BDO Prequal'!C53 -> 2499 | D19: ='BDO Prequal'!D53 -> 2499 | E19: ='BDO Prequal'!E53 -> 2499 | F19: ='BDO Prequal'!F53 -> 2499 | G19: ='BDO Prequal'!G53 -> 2499 | H19: ='BDO Prequal'!H53 -> 10 | I19: ='BDO Prequal'!I53 -> 1 | J19: ='BDO Prequal'!J53 -> 2 | K19: ='BDO Prequal'!K53 -> 2512
B20: Inventory | C20: ='BDO Prequal'!C54 -> 4202 | D20: ='BDO Prequal'!D54 -> 4202 | E20: ='BDO Prequal'!E54 -> 4202 | F20: ='BDO Prequal'!F54 -> 4202 | G20: ='BDO Prequal'!G54 -> 4202 | H20: ='BDO Prequal'!H54 -> 10 | I20: ='BDO Prequal'!I54 -> 1 | J20: ='BDO Prequal'!J54 -> 2 | K20: ='BDO Prequal'!K54 -> 4215
B21: Working Capital | C21: ='BDO Prequal'!C55 -> 84348 | D21: ='BDO Prequal'!D55 -> 84348 | E21: ='BDO Prequal'!E55 -> 84348 | F21: ='BDO Prequal'!F55 -> 84348 | G21: ='BDO Prequal'!G55 -> 84348 | H21: ='BDO Prequal'!H55 -> 10 | I21: ='BDO Prequal'!I55 -> 1 | J21: ='BDO Prequal'!J55 -> 2 | K21: ='BDO Prequal'!K55 -> 84361
B22: Working Capital - Pre Opening | C22: ='BDO Prequal'!C56 -> 58397 | D22: ='BDO Prequal'!D56 -> 58397 | E22: ='BDO Prequal'!E56 -> 58397 | F22: ='BDO Prequal'!F56 -> 58397 | G22: ='BDO Prequal'!G56 -> 58397 | H22: ='BDO Prequal'!H56 -> 10 | I22: ='BDO Prequal'!I56 -> 1 | J22: ='BDO Prequal'!J56 -> 2 | K22: ='BDO Prequal'!K56 -> 58410
B23: Business Acquisition | C23: ='BDO Prequal'!C57 -> 2919 | D23: ='BDO Prequal'!D57 -> 2919 | E23: ='BDO Prequal'!E57 -> 2919 | F23: ='BDO Prequal'!F57 -> 2919 | G23: ='BDO Prequal'!G57 -> 2919 | H23: ='BDO Prequal'!H57 -> 10 | I23: ='BDO Prequal'!I57 -> 1 | J23: ='BDO Prequal'!J57 -> 2 | K23: ='BDO Prequal'!K57 -> 2932
B24: Franchise Fees | C24: ='BDO Prequal'!C58 -> 3593 | D24: ='BDO Prequal'!D58 -> 3593 | E24: ='BDO Prequal'!E58 -> 3593 | F24: ='BDO Prequal'!F58 -> 3593 | G24: ='BDO Prequal'!G58 -> 3593 | H24: ='BDO Prequal'!H58 -> 10 | I24: ='BDO Prequal'!I58 -> 1 | J24: ='BDO Prequal'!J58 -> 2 | K24: ='BDO Prequal'!K58 -> 3606
B25: Construction Hard Costs | C25: ='BDO Prequal'!C59 -> 45097 | D25: ='BDO Prequal'!D59 -> 45097 | E25: ='BDO Prequal'!E59 -> 45097 | F25: ='BDO Prequal'!F59 -> 45097 | G25: ='BDO Prequal'!G59 -> 45097 | H25: ='BDO Prequal'!H59 -> 10 | I25: ='BDO Prequal'!I59 -> 1 | J25: ='BDO Prequal'!J59 -> 2 | K25: ='BDO Prequal'!K59 -> 45110
B26: Interim Interest Reserve | C26: ='BDO Prequal'!C60 -> 8000 | D26: ='BDO Prequal'!D60 -> 200 | E26: ='BDO Prequal'!E60 -> 2230 | F26: ='BDO Prequal'!F60 -> 2000 | G26: ='BDO Prequal'!G60 -> 0 | H26: ='BDO Prequal'!H60 -> 373817 | I26: ='BDO Prequal'!I60 -> 8000 | J26: ='BDO Prequal'!J60 -> 800 | K26: ='BDO Prequal'!K60 -> 381817
... B31: Total | C31: ='BDO Prequal'!C65 -> -115502 | D31: ='BDO Prequal'!D65 -> -128272 | E31: ='BDO Prequal'!E65 -> -125522 | F31: ='BDO Prequal'!F65 -> -126472 | G31: ='BDO Prequal'!G65 -> -128552 | H31: ='BDO Prequal'!H65 -> 1336917 | I31: ='BDO Prequal'!I65 -> 257182 | J31: ='BDO Prequal'!J65 -> 214570 | K31: ='BDO Prequal'!K65 -> 1684367
B32: Percentage of Project | C32: ='BDO Prequal'!C66 -> -0.068572942 | D32: ='BDO Prequal'!D66 -> -0.076154425 | E32: ='BDO Prequal'!G66 -> -0.076320659 | F32: ='BDO Prequal'!H66 -> 0.79372073 | G32: ='BDO Prequal'!I66 -> 0.15268763 | H32: ='BDO Prequal'!H66 -> 0.79372073 | I32: ='BDO Prequal'!I66 -> 0.15268763 | J32: ='BDO Prequal'!J66 -> 0.1273891 | K32: ='BDO Prequal'!K66 -> 1
B34: Income Statement Spreads
C35: Period 1 | D35: Period 2 | E35: Period 3 | F35: Period 4
B36: Statement Date | C36: ='BDO Prequal'!D85 -> 44926 | D36: ='BDO Prequal'!F85 -> 45291 | E36: ='BDO Prequal'!H85 -> 45657 | F36: ='BDO Prequal'!J85 -> 45747
B37: Months Covered | C37: ='BDO Prequal'!D86 -> 12 | D37: ='BDO Prequal'!F86 -> 12 | E37: ='BDO Prequal'!H86 -> 12 | F37: ='BDO Prequal'!J86 -> 3
B38: Statement Type (Tax Returns / Internal) | C38: =IF(OR('BDO Prequal'!D87="",'BDO Prequal'!D87=0),"",'BDO Prequal'!D87) -> Tax Returns | D38: =IF(OR('BDO Prequal'!F87="",'BDO Prequal'!F87=0),"",'BDO Prequal'!F87) -> Tax Returns | E38: =IF(OR('BDO Prequal'!H87="",'BDO Prequal'!H87=0),"",'BDO Prequal'!H87) -> Form 10K | F38: =IF(OR('BDO Prequal'!J87="",'BDO Prequal'!J87=0),"",'BDO Prequal'!J87) -> Internal
B39: Revenue Recognition (Cash / Accrual) | C39: =IF(OR('BDO Prequal'!D88="",'BDO Prequal'!D88=0),"",'BDO Prequal'!D88) -> Accrual | D39: =IF(OR('BDO Prequal'!F88="",'BDO Prequal'!F88=0),"",'BDO Prequal'!F88) -> Accrual | E39: =IF(OR('BDO Prequal'!H88="",'BDO Prequal'!H88=0),"",'BDO Prequal'!H88) -> Cash | F39: =IF(OR('BDO Prequal'!J88="",'BDO Prequal'!J88=0),"",'BDO Prequal'!J88) -> Cash
B40: GROSS INCOME
B41: Total Revenue | C41: ='BDO Prequal'!D99 -> 9000 | D41: ='BDO Prequal'!F99 -> 2166 | E41: ='BDO Prequal'!H99 -> 1145 | F41: ='BDO Prequal'!J99 -> 880
B42: Total COGS | C42: ='BDO Prequal'!D100 -> 50 | D42: ='BDO Prequal'!F100 -> 500 | E42: ='BDO Prequal'!H100 -> 400 | F42: ='BDO Prequal'!J100 -> 8000
B43: Total Gross Margin | C43: ='BDO Prequal'!D101 -> 8950 | D43: ='BDO Prequal'!F101 -> 1666 | E43: ='BDO Prequal'!H101 -> 745 | F43: ='BDO Prequal'!J101 -> -7120
B44: NET INCOME
B45: Total Operating Expenses | C45: ='BDO Prequal'!D128 -> 800 | D45: ='BDO Prequal'!F128 -> 800 | E45: ='BDO Prequal'!H128 -> 500 | F45: ='BDO Prequal'!J128 -> 5000
B46: Ordinary Income | C46: ='BDO Prequal'!D130 -> 8150 | D46: ='BDO Prequal'!F130 -> 866 | E46: ='BDO Prequal'!H130 -> 245 | F46: ='BDO Prequal'!G130 -> 0.39981533
B47: Total Other Income/Expenses | C47: ='BDO Prequal'!D136 -> 5050 | D47: ='BDO Prequal'!F136 -> 6050 | E47: ='BDO Prequal'!H136 -> 8600 | F47: ='BDO Prequal'!G136 -> 2.7931671
B48: Net Income Before Taxes | C48: ='BDO Prequal'!D138 -> 13200 | D48: ='BDO Prequal'!F138 -> 6916 | E48: ='BDO Prequal'!H138 -> 8845 | F48: ='BDO Prequal'!G138 -> 3.1929825
B49: ADD BACKS & ADJUSTMENTS
B50: Standard Add Backs | C50: ='BDO Prequal'!D144+'BDO Prequal'!D145+'BDO Prequal'!D146+'BDO Prequal'!D147 -> 9000 | D50: ='BDO Prequal'!F144+'BDO Prequal'!F145+'BDO Prequal'!F146+'BDO Prequal'!F147 -> 4562 | E50: ='BDO Prequal'!H144+'BDO Prequal'!H145+'BDO Prequal'!H146+'BDO Prequal'!H147 -> 461 | F50: ='BDO Prequal'!J144+'BDO Prequal'!J145+'BDO Prequal'!J146+'BDO Prequal'!J147 -> 621
B51: Other Add Back 1 | C51: ='BDO Prequal'!D148 -> 45 | D51: ='BDO Prequal'!F148 -> 46 | E51: ='BDO Prequal'!H148 -> 10 | F51: ='BDO Prequal'!J148 -> 11
B52: Other Add Back 2 | C52: ='BDO Prequal'!D149 -> 21 | D52: ='BDO Prequal'!F149 -> 21 | E52: ='BDO Prequal'!H149 -> 22 | F52: ='BDO Prequal'!J149 -> 23
B53: Other Add Back 3 | C53: ='BDO Prequal'!D150 -> 0 | D53: ='BDO Prequal'!F150 -> 0 | E53: ='BDO Prequal'!H150 -> 0 | F53: ='BDO Prequal'!J150 -> 0
B54: Other Add Back 4
B55: Other Add Back 5
B56: DEBT COVERAGE
B57: Cash Available | C57: ='BDO Prequal'!D153 -> 23165 | D57: ='BDO Prequal'!F153 -> 12543 | E57: ='BDO Prequal'!H153 -> 9405 | F57: ='BDO Prequal'!J153 -> -1663
B58: Existing Debt Service | C58: ='BDO Prequal'!D155 -> 600 | D58: ='BDO Prequal'!F155 -> 700 | E58: ='BDO Prequal'!H155 -> 8000 | F58: ='BDO Prequal'!J155 -> 600
B59: Proposed 7a Debt | C59: ='BDO Prequal'!D156 -> 152.05897 | D59: ='BDO Prequal'!F156 -> 152.05897 | E59: ='BDO Prequal'!H156 -> 152.05897 | F59: ='BDO Prequal'!J156 -> 38.014743
B60: Proposed 504 Debt
B61: Proposed CDC Debt
B62: Proposed Seller Note | C62: ='BDO Prequal'!D159 -> 37443.928 | D62: ='BDO Prequal'!F159 -> 37443.928 | E62: ='BDO Prequal'!H159 -> 37443.928 | F62: ='BDO Prequal'!J159 -> 9360.982
B63: Proposed 3rd Party Financing | C63: ='BDO Prequal'!D160 -> 100 | D63: ='BDO Prequal'!F160 -> 200 | E63: ='BDO Prequal'!H160 -> 1400 | F63: ='BDO Prequal'!J160 -> 3000
B64: Total Debt Service | C64: ='BDO Prequal'!D161 -> 38295.987 | D64: ='BDO Prequal'!F161 -> 38495.987 | E64: ='BDO Prequal'!H161 -> 46995.987 | F64: ='BDO Prequal'!J161 -> 12998.997
B65: Debt Coverage Ratio | C65: ='BDO Prequal'!D163 -> 0.60489367 | D65: ='BDO Prequal'!F163 -> 0.32582617 | E65: ='BDO Prequal'!H163 -> 0.20012347 | F65: ='BDO Prequal'!J163 -> -0.12793295
B66: GLOBAL DEBT COVERAGE
B67: Total Affiliate Cash Available | C67: ='BDO Prequal'!D194 -> 27896 | D67: ='BDO Prequal'!F194 -> 17543 | E67: ='BDO Prequal'!H194 -> 11335 | F67: ='BDO Prequal'!J194 -> 18581
B68: Total Subject Business Cash Available | C68: ='BDO Prequal'!D171 -> 22265 | D68: ='BDO Prequal'!F171 -> 11543 | E68: ='BDO Prequal'!H171 -> 9335 | F68: ='BDO Prequal'!J171 -> -1670
B69: Total Global Cash Available | C69: =C67+C68 -> 50161 | D69: =D67+D68 -> 29086 | E69: =E67+E68 -> 20670 | F69: =F67+F68 -> 16911
B70: Total Affiliate Debt Service | C70: ='BDO Prequal'!D195 -> 52408.987 | D70: ='BDO Prequal'!F195 -> 43495.987 | E70: ='BDO Prequal'!H195 -> 47045.987 | F70: ='BDO Prequal'!J195 -> 13118.997
B71: Total Subject Business Debt Service | C71: ='BDO Prequal'!D172 -> 38295.987 | D71: ='BDO Prequal'!F172 -> 38495.987 | E71: ='BDO Prequal'!H172 -> 46995.987 | F71: ='BDO Prequal'!J172 -> 12998.997
B72: Total Global Debt Service | C72: =C70+C71 -> 90704.974 | D72: =D70+D71 -> 81991.974 | E72: =E70+E71 -> 94041.974 | F72: =F70+F71 -> 26117.994
B73: Global Debt Coverage Ratio | C73: =C69/C72 -> 0.55301267 | D73: =D69/D72 -> 0.35474204 | E73: =E69/E72 -> 0.21979547 | F73: =F69/F72 -> 0.64748465

Sheet Summary
B2: Loan ID
B4: Financing Structure
B5: Terms | C5: Source 1 | D5: Source 2 | E5: Source 3 | F5: Source 4 | G5: Source 5 | H5: Source 6 | I5: Source 7 | J5: Source 8
B6: Financing Type | C6: ='BDO Prequal'!C31 -> T Bank Loan | D6: ='BDO Prequal'!D31 -> T Bank Loan | E6: ='BDO Prequal'!E31 -> CDC Debenture | F6: ='BDO Prequal'!F31 -> T Bank Loan | G6: ='BDO Prequal'!G31 -> T Bank Loan | H6: ='BDO Prequal'!H31 -> Equity | I6: ='BDO Prequal'!I31 -> Seller Note | J6: ='BDO Prequal'!J31 -> 3rd Party
B7: SBA Product Type | C7: =IF('BDO Prequal'!C32=0,"", 'BDO Prequal'!C32) -> P&E | D7: =IF('BDO Prequal'!D32=0,"", 'BDO Prequal'!D32) -> USDA | E7: =IF('BDO Prequal'!E32=0,"", 'BDO Prequal'!E32) -> Conventional | F7: =IF('BDO Prequal'!F32=0,"", 'BDO Prequal'!F32) -> 7A Express | G7: =IF('BDO Prequal'!G32=0,"", 'BDO Prequal'!G32) -> CAPLine | H7: ='BDO Prequal'!H31 -> Equity | I7: ='BDO Prequal'!I31 -> Seller Note | J7: ='BDO Prequal'!J31 -> 3rd Party
B8: Guarantee % | C8: 0.75
B9: Amount | C9: ='BDO Prequal'!C33 -> 1000 | D9: ='BDO Prequal'!D33 -> 20000 | E9: ='BDO Prequal'!E33 -> 30000 | F9: ='BDO Prequal'!F33 -> 4 | G9: ='BDO Prequal'!G33 -> 5 | H9: ='BDO Prequal'!H33 -> 6 | I9: ='BDO Prequal'!I33 -> 7 | J9: ='BDO Prequal'!J33 -> 8
B10: Rate Type | C10: Variable
B11: Term Yrs | C11: ='BDO Prequal'!C38 -> 10 | D11: ='BDO Prequal'!D38 -> 10 | E11: ='BDO Prequal'!E38 -> 10 | F11: ='BDO Prequal'!F38 -> 10 | G11: ='BDO Prequal'!G38 -> 0 | H11: ='BDO Prequal'!H38 -> 0 | I11: ='BDO Prequal'!I38 -> 10 | J11: ='BDO Prequal'!J38 -> 25
B12: Amortization (Months) | C12: ='BDO Prequal'!C39 -> 120 | D12: ='BDO Prequal'!D39 -> 120 | E12: ='BDO Prequal'!E39 -> 120 | F12: ='BDO Prequal'!F39 -> 120 | G12: ='BDO Prequal'!G39 -> 0 | H12: ='BDO Prequal'!H39 -> 0 | I12: ='BDO Prequal'!I39 -> 120 | J12: ='BDO Prequal'!J39 -> 300
B13: Base Rate | C13: ='BDO Prequal'!C34 -> 0.075 | D13: ='BDO Prequal'!D34 -> 0.075 | E13: ='BDO Prequal'!E34 -> 0.075 | F13: ='BDO Prequal'!F34 -> 0.075 | G13: ='BDO Prequal'!G34 -> 0 | H13: ='BDO Prequal'!H34 -> 0 | I13: ='BDO Prequal'!I34 -> 0.08 | J13: ='BDO Prequal'!J34 -> 0.0624
B14: Spread | C14: ='BDO Prequal'!C35 -> 0.015 | D14: ='BDO Prequal'!D35 -> 0.015 | E14: ='BDO Prequal'!E35 -> 0.015 | F14: ='BDO Prequal'!F35 -> 0.015 | G14: ='BDO Prequal'!G35 -> 0 | H14: ='BDO Prequal'!H35 -> 0 | I14: ='BDO Prequal'!I35 -> 0 | J14: ='BDO Prequal'!J35 -> 0
B15: Total Rate | C15: =C13+C14 -> 0.09 | D15: =D13+D14 -> 0.09 | E15: =E13+E14 -> 0.09 | F15: =F13+F14 -> 0.09 | G15: =G13+G14 -> 0 | H15: =H13+H14 -> 0 | I15: =I13+I14 -> 0.08 | J15: =J13+J14 -> 0.0624
B18: Sources and Uses of Proceeds
B19: Direct Project Costs | C19: ='BDO Prequal'!C47 -> P&E | D19: ='BDO Prequal'!D47 -> USDA | E19: ='BDO Prequal'!E47 -> Conventional | F19: ='BDO Prequal'!F47 -> 7A Express | G19: ='BDO Prequal'!G47 -> CAPLine | H19: ='BDO Prequal'!H47 -> Equity | I19: ='BDO Prequal'!I47 -> Seller Note | J19: ='BDO Prequal'!J47 -> 3rd Party | K19: ='BDO Prequal'!K47 -> Total
B20: Real Estate Acquisition | C20: ='BDO Prequal'!C49 -> 896000 | D20: ='BDO Prequal'!D49 -> 896000 | E20: ='BDO Prequal'!E49 -> 896000 | F20: ='BDO Prequal'!F49 -> 896000 | G20: ='BDO Prequal'!G49 -> 896000 | H20: ='BDO Prequal'!H49 -> 8000 | I20: ='BDO Prequal'!I49 -> 80000 | J20: ='BDO Prequal'!J49 -> 16000 | K20: =SUM(C20:J20) -> 4584000
B21: Debt Refi - CRE | C21: ='BDO Prequal'!C50 -> 5387 | D21: ='BDO Prequal'!D50 -> 5387 | E21: ='BDO Prequal'!E50 -> 5387 | F21: ='BDO Prequal'!F50 -> 5387 | G21: ='BDO Prequal'!G50 -> 5387 | H21: ='BDO Prequal'!H50 -> 10 | I21: ='BDO Prequal'!I50 -> 1 | J21: ='BDO Prequal'!J50 -> 2 | K21: =SUM(C21:J21) -> 26948
B22: Debt Refi - Non-CRE | C22: ='BDO Prequal'!C51 -> 55987 | D22: ='BDO Prequal'!D51 -> 55987 | E22: ='BDO Prequal'!E51 -> 55987 | F22: ='BDO Prequal'!F51 -> 55987 | G22: ='BDO Prequal'!G51 -> 55987 | H22: ='BDO Prequal'!H51 -> 10 | I22: ='BDO Prequal'!I51 -> 1 | J22: ='BDO Prequal'!J51 -> 2 | K22: =SUM(C22:J22) -> 279948
B23: Machinery & Equipment | C23: ='BDO Prequal'!C52 -> 4499 | D23: ='BDO Prequal'!D52 -> 4499 | E23: ='BDO Prequal'!E52 -> 4499 | F23: ='BDO Prequal'!F52 -> 4499 | G23: ='BDO Prequal'!G52 -> 4499 | H23: ='BDO Prequal'!H52 -> 10 | I23: ='BDO Prequal'!I52 -> 1 | J23: ='BDO Prequal'!J52 -> 2 | K23: =SUM(C23:J23) -> 22508
B24: Furniture & Fixtures (TIs) | C24: ='BDO Prequal'!C53 -> 2499 | D24: ='BDO Prequal'!D53 -> 2499 | E24: ='BDO Prequal'!E53 -> 2499 | F24: ='BDO Prequal'!F53 -> 2499 | G24: ='BDO Prequal'!G53 -> 2499 | H24: ='BDO Prequal'!H53 -> 10 | I24: ='BDO Prequal'!I53 -> 1 | J24: ='BDO Prequal'!J53 -> 2 | K24: =SUM(C24:J24) -> 12508
B25: Inventory | C25: ='BDO Prequal'!C54 -> 4202 | D25: ='BDO Prequal'!D54 -> 4202 | E25: ='BDO Prequal'!E54 -> 4202 | F25: ='BDO Prequal'!F54 -> 4202 | G25: ='BDO Prequal'!G54 -> 4202 | H25: ='BDO Prequal'!H54 -> 10 | I25: ='BDO Prequal'!I54 -> 1 | J25: ='BDO Prequal'!J54 -> 2 | K25: =SUM(C25:J25) -> 21023
B26: Working Capital | C26: ='BDO Prequal'!C55 -> 84348 | D26: ='BDO Prequal'!D55 -> 84348 | E26: ='BDO Prequal'!E55 -> 84348 | F26: ='BDO Prequal'!F55 -> 84348 | G26: ='BDO Prequal'!G55 -> 84348 | H26: ='BDO Prequal'!H55 -> 10 | I26: ='BDO Prequal'!I55 -> 1 | J26: ='BDO Prequal'!J55 -> 2 | K26: =SUM(C26:J26) -> 421753
B27: Working Capital - Pre Opening | C27: ='BDO Prequal'!C56 -> 58397 | D27: ='BDO Prequal'!D56 -> 58397 | E27: ='BDO Prequal'!E56 -> 58397 | F27: ='BDO Prequal'!F56 -> 58397 | G27: ='BDO Prequal'!G56 -> 58397 | H27: ='BDO Prequal'!H56 -> 10 | I27: ='BDO Prequal'!I56 -> 1 | J27: ='BDO Prequal'!J56 -> 2 | K27: =SUM(C27:J27) -> 291998
B28: Business Acquisition | C28: ='BDO Prequal'!C57 -> 2919 | D28: ='BDO Prequal'!D57 -> 2919 | E28: ='BDO Prequal'!E57 -> 2919 | F28: ='BDO Prequal'!F57 -> 2919 | G28: ='BDO Prequal'!G57 -> 2919 | H28: ='BDO Prequal'!H57 -> 10 | I28: ='BDO Prequal'!I57 -> 1 | J28: ='BDO Prequal'!J57 -> 2 | K28: =SUM(C28:J28) -> 14608
B29: Franchise Fees | C29: ='BDO Prequal'!C58 -> 3593 | D29: ='BDO Prequal'!D58 -> 3593 | E29: ='BDO Prequal'!E58 -> 3593 | F29: ='BDO Prequal'!F58 -> 3593 | G29: ='BDO Prequal'!G58 -> 3593 | H29: ='BDO Prequal'!H58 -> 10 | I29: ='BDO Prequal'!I58 -> 1 | J29: ='BDO Prequal'!J58 -> 2 | K29: =SUM(C29:J29) -> 17978
B30: Construction Hard Costs | C30: ='BDO Prequal'!C59 -> 45097 | D30: ='BDO Prequal'!D59 -> 45097 | E30: ='BDO Prequal'!E59 -> 45097 | F30: ='BDO Prequal'!F59 -> 45097 | G30: ='BDO Prequal'!G59 -> 45097 | H30: ='BDO Prequal'!H59 -> 10 | I30: ='BDO Prequal'!I59 -> 1 | J30: ='BDO Prequal'!J59 -> 2 | K30: =SUM(C30:J30) -> 225498
B31: Interim Interest Reserve | C31: ='BDO Prequal'!C60 -> 8000 | D31: ='BDO Prequal'!D60 -> 200 | E31: ='BDO Prequal'!E60 -> 2230 | F31: ='BDO Prequal'!F60 -> 2000 | G31: ='BDO Prequal'!G60 -> 0 | H31: ='BDO Prequal'!H60 -> 373817 | I31: ='BDO Prequal'!I60 -> 8000 | J31: ='BDO Prequal'!J60 -> 800 | K31: =SUM(C31:J31) -> 395047
... B35: SBA Gty Fee | C35: ='BDO Prequal'!C64 -> 5050 | D35: ='BDO Prequal'!D64 -> 80 | E35: ='BDO Prequal'!E64 -> 800 | F35: ='BDO Prequal'!F64 -> 80 | G35: ='BDO Prequal'!G64 -> 0 | H35: ='BDO Prequal'!H64 -> -5050 | I35: ='BDO Prequal'!I64 -> 0 | J35: ='BDO Prequal'!J64 -> 0 | K35: =SUM(C35:J35) -> 960
B36: Total | C36: =SUM(C20:C35) -> -115502 | D36: =SUM(D20:D35) -> -128272 | E36: =SUM(E20:E35) -> -125522 | F36: =SUM(F20:F35) -> -126472 | G36: =SUM(G20:G35) -> -128552 | H36: =SUM(H20:H35) -> 1336917 | I36: =SUM(I20:I35) -> 257182 | J36: =SUM(J20:J35) -> 214570 | K36: =SUM(C36:J36) -> 1184349
B37: Percentage of Project | C37: =C36/$K$36 -> -0.097523618 | D37: =D36/$K$36 -> -0.10830591 | E37: =E36/$K$36 -> -0.10598396 | F37: =F36/$K$36 -> -0.10678609 | G37: =G36/$K$36 -> -0.10854233 | H37: =H36/$K$36 -> 1.1288201 | I37: =I36/$K$36 -> 0.21715052 | J37: =J36/$K$36 -> 0.18117126 | K37: =K36/K36 -> 1
B39: Income Statement Spreads - Subject Business | H39: Income Statement Projections
B40: ='BDO Prequal'!B83 -> {Insert business name which represents PSOR} | H40: ='BDO Prequal'!B83 -> {Insert business name which represents PSOR}
C42: Statement Date | D42: ='BDO Prequal'!D85 -> 44926 | E42: ='BDO Prequal'!F85 -> 45291 | F42: ='BDO Prequal'!H85 -> 45657 | G42: ='BDO Prequal'!J85 -> 45747 | H42: Projections | I42: Projections
C43: Months Covered | D43: ='BDO Prequal'!D86 -> 12 | E43: ='BDO Prequal'!F86 -> 12 | F43: ='BDO Prequal'!H86 -> 12 | G43: ='BDO Prequal'!J86 -> 3 | H43: Customer | I43: Customer
C44: Statement Type | D44: ='BDO Prequal'!D87 -> Tax Returns | E44: ='BDO Prequal'!F87 -> Tax Returns | F44: ='BDO Prequal'!H87 -> Form 10K | G44: ='BDO Prequal'!J87 -> Internal | H44: Year | I44: Year
C45: Revenue Recognition | D45: ='BDO Prequal'!D88 -> Accrual | E45: ='BDO Prequal'!F88 -> Accrual | F45: ='BDO Prequal'!H88 -> Cash | G45: ='BDO Prequal'!J88 -> Cash | H45: 1 | I45: 2
C47: Total Revenue | D47: ='BDO Prequal'!D99 -> 9000 | E47: ='BDO Prequal'!F99 -> 2166 | F47: ='BDO Prequal'!H99 -> 1145 | G47: ='BDO Prequal'!J99 -> 880 | H47: ='BDO Prequal'!N99 -> 210 | I47: ='BDO Prequal'!P99 -> 620
C48: Total COGS | D48: ='BDO Prequal'!D100 -> 50 | E48: ='BDO Prequal'!F100 -> 500 | F48: ='BDO Prequal'!H100 -> 400 | G48: ='BDO Prequal'!J100 -> 8000 | H48: ='BDO Prequal'!N100 -> 30 | I48: ='BDO Prequal'!P100 -> 0
C49: Total Gross Margin | D49: ='BDO Prequal'!D101 -> 8950 | E49: ='BDO Prequal'!F101 -> 1666 | F49: ='BDO Prequal'!H101 -> 745 | G49: ='BDO Prequal'!J101 -> -7120 | H49: ='BDO Prequal'!N101 -> 180 | I49: ='BDO Prequal'!P101 -> 620
C51: Total Operating Expenses | D51: ='BDO Prequal'!D128 -> 800 | E51: ='BDO Prequal'!F128 -> 800 | F51: ='BDO Prequal'!H128 -> 500 | G51: ='BDO Prequal'!J128 -> 5000 | H51: ='BDO Prequal'!N128 -> 6747 | I51: ='BDO Prequal'!P128 -> 7603
C53: Ordinary Income | D53: ='BDO Prequal'!D130 -> 8150 | E53: ='BDO Prequal'!F130 -> 866 | F53: ='BDO Prequal'!H130 -> 245 | G53: ='BDO Prequal'!J128 -> 5000 | H53: ='BDO Prequal'!N130 -> -6567 | I53: ='BDO Prequal'!P130 -> -6983
C55: Total Other Income (Expenses) | D55: ='BDO Prequal'!D130 -> 8150 | E55: ='BDO Prequal'!F136 -> 6050 | F55: ='BDO Prequal'!H136 -> 8600 | G55: ='BDO Prequal'!J136 -> 9801 | H55: ='BDO Prequal'!N130 -> -6567 | I55: ='BDO Prequal'!P130 -> -6983
C57: Net Income Before Taxes | D57: ='BDO Prequal'!D138 -> 13200 | E57: ='BDO Prequal'!F138 -> 6916 | F57: ='BDO Prequal'!H138 -> 8845 | G57: ='BDO Prequal'!J138 -> -2319 | H57: ='BDO Prequal'!N138 -> -6057 | I57: ='BDO Prequal'!P138 -> -6483
C58: Income Taxes | D58: ='BDO Prequal'!D139 -> 1 | E58: ='BDO Prequal'!F139 -> 2 | F58: ='BDO Prequal'!H139 -> 3 | G58: ='BDO Prequal'!J139 -> 6 | H58: ='BDO Prequal'!N139 -> 70 | I58: ='BDO Prequal'!P139 -> 63
C60: NET INCOME AFTER TAXES | D60: ='BDO Prequal'!D141 -> 13199 | E60: ='BDO Prequal'!F141 -> 6914 | F60: ='BDO Prequal'!H141 -> 8842 | G60: ='BDO Prequal'!J141 -> -2325 | H60: ='BDO Prequal'!N141 -> -6127 | I60: ='BDO Prequal'!P141 -> -6546
C62: Add Backs :
C63: Standard Add Backs | D63: ='BDO Prequal'!D144+'BDO Prequal'!D145+'BDO Prequal'!D146+'BDO Prequal'!D147 -> 9000 | E63: ='BDO Prequal'!F144+'BDO Prequal'!F145+'BDO Prequal'!F146+'BDO Prequal'!F147 -> 4562 | F63: ='BDO Prequal'!H144+'BDO Prequal'!H145+'BDO Prequal'!H146+'BDO Prequal'!H147 -> 461 | G63: ='BDO Prequal'!J144+'BDO Prequal'!J145+'BDO Prequal'!J146+'BDO Prequal'!J147 -> 621 | H63: ='BDO Prequal'!N144+'BDO Prequal'!N145+'BDO Prequal'!N146+'BDO Prequal'!N147 -> 423 | I63: ='BDO Prequal'!P144+'BDO Prequal'!P145+'BDO Prequal'!P146+'BDO Prequal'!P147 -> 1527
C64: + - Other | D64: ='BDO Prequal'!D148 -> 45 | E64: ='BDO Prequal'!F148 -> 46 | F64: ='BDO Prequal'!H148 -> 10 | G64: ='BDO Prequal'!J148 -> 11 | H64: ='BDO Prequal'!N148 -> 12 | I64: ='BDO Prequal'!P148 -> 12
C65: + - Other | D65: ='BDO Prequal'!D149 -> 21 | E65: ='BDO Prequal'!F149 -> 21 | F65: ='BDO Prequal'!H149 -> 22 | G65: ='BDO Prequal'!J149 -> 23 | H65: ='BDO Prequal'!N149 -> 40 | I65: ='BDO Prequal'!P149 -> 13
C66: - Required Owner's Draw | D66: ='BDO Prequal'!D151 -> 900 | E66: ='BDO Prequal'!F151 -> 1000 | F66: ='BDO Prequal'!H151 -> 70 | G66: ='BDO Prequal'!J151 -> 7 | H66: ='BDO Prequal'!N151 -> 70 | I66: ='BDO Prequal'!P151 -> 70
C68: Subject Business Cash Flow
C69: Cash Available | D69: ='BDO Prequal'!D153 -> 23165 | E69: ='BDO Prequal'!F153 -> 12543 | F69: ='BDO Prequal'!H153 -> 9405 | G69: ='BDO Prequal'!J153 -> -1663 | H69: ='BDO Prequal'!N153 -> -5582 | I69: ='BDO Prequal'!P153 -> -4924
C71: Existing Debt Service | D71: ='BDO Prequal'!D155 -> 600 | E71: ='BDO Prequal'!F155 -> 700 | F71: ='BDO Prequal'!F155 -> 700 | G71: ='BDO Prequal'!H155 -> 8000 | H71: ='BDO Prequal'!N155 -> 1 | I71: ='BDO Prequal'!P155 -> 10
C73: Proposed Debt Payments
C74: SBA 7a Loan | D74: ='BDO Prequal'!D156 -> 152.05897 | E74: ='BDO Prequal'!F156 -> 152.05897 | F74: ='BDO Prequal'!H156 -> 152.05897 | G74: ='BDO Prequal'!J156 -> 38.014743 | H74: ='BDO Prequal'!N156 -> 1000 | I74: ='BDO Prequal'!P156 -> 1000
C75: SBA 504 Loan
C76: CDC Loan
C77: Seller Note | D77: ='BDO Prequal'!D159 -> 37443.928 | E77: ='BDO Prequal'!F159 -> 37443.928 | F77: ='BDO Prequal'!H159 -> 37443.928 | G77: ='BDO Prequal'!J159 -> 9360.982 | H77: ='BDO Prequal'!N159 -> 6000 | I77: ='BDO Prequal'!P159 -> 9000
C78: 3rd Party | D78: ='BDO Prequal'!D160 -> 100 | E78: ='BDO Prequal'!F160 -> 200 | F78: ='BDO Prequal'!H160 -> 1400 | G78: ='BDO Prequal'!J160 -> 3000 | H78: ='BDO Prequal'!N160 -> 15000 | I78: ='BDO Prequal'!P160 -> 6000
C79: Total Debt | D79: ='BDO Prequal'!D161 -> 38295.987 | E79: ='BDO Prequal'!F161 -> 38495.987 | F79: ='BDO Prequal'!H161 -> 46995.987 | G79: ='BDO Prequal'!J161 -> 12998.997 | H79: ='BDO Prequal'!N161 -> 22001 | I79: ='BDO Prequal'!P161 -> 16010
C81: DCR | D81: ='BDO Prequal'!D163 -> 0.60489367 | E81: ='BDO Prequal'!F163 -> 0.32582617 | F81: ='BDO Prequal'!H163 -> 0.20012347 | G81: ='BDO Prequal'!J163 -> -0.12793295 | H81: ='BDO Prequal'!N163 -> -0.25371574 | I81: ='BDO Prequal'!P163 -> -0.30755778
C84: Operating Cash Available | D84: ='BDO Prequal'!D171 -> 22265 | E84: ='BDO Prequal'!F171 -> 11543 | F84: ='BDO Prequal'!H171 -> 9335 | G84: ='BDO Prequal'!J171 -> -1670
C85: Operating Debt Service | D85: ='BDO Prequal'!D172 -> 38295.987 | E85: ='BDO Prequal'!F172 -> 38495.987 | F85: ='BDO Prequal'!H172 -> 46995.987 | G85: ='BDO Prequal'!J172 -> 12998.997
C87: Total Affiliate Cash Available | D87: ='BDO Prequal'!D194 -> 27896 | E87: ='BDO Prequal'!F194 -> 17543 | F87: ='BDO Prequal'!H194 -> 11335 | G87: ='BDO Prequal'!J194 -> 18581
C88: Total Affiliate Debt Service | D88: ='BDO Prequal'!D195 -> 52408.987 | E88: ='BDO Prequal'!F195 -> 43495.987 | F88: ='BDO Prequal'!H195 -> 47045.987 | G88: ='BDO Prequal'!J195 -> 13118.997
C91: Global DCR | D91: ='BDO Prequal'!D198 -> 0.53227512 | E91: ='BDO Prequal'!F198 -> 0.40332456 | F91: ='BDO Prequal'!H198 -> 0.24093447 | G91: ='BDO Prequal'!J198 -> 1.4163431
B95: Business Debt Schedule
B96: Lender | C96: Current Balance | D96: Mthly Pmt | E96: Collateral | F96: Refinance? | G96: % of Loan | H96: Refi Pmt | I96: % Chg | J96: CF Debt Svc | K96: Reserved
B97: ='BDO Prequal'!B207 -> tester lending lender loans | C97: ='BDO Prequal'!C207 -> 6000 | D97: ='BDO Prequal'!D207 -> 60 | E97: ='BDO Prequal'!E207 -> 0 | F97: ='BDO Prequal'!F207 -> Yes | G97: ='BDO Prequal'!G207 -> -0.051947152 | H97: ='BDO Prequal'!H207 -> 76.005464 | I97: ='BDO Prequal'!I207 -> -0.26675774 | ... K97: ='BDO Prequal'!K207 -> 0
B98: ='BDO Prequal'!B208 -> 0 | C98: ='BDO Prequal'!C208 -> 0 | D98: ='BDO Prequal'!D208 -> 0 | E98: ='BDO Prequal'!E208 -> 0 | F98: ='BDO Prequal'!F208 -> 0 | G98: ='BDO Prequal'!G208 -> 0 | H98: ='BDO Prequal'!H208 -> 0 | I98: ='BDO Prequal'!I208 -> 0 | J98: ='BDO Prequal'!J208 -> 0
B99: ='BDO Prequal'!B209 -> 0 | C99: ='BDO Prequal'!C209 -> 0 | D99: ='BDO Prequal'!D209 -> 0 | E99: ='BDO Prequal'!E209 -> 0 | F99: ='BDO Prequal'!F209 -> 0 | G99: ='BDO Prequal'!G209 -> 0 | H99: ='BDO Prequal'!H209 -> 0 | I99: ='BDO Prequal'!I209 -> 0 | J99: ='BDO Prequal'!J209 -> 0
B100: ='BDO Prequal'!B210 -> 0 | C100: ='BDO Prequal'!C210 -> 0 | D100: ='BDO Prequal'!D210 -> 0 | E100: ='BDO Prequal'!E210 -> 0 | F100: ='BDO Prequal'!F210 -> 0 | G100: ='BDO Prequal'!G210 -> 0 | H100: ='BDO Prequal'!H210 -> 0 | I100: ='BDO Prequal'!I210 -> 0 | J100: ='BDO Prequal'!J210 -> 0
B101: ='BDO Prequal'!B211 -> 0 | C101: ='BDO Prequal'!C211 -> 0 | D101: ='BDO Prequal'!D211 -> 0 | E101: ='BDO Prequal'!E211 -> 0 | F101: ='BDO Prequal'!F211 -> 0 | G101: ='BDO Prequal'!G211 -> 0 | H101: ='BDO Prequal'!H211 -> 0 | I101: ='BDO Prequal'!I211 -> 0 | J101: ='BDO Prequal'!J211 -> 0
B102: ='BDO Prequal'!B212 -> 0 | C102: ='BDO Prequal'!C212 -> 0 | D102: ='BDO Prequal'!D212 -> 0 | E102: ='BDO Prequal'!E212 -> 0 | F102: ='BDO Prequal'!F212 -> 0 | G102: ='BDO Prequal'!G212 -> 0 | H102: ='BDO Prequal'!H212 -> 0 | I102: ='BDO Prequal'!I212 -> 0 | J102: ='BDO Prequal'!J212 -> 0
B103: ='BDO Prequal'!B213 -> 0 | C103: ='BDO Prequal'!C213 -> 0 | D103: ='BDO Prequal'!D213 -> 0 | E103: ='BDO Prequal'!E213 -> 0 | F103: ='BDO Prequal'!F213 -> 0 | G103: ='BDO Prequal'!G213 -> 0 | H103: ='BDO Prequal'!H213 -> 0 | I103: ='BDO Prequal'!I213 -> 0 | J103: ='BDO Prequal'!J213 -> 0
B104: ='BDO Prequal'!B214 -> 0 | C104: ='BDO Prequal'!C214 -> 0 | D104: ='BDO Prequal'!D214 -> 0 | E104: ='BDO Prequal'!E214 -> 0 | F104: ='BDO Prequal'!F214 -> 0 | G104: ='BDO Prequal'!G214 -> 0 | H104: ='BDO Prequal'!H214 -> 0 | I104: ='BDO Prequal'!I214 -> 0 | J104: ='BDO Prequal'!J214 -> 0
B105: ='BDO Prequal'!B215 -> 0 | C105: ='BDO Prequal'!C215 -> 0 | D105: ='BDO Prequal'!D215 -> 0 | E105: ='BDO Prequal'!E215 -> 0 | F105: ='BDO Prequal'!F215 -> 0 | G105: ='BDO Prequal'!G215 -> 0 | H105: ='BDO Prequal'!H215 -> 0 | I105: ='BDO Prequal'!I215 -> 0 | J105: ='BDO Prequal'!J215 -> 0
B106: ='BDO Prequal'!B216 -> 0 | C106: ='BDO Prequal'!C216 -> 0 | D106: ='BDO Prequal'!D216 -> 0 | E106: ='BDO Prequal'!E216 -> 0 | F106: ='BDO Prequal'!F216 -> 0 | G106: ='BDO Prequal'!G216 -> 0 | H106: ='BDO Prequal'!H216 -> 0 | I106: ='BDO Prequal'!I216 -> 0 | J106: ='BDO Prequal'!J216 -> 0
B107: =[1]!Table2[[#Totals],[Lender]] -> #REF! | C107: =Table2[[#Totals],[Current Balance]] -> 6000 | D107: =Table2[[#Totals],[Mthly Pmt]] -> 60 | E107: =Table2[[#Totals],[Collateral]] -> 0 | F107: =Table2[[#Totals],[Refinance?]] -> 0 | G107: =Table2[[#Totals],[% of Loan]] -> -0.051947152 | H107: =Table2[[#Totals],[Refi Pmt]] -> 76.005464 | I107: =Table2[[#Totals],[% Chg]] -> -0.26675774 | J107: =Table2[[#Totals],[CF Debt Svc]] -> 0 | K107: =[1]!Table2[[#Totals],[Reserved]] -> #REF!
B109: Curr Pmts on Debt to Be Refinanced | C109: ='BDO Prequal'!C219 -> 60 | D109: Proposed Pmt: | E109: ='BDO Prequal'!E219 -> 76.005464 | F109: % Savings: | G109: ='BDO Prequal'!G219 -> -0.26675774

Sheet BDO Prequal
B2: BDO Prequalification
B7: Loan Structure
B8: Purchase and Sale Close Date, if known, otherwise Target Closing Date
B11: Entity Name: | D11: Role | F11: Yrs. In Bus. | G11: Guarantor?
I12: BDO:
I13: Cooperating BDO:
I14: Broker Name:
I15: Broker Fee:
B17: * List entities in the following order (as applicable): Borrower, Co-Borrower, Operating Entity, Corp. Guarantor, Affiliate.
B18: Individual Guarantor Info: | C18: Ownership Exp. (yrs) | D18: Ownership % | E18: FICO | F18: Prior BK? | G18: Prior Loss to Gov't | H18: Debarred by SBA? | I18: Pending Legal Action? | J18: Criminal History?
B26: Business / Property Address:
C27: (Street) | F27: (City) (State) (ZIP)
B29: Loan Terms | Q29: Closing Costs | R29: Cost | S29: Quantity | T29: Total | Y29: Closing Cost Calculator ---> Expand/Collapse Above --->
S30: Loan Packaging Fee | T30: 2500 | U30: 1 | V30: =T30*U30 -> 2500 | W30: $1.5M - 2.5M
C31: T Bank Loan | D31: T Bank Loan | E31: CDC Debenture | F31: T Bank Loan | G31: T Bank Loan | H31: Equity | I31: Seller Note | J31: 3rd Party | Q31: Title Insurance | R31: 0 | S31: 0 | T31: =R31*S31 -> 0 | U31: 0.5%-1% of CRE value (FL & NY +)
B32: Product Type | C32: P&E | D32: USDA | E32: Conventional | F32: 7A Express | G32: CAPLine | M32: SBA Gty % | N32: 0.75 | Q32: Real Estate Tax Fee | R32: 0 | S32: 0 | T32: =R32*S32 -> 0 | U32: $150 for 1st $500M, $200 for $956M
B33: Loan Amount/Injection | C33: 1000 | D33: 20000 | E33: 30000 | F33: 4 | G33: 5 | H33: 6 | I33: 7 | J33: 8 | M33: Est. Appraisal Costs | N33: =SUM(T34,T35,T36,T40) -> 0 | Q33: Survey Charges | R33: 3000 | S33: 0 | T33: =R33*S33 -> 0 | U33: $1M - $3M
B34: Base Rate | C34: 0.075 | D34: 0.075 | E34: 0.075 | F34: 0.075 | I34: 0.08 | J34: 0.0624 | M34: Est. Environmental Report Costs | N34: =SUM(T37,T38) -> 0 | Q34: CRE Appraisal | R34: 3500 | S34: 0 | T34: =R34*S34 -> 0 | U34: $3.5M - $6.0M
B35: Spread | C35: 0.015 | D35: 0.015 | E35: 0.015 | F35: 0.015 | I35: 0 | J35: 0 | M35: Packaging Fee | N35: =SUM(V30) -> 2500 | Q35: Equipment Appraisal | R35: 0 | S35: 0 | T35: =R35*S35 -> 0 | U35: $1.5M - $3.5M
B36: Indicative Rate | C36: =C34+C35 -> 0.09 | D36: =D34+D35 -> 0.09 | E36: =E34+E35 -> 0.09 | F36: =F34+F35 -> 0.09 | I36: =I34+I35 -> 0.08 | J36: =J34+J35 -> 0.0624 | M36: Survey | N36: =SUM(T33) -> 0 | Q36: Appraisal Review | R36: 0 | S36: 0 | T36: =R36*S36 -> 0 | U36: $250 - $900
B37: Amortization Basis | C37: Actual/365 | D37: Actual/365 | E37: Actual/365 | F37: Actual/366 | M37: Business Valuation | N37: =SUM(T39) -> 0 | Q37: Site Visit | R37: 350 | S37: 0 | T37: =R37*S37 -> 0 | U37: 200
B38: Term (years) | C38: 10 | D38: 10 | E38: 10 | F38: 10 | I38: 10 | J38: 25 | M38: Title / Escrow / Closing | N38: =SUM(T31,T32) -> 0 | Q38: Environmental Investigation | R38: 2500 | S38: 0 | T38: =R38*S38 -> 0 | U38: $2M
B39: Amortization (mos) | C39: =C38*12 -> 120 | D39: =D38*12 -> 120 | E39: =E38*12 -> 120 | F39: =F38*12 -> 120 | I39: =I38*12 -> 120 | J39: =J38*12 -> 300 | M39: SBA GTY Fee | N39: =BE56 -> 0 | Q39: Business Valuation | R39: 2500 | S39: 0 | T39: =R39*S39 -> 0 | U39: $2.5M - $3M
B40: Estimated Payment | C40: =IFERROR(INDEX($BL$82:$BL$84,MATCH($C$37,$BC$82:$BC$84,0)),0) -> 12.671581 | D40: =IFERROR(INDEX($BL$82:$BL$84,MATCH($C$37,$BC$82:$BC$84,0)),0) -> 12.671581 | E40: =IFERROR(INDEX($BL$82:$BL$84,MATCH($C$37,$BC$82:$BC$84,0)),0) -> 12.671581 | F40: =IFERROR(INDEX($BL$82:$BL$84,MATCH($C$37,$BC$82:$BC$84,0)),0) -> 12.671581 | I40: =IFERROR(PMT(I36/12,I39,-I33),0) -> 0.084929316 | J40: =IFERROR(PMT(J36/12,J39,-J33),0) -> 0.05272411 | M40: Other Costs | N40: =T46-SUM(N33:O38) -> -2500 | Q40: Residential Appr / Valuation | R40: 0 | S40: 0 | T40: =R40*S40 -> 0 | U40: $500 - $700
B41: Est Const Period (mths) | C41: 120 | D41: 0 | E41: 0 | F41: 0 | M41: Total SBA Fees & Closing Costs | N41: =SUM(N33:O40) -> 0 | Q41: Attorney Doc Prep | R41: 6000 | S41: 1 | T41: =R41*S41 -> 6000 | U41: $3.5M-$6.0M
B42: Are there funded SBA Loans in last 90 days? | C42: No | D42: No | E42: No | F42: No | H42: Amount? | I42: 0 | J42: Guarantee %? | K42: 0 | Q42: Interim Loan Fee / Origination | R42: 0 | S42: 1 | T42: =R42*S42 -> 0 | U42: 1.0% -2.0% Conv/USDA Loans
Q43: Construction Monitoring | R43: 0 | S43: 1 | T43: =R43*S43 -> 0 | U43: See Partner ESI pricing sheet
Q44: Rounding | R44: 700 | S44: 1 | T44: =R44*S44 -> 700 | U44: =_xlfn.CONCAT("<--- To round to next $100, input $",ROUNDUP(T46,-2)-T46) -> <--- To round to next $100, input $0
B45: Sources and Uses of Proceeds | Q45: Other: UCCs and Misc Closing | T45: =T58 -> 800 | BC45: =IF(C32="SBA 7a","SBA 7a","Not 7a, Guaranty Calculation not applicable") -> Not 7a, Guaranty Calculation not applicable
Q46: Total Estimated Closing Costs | T46: =SUM(P30:P45) -> 0 | BF46: SBA Guaranty % | BH46: =N32 -> 0.75
C47: =IF(C32=0,"",C32) -> P&E | D47: =IF(D32=0,"",D32) -> USDA | E47: =IF(E32=0,"",E32) -> Conventional | F47: =IF(F32=0,"",F32) -> 7A Express | G47: =IF(G32=0,"",G32) -> CAPLine | H47: =H31 -> Equity | I47: =I31 -> Seller Note | J47: =J31 -> 3rd Party | K47: Total | L47: SBA Term (yrs) | M47: % | N47: Wgt | BC47: If there has been a previous SBA 7a loan funded within the last 90 days, enter loan amount and guaranty %.
B48: Direct Project Costs | Q48: Miscellaneous Closing Costs | R48: Cost | S48: Quantity | T48: Total | BC48: Previous Loan Amount | BG48: =I42 -> 0
B49: Real Estate Acquisition | C49: =$K49-SUM($H49:$J49) -> 896000 | D49: =$K49-SUM($H49:$J49) -> 896000 | E49: =$K49-SUM($H49:$J49) -> 896000 | F49: =$K49-SUM($H49:$J49) -> 896000 | G49: =$K49-SUM($H49:$J49) -> 896000 | H49: 8000 | I49: 80000 | J49: 16000 | K49: 1000000 | L49: 25 | M49: =IF($C$65=0,0,C49/$C$65) -> -7.7574414 | N49: =L49*M49 -> -193.93604 | Q49: Business Credit Report | R49: 35 | S49: 1 | T49: =R49*S49 -> 35 | BC49: Previous Guaranty % | BG49: =K42 -> 0
B50: Debt Refi - CRE | C50: =$K50-SUM($H50:$J50) -> 5387 | D50: =$K50-SUM($H50:$J50) -> 5387 | E50: =$K50-SUM($H50:$J50) -> 5387 | F50: =$K50-SUM($H50:$J50) -> 5387 | G50: =$K50-SUM($H50:$J50) -> 5387 | H50: 10 | I50: 1 | J50: 2 | K50: 5400 | L50: 25 | M50: =IF($C$65=0,0,C50/$C$65) -> -0.046639885 | N50: =L50*M50 -> -1.1659971 | Q50: Personal Credit Report | R50: 25 | S50: 2 | T50: =R50*S50 -> 50 | BC50: SBA Guaranty Fee Calculation
B51: Debt Refi - Non-CRE | C51: =$K51-SUM($H51:$J51) -> 55987 | D51: =$K51-SUM($H51:$J51) -> 55987 | E51: =$K51-SUM($H51:$J51) -> 55987 | F51: =$K51-SUM($H51:$J51) -> 55987 | G51: =$K51-SUM($H51:$J51) -> 55987 | H51: 10 | I51: 1 | J51: 2 | K51: 56000 | L51: 10 | M51: =IF($C$65=0,0,C51/$C$65) -> -0.48472754 | N51: =L51*M51 -> -4.8472754 | Q51: IRS Transcript Service | R51: 65 | S51: 2 | T51: =R51*S51 -> 130 | BC51: T Bank SBA Loan | BG51: Previous SBA Loan Within 90 Days | BJ51: Two Loans Combined
B52: Machinery & Equipment | C52: =$K52-SUM($H52:$J52) -> 4499 | D52: =$K52-SUM($H52:$J52) -> 4499 | E52: =$K52-SUM($H52:$J52) -> 4499 | F52: =$K52-SUM($H52:$J52) -> 4499 | G52: =$K52-SUM($H52:$J52) -> 4499 | H52: 10 | I52: 1 | J52: 2 | K52: 4512 | L52: 10 | M52: =IF($C$65=0,0,C52/$C$65) -> -0.038951706 | N52: =L52*M52 -> -0.38951706 | Q52: UCC Searches | R52: 300 | S52: 1 | T52: =R52*S52 -> 300 | BC52: Loan Amount | BF52: =IF(BC45="SBA 7a",C65,0) -> 0 | BG52: Loan Amount | BI52: =BG48 -> 0 | BJ52: Loan Amount | BL52: =BI52+BF52 -> 0
B53: Furniture & Fixtures (TIs) | C53: =$K53-SUM($H53:$J53) -> 2499 | D53: =$K53-SUM($H53:$J53) -> 2499 | E53: =$K53-SUM($H53:$J53) -> 2499 | F53: =$K53-SUM($H53:$J53) -> 2499 | G53: =$K53-SUM($H53:$J53) -> 2499 | H53: 10 | I53: 1 | J53: 2 | K53: 2512 | L53: 10 | M53: =IF($C$65=0,0,C53/$C$65) -> -0.021635989 | N53: =L53*M53 -> -0.21635989 | Q53: Certificate of Good Standing | R53: 20 | S53: 1 | T53: =R53*S53 -> 20 | BC53: Guaranteed Portion | BF53: =BF52*BH46 -> 0 | BG53: Guaranteed Portion | BI53: =BI52*BG49 -> 0 | BJ53: Guaranteed Portion | BL53: =BF53+BI53 -> 0
B54: Inventory | C54: =$K54-SUM($H54:$J54) -> 4202 | D54: =$K54-SUM($H54:$J54) -> 4202 | E54: =$K54-SUM($H54:$J54) -> 4202 | F54: =$K54-SUM($H54:$J54) -> 4202 | G54: =$K54-SUM($H54:$J54) -> 4202 | H54: 10 | I54: 1 | J54: 2 | K54: 4215 | L54: 10 | M54: =IF($C$65=0,0,C54/$C$65) -> -0.036380322 | N54: =L54*M54 -> -0.36380322 | Q54: Flood Certification | R54: 18 | S54: 1 | T54: =R54*S54 -> 18 | BC54: Guaranty Fee | BF54: =SUM(BF59:BF63) -> 0 | BG54: Guaranty Fee | BI54: =SUM(BG59:BH63) -> 0 | BJ54: Guaranty Fee | BL54: =SUM(BK59:BK63) -> 0
B55: Working Capital | C55: =$K55-SUM($H55:$J55) -> 84348 | D55: =$K55-SUM($H55:$J55) -> 84348 | E55: =$K55-SUM($H55:$J55) -> 84348 | F55: =$K55-SUM($H55:$J55) -> 84348 | G55: =$K55-SUM($H55:$J55) -> 84348 | H55: 10 | I55: 1 | J55: 2 | K55: 84361 | L55: 10 | M55: =IF($C$65=0,0,C55/$C$65) -> -0.73027307 | N55: =L55*M55 -> -7.3027307 | Q55: Filing & Recording Fees | R55: 100 | S55: 1 | T55: =R55*S55 -> 100 | U55: avg $100 | BC55: Add'l Gty Fee | BF55: =IF(BG48>0,BL54-BI54-BF54,0) -> 0
B56: Working Capital - Pre Opening | C56: =$K56-SUM($H56:$J56) -> 58397 | D56: =$K56-SUM($H56:$J56) -> 58397 | E56: =$K56-SUM($H56:$J56) -> 58397 | F56: =$K56-SUM($H56:$J56) -> 58397 | G56: =$K56-SUM($H56:$J56) -> 58397 | H56: 10 | I56: 1 | J56: 2 | K56: 58410 | L56: 10 | M56: =IF($C$65=0,0,C56/$C$65) -> -0.50559298 | N56: =L56*M56 -> -5.0559298 | Q56: FedEx Charges | R56: 50 | S56: 1 | T56: =R56*S56 -> 50 | U56: avg $50 | BC56: Total Gty Fee (Rounded) | BE56: =ROUNDUP(BF54+BF55,-0.1) -> 0 | BG56: Total Gty Fee (Rounded) | BI56: =ROUNDUP(BI54+BI55,-0.1) -> 0 | BJ56: Total Gty Fee (Rounded) | BL56: =ROUNDUP(BL54+BL55,-0.1) -> 0
B57: Business Acquisition | C57: =$K57-SUM($H57:$J57) -> 2919 | D57: =$K57-SUM($H57:$J57) -> 2919 | E57: =$K57-SUM($H57:$J57) -> 2919 | F57: =$K57-SUM($H57:$J57) -> 2919 | G57: =$K57-SUM($H57:$J57) -> 2919 | H57: 10 | I57: 1 | J57: 2 | K57: 2932 | L57: 10 | M57: =IF($C$65=0,0,C57/$C$65) -> -0.02527229 | N57: =L57*M57 -> -0.2527229 | Q57: Other: rounding | R57: 97 | S57: 1 | T57: =R57*S57 -> 97 | U57: =_xlfn.CONCAT("<--- To round to next $100, input $",ROUNDUP(R58,-2)-R45) -> <--- To round to next $100, input $0
B58: Franchise Fees | C58: =$K58-SUM($H58:$J58) -> 3593 | D58: =$K58-SUM($H58:$J58) -> 3593 | E58: =$K58-SUM($H58:$J58) -> 3593 | F58: =$K58-SUM($H58:$J58) -> 3593 | G58: =$K58-SUM($H58:$J58) -> 3593 | H58: 10 | I58: 1 | J58: 2 | K58: 3606 | L58: 10 | M58: =IF($C$65=0,0,C58/$C$65) -> -0.031107686 | N58: =L58*M58 -> -0.31107686 | Q58: Total Misc. Closing Costs | T58: =SUM(T49:T57) -> 800 | BC58: Proposed Loan Amount | BD58: Fee % | BG58: Prior Loan Amount Calc | BJ58: Total Combined | BK58: Fee %
B59: Construction Hard Costs | C59: =$K59-SUM($H59:$J59) -> 45097 | D59: =$K59-SUM($H59:$J59) -> 45097 | E59: =$K59-SUM($H59:$J59) -> 45097 | F59: =$K59-SUM($H59:$J59) -> 45097 | G59: =$K59-SUM($H59:$J59) -> 45097 | H59: 10 | I59: 1 | J59: 2 | K59: 45110 | L59: 25 | M59: =IF($C$65=0,0,C59/$C$65) -> -0.39044346 | N59: =L59*M59 -> -9.7610864 | BC59: < | BD59: 150000 | BE59: 0.02 | BF59: =IF(BF52<=$BD$59,BF53*$BE$59,0) -> 0 | BG59: =IF(BI52<=$BD$59,BI53*$BE$59,0) -> 0 | BK59: =IF(BL52<=$BD$59,BL53*$BE$59,0) -> 0
B60: Interim Interest Reserve | C60: 8000 | D60: 200 | E60: 2230 | F60: 2000 | G60: 0 | H60: =K60-C60 -> 373817 | I60: 8000 | J60: 800 | K60: =ROUND(((C49+J49)*C36/12)*C41+((C65-C49+J65-J49)*C36*0.6/12)*C41,0) -> 381817 | L60: 25 | M60: =IF($C$65=0,0,C60/$C$65) -> -0.06926287 | N60: =L60*M60 -> -1.7315717 | O60: Const Contigency | Q60: Total Project | R60: =SUM(R61:R63) -> 1 | S60: =K65 -> 1684367 | T60: (difference) | BC60: 150001 | BD60: 700000 | BE60: 0.03 | BF60: =IF($BF$52>=$BD$60+1,0,IF($BF$52>=$BC$60,$BF$53*$BE$60,0)) -> 0 | BG60: =IF($BI$52>=$BD$60+1,0,IF($BI$52>=$BC$60,$BI$53*$BE$60,0)) -> 0 | BH60: =IF($BF$52>=$BD$60+1,0,IF($BF$52>=$BC$60,$BF$53*$BE$60,0)) -> 0 | BK60: =IF($BL$52>=$BD$60+1,0,IF($BL$52>=$BC$60,$BL$53*$BE$60,0)) -> 0
B61: Construction Contingency | C61: =K61-H61-I61-J61 -> -115579 | D61: =K61-H61-I61-J61 -> -115579 | E61: =K61-H61-I61-J61 -> -115579 | F61: =K61-H61-I61-J61 -> -115579 | G61: =K61-H61-I61-J61 -> -115579 | H61: 60000 | I61: 51210 | J61: 8880 | K61: =ROUND(K59*O61,0) -> 4511 | L61: 25 | M61: =IF($C$65=0,0,C61/$C$65) -> 1.0006667 | N61: =L61*M61 -> 25.016666 | O61: 0.1 | Q61: Bank Loan % | R61: 0.5 | S61: =S60*R61 -> 842183.5 | T61: =C65-S61 -> -957685.5 | BE61: 0 | BF61: =IF(BF52>=$BD$60+1,0,IF(BF52>=$BC$60,IF(BF53>1000000,(BF53-1000000)*$BE$61,0),0)) -> 0 | BG61: =IF(BI52>=$BD$60+1,0,IF(BI52>=$BC$60,IF(BI53>1000000,(BI53-1000000)*$BE$61,0),0)) -> 0 | BK61: =IF(BL52>=$BD$60+1,0,IF(BL52>=$BC$60,IF(BL53>1000000,(BL53-1000000)*$BE$61,0),0)) -> 0
B62: Other Construction Soft Costs | C62: =K62-SUM(H62:J62) -> -1095120 | D62: =$K62-SUM($H62:$J62) -> -1095120 | E62: =$K62-SUM($H62:$J62) -> -1095120 | F62: =$K62-SUM($H62:$J62) -> -1095120 | G62: =$K62-SUM($H62:$J62) -> -1095120 | H62: 900000 | I62: 112121 | J62: 88880 | K62: 5881 | L62: 25 | M62: =IF($C$65=0,0,C62/$C$65) -> 9.4813943 | N62: =L62*M62 -> 237.03486 | Q62: CDC Loan % | R62: 0.4 | S62: =S60*R62 -> 673746.8 | T62: =J65-S62 -> -459176.8 | BC62: 700001 | BD62: 5000000 | BE62: 0.035 | BF62: =IF(BF52>=$BC$62,1000000*$BE$62,0) -> 0 | BG62: =MIN(35000,IF(BI52>=$BD$62+1,1000000*$BE$62,0)) -> 0 | BK62: =MIN(35000,IF(BL52>=$BD$62+1,1000000*$BE$62,0)) -> 0
B63: Closing Costs | C63: =K63-SUM(H63:J63) -> -80781 | D63: =$K63-SUM($H63:$J63) -> -80781 | E63: =$K63-SUM($H63:$J63) -> -80781 | F63: =$K63-SUM($H63:$J63) -> -80781 | G63: =$K63-SUM($H63:$J63) -> -80781 | H63: 50 | I63: 5841 | J63: 99990 | K63: 25100 | L63: 10 | M63: =IF($C$65=0,0,C63/$C$65) -> 0.69939049 | N63: =L63*M63 -> 6.9939049 | Q63: Borrower % | R63: 0.1 | S63: =S60*R63 -> 168436.7 | T63: =H65-S63 -> 1168480.3 | BE63: 0.0375 | BF63: =IF(BF52>=$BC$62,(BF53-1000000)*$BE$63,0) -> 0 | BG63: =IF((BI53-$BC$62)*$BE$63<=0,0,(BI53-1000000)*$BE$63) -> 0 | BK63: =IF((BL53-$BC$62)*$BE$63<=0,0,(BL53-1000000)*$BE$63) -> 0
B64: SBA Gty Fee | C64: 5050 | D64: 80 | E64: 800 | F64: 80 | G64: 0 | H64: =K64-C64 -> -5050 | K64: =BE56 -> 0 | L64: 10 | M64: =IF($C$65=0,0,C64/$C$65) -> -0.043722187 | N64: =L64*M64 -> -0.43722187
C65: =SUM(C49:C64) -> -115502 | D65: =SUM(D49:D64) -> -128272 | E65: =SUM(E49:E64) -> -125522 | F65: =SUM(F49:F64) -> -126472 | G65: =SUM(G49:G64) -> -128552 | H65: =SUM(H49:H64) -> 1336917 | I65: =SUM(I49:I64) -> 257182 | J65: =SUM(J49:J64) -> 214570 | K65: =SUM(K49:K64) -> 1684367 | M65: Weighted Term | N65: =SUM(N49:N64) -> 43.274099 | Q65: Bank Interim Loan Fee % | R65: 0.015 | S65: =S61*R65 -> 12632.752
C66: =IFERROR(C65/$K$65,0) -> -0.068572942 | D66: =IFERROR(D65/$K$65,0) -> -0.076154425 | E66: =IFERROR(E65/$K$65,0) -> -0.074521764 | F66: =IFERROR(F65/$K$65,0) -> -0.075085774 | G66: =IFERROR(G65/$K$65,0) -> -0.076320659 | H66: =IFERROR(H65/$K$65,0) -> 0.79372073 | I66: =IFERROR(I65/$K$65,0) -> 0.15268763 | J66: =IFERROR(J65/$K$65,0) -> 0.1273891 | K66: =IFERROR(K65/$K$65,0) -> 1 | Q66: SBA TPL Fee % | R66: 0.005 | S66: =S61*R66 -> 4210.9175
Q67: Referral Fee % | R67: 0.01 | S67: =S61*R67 -> 8421.835
Q68: Participant Fee % | R68: 0 | S68: =R68*C65 -> 0
B69: Liquidity Review | Q69: Origination Fee Total | R69: =SUM(N65:N68) -> 43.274099 | S69: =SUM(O65:O68) -> 0
C71: Amount | D71: As of: | G71: Amount | H71: As of: | Q71: Interim Loan | R71: =C65+J65 -> 99068
B72: Operating Company Liquidity | C72: 0 | F72: Affiliate 1 | G72: 0 | Q72: Rounded Fee | R72: =ROUNDUP(S69,-3) -> 0
B73: Owner/Guarantor 1 | C73: =C622 -> 0 | F73: Affiliate 2 | G73: 0 | Q73: Fee % to Interim Loan | R73: =R72/R71 -> 0
B74: Owner/Guarantor 2 | C74: =E622 -> 0 | F74: Affiliate 3 | G74: 0 | Q74: Blended Rate | R74: =(C65*C36+J65*J36)/SUM(C33+J33) -> 2.9702262
B75: Owner/Guarantor 3 | C75: =G622 -> 0 | F75: Affiliate 4 | G75: 0
B76: Owner/Guarantor 4 | C76: =I622 -> 0 | F76: Affiliate 5 | G76: 0 | R76: From UOP | S76: 0.8 | T76: Sum
Q77: Guaranty Fee @ 3.0% | R77: =C65-C59-C61 -> -45020 | S77: =R77*S76 -> -36016 | T77: =S77*0.03 -> -1080.48
C78: Total Available Liquidity | D78: =SUM(C72:C76,G72:G76) -> 0 | E78: Expected Injection | F78: =H65 -> 1336917 | G78: Remaining Available | H78: =D78-F78 -> -1336917 | Q78: Guaranty Fee @ 3.5% - Construction | R78: =C59+C61 -> -70482 | S78: =R78*S76 -> -56385.6 | T78: =S78*0.035 -> -1973.496
Q79: Total USDA Guaranty Fee | T79: =ROUNDUP(T77+T78,0) -> -3054
B80: Click to expand/collapse liquidity | Q80: 504 & USDA Worksheets | BC80: Request 1 | BE80: 504 Perm 1st
BC81: Basis | BD81: Loan Amount | BE81: Interest Rate | BF81: Term (mo) | BG81: Amo (mo) | BH81: Start Month | BI81: End Month | BJ81: # days | BK81: Interest Rate Conversion | BL81: Pmt
B82: Income Statement Spreads | BC82: 30/360 | BD82: =IF($BF$80>0,$BF$80,IF($C$65>0,$C$65,$C$33)) -> 1000 | BE82: =$C$36 -> 0.09 | BF82: =$C$38*12 -> 120 | BG82: =$C$39 -> 120 | BH82: =TODAY()+45 -> 46170 | BI82: =DATE(YEAR(BH82)+BG82/12,MONTH(BH82),DAY(BH82)) -> 49823 | BJ82: =BI82-BH82 -> 3653 | BK82: =IFERROR((BE82/360)*30*12,0) -> 0.09 | BL82: =IFERROR(PMT(BK82/12,BG82,-BD82),"Incomplete Data") -> 12.667577
B83: {Insert business name which represents PSOR} | BC83: Actual/365 | BD83: =IF($BF$80>0,$BF$80,IF($C$65>0,$C$65,$C$33)) -> 1000 | BE83: =$C$36 -> 0.09 | BF83: =$C$38*12 -> 120 | BG83: =$C$39 -> 120 | BH83: =TODAY()+45 -> 46170 | BI83: =DATE(YEAR(BH83)+BG83/12,MONTH(BH83),DAY(BH83)) -> 49823 | BJ83: =BI83-BH83 -> 3653 | BK83: =IFERROR((BE83/(365*BG83/12))*BJ83,0) -> 0.090073973 | BL83: =IFERROR(PMT(BK83/12,BG83,-BD83),"Incomplete Data") -> 12.671581
B84: Include in Global? | C84: Yes | BC84: Actual/360 | BD84: =IF($BF$80>0,$BF$80,IF($C$65>0,$C$65,$C$33)) -> 1000 | BE84: =$C$36 -> 0.09 | BF84: =$C$38*12 -> 120 | BG84: =$C$39 -> 120 | BH84: =TODAY()+45 -> 46170 | BI84: =DATE(YEAR(BH84)+BG84/12,MONTH(BH84),DAY(BH84)) -> 49823 | BJ84: =BI84-BH84 -> 3653 | BK84: =IFERROR((BE84/(360*BG84/12))*BJ84,0) -> 0.091325 | BL84: =IFERROR(PMT(BK84/12,BG84,-BD84),"Incomplete Data") -> 12.739397
B85: Statement Date | D85: 44926 | F85: =EOMONTH(D85,F86) -> 45291 | H85: =EOMONTH(F85,H86) -> 45657 | J85: =EOMONTH(H85,J86) -> 45747 | N85: Projections | P85: Projections
B86: Months Covered | D86: 12 | F86: 12 | H86: 12 | J86: 3 | N86: Customer | P86: Customer | BC86: Plus 1%
B87: Statement Type | D87: Tax Returns | F87: Tax Returns | H87: Form 10K | J87: Internal | N87: Year | P87: Year | BC87: Basis | BD87: Loan Amount | BE87: Interest Rate | BF87: Term (mo) | BG87: Amo (mo) | BH87: Start Month | BI87: End Month | BJ87: # days | BK87: Interest Rate Conversion | BL87: Pmt
B88: Revenue Recognition | D88: Accrual | F88: Accrual | H88: Cash | J88: Cash | N88: 1 | P88: 2 | BC88: 30/360 | BD88: =IF($BF$80>0,$BF$80,IF($C$65>0,$C$65,$C$33)) -> 1000 | BE88: =$C$36+1% -> 0.1 | BF88: =$C$38*12 -> 120 | BG88: =$C$39 -> 120 | BH88: =TODAY()+45 -> 46170 | BI88: =DATE(YEAR(BH88)+BG88/12,MONTH(BH88),DAY(BH88)) -> 49823 | BJ88: =BI88-BH88 -> 3653 | BK88: =IFERROR((BE88/360)*30*12,0) -> 0.1 | BL88: =IFERROR(PMT(BK88/12,BG88,-BD88),"Incomplete Data") -> 13.215074
B89: REVENUE | J89: =(J90/J86)*12 -> 0 | BC89: Actual/365 | BD89: =IF($BF$80>0,$BF$80,IF($C$65>0,$C$65,$C$33)) -> 1000 | BE89: =$C$36+1% -> 0.1 | BF89: =$C$38*12 -> 120 | BG89: =$C$39 -> 120 | BH89: =TODAY()+45 -> 46170 | BI89: =DATE(YEAR(BH89)+BG89/12,MONTH(BH89),DAY(BH89)) -> 49823 | BJ89: =BI89-BH89 -> 3653 | BK89: =IFERROR((BE89/(365*BG89/12))*BJ89,0) -> 0.10008219 | BL89: =IFERROR(PMT(BK89/12,BG89,-BD89),"Incomplete Data") -> 13.219626
B90: Revenue | C90: (Product Line #1) | D90: 6000 | E90: =IF(D$99=0,0,D90/D$99) -> 0.66666667 | F90: 700 | G90: =IF(F$99=0,0,F90/F$99) -> 0.32317636 | H90: 700 | I90: =IF(H$99=0,0,H90/H$99) -> 0.61135371 | J90: 0 | K90: =IF(J$99=0,0,J90/J$99) -> 0 | M90: Revenue (Product Line #1) | N90: 10 | O90: =IF(N$99=0,0,N90/N$99) -> 0.047619048 | P90: 20 | Q90: =IF(P$99=0,0,P90/P$99) -> 0.032258065 | BC90: Actual/360 | BD90: =IF($BF$80>0,$BF$80,IF($C$65>0,$C$65,$C$33)) -> 1000 | BE90: =$C$36+1% -> 0.1 | BF90: =$C$38*12 -> 120 | BG90: =$C$39 -> 120 | BH90: =TODAY()+45 -> 46170 | BI90: =DATE(YEAR(BH90)+BG90/12,MONTH(BH90),DAY(BH90)) -> 49823 | BJ90: =BI90-BH90 -> 3653 | BK90: =IFERROR((BE90/(360*BG90/12))*BJ90,0) -> 0.10147222 | BL90: =IFERROR(PMT(BK90/12,BG90,-BD90),"Incomplete Data") -> 13.296733
B91: COGS | C91: (Product Line #1) | E91: =IF(D$99=0,0,D91/D$99) -> 0 | F91: 0 | G91: =IF(F$99=0,0,F91/F$99) -> 0 | H91: 400 | I91: =IF(H$99=0,0,H91/H$99) -> 0.34934498 | J91: 0 | K91: =IF(J$99=0,0,J91/J$99) -> 0 | M91: COGS (Product Line #1) | N91: 30 | O91: =IF(N$99=0,0,N91/N$99) -> 0.14285714 | P91: 0 | Q91: =IF(P$99=0,0,P91/P$99) -> 0
B92: Gross Margin | C92: (Product Line #1) | D92: =D90-D91 -> 6000 | E92: =IF(D$99=0,0,D92/D$99) -> 0.66666667 | F92: =F90-F91 -> 700 | G92: =IF(F$99=0,0,F92/F$99) -> 0.32317636 | H92: =H90-H91 -> 300 | I92: =IF(H$99=0,0,H92/H$99) -> 0.26200873 | J92: =J90-J91 -> 0 | K92: =IF(J$99=0,0,J92/J$99) -> 0 | M92: Gross Margin (Product Line #1) | N92: =N90-N91 -> -20 | O92: =IF(N$99=0,0,N92/N$99) -> -0.095238095 | P92: =P90-P91 -> 20 | Q92: =IF(P$99=0,0,P92/P$99) -> 0.032258065 | BC92: Plus 2%
B93: Revenue | C93: (Product Line #2) | D93: 2000 | E93: =IF(D$99=0,0,D93/D$99) -> 0.22222222 | F93: 800 | G93: =IF(F$99=0,0,F93/F$99) -> 0.36934441 | H93: 445 | I93: =IF(H$99=0,0,H93/H$99) -> 0.38864629 | J93: 0 | K93: =IF(J$99=0,0,J93/J$99) -> 0 | M93: Revenue (Product Line #2) | N93: 0 | O93: =IF(N$99=0,0,N93/N$99) -> 0 | P93: 0 | Q93: =IF(P$99=0,0,P93/P$99) -> 0 | BC93: Basis | BD93: Loan Amount | BE93: Interest Rate | BF93: Term (mo) | BG93: Amo (mo) | BH93: Start Month | BI93: End Month | BJ93: # days | BK93: Interest Rate Conversion | BL93: Pmt
B94: COGS | C94: (Product Line #2) | D94: 0 | E94: =IF(D$99=0,0,D94/D$99) -> 0 | F94: 0 | G94: =IF(F$99=0,0,F94/F$99) -> 0 | H94: 0 | I94: =IF(H$99=0,0,H94/H$99) -> 0 | J94: 8000 | K94: =IF(J$99=0,0,J94/J$99) -> 9.0909091 | M94: COGS (Product Line #2) | N94: 0 | O94: =IF(N$99=0,0,N94/N$99) -> 0 | P94: 0 | Q94: =IF(P$99=0,0,P94/P$99) -> 0 | BC94: 30/360 | BD94: =IF($BF$80>0,$BF$80,IF($C$65>0,$C$65,$C$33)) -> 1000 | BE94: =$C$36+2% -> 0.11 | BF94: =$C$38*12 -> 120 | BG94: =$C$39 -> 120 | BH94: =TODAY()+45 -> 46170 | BI94: =DATE(YEAR(BH94)+BG94/12,MONTH(BH94),DAY(BH94)) -> 49823 | BJ94: =BI94-BH94 -> 3653 | BK94: =IFERROR((BE94/360)*30*12,0) -> 0.11 | BL94: =IFERROR(PMT(BK94/12,BG94,-BD94),"Incomplete Data") -> 13.775001
B95: Gross Margin | C95: (Product Line #2) | D95: =D93-D94 -> 2000 | E95: =IF(D$99=0,0,D95/D$99) -> 0.22222222 | F95: =F93-F94 -> 800 | G95: =IF(F$99=0,0,F95/F$99) -> 0.36934441 | H95: =H93-H94 -> 445 | I95: =IF(H$99=0,0,H95/H$99) -> 0.38864629 | J95: =J93-J94 -> -8000 | K95: =IF(J$99=0,0,J95/J$99) -> -9.0909091 | M95: Gross Margin (Product Line #2) | N95: =N93-N94 -> 0 | O95: =IF(N$99=0,0,N95/N$99) -> 0 | P95: =P93-P94 -> 0 | Q95: =IF(P$99=0,0,P95/P$99) -> 0 | BC95: Actual/365 | BD95: =IF($BF$80>0,$BF$80,IF($C$65>0,$C$65,$C$33)) -> 1000 | BE95: =$C$36+2% -> 0.11 | BF95: =$C$38*12 -> 120 | BG95: =$C$39 -> 120 | BH95: =TODAY()+45 -> 46170 | BI95: =DATE(YEAR(BH95)+BG95/12,MONTH(BH95),DAY(BH95)) -> 49823 | BJ95: =BI95-BH95 -> 3653 | BK95: =IFERROR((BE95/(365*BG95/12))*BJ95,0) -> 0.11009041 | BL95: =IFERROR(PMT(BK95/12,BG95,-BD95),"Incomplete Data") -> 13.780119
B96: Revenue | C96: (Product Line #3) | D96: 1000 | E96: =IF(D$99=0,0,D96/D$99) -> 0.11111111 | F96: 666 | G96: =IF(F$99=0,0,F96/F$99) -> 0.30747922 | H96: 0 | I96: =IF(H$99=0,0,H96/H$99) -> 0 | J96: 880 | K96: =IF(J$99=0,0,J96/J$99) -> 1 | M96: Revenue (Product Line #3) | N96: 200 | O96: =IF(N$99=0,0,N96/N$99) -> 0.95238095 | P96: 600 | Q96: =IF(P$99=0,0,P96/P$99) -> 0.96774194 | BC96: Actual/360 | BD96: =IF($BF$80>0,$BF$80,IF($C$65>0,$C$65,$C$33)) -> 1000 | BE96: =$C$36+2% -> 0.11 | BF96: =$C$38*12 -> 120 | BG96: =$C$39 -> 120 | BH96: =TODAY()+45 -> 46170 | BI96: =DATE(YEAR(BH96)+BG96/12,MONTH(BH96),DAY(BH96)) -> 49823 | BJ96: =BI96-BH96 -> 3653 | BK96: =IFERROR((BE96/(360*BG96/12))*BJ96,0) -> 0.11161944 | BL96: =IFERROR(PMT(BK96/12,BG96,-BD96),"Incomplete Data") -> 13.86683
B97: COGS | C97: (Product Line #3) | D97: 50 | E97: =IF(D$99=0,0,D97/D$99) -> 0.0055555556 | F97: 500 | G97: =IF(F$99=0,0,F97/F$99) -> 0.23084026 | H97: 0 | I97: =IF(H$99=0,0,H97/H$99) -> 0 | J97: 0 | K97: =IF(J$99=0,0,J97/J$99) -> 0 | M97: COGS (Product Line #3) | N97: 0 | O97: =IF(N$99=0,0,N97/N$99) -> 0 | P97: 0 | Q97: =IF(P$99=0,0,P97/P$99) -> 0
B98: Gross Margin | C98: (Product Line #3) | D98: =D96-D97 -> 950 | E98: =IF(D$99=0,0,D98/D$99) -> 0.10555556 | F98: =F96-F97 -> 166 | G98: =IF(F$99=0,0,F98/F$99) -> 0.076638966 | H98: =H96-H97 -> 0 | I98: =IF(H$99=0,0,H98/H$99) -> 0 | J98: =J96-J97 -> 880 | K98: =IF(J$99=0,0,J98/J$99) -> 1 | M98: Gross Margin (Product Line #3) | N98: =N96-N97 -> 200 | O98: =IF(N$99=0,0,N98/N$99) -> 0.95238095 | P98: =P96-P97 -> 600 | Q98: =IF(P$99=0,0,P98/P$99) -> 0.96774194 | BC98: Plus 3%
B99: Click to expand/collapse | C99: Total Revenue | D99: =D90+D93+D96 -> 9000 | E99: =IF(D$99=0,0,D99/D$99) -> 1 | F99: =F90+F93+F96 -> 2166 | G99: =IF(F$99=0,0,F99/F$99) -> 1 | H99: =H90+H93+H96 -> 1145 | I99: =IF(H$99=0,0,H99/H$99) -> 1 | J99: =J90+J93+J96 -> 880 | K99: =IF(J$99=0,0,J99/J$99) -> 1 | M99: Total Revenue | N99: =N90+N93+N96 -> 210 | O99: =IF(N$99=0,0,N99/N$99) -> 1 | P99: =P90+P93+P96 -> 620 | Q99: =IF(P$99=0,0,P99/P$99) -> 1 | BC99: Basis | BD99: Loan Amount | BE99: Interest Rate | BF99: Term (mo) | BG99: Amo (mo) | BH99: Start Month | BI99: End Month | BJ99: # days | BK99: Interest Rate Conversion | BL99: Pmt
C100: Total COGS | D100: =D91+D94+D97 -> 50 | E100: =IF(D$99=0,0,D100/D$99) -> 0.0055555556 | F100: =F91+F94+F97 -> 500 | G100: =IF(F$99=0,0,F100/F$99) -> 0.23084026 | H100: =H91+H94+H97 -> 400 | I100: =IF(H$99=0,0,H100/H$99) -> 0.34934498 | J100: =J91+J94+J97 -> 8000 | K100: =IF(J$99=0,0,J100/J$99) -> 9.0909091 | M100: Total COGS | N100: =N91+N94+N97 -> 30 | O100: =IF(N$99=0,0,N100/N$99) -> 0.14285714 | P100: =P91+P94+P97 -> 0 | Q100: =IF(P$99=0,0,P100/P$99) -> 0 | BC100: 30/360 | BD100: =IF($BF$80>0,$BF$80,IF($C$65>0,$C$65,$C$33)) -> 1000 | BE100: =$C$36+3% -> 0.12 | BF100: =$C$38*12 -> 120 | BG100: =$C$39 -> 120 | BH100: =TODAY()+45 -> 46170 | BI100: =DATE(YEAR(BH100)+BG100/12,MONTH(BH100),DAY(BH100)) -> 49823 | BJ100: =BI100-BH100 -> 3653 | BK100: =IFERROR((BE100/360)*30*12,0) -> 0.12 | BL100: =IFERROR(PMT(BK100/12,BG100,-BD100),"Incomplete Data") -> 14.347095
C101: Total Gross Margin | D101: =D99-D100 -> 8950 | E101: =IF(D$99=0,0,D101/D$99) -> 0.99444444 | F101: =F99-F100 -> 1666 | G101: =IF(F$99=0,0,F101/F$99) -> 0.76915974 | H101: =H99-H100 -> 745 | I101: =IF(H$99=0,0,H101/H$99) -> 0.65065502 | J101: =J99-J100 -> -7120 | K101: =IF(J$99=0,0,J101/J$99) -> -8.0909091 | M101: Total Gross Margin | N101: =N99-N100 -> 180 | O101: =IF(N$99=0,0,N101/N$99) -> 0.85714286 | P101: =P99-P100 -> 620 | Q101: =IF(P$99=0,0,P101/P$99) -> 1 | BC101: Actual/365 | BD101: =IF($BF$80>0,$BF$80,IF($C$65>0,$C$65,$C$33)) -> 1000 | BE101: =$C$36+3% -> 0.12 | BF101: =$C$38*12 -> 120 | BG101: =$C$39 -> 120 | BH101: =TODAY()+45 -> 46170 | BI101: =DATE(YEAR(BH101)+BG101/12,MONTH(BH101),DAY(BH101)) -> 49823 | BJ101: =BI101-BH101 -> 3653 | BK101: =IFERROR((BE101/(365*BG101/12))*BJ101,0) -> 0.12009863 | BL101: =IFERROR(PMT(BK101/12,BG101,-BD101),"Incomplete Data") -> 14.352797
BC102: Actual/360 | BD102: =IF($BF$80>0,$BF$80,IF($C$65>0,$C$65,$C$33)) -> 1000 | BE102: =$C$36+3% -> 0.12 | BF102: =$C$38*12 -> 120 | BG102: =$C$39 -> 120 | BH102: =TODAY()+45 -> 46170 | BI102: =DATE(YEAR(BH102)+BG102/12,MONTH(BH102),DAY(BH102)) -> 49823 | BJ102: =BI102-BH102 -> 3653 | BK102: =IFERROR((BE102/(360*BG102/12))*BJ102,0) -> 0.12176667 | BL102: =IFERROR(PMT(BK102/12,BG102,-BD102),"Incomplete Data") -> 14.449408
C103: OPERATING EXPENSES | M103: OPERATING EXPENSES
C104: Officer's Compensation | D104: 0 | E104: =IF(D$99=0,0,D104/D$99) -> 0 | F104: 0 | G104: =IF(F$99=0,0,F104/F$99) -> 0 | H104: 0 | I104: =IF(H$99=0,0,H104/H$99) -> 0 | J104: 0 | K104: =IF(J$99=0,0,J104/J$99) -> 0 | M104: Officer's Compensation | N104: 6223 | O104: =IF(N$99=0,0,N104/N$99) -> 29.633333 | P104: 0 | Q104: =IF(P$99=0,0,P104/P$99) -> 0 | BC104: Plus 4%
C105: Salaries & Wages | D105: 800 | E105: =IF(D$99=0,0,D105/D$99) -> 0.088888889 | F105: 800 | G105: =IF(F$99=0,0,F105/F$99) -> 0.36934441 | H105: 500 | I105: =IF(H$99=0,0,H105/H$99) -> 0.43668122 | J105: 5000 | K105: =IF(J$99=0,0,J105/J$99) -> 5.6818182 | M105: Salaries & Wages | N105: 1 | O105: =IF(N$99=0,0,N105/N$99) -> 0.0047619048 | P105: 980 | Q105: =IF(P$99=0,0,P105/P$99) -> 1.5806452 | BC105: Basis | BD105: Loan Amount | BE105: Interest Rate | BF105: Term (mo) | BG105: Amo (mo) | BH105: Start Month | BI105: End Month | BJ105: # days | BK105: Interest Rate Conversion | BL105: Pmt
C106: Repairs & Maintenance | D106: 0 | E106: =IF(D$99=0,0,D106/D$99) -> 0 | F106: 0 | G106: =IF(F$99=0,0,F106/F$99) -> 0 | H106: 0 | I106: =IF(H$99=0,0,H106/H$99) -> 0 | J106: 0 | K106: =IF(J$99=0,0,J106/J$99) -> 0 | M106: Repairs & Maintenance | N106: 233 | O106: =IF(N$99=0,0,N106/N$99) -> 1.1095238 | P106: 5121 | Q106: =IF(P$99=0,0,P106/P$99) -> 8.2596774 | BC106: 30/360 | BD106: =IF($BF$80>0,$BF$80,IF($C$65>0,$C$65,$C$33)) -> 1000 | BE106: =$C$36+4% -> 0.13 | BF106: =$C$38*12 -> 120 | BG106: =$C$39 -> 120 | BH106: =TODAY()+45 -> 46170 | BI106: =DATE(YEAR(BH106)+BG106/12,MONTH(BH106),DAY(BH106)) -> 49823 | BJ106: =BI106-BH106 -> 3653 | BK106: =IFERROR((BE106/360)*30*12,0) -> 0.13 | BL106: =IFERROR(PMT(BK106/12,BG106,-BD106),"Incomplete Data") -> 14.931074
C107: Bad Debts | D107: 0 | E107: =IF(D$99=0,0,D107/D$99) -> 0 | F107: 0 | G107: =IF(F$99=0,0,F107/F$99) -> 0 | H107: 0 | I107: =IF(H$99=0,0,H107/H$99) -> 0 | J107: 0 | K107: =IF(J$99=0,0,J107/J$99) -> 0 | M107: Bad Debts | N107: 1 | O107: =IF(N$99=0,0,N107/N$99) -> 0.0047619048 | P107: 212 | Q107: =IF(P$99=0,0,P107/P$99) -> 0.34193548 | BC107: Actual/365 | BD107: =IF($BF$80>0,$BF$80,IF($C$65>0,$C$65,$C$33)) -> 1000 | BE107: =$C$36+4% -> 0.13 | BF107: =$C$38*12 -> 120 | BG107: =$C$39 -> 120 | BH107: =TODAY()+45 -> 46170 | BI107: =DATE(YEAR(BH107)+BG107/12,MONTH(BH107),DAY(BH107)) -> 49823 | BJ107: =BI107-BH107 -> 3653 | BK107: =IFERROR((BE107/(365*BG107/12))*BJ107,0) -> 0.13010685 | BL107: =IFERROR(PMT(BK107/12,BG107,-BD107),"Incomplete Data") -> 14.937377
C108: Rents | D108: 0 | E108: =IF(D$99=0,0,D108/D$99) -> 0 | F108: 0 | G108: =IF(F$99=0,0,F108/F$99) -> 0 | H108: 0 | I108: =IF(H$99=0,0,H108/H$99) -> 0 | J108: 0 | K108: =IF(J$99=0,0,J108/J$99) -> 0 | M108: Rents | N108: 20 | O108: =IF(N$99=0,0,N108/N$99) -> 0.095238095 | P108: 1 | Q108: =IF(P$99=0,0,P108/P$99) -> 0.0016129032 | BC108: Actual/360 | BD108: =IF($BF$80>0,$BF$80,IF($C$65>0,$C$65,$C$33)) -> 1000 | BE108: =$C$36+4% -> 0.13 | BF108: =$C$38*12 -> 120 | BG108: =$C$39 -> 120 | BH108: =TODAY()+45 -> 46170 | BI108: =DATE(YEAR(BH108)+BG108/12,MONTH(BH108),DAY(BH108)) -> 49823 | BJ108: =BI108-BH108 -> 3653 | BK108: =IFERROR((BE108/(360*BG108/12))*BJ108,0) -> 0.13191389 | BL108: =IFERROR(PMT(BK108/12,BG108,-BD108),"Incomplete Data") -> 15.044172
C109: Taxes & Licenses | D109: 0 | E109: =IF(D$99=0,0,D109/D$99) -> 0 | F109: 0 | G109: =IF(F$99=0,0,F109/F$99) -> 0 | H109: 0 | I109: =IF(H$99=0,0,H109/H$99) -> 0 | J109: 0 | K109: =IF(J$99=0,0,J109/J$99) -> 0 | M109: Taxes & Licenses | N109: 1 | O109: =IF(N$99=0,0,N109/N$99) -> 0.0047619048 | P109: 2 | Q109: =IF(P$99=0,0,P109/P$99) -> 0.0032258065
C110: Interest | D110: 0 | E110: =IF(D$99=0,0,D110/D$99) -> 0 | F110: 0 | G110: =IF(F$99=0,0,F110/F$99) -> 0 | H110: 0 | I110: =IF(H$99=0,0,H110/H$99) -> 0 | J110: 0 | K110: =IF(J$99=0,0,J110/J$99) -> 0 | M110: Interest | N110: 233 | O110: =IF(N$99=0,0,N110/N$99) -> 1.1095238 | P110: 2 | Q110: =IF(P$99=0,0,P110/P$99) -> 0.0032258065
C111: Depreciation & Amortization | D111: 0 | E111: =IF(D$99=0,0,D111/D$99) -> 0 | F111: 0 | G111: =IF(F$99=0,0,F111/F$99) -> 0 | H111: 0 | I111: =IF(H$99=0,0,H111/H$99) -> 0 | J111: 0 | K111: =IF(J$99=0,0,J111/J$99) -> 0 | M111: Depreciation & Amortization | N111: 20 | O111: =IF(N$99=0,0,N111/N$99) -> 0.095238095 | P111: 3 | Q111: =IF(P$99=0,0,P111/P$99) -> 0.0048387097
C112: Advertising | D112: 0 | E112: =IF(D$99=0,0,D112/D$99) -> 0 | F112: 0 | G112: =IF(F$99=0,0,F112/F$99) -> 0 | H112: 0 | I112: =IF(H$99=0,0,H112/H$99) -> 0 | J112: 0 | K112: =IF(J$99=0,0,J112/J$99) -> 0 | M112: Advertising | N112: 1 | O112: =IF(N$99=0,0,N112/N$99) -> 0.0047619048 | P112: 2 | Q112: =IF(P$99=0,0,P112/P$99) -> 0.0032258065
C113: Pension, Profit Sharing | D113: 0 | E113: =IF(D$99=0,0,D113/D$99) -> 0 | F113: 0 | G113: =IF(F$99=0,0,F113/F$99) -> 0 | H113: 0 | I113: =IF(H$99=0,0,H113/H$99) -> 0 | J113: 0 | K113: =IF(J$99=0,0,J113/J$99) -> 0 | M113: Pension, Profit Sharing | N113: 1 | O113: =IF(N$99=0,0,N113/N$99) -> 0.0047619048 | P113: 4 | Q113: =IF(P$99=0,0,P113/P$99) -> 0.0064516129
C114: Employee Benefits | D114: 0 | E114: =IF(D$99=0,0,D114/D$99) -> 0 | F114: 0 | G114: =IF(F$99=0,0,F114/F$99) -> 0 | H114: 0 | I114: =IF(H$99=0,0,H114/H$99) -> 0 | J114: 0 | K114: =IF(J$99=0,0,J114/J$99) -> 0 | M114: Employee Benefits | N114: 1 | O114: =IF(N$99=0,0,N114/N$99) -> 0.0047619048 | P114: 5 | Q114: =IF(P$99=0,0,P114/P$99) -> 0.0080645161
C115: Insurance | D115: 0 | E115: =IF(D$99=0,0,D115/D$99) -> 0 | F115: 0 | G115: =IF(F$99=0,0,F115/F$99) -> 0 | H115: 0 | I115: =IF(H$99=0,0,H115/H$99) -> 0 | J115: 0 | K115: =IF(J$99=0,0,J115/J$99) -> 0 | M115: Insurance | N115: 1 | O115: =IF(N$99=0,0,N115/N$99) -> 0.0047619048 | P115: 6 | Q115: =IF(P$99=0,0,P115/P$99) -> 0.0096774194
C116: Utilities, Telephone, Cable, Internet | D116: 0 | E116: =IF(D$99=0,0,D116/D$99) -> 0 | F116: 0 | G116: =IF(F$99=0,0,F116/F$99) -> 0 | H116: 0 | I116: =IF(H$99=0,0,H116/H$99) -> 0 | J116: 0 | K116: =IF(J$99=0,0,J116/J$99) -> 0 | M116: Utilities, Telephone, Cable, Internet | N116: 1 | O116: =IF(N$99=0,0,N116/N$99) -> 0.0047619048 | P116: 384 | Q116: =IF(P$99=0,0,P116/P$99) -> 0.61935484
C117: Legal, Professional, Accounting | D117: 0 | E117: =IF(D$99=0,0,D117/D$99) -> 0 | F117: 0 | G117: =IF(F$99=0,0,F117/F$99) -> 0 | H117: 0 | I117: =IF(H$99=0,0,H117/H$99) -> 0 | J117: 0 | K117: =IF(J$99=0,0,J117/J$99) -> 0 | M117: Legal, Professional, Accounting | N117: 1 | O117: =IF(N$99=0,0,N117/N$99) -> 0.0047619048 | P117: 0 | Q117: =IF(P$99=0,0,P117/P$99) -> 0
...

Sheet Scores
B2: T Bank, N.A. SCORING GRID
B3: Total Score | C3: REPAYMENT | D3: MANAGEMENT | E3: CREDIT | F3: EQUITY | G3: COLLATERAL | H3: Working Capital/Liquidity
B4: =SUM(C4:H4) -> 0
B5: 5 | C5: Pro forma DSC of 1.40x in the most recent year and 1.25x or better for the prior 2 years plus stable/positive trends in the interim. Stable is considered + - 0.05 change in DSC. | D5: 3 or more years ownership in SBC or 3 years as primary responsible employee in SBC or 5 years recent experience in near identical type business as Principal Manager with P&L and HR responsibility. | E5: N/A | F5: 25% cash equity from personal sources Expansions: pro forma tangible D/W of 4:1 or less. | G5: Secured 120% of the loan on a discounted basis with any collateral or 100% secured with 1st lien on RE. 504 1st lien No construction | H5: N/A
B6: 4 | C6: Pro forma DSC of 1.40x or better for most recent years plus 1.25x for the 1 prior year plus stable/positive trends in the interim. Stable is considered + - 0.05 change in DSC. | D6: 2 or more years ownership in SBC or 3 years experience in near identical type business. For startups - this experience, must have been within the last 5 years AND one of the guarantors will devote 100% of time to SBC | E6: FICO Score greater than 750. | F6: 25% cash equity from any source or 20% from personal sources Expansions: pro forma tangible D/W of 5:1 or less. | G6: Secured 100% of the loan on a discounted basis with any collateral or 75% with 1st lien on RE. 504 1st Lien Construction | H6: N/A
B7: 3 | C7: Pro forma DSC of an 1.25x or better in most recent FYE and interim plus stable/positive trends in the interim. Stable is considered + - 0.05 change in DSC. Regardless of DSC declining revenue or profitability trends in the most recent year and/or interim. | D7: 2 years ownership in any industry or 3 years of transferable management experience in any industry, or approved franchise For startups - this experience, must have been within the last 5 years AND one of the guarantors will devote 100% of time to SBC. | E7: FICO Score of 700 to 749. Regardless of any higher FICO score BK between 3 and 5 years in time. Regardless of any higher FICO score expected continuing income of between $5500 and $6000 for every $1000 of CC debt | F7: 20% cash equity from any source or 15% from personal sources Expansions: pro forma tangible D/W of 6:1 or less. | G7: Secured 75% of the loan on a discounted basis with any collateral or 50% with 1st lien on RE. | H7: No or minimal working capital requirement OR Borrower has 1.5X working capital from own liquid resources. Minimal is the lesser of 5% of loan amount or $50K. None is included in loan.
B8: 2 | C8: Pro forma DSC of 1.15x or better in most recent FYE and interim plus positive trends in the interim. Regardless of DSC declining revenue or profitability trends in all periods Projection Based or Start Up with Approved Franchise. | D8: 2 years transferable management experience not specific to this industry or non-approved franchise. For startups - this experience must have been within the last 3 years AND one of the guarantors will 100% of time devoted to SBC | E8: FICO Score 650 to 699 Regardless of any higher FICO score expected continuing income of between $5000 and $5499 for every $1000 of CC debt | F8: 10% cash equity from any source Expansions: pro forma tangible D/W of 8:1 or less. | G8: Secured 50% of the loan on a discounted basis with any collateral or 25% with 1st lien on RE. | H8: Borrower has sufficient documented working Capital to inject from own resources (WC as calculated by U/W). In loan is OK as long as borrower has 1x or greater residual liquidity.
B9: 1 | C9: Projection based or start-up. | D9: Less than 2 years transferable management experience OR reliant on prior owner or franchisor for training. For startups - the experience was over 3 years ago. | E9: FICO Score less than 650 Regardless of any higher FICO score expected continuing income of between $4500 and $4999 for every $1000 of CC debt | F9: Less than 10% injection and/or 50% or more Equity is from Seller note on full standby | G9: < 50% secured with any collateral or less than 25% 1st lien on RE. | H9: All, or substantially all of W/C is included in loan or companion loan and borrower has little or no residual liquidity.
B10: 0 | C10: N/A | D10: Remote management or long distance management with no prior experience of remote management. | E10: BK in the last 3 years. Regardless of any higher FICO score expected continuing income of less than $4500 for every $1000 of CC debt | F10: Any other allowable SBA SOP structure that does not require injection. | G10: No CRE included in collateral or only junior liens on residential. | H10: Working capital included in loan proceeds exceeds 50% of borrower cash injection.
C14: ='BDO Prequal'!B73 -> Owner/Guarantor 1 | E14: ='BDO Prequal'!B74 -> Owner/Guarantor 2 | G14: ='BDO Prequal'!B75 -> Owner/Guarantor 3
C15: Income | D15: ='BDO Prequal'!C632 -> 0 | E15: Income | F15: ='BDO Prequal'!E632 -> 0 | G15: Income | H15: ='BDO Prequal'!G632 -> 0
C16: CC Debt | D16: 0 | E16: CC Debt | F16: 0 | G16: CC Debt | H16: 0
C17: Income Needed $4,500 | D17: =D16*4.5 -> 0 | E17: Income Needed $4,500 | F17: =F16*4.5 -> 0 | G17: Income Needed $4,500 | H17: =H16*4.5 -> 0
C18: Income Needed $4,999 | D18: =D16*4.999 -> 0 | E18: Income Needed $4,999 | F18: =F16*4.999 -> 0 | G18: Income Needed $4,999 | H18: =H16*4.999 -> 0
C19: Income Needed $5,499 | D19: =D16*5.499 -> 0 | E19: Income Needed $5,499 | F19: =F16*5.499 -> 0 | G19: Income Needed $5,499 | H19: =H16*5.499 -> 0
C20: Income Needed $6,000+ | D20: =D16*6 -> 0 | E20: Income Needed $6,000+ | F20: =F16*6 -> 0 | G20: Income Needed $6,000+ | H20: =H16*6 -> 0
C21: ='BDO Prequal'!B76 -> Owner/Guarantor 4
C22: Income | D22: ='BDO Prequal'!I632 -> 0 | E22: Income | F22: 0 | G22: Income | H22: 0
C23: CC Debt | D23: 0 | E23: CC Debt | F23: 0 | G23: CC Debt | H23: 0
C24: Income Needed $4,500 | D24: =D23*4.5 -> 0 | E24: Income Needed $4,500 | F24: =F23*4.5 -> 0 | G24: Income Needed $4,500 | H24: =H23*4.5 -> 0
C25: Income Needed $4,999 | D25: =D23*4.999 -> 0 | E25: Income Needed $4,999 | F25: =F23*4.999 -> 0 | G25: Income Needed $4,999 | H25: =H23*4.999 -> 0
C26: Income Needed $5,499 | D26: =D23*5.499 -> 0 | E26: Income Needed $5,499 | F26: =F23*5.499 -> 0 | G26: Income Needed $5,499 | H26: =H23*5.499 -> 0
C27: Income Needed $6,000+ | D27: =D23*6 -> 0 | E27: Income Needed $6,000+ | F27: =F23*6 -> 0 | G27: Income Needed $6,000+ | H27: =H23*6 -> 0

Sheet Charts
B3: Loan Request | I3: Loan Request | N3: Loan Request | T3: Loan Request
C5: ='BDO Prequal'!C47 -> P&E | D5: ='BDO Prequal'!H47 -> Equity | E5: ='BDO Prequal'!I47 -> Seller Note | F5: ='BDO Prequal'!J47 -> 3rd Party | G5: ='BDO Prequal'!K47 -> Total | J5: =C5 -> P&E | K5: =D5 -> Equity | L5: =G5 -> Total | O5: =C5 -> P&E | P5: =D5 -> Equity | Q5: =E5 -> Seller Note | R5: =G5 -> Total | U5: =C5 -> P&E | V5: =D5 -> Equity | W5: =F5 -> 3rd Party | X5: =G5 -> Total
B6: ='BDO Prequal'!B49 -> Real Estate Acquisition | C6: ='BDO Prequal'!C49 -> 896000 | D6: ='BDO Prequal'!H49 -> 8000 | E6: ='BDO Prequal'!I49 -> 80000 | F6: ='BDO Prequal'!J49 -> 16000 | G6: ='BDO Prequal'!K49 -> 1000000 | I6: =B6 -> Real Estate Acquisition | J6: =C6 -> 896000 | K6: =D6 -> 8000 | L6: =G6 -> 1000000 | N6: =B6 -> Real Estate Acquisition | O6: =C6 -> 896000 | P6: =D6 -> 8000 | Q6: =E6 -> 80000 | R6: =G6 -> 1000000 | T6: =B6 -> Real Estate Acquisition | U6: =C6 -> 896000 | V6: =D6 -> 8000 | W6: =F6 -> 16000 | X6: =G6 -> 1000000
B7: ='BDO Prequal'!B50 -> Debt Refi - CRE | C7: ='BDO Prequal'!C50 -> 5387 | D7: ='BDO Prequal'!H50 -> 10 | E7: ='BDO Prequal'!I50 -> 1 | F7: ='BDO Prequal'!J50 -> 2 | G7: ='BDO Prequal'!K50 -> 5400 | I7: =B7 -> Debt Refi - CRE | J7: =C7 -> 5387 | K7: =D7 -> 10 | L7: =G7 -> 5400 | N7: =B7 -> Debt Refi - CRE | O7: =C7 -> 5387 | P7: =D7 -> 10 | Q7: =E7 -> 1 | R7: =G7 -> 5400 | T7: =B7 -> Debt Refi - CRE | U7: =C7 -> 5387 | V7: =D7 -> 10 | W7: =F7 -> 2 | X7: =G7 -> 5400
B8: ='BDO Prequal'!B51 -> Debt Refi - Non-CRE | C8: ='BDO Prequal'!C51 -> 55987 | D8: ='BDO Prequal'!H51 -> 10 | E8: ='BDO Prequal'!I51 -> 1 | F8: ='BDO Prequal'!J51 -> 2 | G8: ='BDO Prequal'!K51 -> 56000 | I8: =B8 -> Debt Refi - Non-CRE | J8: =C8 -> 55987 | K8: =D8 -> 10 | L8: =G8 -> 56000 | N8: =B8 -> Debt Refi - Non-CRE | O8: =C8 -> 55987 | P8: =D8 -> 10 | Q8: =E8 -> 1 | R8: =G8 -> 56000 | T8: =B8 -> Debt Refi - Non-CRE | U8: =C8 -> 55987 | V8: =D8 -> 10 | W8: =F8 -> 2 | X8: =G8 -> 56000
B9: ='BDO Prequal'!B52 -> Machinery & Equipment | C9: ='BDO Prequal'!C52 -> 4499 | D9: ='BDO Prequal'!H52 -> 10 | E9: ='BDO Prequal'!I52 -> 1 | F9: ='BDO Prequal'!J52 -> 2 | G9: ='BDO Prequal'!K52 -> 4512 | I9: =B9 -> Machinery & Equipment | J9: =C9 -> 4499 | K9: =D9 -> 10 | L9: =G9 -> 4512 | N9: =B9 -> Machinery & Equipment | O9: =C9 -> 4499 | P9: =D9 -> 10 | Q9: =E9 -> 1 | R9: =G9 -> 4512 | T9: =B9 -> Machinery & Equipment | U9: =C9 -> 4499 | V9: =D9 -> 10 | W9: =F9 -> 2 | X9: =G9 -> 4512
B10: ='BDO Prequal'!B53 -> Furniture & Fixtures (TIs) | C10: ='BDO Prequal'!C53 -> 2499 | D10: ='BDO Prequal'!H53 -> 10 | E10: ='BDO Prequal'!I53 -> 1 | F10: ='BDO Prequal'!J53 -> 2 | G10: ='BDO Prequal'!K53 -> 2512 | I10: =B10 -> Furniture & Fixtures (TIs) | J10: =C10 -> 2499 | K10: =D10 -> 10 | L10: =G10 -> 2512 | N10: =B10 -> Furniture & Fixtures (TIs) | O10: =C10 -> 2499 | P10: =D10 -> 10 | Q10: =E10 -> 1 | R10: =G10 -> 2512 | T10: =B10 -> Furniture & Fixtures (TIs) | U10: =C10 -> 2499 | V10: =D10 -> 10 | W10: =F10 -> 2 | X10: =G10 -> 2512
B11: ='BDO Prequal'!B54 -> Inventory | C11: ='BDO Prequal'!C54 -> 4202 | D11: ='BDO Prequal'!H54 -> 10 | E11: ='BDO Prequal'!I54 -> 1 | F11: ='BDO Prequal'!J54 -> 2 | G11: ='BDO Prequal'!K54 -> 4215 | I11: =B11 -> Inventory | J11: =C11 -> 4202 | K11: =D11 -> 10 | L11: =G11 -> 4215 | N11: =B11 -> Inventory | O11: =C11 -> 4202 | P11: =D11 -> 10 | Q11: =E11 -> 1 | R11: =G11 -> 4215 | T11: =B11 -> Inventory | U11: =C11 -> 4202 | V11: =D11 -> 10 | W11: =F11 -> 2 | X11: =G11 -> 4215
B12: ='BDO Prequal'!B55 -> Working Capital | C12: ='BDO Prequal'!C55 -> 84348 | D12: ='BDO Prequal'!H55 -> 10 | E12: ='BDO Prequal'!I55 -> 1 | F12: ='BDO Prequal'!J55 -> 2 | G12: ='BDO Prequal'!K55 -> 84361 | I12: =B12 -> Working Capital | J12: =C12 -> 84348 | K12: =D12 -> 10 | L12: =G12 -> 84361 | N12: =B12 -> Working Capital | O12: =C12 -> 84348 | P12: =D12 -> 10 | Q12: =E12 -> 1 | R12: =G12 -> 84361 | T12: =B12 -> Working Capital | U12: =C12 -> 84348 | V12: =D12 -> 10 | W12: =F12 -> 2 | X12: =G12 -> 84361
B13: ='BDO Prequal'!B56 -> Working Capital - Pre Opening | C13: ='BDO Prequal'!C56 -> 58397 | D13: ='BDO Prequal'!H56 -> 10 | E13: ='BDO Prequal'!I56 -> 1 | F13: ='BDO Prequal'!J56 -> 2 | G13: ='BDO Prequal'!K56 -> 58410 | I13: =B13 -> Working Capital - Pre Opening | J13: =C13 -> 58397 | K13: =D13 -> 10 | L13: =G13 -> 58410 | N13: =B13 -> Working Capital - Pre Opening | O13: =C13 -> 58397 | P13: =D13 -> 10 | Q13: =E13 -> 1 | R13: =G13 -> 58410 | T13: =B13 -> Working Capital - Pre Opening | U13: =C13 -> 58397 | V13: =D13 -> 10 | W13: =F13 -> 2 | X13: =G13 -> 58410
B14: ='BDO Prequal'!B57 -> Business Acquisition | C14: ='BDO Prequal'!C57 -> 2919 | D14: ='BDO Prequal'!H57 -> 10 | E14: ='BDO Prequal'!I57 -> 1 | F14: ='BDO Prequal'!J57 -> 2 | G14: ='BDO Prequal'!K57 -> 2932 | I14: =B14 -> Business Acquisition | J14: =C14 -> 2919 | K14: =D14 -> 10 | L14: =G14 -> 2932 | N14: =B14 -> Business Acquisition | O14: =C14 -> 2919 | P14: =D14 -> 10 | Q14: =E14 -> 1 | R14: =G14 -> 2932 | T14: =B14 -> Business Acquisition | U14: =C14 -> 2919 | V14: =D14 -> 10 | W14: =F14 -> 2 | X14: =G14 -> 2932
B15: ='BDO Prequal'!B58 -> Franchise Fees | C15: ='BDO Prequal'!C58 -> 3593 | D15: ='BDO Prequal'!H58 -> 10 | E15: ='BDO Prequal'!I58 -> 1 | F15: ='BDO Prequal'!J58 -> 2 | G15: ='BDO Prequal'!K58 -> 3606 | I15: =B15 -> Franchise Fees | J15: =C15 -> 3593 | K15: =D15 -> 10 | L15: =G15 -> 3606 | N15: =B15 -> Franchise Fees | O15: =C15 -> 3593 | P15: =D15 -> 10 | Q15: =E15 -> 1 | R15: =G15 -> 3606 | T15: =B15 -> Franchise Fees | U15: =C15 -> 3593 | V15: =D15 -> 10 | W15: =F15 -> 2 | X15: =G15 -> 3606
B16: ='BDO Prequal'!B59 -> Construction Hard Costs | C16: ='BDO Prequal'!C59 -> 45097 | D16: ='BDO Prequal'!H59 -> 10 | E16: ='BDO Prequal'!I59 -> 1 | F16: ='BDO Prequal'!J59 -> 2 | G16: ='BDO Prequal'!K59 -> 45110 | I16: =B16 -> Construction Hard Costs | J16: =C16 -> 45097 | K16: =D16 -> 10 | L16: =G16 -> 45110 | N16: =B16 -> Construction Hard Costs | O16: =C16 -> 45097 | P16: =D16 -> 10 | Q16: =E16 -> 1 | R16: =G16 -> 45110 | T16: =B16 -> Construction Hard Costs | U16: =C16 -> 45097 | V16: =D16 -> 10 | W16: =F16 -> 2 | X16: =G16 -> 45110
B17: ='BDO Prequal'!B60 -> Interim Interest Reserve | C17: ='BDO Prequal'!C60 -> 8000 | D17: ='BDO Prequal'!H60 -> 373817 | E17: ='BDO Prequal'!I60 -> 8000 | F17: ='BDO Prequal'!J60 -> 800 | G17: ='BDO Prequal'!K60 -> 381817 | I17: =B17 -> Interim Interest Reserve | J17: =C17 -> 8000 | K17: =D17 -> 373817 | L17: =G17 -> 381817 | N17: =B17 -> Interim Interest Reserve | O17: =C17 -> 8000 | P17: =D17 -> 373817 | Q17: =E17 -> 8000 | R17: =G17 -> 381817 | T17: =B17 -> Interim Interest Reserve | U17: =C17 -> 8000 | V17: =D17 -> 373817 | W17: =F17 -> 800 | X17: =G17 -> 381817
... B21: ='BDO Prequal'!B64 -> SBA Gty Fee | C21: ='BDO Prequal'!C64 -> 5050 | D21: ='BDO Prequal'!H64 -> -5050 | E21: ='BDO Prequal'!I64 -> 0 | F21: ='BDO Prequal'!J64 -> 0 | G21: ='BDO Prequal'!K64 -> 0 | I21: =B21 -> SBA Gty Fee | J21: =C21 -> 5050 | K21: =D21 -> -5050 | L21: =G21 -> 0 | N21: =B21 -> SBA Gty Fee | O21: =C21 -> 5050 | P21: =D21 -> -5050 | Q21: =E21 -> 0 | R21: =G21 -> 0 | T21: =B21 -> SBA Gty Fee | U21: =C21 -> 5050 | V21: =D21 -> -5050 | W21: =F21 -> 0 | X21: =G21 -> 0
B22: Project Total | C22: ='BDO Prequal'!C65 -> -115502 | D22: ='BDO Prequal'!H65 -> 1336917 | E22: ='BDO Prequal'!I65 -> 257182 | F22: ='BDO Prequal'!J65 -> 214570 | G22: ='BDO Prequal'!K65 -> 1684367 | I22: =B22 -> Project Total | J22: =C22 -> -115502 | K22: =D22 -> 1336917 | L22: =G22 -> 1684367 | N22: =B22 -> Project Total | O22: =C22 -> -115502 | P22: =D22 -> 1336917 | Q22: =E22 -> 257182 | R22: =G22 -> 1684367 | T22: =B22 -> Project Total | U22: =C22 -> -115502 | V22: =D22 -> 1336917 | W22: =F22 -> 214570 | X22: =G22 -> 1684367
B23: Percentages | C23: ='BDO Prequal'!C66 -> -0.068572942 | D23: ='BDO Prequal'!H66 -> 0.79372073 | E23: ='BDO Prequal'!I66 -> 0.15268763 | F23: ='BDO Prequal'!J66 -> 0.1273891 | G23: ='BDO Prequal'!K66 -> 1 | I23: =B23 -> Percentages | J23: =C23 -> -0.068572942 | K23: =D23 -> 0.79372073 | L23: =G23 -> 1 | N23: =B23 -> Percentages | O23: =C23 -> -0.068572942 | P23: =D23 -> 0.79372073 | Q23: =E23 -> 0.15268763 | R23: =G23 -> 1 | T23: =B23 -> Percentages | U23: =C23 -> -0.068572942 | V23: =D23 -> 0.79372073 | W23: =F23 -> 0.1273891 | X23: =G23 -> 1
B26: Closing & 3rd Party Costs
B27: (Estimated)
B28: ='BDO Prequal'!S30 -> Loan Packaging Fee | C28: ='BDO Prequal'!T30 -> 2500 | D28: ='BDO Prequal'!U30 -> 1 | E28: ='BDO Prequal'!V30 -> 2500
B29: ='BDO Prequal'!Q31 -> Title Insurance | C29: ='BDO Prequal'!R31 -> 0 | D29: ='BDO Prequal'!S31 -> 0 | E29: ='BDO Prequal'!T31 -> 0
B30: ='BDO Prequal'!Q32 -> Real Estate Tax Fee | C30: ='BDO Prequal'!R32 -> 0 | D30: ='BDO Prequal'!S32 -> 0 | E30: ='BDO Prequal'!T32 -> 0
B31: ='BDO Prequal'!Q33 -> Survey Charges | C31: ='BDO Prequal'!R33 -> 3000 | D31: ='BDO Prequal'!S33 -> 0 | E31: ='BDO Prequal'!T33 -> 0
B32: ='BDO Prequal'!Q34 -> CRE Appraisal | C32: ='BDO Prequal'!R34 -> 3500 | D32: ='BDO Prequal'!S34 -> 0 | E32: ='BDO Prequal'!T34 -> 0
B33: ='BDO Prequal'!Q35 -> Equipment Appraisal | C33: ='BDO Prequal'!R35 -> 0 | D33: ='BDO Prequal'!S35 -> 0 | E33: ='BDO Prequal'!T35 -> 0
B34: ='BDO Prequal'!Q36 -> Appraisal Review | C34: ='BDO Prequal'!R36 -> 0 | D34: ='BDO Prequal'!S36 -> 0 | E34: ='BDO Prequal'!T36 -> 0
B35: ='BDO Prequal'!Q37 -> Site Visit | C35: ='BDO Prequal'!R37 -> 350 | D35: ='BDO Prequal'!S37 -> 0 | E35: ='BDO Prequal'!T37 -> 0
B36: ='BDO Prequal'!Q38 -> Environmental Investigation | C36: ='BDO Prequal'!R38 -> 2500 | D36: ='BDO Prequal'!S38 -> 0 | E36: ='BDO Prequal'!T38 -> 0
B37: ='BDO Prequal'!Q39 -> Business Valuation | C37: ='BDO Prequal'!R39 -> 2500 | D37: ='BDO Prequal'!S39 -> 0 | E37: ='BDO Prequal'!T39 -> 0
B38: ='BDO Prequal'!Q40 -> Residential Appr / Valuation | C38: ='BDO Prequal'!R40 -> 0 | D38: ='BDO Prequal'!S40 -> 0 | E38: ='BDO Prequal'!T40 -> 0
B39: ='BDO Prequal'!Q41 -> Attorney Doc Prep | C39: ='BDO Prequal'!R41 -> 6000 | D39: ='BDO Prequal'!S41 -> 1 | E39: ='BDO Prequal'!T41 -> 6000
B40: ='BDO Prequal'!Q42 -> Interim Loan Fee / Origination | C40: ='BDO Prequal'!R42 -> 0 | D40: ='BDO Prequal'!S42 -> 1 | E40: ='BDO Prequal'!T42 -> 0
... B42: ='BDO Prequal'!Q44 -> Rounding | C42: ='BDO Prequal'!R44 -> 700 | D42: ='BDO Prequal'!S44 -> 1 | E42: ='BDO Prequal'!T44 -> 700
B43: ='BDO Prequal'!Q45 -> Other: UCCs and Misc Closing | C43: ='BDO Prequal'!T45 -> 800 | D43: 1 | E43: ='BDO Prequal'!T45 -> 800
B44: Total Estimated Closing Costs | E44: ='BDO Prequal'!T46 -> 0
B47: Structure Table
C49: ='BDO Prequal'!C31 -> T Bank Loan | D49: ='BDO Prequal'!I31 -> Seller Note | E49: ='BDO Prequal'!J31 -> 3rd Party
B50: Loan Amount | C50: ='BDO Prequal'!C33 -> 1000 | D50: ='BDO Prequal'!I33 -> 7 | E50: ='BDO Prequal'!J33 -> 8
B51: ='BDO Prequal'!B34 -> Base Rate | C51: ='BDO Prequal'!C34 -> 0.075 | D51: ='BDO Prequal'!I34 -> 0.08 | E51: ='BDO Prequal'!J34 -> 0.0624
B52: ='BDO Prequal'!B35 -> Spread | C52: ='BDO Prequal'!C35 -> 0.015 | D52: ='BDO Prequal'!I35 -> 0 | E52: ='BDO Prequal'!J35 -> 0
B53: ='BDO Prequal'!B36 -> Indicative Rate | C53: ='BDO Prequal'!C36 -> 0.09 | D53: ='BDO Prequal'!I36 -> 0.08 | E53: ='BDO Prequal'!J36 -> 0.0624
B54: Adjustment / Fix | C54: Quarterly | D54: Fixed | E54: Fixed
B55: ='BDO Prequal'!B38 -> Term (years) | C55: ='BDO Prequal'!C38 -> 10 | D55: ='BDO Prequal'!I38 -> 10 | E55: ='BDO Prequal'!J38 -> 25
B56: ='BDO Prequal'!B40 -> Estimated Payment | C56: ='BDO Prequal'!C40 -> 12.671581 | D56: ='BDO Prequal'!I40 -> 0.084929316 | E56: ='BDO Prequal'!J40 -> 0.05272411
B59: Blended Rate Table
B60: Bank Loan with CDC Loan
C61: Loan | D61: Est. Payment | E61: Rate
B62: ='BDO Prequal'!C31 -> T Bank Loan | C62: ='BDO Prequal'!C33 -> 1000 | D62: ='BDO Prequal'!C40 -> 12.671581 | E62: ='BDO Prequal'!C36 -> 0.09
B63: ='BDO Prequal'!J31 -> 3rd Party | C63: ='BDO Prequal'!J33 -> 8 | D63: ='BDO Prequal'!J40 -> 0.05272411 | E63: ='BDO Prequal'!J36 -> 0.0624
B64: Total/Blend | C64: ='BDO Prequal'!C65+'BDO Prequal'!J65 -> 99068 | D64: ='BDO Prequal'!C40+'BDO Prequal'!J40 -> 12.724305 | E64: =(C62*E62+C63*E63)/C64 -> 0.00091350587
B67: Collateral Analysis
B69: Address | D69: Gross Value | E69: Liquidation Value | F69: Discounted Value | G69: Senior Liens | H69: Liquidation Value
B70: =IF('BDO Prequal'!E669="","",'BDO Prequal'!E669) | D70: ='BDO Prequal'!G669 -> 0 | E70: ='BDO Prequal'!H669 -> 0.85 | F70: ='BDO Prequal'!I669 -> 0 | G70: ='BDO Prequal'!J669 -> 0 | H70: ='BDO Prequal'!K669 -> 0
B71: =IF('BDO Prequal'!E670="","",'BDO Prequal'!E670) | D71: ='BDO Prequal'!G670 -> 0 | E71: ='BDO Prequal'!H670 -> 0.85 | F71: ='BDO Prequal'!I670 -> 0 | G71: ='BDO Prequal'!J670 -> 0 | H71: ='BDO Prequal'!K670 -> 0
B72: =IF('BDO Prequal'!E671="","",'BDO Prequal'!E671) | D72: ='BDO Prequal'!G671 -> 0 | E72: ='BDO Prequal'!H671 -> 0.85 | F72: ='BDO Prequal'!I671 -> 0 | G72: ='BDO Prequal'!J671 -> 0 | H72: ='BDO Prequal'!K671 -> 0
B73: =IF('BDO Prequal'!E672="","",'BDO Prequal'!E672) | D73: ='BDO Prequal'!G672 -> 0 | E73: ='BDO Prequal'!H672 -> 0.1 | F73: ='BDO Prequal'!I672 -> 0 | G73: ='BDO Prequal'!J672 -> 0 | H73: ='BDO Prequal'!K672 -> 0
B74: =IF('BDO Prequal'!E673="","",'BDO Prequal'!E673) | D74: ='BDO Prequal'!G673 -> 0 | E74: ='BDO Prequal'!H673 -> 0.5 | F74: ='BDO Prequal'!I673 -> 0 | G74: ='BDO Prequal'!J673 -> 0 | H74: ='BDO Prequal'!K673 -> 0
B75: =IF('BDO Prequal'!E674="","",'BDO Prequal'!E674) | D75: ='BDO Prequal'!G674 -> 0 | E75: ='BDO Prequal'!H674 -> 0.1 | F75: ='BDO Prequal'!I674 -> 0 | G75: ='BDO Prequal'!J674 -> 0 | H75: ='BDO Prequal'!K674 -> 0
B76: =IF('BDO Prequal'!E675="","",'BDO Prequal'!E675) | D76: ='BDO Prequal'!G675 -> 0 | E76: ='BDO Prequal'!H675 -> 0.1 | F76: ='BDO Prequal'!I675 -> 0 | G76: ='BDO Prequal'!J675 -> 0 | H76: ='BDO Prequal'!K675 -> 0
B77: =IF('BDO Prequal'!E676="","",'BDO Prequal'!E676) | D77: ='BDO Prequal'!G676 -> 0 | E77: ='BDO Prequal'!H676 -> 0.05 | F77: ='BDO Prequal'!I676 -> 0 | G77: ='BDO Prequal'!J676 -> 0 | H77: ='BDO Prequal'!K676 -> 0
B78: =IF('BDO Prequal'!E677="","",'BDO Prequal'!E677) | D78: ='BDO Prequal'!G677 -> 0 | E78: ='BDO Prequal'!H677 -> 0 | F78: ='BDO Prequal'!I677 -> 0 | G78: ='BDO Prequal'!J677 -> 0 | H78: ='BDO Prequal'!K677 -> 0
C79: Totals | D79: ='BDO Prequal'!G678 -> 0 | F79: ='BDO Prequal'!I678 -> 0 | G79: ='BDO Prequal'!J678 -> 0 | H79: ='BDO Prequal'!K678 -> 0
B81: Gross LTV | D81: ='BDO Prequal'!G680 -> 0 | E81: Net LTV | G81: Net LTV | H81: ='BDO Prequal'!K680 -> 0
B82: Gross Coverage | D82: ='BDO Prequal'!G681 -> 0 | E82: Net Coverage | G82: Net Coverage | H82: ='BDO Prequal'!K681 -> 0
B85: Liquidity Analysis
B87: ='BDO Prequal'!B72 -> Operating Company Liquidity | C87: ='BDO Prequal'!C72 -> 0
B88: ='BDO Prequal'!B73 -> Owner/Guarantor 1 | C88: ='BDO Prequal'!C73 -> 0
B89: ='BDO Prequal'!B74 -> Owner/Guarantor 2 | C89: ='BDO Prequal'!C74 -> 0
B90: ='BDO Prequal'!B75 -> Owner/Guarantor 3 | C90: ='BDO Prequal'!C75 -> 0
B91: ='BDO Prequal'!B76 -> Owner/Guarantor 4 | C91: ='BDO Prequal'!C76 -> 0
B92: ='BDO Prequal'!F72 -> Affiliate 1 | C92: ='BDO Prequal'!G72 -> 0
B93: ='BDO Prequal'!F73 -> Affiliate 2 | C93: ='BDO Prequal'!G73 -> 0
B94: ='BDO Prequal'!F74 -> Affiliate 3 | C94: ='BDO Prequal'!G74 -> 0
B95: ='BDO Prequal'!F75 -> Affiliate 4 | C95: ='BDO Prequal'!G75 -> 0
B96: ='BDO Prequal'!F76 -> Affiliate 5 | C96: ='BDO Prequal'!G76 -> 0
B97: ='BDO Prequal'!C78 -> Total Available Liquidity | C97: ='BDO Prequal'!D78 -> 0
B98: ='BDO Prequal'!E78 -> Expected Injection | C98: ='BDO Prequal'!F78*-1 -> -1336917
B99: Post Close Liquidity | C99: ='BDO Prequal'!H78 -> -1336917
B102: Stand-Alone DSCR
B104: ='BDO Prequal'!B83 -> {Insert business name which represents PSOR} | G104: Projections
C106: ='BDO Prequal'!D85 -> 44926 | D106: ='BDO Prequal'!F85 -> 45291 | E106: ='BDO Prequal'!H85 -> 45657 | F106: ='BDO Prequal'!J85 -> 45747 | G106: Year 1 | H106: Year 2
F107: ='BDO Prequal'!J89 -> 0
B108: ='BDO Prequal'!C99 -> Total Revenue | C108: ='BDO Prequal'!D99 -> 9000 | D108: ='BDO Prequal'!F99 -> 2166 | E108: ='BDO Prequal'!H99 -> 1145 | F108: ='BDO Prequal'!J99 -> 880 | G108: ='BDO Prequal'!N99 -> 210 | H108: ='BDO Prequal'!P99 -> 620
B109: ='BDO Prequal'!C100 -> Total COGS | C109: ='BDO Prequal'!D100 -> 50 | D109: ='BDO Prequal'!F100 -> 500 | E109: ='BDO Prequal'!H100 -> 400 | F109: ='BDO Prequal'!J100 -> 8000 | G109: ='BDO Prequal'!N100 -> 30 | H109: ='BDO Prequal'!P100 -> 0
B110: ='BDO Prequal'!C101 -> Total Gross Margin | C110: ='BDO Prequal'!D101 -> 8950 | D110: ='BDO Prequal'!F101 -> 1666 | E110: ='BDO Prequal'!H101 -> 745 | F110: ='BDO Prequal'!J101 -> -7120 | G110: ='BDO Prequal'!N101 -> 180 | H110: ='BDO Prequal'!P101 -> 620
B111: ='BDO Prequal'!C128 -> Total Operating Expenses | C111: ='BDO Prequal'!D128 -> 800 | D111: ='BDO Prequal'!F128 -> 800 | E111: ='BDO Prequal'!H128 -> 500 | F111: ='BDO Prequal'!J128 -> 5000 | G111: ='BDO Prequal'!N128 -> 6747 | H111: ='BDO Prequal'!P128 -> 7603
B112: ='BDO Prequal'!C130 -> Ordinary Income | C112: ='BDO Prequal'!D130 -> 8150 | D112: ='BDO Prequal'!F130 -> 866 | E112: ='BDO Prequal'!H130 -> 245 | F112: ='BDO Prequal'!J130 -> -12120 | G112: ='BDO Prequal'!N130 -> -6567 | H112: ='BDO Prequal'!P130 -> -6983
B113: ='BDO Prequal'!C136 -> Total Other Income (Expenses) | C113: ='BDO Prequal'!D136 -> 5050 | D113: ='BDO Prequal'!F136 -> 6050 | E113: ='BDO Prequal'!H136 -> 8600 | F113: ='BDO Prequal'!J136 -> 9801 | G113: ='BDO Prequal'!N136 -> 510 | H113: ='BDO Prequal'!P136 -> 500
B114: ='BDO Prequal'!C138 -> Net Income Before Taxes | C114: ='BDO Prequal'!D138 -> 13200 | D114: ='BDO Prequal'!F138 -> 6916 | E114: ='BDO Prequal'!H138 -> 8845 | F114: ='BDO Prequal'!J138 -> -2319 | G114: ='BDO Prequal'!N138 -> -6057 | H114: ='BDO Prequal'!P138 -> -6483
B115: ='BDO Prequal'!C139 -> Income Taxes | C115: ='BDO Prequal'!D139 -> 1 | D115: ='BDO Prequal'!F139 -> 2 | E115: ='BDO Prequal'!H139 -> 3 | F115: ='BDO Prequal'!J139 -> 6 | G115: ='BDO Prequal'!N139 -> 70 | H115: ='BDO Prequal'!P139 -> 63
B116: ='BDO Prequal'!C141 -> NET INCOME AFTER TAXES | C116: ='BDO Prequal'!D141 -> 13199 | D116: ='BDO Prequal'!F141 -> 6914 | E116: ='BDO Prequal'!H141 -> 8842 | F116: ='BDO Prequal'!J141 -> -2325 | G116: ='BDO Prequal'!N141 -> -6127 | H116: ='BDO Prequal'!P141 -> -6546
B118: Add Backs :
B119: ='BDO Prequal'!C144 -> + Compensation of Officers | C119: ='BDO Prequal'!D144 -> 9000 | D119: ='BDO Prequal'!F144 -> 4562 | E119: ='BDO Prequal'!H144 -> 461 | F119: ='BDO Prequal'!J144 -> 621 | G119: ='BDO Prequal'!N144 -> 150 | H119: ='BDO Prequal'!P144 -> 1521
B120: ='BDO Prequal'!C145 -> + Depreciation/Amortization | C120: ='BDO Prequal'!D145 -> 0 | D120: ='BDO Prequal'!F145 -> 0 | E120: ='BDO Prequal'!H145 -> 0 | F120: ='BDO Prequal'!J145 -> 0 | G120: ='BDO Prequal'!N145 -> 20 | H120: ='BDO Prequal'!P145 -> 3
B121: ='BDO Prequal'!C146 -> + Interest Expense | C121: ='BDO Prequal'!D146 -> 0 | D121: ='BDO Prequal'!F146 -> 0 | E121: ='BDO Prequal'!H146 -> 0 | F121: ='BDO Prequal'!J146 -> 0 | G121: ='BDO Prequal'!N146 -> 233 | H121: ='BDO Prequal'!P146 -> 2
B122: ='BDO Prequal'!C147 -> + Rent Add Back | C122: ='BDO Prequal'!D147 -> 0 | D122: ='BDO Prequal'!F147 -> 0 | E122: ='BDO Prequal'!H147 -> 0 | F122: ='BDO Prequal'!J147 -> 0 | G122: ='BDO Prequal'!N147 -> 20 | H122: ='BDO Prequal'!P147 -> 1
B123: ='BDO Prequal'!C148 -> + - Other | C123: ='BDO Prequal'!D148 -> 45 | D123: ='BDO Prequal'!F148 -> 46 | E123: ='BDO Prequal'!H148 -> 10 | F123: ='BDO Prequal'!J148 -> 11 | G123: ='BDO Prequal'!N148 -> 12 | H123: ='BDO Prequal'!P148 -> 12
B124: ='BDO Prequal'!C149 -> + - Other | C124: ='BDO Prequal'!D149 -> 21 | D124: ='BDO Prequal'!F149 -> 21 | E124: ='BDO Prequal'!H149 -> 22 | F124: ='BDO Prequal'!J149 -> 23 | G124: ='BDO Prequal'!N149 -> 40 | H124: ='BDO Prequal'!P149 -> 13
B125: ='BDO Prequal'!C150 -> - Estimated Property Tax | C125: ='BDO Prequal'!D150 -> 0 | D125: ='BDO Prequal'!F150 -> 0 | E125: ='BDO Prequal'!H150 -> 0 | F125: ='BDO Prequal'!J150 -> 0 | G125: ='BDO Prequal'!N150 -> 0 | H125: ='BDO Prequal'!P150 -> 0
B126: ='BDO Prequal'!C151 -> - Required Owner's Draw | C126: ='BDO Prequal'!D151 -> 900 | D126: ='BDO Prequal'!F151 -> 1000 | E126: ='BDO Prequal'!H151 -> 70 | F126: ='BDO Prequal'!J151 -> 7 | G126: ='BDO Prequal'!N151 -> 70 | H126: ='BDO Prequal'!P151 -> 70
...

Sheet 504-Hybrid
B3: Loan Terms | J3: Total Project | K3: =SUM(K4:K6) -> 1 | L3: =O36 -> 0 | M3: (difference) | R3: Closing Costs | S3: Cost | T3: Quantity | U3: Total
J4: Bank Loan % | K4: 0.5 | L4: =L3*K4 -> 0 | M4: =K36-L4 -> 0 | R4: Loan Packaging Fee | S4: 2500 | T4: 0 | U4: =S4*T4 -> 0
C5: T Bank 7(a) | D5: Borrower | E5: Seller Note | F5: T Bank 504 | G5: CDC 504 | J5: CDC Loan % | K5: 0.4 | L5: =L3*K5 -> 0 | M5: =N36-L5 -> 0 | R5: Title Insurance | S5: 0 | T5: 0 | U5: =S5*T5 -> 0
B6: Base Rate | C6: 0.075 | E6: 0.08 | F6: 0.075 | G6: 0.0624 | J6: Borrower % | K6: 0.1 | L6: =L3*K6 -> 0 | M6: =L36-L6 -> 0 | R6: Real Estate Tax Fee | S6: 0 | T6: 0 | U6: =S6*T6 -> 0
B7: Spread | C7: 0.015 | E7: 0 | F7: 0.015 | G7: 0 | R7: Survey Charges | S7: 0 | T7: 0 | U7: =S7*T7 -> 0
B8: Indicative Rate | C8: =C6+C7 -> 0.09 | E8: =E6+E7 -> 0.08 | F8: =F6+F7 -> 0.09 | G8: =G6+G7 -> 0.0624 | J8: Bank Interim Loan Fee % | K8: 0.025 | L8: =L4*K8 -> 0 | M8: Blended Rate | N8: =(K36*F8+N36*G8)/SUM(K36+N36) -> #DIV/0! | R8: CRE Appraisal | S8: 3500 | T8: 0 | U8: =S8*T8 -> 0
B9: Amortization Basis | C9: Actual/365 | F9: Actual/365 | J9: SBA TPL Fee % | K9: 0.005 | L9: =L4*K9 -> 0 | R9: Equipment Appraisal | S9: 7500 | T9: 0 | U9: =S9*T9 -> 0
B10: Term (years) | C10: 10 | E10: 10 | F10: 10 | G10: 25 | J10: Referral Fee % | K10: 0 | L10: =K10*L4 -> 0 | M10: Interim Loan | N10: =K36+N36 -> 0 | R10: Appraisal Review | S10: 0 | T10: 0 | U10: =S10*T10 -> 0
B11: Amortization (mos) | C11: =C10*12 -> 120 | E11: =E10*12 -> 120 | F11: =F10*12 -> 120 | G11: =G10*12 -> 300 | J11: Participant Fee % | K11: 0 | L11: =K11*L4 -> 0 | M11: Rounded Fee | N11: =ROUNDUP(L12,-3) -> 0 | R11: Site Visit | S11: 350 | T11: 0 | U11: =S11*T11 -> 0
B12: Est Const Period (mths) | C12: 0 | J12: Origination Fee Total | K12: =SUM(K8:K11) -> 0.03 | L12: =SUM(L8:L11) -> 0 | M12: Fee % to Interim | N12: =N11/N10 -> #DIV/0! | R12: Environmental Investigation | S12: 2500 | T12: 0 | U12: =S12*T12 -> 0
J13: 504 Loan Project | R13: Business Valuation | S13: 2500 | T13: 0 | U13: =S13*T13 -> 0
R14: Residential Appr/Valuation | S14: 0 | T14: 0 | U14: =S14*T14 -> 0
R15: Attorney Doc Prep | S15: 8000 | T15: 0 | U15: =S15*T15 -> 0
B16: Sources and Uses of Proceeds - 7(a) | J16: Sources and Uses of Proceeds - 504 | R16: Interim Loan Fee / Origination | S16: 64000 | T16: 0 | U16: =S16*T16 -> 0
R17: SBA TPL Fee | S17: 13000 | T17: 0 | U17: =S17*T17 -> 0
C18: =C5 -> T Bank 7(a) | D18: =D5 -> Borrower | E18: =E5 -> Seller Note | F18: =G5 -> CDC 504 | G18: Total | K18: T Bank 504 | L18: =D5 -> Borrower | M18: =E5 -> Seller Note | N18: =G5 -> CDC 504 | O18: Total | R18: Rounding | S18: 300 | T18: 0 | U18: =S18*T18 -> 0
B19: Direct Project Costs | J19: Direct Project Costs | R19: Other: UCCs and Misc Closing | U19: =U32 -> 0
B20: Real Estate Acquisition | C20: =G20-SUM(D20:F20) -> 0 | D20: 0 | E20: 0 | F20: 0 | G20: 0 | J20: Real Estate Acquisition | K20: =O20-SUM(L20:N20) -> 0 | L20: 0 | M20: 0 | N20: 0 | O20: 0 | R20: Total Estimated Closing Costs | U20: =SUM(U4:U19) -> 0
B21: Debt Refi - CRE | C21: =G21-SUM(D21:F21) -> 0 | D21: 0 | E21: 0 | F21: 0 | G21: 0 | J21: Debt Refi - CRE | K21: =O21-SUM(L21:N21) -> 0 | L21: 0 | M21: 0 | N21: 0 | O21: 0
B22: Debt Refi - Non-CRE | C22: =G22-SUM(D22:F22) -> 0 | D22: 0 | E22: 0 | F22: 0 | G22: 0 | J22: Debt Refi - Non-CRE | K22: =O22-SUM(L22:N22) -> 0 | L22: 0 | M22: 0 | N22: 0 | O22: 0 | R22: Miscellaneous Closing Costs | S22: Cost | T22: Quantity | U22: Total
B23: Machinery & Equipment | C23: =G23-SUM(D23:F23) -> 0 | D23: 0 | E23: 0 | F23: 0 | G23: 0 | J23: Machinery & Equipment | K23: =O23-SUM(L23:N23) -> 0 | L23: 0 | M23: 0 | N23: 0 | O23: 0 | R23: Business Credit Report | S23: 35 | T23: 0 | U23: =S23*T23 -> 0
B24: Furniture & Fixtures (TIs) | C24: =G24-SUM(D24:F24) -> 0 | D24: 0 | E24: 0 | F24: 0 | G24: 0 | J24: Furniture & Fixtures (TIs) | K24: =O24-SUM(L24:N24) -> 0 | L24: 0 | M24: 0 | N24: 0 | O24: 0 | R24: Personal Credit Report | S24: 25 | T24: 0 | U24: =S24*T24 -> 0
B25: Inventory | C25: =G25-SUM(D25:F25) -> 0 | D25: 0 | E25: 0 | F25: 0 | G25: 0 | J25: Inventory | K25: =O25-SUM(L25:N25) -> 0 | L25: 0 | M25: 0 | N25: 0 | O25: 0 | R25: IRS Transcript Service | S25: 65 | T25: 0 | U25: =S25*T25 -> 0
B26: Working Capital | C26: =G26-SUM(D26:F26) -> 0 | D26: 0 | E26: 0 | F26: 0 | G26: 0 | J26: Working Capital | K26: =O26-SUM(L26:N26) -> 0 | L26: 0 | M26: 0 | N26: 0 | O26: 0 | R26: UCC Searches | S26: 300 | T26: 0 | U26: =S26*T26 -> 0
B27: Working Capital - Pre Opening | C27: =G27-SUM(D27:F27) -> 0 | D27: 0 | E27: 0 | F27: 0 | G27: 0 | J27: Working Capital - Pre Opening | K27: =O27-SUM(L27:N27) -> 0 | L27: 0 | M27: 0 | N27: 0 | O27: 0 | R27: Certificate of Good Standing | S27: 20 | T27: 0 | U27: =S27*T27 -> 0
B28: Business Acquisition | C28: =G28-SUM(D28:F28) -> 0 | D28: 0 | E28: 0 | F28: 0 | G28: 0 | J28: Business Acquisition | K28: =O28-SUM(L28:N28) -> 0 | L28: 0 | M28: 0 | N28: 0 | O28: 0 | R28: Flood Certification | S28: 18 | T28: 0 | U28: =S28*T28 -> 0
B29: Franchise Fees | C29: =G29-SUM(D29:F29) -> 0 | D29: 0 | E29: 0 | F29: 0 | G29: 0 | J29: Franchise Fees | K29: =O29-SUM(L29:N29) -> 0 | L29: 0 | M29: 0 | N29: 0 | O29: 0 | R29: Filing & Recording Fees | S29: 100 | T29: 0 | U29: =S29*T29 -> 0
B30: Construction Hard Costs | C30: =G30-SUM(D30:F30) -> 0 | D30: 0 | E30: 0 | F30: 0 | G30: 0 | J30: Construction Hard Costs | K30: =O30-SUM(L30:N30) -> 0 | L30: 0 | M30: 0 | N30: 0 | O30: 0 | R30: FedEx Charges | S30: 50 | T30: 0 | U30: =S30*T30 -> 0
B31: Interim Interest Reserve | C31: 0 | D31: =G31-C31 -> 0 | E31: 0 | F31: 0 | G31: =ROUND(((C20+F20)*C8/12)*C12+((C36-C20+F36-F20)*C8*0.6/12)*C12,0) -> 0 | H31: Const Contigency | J31: Interim Interest Reserve | K31: 0 | L31: =O31-K31 -> 0 | M31: 0 | N31: 0 | O31: 0 | P31: Const Contigency | R31: Other: rounding | S31: 77 | T31: 0 | U31: =S31*T31 -> 0
B32: Construction Contingency | C32: =G32-D32-E32-F32 -> 0 | D32: 0 | E32: 0 | F32: 0 | G32: =ROUND(G30*H32,0) -> 0 | H32: 0.1 | J32: Construction Contingency | K32: =O32-L32-M32-N32 -> 0 | L32: 0 | M32: 0 | N32: 0 | O32: =ROUND(O30*P32,0) -> 0 | P32: 0.1 | R32: Total Misc. Closing Costs | U32: =SUM(U23:U31) -> 0
B33: Other Construction Soft Costs | C33: =G33-SUM(D33:F33) -> 0 | D33: 0 | E33: 0 | F33: 0 | G33: 0 | J33: Other Construction Soft Costs | K33: =O33-SUM(L33:N33) -> 0 | L33: 0 | M33: 0 | N33: 0 | O33: 0
B34: Closing Costs | C34: =G34-SUM(D34:F34) -> 0 | D34: 0 | E34: 0 | F34: 0 | G34: 0 | J34: Closing Costs | K34: =O34-SUM(L34:N34) -> 0 | L34: 0 | M34: 0 | N34: 0 | O34: 0
B35: SBA Gty Fee | C35: 0 | D35: =G35-C35 -> 0 | G35: 0 | J35: SBA Gty Fee | K35: 0 | L35: =O35-K35 -> 0 | O35: 0
C36: =SUM(C20:C35) -> 0 | D36: =SUM(D20:D35) -> 0 | E36: =SUM(E20:E35) -> 0 | F36: =SUM(F20:F35) -> 0 | G36: =SUM(G20:G35) -> 0 | K36: =SUM(K20:K35) -> 0 | L36: =SUM(L20:L35) -> 0 | M36: =SUM(M20:M35) -> 0 | N36: =SUM(N20:N35) -> 0 | O36: =SUM(O20:O35) -> 0
C37: =IFERROR(C36/$G$36,0) -> 0 | D37: =IFERROR(D36/$G$36,0) -> 0 | E37: =IFERROR(E36/$G$36,0) -> 0 | F37: =IFERROR(F36/$G$36,0) -> 0 | G37: =IFERROR(G36/$G$36,0) -> 0 | K37: =IFERROR(K36/$O$36,0) -> 0 | L37: =IFERROR(L36/$O$36,0) -> 0 | M37: =IFERROR(M36/$O$36,0) -> 0 | N37: =IFERROR(N36/$O$36,0) -> 0 | O37: =IFERROR(O36/$O$36,0) -> 0
C41: =C18 -> T Bank 7(a) | D41: =D18 -> Borrower | E41: =E18 -> Seller Note | F41: =G18 -> Total | K41: =K18 -> T Bank 504 | L41: =L18 -> Borrower | M41: =M18 -> Seller Note | N41: =N18 -> CDC 504 | O41: =O18 -> Total
B42: =B20 -> Real Estate Acquisition | C42: =C20 -> 0 | D42: =D20 -> 0 | E42: =E20 -> 0 | F42: =G20 -> 0 | J42: =J20 -> Real Estate Acquisition | K42: =K20 -> 0 | L42: =L20 -> 0 | M42: =M20 -> 0 | N42: =N20 -> 0 | O42: =O20 -> 0
B43: =B21 -> Debt Refi - CRE | C43: =C21 -> 0 | D43: =D21 -> 0 | E43: =E21 -> 0 | F43: =G21 -> 0 | J43: =J21 -> Debt Refi - CRE | K43: =K21 -> 0 | L43: =L21 -> 0 | M43: =M21 -> 0 | N43: =N21 -> 0 | O43: =O21 -> 0
B44: =B22 -> Debt Refi - Non-CRE | C44: =C22 -> 0 | D44: =D22 -> 0 | E44: =E22 -> 0 | F44: =G22 -> 0 | J44: =J22 -> Debt Refi - Non-CRE | K44: =K22 -> 0 | L44: =L22 -> 0 | M44: =M22 -> 0 | N44: =N22 -> 0 | O44: =O22 -> 0
B45: =B23 -> Machinery & Equipment | C45: =C23 -> 0 | D45: =D23 -> 0 | E45: =E23 -> 0 | F45: =G23 -> 0 | J45: =J23 -> Machinery & Equipment | K45: =K23 -> 0 | L45: =L23 -> 0 | M45: =M23 -> 0 | N45: =N23 -> 0 | O45: =O23 -> 0
B46: =B24 -> Furniture & Fixtures (TIs) | C46: =C24 -> 0 | D46: =D24 -> 0 | E46: =E24 -> 0 | F46: =G24 -> 0 | J46: =J24 -> Furniture & Fixtures (TIs) | K46: =K24 -> 0 | L46: =L24 -> 0 | M46: =M24 -> 0 | N46: =N24 -> 0 | O46: =O24 -> 0
B47: =B25 -> Inventory | C47: =C25 -> 0 | D47: =D25 -> 0 | E47: =E25 -> 0 | F47: =G25 -> 0 | J47: =J25 -> Inventory | K47: =K25 -> 0 | L47: =L25 -> 0 | M47: =M25 -> 0 | N47: =N25 -> 0 | O47: =O25 -> 0
B48: =B26 -> Working Capital | C48: =C26 -> 0 | D48: =D26 -> 0 | E48: =E26 -> 0 | F48: =G26 -> 0 | J48: =J26 -> Working Capital | K48: =K26 -> 0 | L48: =L26 -> 0 | M48: =M26 -> 0 | N48: =N26 -> 0 | O48: =O26 -> 0
B49: =B27 -> Working Capital - Pre Opening | C49: =C27 -> 0 | D49: =D27 -> 0 | E49: =E27 -> 0 | F49: =G27 -> 0 | J49: =J27 -> Working Capital - Pre Opening | K49: =K27 -> 0 | L49: =L27 -> 0 | M49: =M27 -> 0 | N49: =N27 -> 0 | O49: =O27 -> 0
B50: =B28 -> Business Acquisition | C50: =C28 -> 0 | D50: =D28 -> 0 | E50: =E28 -> 0 | F50: =G28 -> 0 | J50: =J28 -> Business Acquisition | K50: =K28 -> 0 | L50: =L28 -> 0 | M50: =M28 -> 0 | N50: =N28 -> 0 | O50: =O28 -> 0
B51: =B29 -> Franchise Fees | C51: =C29 -> 0 | D51: =D29 -> 0 | E51: =E29 -> 0 | F51: =G29 -> 0 | J51: =J29 -> Franchise Fees | K51: =K29 -> 0 | L51: =L29 -> 0 | M51: =M29 -> 0 | N51: =N29 -> 0 | O51: =O29 -> 0
B52: =B30 -> Construction Hard Costs | C52: =C30 -> 0 | D52: =D30 -> 0 | E52: =E30 -> 0 | F52: =G30 -> 0 | J52: =J30 -> Construction Hard Costs | K52: =K30 -> 0 | L52: =L30 -> 0 | M52: =M30 -> 0 | N52: =N30 -> 0 | O52: =O30 -> 0
B53: =B31 -> Interim Interest Reserve | C53: =C31 -> 0 | D53: =D31 -> 0 | E53: =E31 -> 0 | F53: =G31 -> 0 | J53: =J31 -> Interim Interest Reserve | K53: =K31 -> 0 | L53: =L31 -> 0 | M53: =M31 -> 0 | N53: =N31 -> 0 | O53: =O31 -> 0
... B57: =B35 -> SBA Gty Fee | C57: =C35 -> 0 | D57: =D35 -> 0 | E57: =E35 -> 0 | F57: =G35 -> 0 | J57: =J35 -> SBA Gty Fee | K57: =K35 -> 0 | L57: =L35 -> 0 | M57: =M35 -> 0 | N57: =N35 -> 0 | O57: =O35 -> 0
B58: Project Total | C58: =C36 -> 0 | D58: =D36 -> 0 | E58: =E36 -> 0 | F58: =G36 -> 0 | J58: Project Total | K58: =K36 -> 0 | L58: =L36 -> 0 | M58: =M36 -> 0 | N58: =N36 -> 0 | O58: =O36 -> 0
B59: Percentages | C59: =C37 -> 0 | D59: =D37 -> 0 | E59: =E37 -> 0 | F59: =G37 -> 0 | J59: Percentages | K59: =K37 -> 0 | L59: =L37 -> 0 | M59: =M37 -> 0 | N59: =N37 -> 0 | O59: =O37 -> 0

Sheet Lists
A1: Version | B1: Loan Type | C1: Basics | D1: Request | E1: UW | F1: BDO
A3: Original | B3: N/A | C3: Yes | D3: New | E3: Andrew Taylor | F3: Audrey Wendel
A4: Mod 1 | B4: SBA 7a | C4: No | D4: Renewal | E4: Antony Parker | F4: Ben Eakin
A5: Mod 2 | B5: SBA Express | C5: N/A | D5: Modification | E5: Brent Ruch | F5: Cameron Brewer
A6: Mod 3 | B6: 504 | E6: Jennifer Dennis | F6: Eric Wadley
A7: Mod 4 | B7: USDA | C7: Disbursement | E7: Jessica Gauden | F7: Glenn Giro
A8: Mod 5 | B8: P&E | E8: Rodney Johnson | F8: Greg Swett
A9: Mod 6 | B9: Conventional | C9: Multi | E9: Rose Haynes-Taylor | F9: Jordan Sayler
A10: Mod 7 | C10: Single | D10: True/False | E10: Connor Shaw | F10: Kandace Moon
A11: Mod 8 | E11: Sheila Simms | F11: Kerry Smith
A12: Mod 9 | D12: True | F12: Kevin Coffman
A13: Mod 10 | D13: False | F13: Mike Ramsay
F14: Patrick Phillips
A15: Entity Types | B15: Loan Program | C15: Risk Rating | D15: Statement Type | E15: Revenue Recognition | F15: Rick McMann
F16: Rod Rodriguez
A17: TBD | B17: N/A | C17: 1 | D17: Tax Returns | E17: Cash | F17: Steve Jones
A18: Sole Prop | B18: PLP | C18: 2 | D18: Audited | E18: Accrual
A19: LLC | B19: GP | C19: 3 | D19: Reviewed | E19: Hybrid
A20: S-Corp | B20: 504 | C20: 4 | D20: Compiled | E20: Other
A21: C-Corp | B21: USDA | C21: 5 | D21: Schedule C | F21: Proforma BS
A22: Prof Corp | C22: 5.5 | D22: Internal
A23: Prof LLC | C23: 6 | D23: Form 10K | F23: New BS
A24: Trust | C24: 7 | D24: Form 10Q | F24: Last Year End
A25: LTD Partnership | C25: 8 | D25: Other | F25: Interim
A26: Partnership | C26: 9
F28: Submission
A29: Rate Adjustment | B29: Lien Position | D29: Property Type | E29: Valuation Method
C30: UCC Lien Type | F30: PLP
A31: Daily | B31: First | D31: C-Store | E31: Cost | F31: Standard
A32: Monthly | B32: Second | C32: Purchase Money UCC | D32: Hotel | E32: Appraisal
A33: Calendar Qtr | B33: Third | C33: Blanket UCC | D33: Industrial | E33: Book Value
A34: Other | B34: Fourth | C34: Security Interest | D34: Medical Office | E34: BPO
B35: Best Available | D35: Mixed-Use | E35: Invoice
D36: Mobile Home Park | E36: Estimated | F36: Construction Type
D37: Multi Family | E37: Tax
A38: Entity Class | B38: PFS RE Type | D38: Office | E38: Other | F38: Wood Frame
D39: Office/Warehouse | E39: Roof Type | F39: Steel Frame
A40: Holding Company/EPC | B40: Single Family | D40: Residential | F40: Concrete Frame
A41: Operating Company | B41: Multi Family | D41: Restaurant | E41: Flat - Built Up | F41: Concrete Tilt Up
A42: Affiliate | B42: Commercial | D42: Retail | E42: Flat - Membrane | F42: Concrete Wall
D43: Self Storage | E43: Flat - Other | F43: Hollow Clay Tile / Adobe
D44: Vacant Land | E44: Pitched - Metal | F44: Steel Frame w/Metal Skin
C45: Borrower/Guarantor | D45: Other | E45: Pitched - Shingle | F45: Reinforced Masonry
E46: Pitched - Other | F46: Unreinforced Masonry
A47: CDC Term | B47: Trend | C47: N/A | E47: Other | F47: Other
C48: None | E48: Not Known | F48: Not Known
A49: 10 | B49: Increasing | C49: Borrower
A50: 20 | B50: Decreasing | C50: Guarantor
A51: 25 | B51: Stable | D51: Guarantee
B52: Un Stable | C52: Recourse | E52: Rate Type | F52: Appraisal Value
A53: Request # | B53: Consistent | D53: N/A
B54: Inconsistent | C54: N/A | D54: Full Unsecured | E54: Fixed | F54: As Is
A55: Request 1 | C55: Full | D55: Full Secured | E55: Variable | F55: As Complete
A56: Request 2 | C56: Non | D56: Lim. Unsecured | F56: As Stablized
C57: Partial | D57: Lim. Secured
D58: Spousal Int.
F59: Origination/Packaging
A60: Facility Type | B60: SBA Initial Rate Set | D60: Checks | E60: X/O
C61: Amortization Basis | F61: Packaging Fee
A62: N/A | B62: Day of SBA/USDA Sub | D62: N/A | E62: x | F62: Origination Fee
A63: Term Loan | B63: 5 Days before Closing | C63: 30/360 | D63: Clear
A64: RLOC | B64: Other | C64: Actual/365 | D64: Not Clear
A65: GLOC | C65: Actual/360
A66: Const
A67: Non Rev Adv | F67: Breakeven
A68: Letter of Credit
F69: =#REF! -> #REF!
A70: Tract Income Level | B70: Coll RE Type | C70: HLTV Max | D70: Branch | E70: BSA Rating | F70: =#REF! -> #REF!
F71: =#REF! -> #REF!
A72: Upper | B72: Primary CRE | C72: 0.65 | D72: 12- SMJ | E72: 1- Low | F72: =#REF! -> #REF!
A73: Moderate | B73: Primary Residence | C73: 0.75 | D73: 14-AMW | E73: 2- Low Medium
A74: Middle | B74: Secondary RE | C74: 0.8 | D74: 15-HSE | E74: 3- Medium | F74: Exception Clearing
A75: Low | C75: 0.85 | D75: 21-SBA | E75: 4- Moderate
D76: 22- Wendel Loans | E76: 5-High | F76: Amber- Rose McCool
D77: 76- Integra | F77: Andrew Taylor
F78: Audrey Wendel
A79: Rate Index | F79: Casey McDonald
F80: Gina Bedsole
A81: WSJ Prime | F81: KT Head
A82: SOFR | F82: Lorenzo Saavedra
A83: 10 Yr Treas | F83: Nick Vu
F84: Rachel Preston
