Workbook
Name Beg_Bal: #REF!
Name Beg_Bal: #REF!
Name Cum_Int: #REF!
Name Data: #REF!
Name DisbursementType: #REF!
Name DisbursementType: #REF!
Name End_Bal: #REF!
Name End_Bal: #REF!
Name EXPENSES: #REF!
Name EXPENSES: #REF!
Name Extra_Pay: #REF!
Name Extra_Pay: #REF!
Name Full_Print: #REF!
Name Full_Print: #REF!
Name Header_Row: ROW(#REF!)
Name Header_Row: ROW(#REF!)
Name Int: #REF!
Name Int: #REF!
Name Interest_Rate: #REF!
Name Interest_Rate: #REF!
Name Last_Row: IF('504-Hybrid'!Values_Entered,Header_Row+'504-Hybrid'!Number_of_Payments,Header_Row)
Name Last_Row: IF(Scores!Values_Entered,Scores!Header_Row+Scores!Number_of_Payments,Scores!Header_Row)
Name Last_Row: IF(Values_Entered,Header_Row+Number_of_Payments,Header_Row)
Name Loan_Amount: #REF!
Name Loan_Amount: #REF!
Name Loan_Start: #REF!
Name Loan_Start: #REF!
Name Loan_Years: #REF!
Name Loan_Years: #REF!
Name MajorExpensesList: #REF!
Name MajorExpensesList: #REF!
Name Num_Pmt_Per_Year: #REF!
Name Num_Pmt_Per_Year: #REF!
Name Number_of_Payments: MATCH(0.01,End_Bal,-1)+1
Name Number_of_Payments: MATCH(0.01,Scores!End_Bal,-1)+1
Name Number_of_Payments: MATCH(0.01,End_Bal,-1)+1
Name Pay_Date: #REF!
Name Pay_Num: #REF!
Name Pay_Num: #REF!
Name Payment_Date: DATE(YEAR(Scores!Loan_Start),MONTH(Scores!Loan_Start)+Payment_Number,DAY(Scores!Loan_Start))
Name Payment_Date: DATE(YEAR(Loan_Start),MONTH(Loan_Start)+Payment_Number,DAY(Loan_Start))
Name Periodic_rate: Annual_interest_rate/Payments_per_year
Name Periodic_rate: Annual_interest_rate/Payments_per_year
Name Periodic_rate: Annual_interest_rate/Payments_per_year
Name Princ: #REF!
Name Princ: #REF!
Name Print_Area_Reset: OFFSET(Full_Print,0,0,[0]!Last_Row)
Name Print_Area_Reset: OFFSET(Scores!Full_Print,0,0,Scores!Last_Row)
Name Print_Area_Reset: OFFSET(Full_Print,0,0,Last_Row)
Name Sched_Pay: #REF!
Name Sched_Pay: #REF!
Name Scheduled_Extra_Payments: #REF!
Name Scheduled_Extra_Payments: #REF!
Name Scheduled_Interest_Rate: #REF!
Name Scheduled_Monthly_Payment: #REF!
Name Scheduled_Monthly_Payment: #REF!
Name Total_Interest: #REF!
Name Total_Pay: #REF!
Name Total_Pay: #REF!
Name Total_Payment: Scheduled_Payment+Extra_Payment

Sheet BDO Prequal
B2: BDO Prequalification | U2: Closing Cost Calculator ---> Expand/Collapse Above ---> | AD2: Loan Term Calculator ---> Expand/Collapse Above ---> | AN2: 507 / 7(a) Hybrid Planning ---> Expand/Collapse Above --->
AF6: 504 - Project | AG6: %'s | AH6: Difference
B7: Project | AF7: T Bank Loan | AG7: =P46 -> 0.5 | AH7: =Q46 -> -2886462.5
AF8: CDC Debenture | AG8: =P47 -> 0.3 | AH8: =Q47 -> -669942.5
B9: Business Name: | AF9: Borrower Equity | AG9: =P48 -> 0.2 | AH9: =Q48 -> -122793
I10: BDO: | AF10: Total | AG10: =SUM(AG7:AG9) -> 1 | AH10: =AG55 -> 3541935
I11: Cooperating BDO:
AG13: =C36 -> Total | AH13: =D36 -> Equity | AI13: =Lists!L4 -> SBA 7(a) | AJ13: =Lists!L9 -> Seller Note
B14: Loan Terms | N14: Closing Costs | O14: Cost | P14: Quantity | Q14: Total | AF14: SBA 7(a) Project
E15: 1 | F15: 2 | G15: 3 | H15: 4 | I15: 5 | J15: 6 | K15: 7 | L15: TOTAL | N15: Title Insurance | O15: 0 | P15: 0 | Q15: =O15*P15 -> 0 | R15: 0.5%-1% of CRE value (FL & NY +) | AF15: =B38 -> Real Estate Acquisition | AG15: =SUM(AH15:AJ15) -> 0 | AH15: 0 | AI15: =IFERROR(INDEX($C38:$K38,MATCH(AI$13,$C$36:$K$36,0)),0) -> 0 | AJ15: =IFERROR(INDEX($C38:$K38,MATCH(AJ$13,$C$36:$K$36,0)),0) -> 0
C16: Party | D16: Borrower | E16: T Bank | F16: T Bank | G16: T Bank | H16: Seller | I16: CDC | J16: N/A | K16: N/A | N16: Real Estate Tax Fee | O16: 0 | P16: 0 | Q16: =O16*P16 -> 0 | R16: $166 for 1st $500M, $10 for every $100M after | AF16: =B39 -> Debt Refi - CRE | AG16: =SUM(AH16:AJ16) -> 0 | AH16: 0 | AI16: =IFERROR(INDEX($C39:$K39,MATCH(AI$13,$C$36:$K$36,0)),0) -> 0 | AJ16: =IFERROR(INDEX($C39:$K39,MATCH(AJ$13,$C$36:$K$36,0)),0) -> 0
C17: Financing Type | D17: Equity | E17: SBA 7(a) | F17: SBA 7(a) | G17: SBA 504 | H17: Seller Note | I17: Debenture | J17: N/A | K17: N/A | N17: Survey Charges | O17: 3000 | P17: 0 | Q17: =O17*P17 -> 0 | R17: $1M - $3M | AF17: =B40 -> Debt Refi - Non-CRE | AG17: =SUM(AH17:AJ17) -> 0 | AH17: 0 | AI17: =IFERROR(INDEX($C40:$K40,MATCH(AI$13,$C$36:$K$36,0)),0) -> 0 | AJ17: =IFERROR(INDEX($C40:$K40,MATCH(AJ$13,$C$36:$K$36,0)),0) -> 0
C18: Loan Amount/Injection | D18: =D55 -> 1571792 | E18: =E55 -> 612591 | F18: =F55 -> 2746607 | G18: =G55 -> 1350000 | H18: =H55 -> 320000 | I18: =I55 -> 1871935 | J18: =J55 -> 0 | K18: =K55 -> 0 | N18: CRE Appraisal | O18: 3500 | P18: 0 | Q18: =O18*P18 -> 0 | R18: $3.5M - $6.0M | AF18: =B41 -> Machinery & Equipment | AG18: =SUM(AH18:AJ18) -> 0 | AH18: 0 | AI18: =IFERROR(INDEX($C41:$K41,MATCH(AI$13,$C$36:$K$36,0)),0) -> 0 | AJ18: =IFERROR(INDEX($C41:$K41,MATCH(AJ$13,$C$36:$K$36,0)),0) -> 0
C19: Base Rate | E19: 0.0675 | F19: 0.0594 | G19: 0.0675 | H19: 0.05 | I19: 0.05 | J19: 0.0675 | K19: 0 | N19: Environmental Investigation | O19: 2500 | P19: 0 | Q19: =O19*P19 -> 0 | R19: $2M | AF19: =B42 -> Furniture & Fixtures | AG19: =SUM(AH19:AJ19) -> 0 | AH19: 0 | AI19: =IFERROR(INDEX($C42:$K42,MATCH(AI$13,$C$36:$K$36,0)),0) -> 0 | AJ19: =IFERROR(INDEX($C42:$K42,MATCH(AJ$13,$C$36:$K$36,0)),0) -> 0
C20: Spread | E20: 0.015 | F20: 0 | G20: 0.0275 | H20: 0 | I20: 0.01 | J20: 0.03 | K20: 0 | N20: Residential Appr / Valuation | O20: 500 | P20: 0 | Q20: =O20*P20 -> 0 | R20: $500 - $700 | AF20: =B43 -> Inventory | AG20: =SUM(AH20:AJ20) -> 0 | AH20: 0 | AI20: =IFERROR(INDEX($C43:$K43,MATCH(AI$13,$C$36:$K$36,0)),0) -> 0 | AJ20: =IFERROR(INDEX($C43:$K43,MATCH(AJ$13,$C$36:$K$36,0)),0) -> 0
C21: Indicative Rate | E21: =E19+E20 -> 0.0825 | F21: =F19+F20 -> 0.0594 | G21: =G19+G20 -> 0.095 | H21: =H19+H20 -> 0.05 | I21: =I19+I20 -> 0.06 | J21: =J19+J20 -> 0.0975 | K21: =K19+K20 -> 0 | N21: Business Valuation | O21: 2500 | P21: 1 | Q21: =O21*P21 -> 2500 | R21: $2.5M - $3M | AF21: =B44 -> Working Capital | AG21: =SUM(AH21:AJ21) -> 0 | AH21: 0 | AI21: =IFERROR(INDEX($C44:$K44,MATCH(AI$13,$C$36:$K$36,0)),0) -> 0 | AJ21: =IFERROR(INDEX($C44:$K44,MATCH(AJ$13,$C$36:$K$36,0)),0) -> 0
C22: Amort Basis - I/O - Standby | E22: Actual/365 | F22: Actual/365 | G22: Actual/365 | H22: Actual/365 | I22: Actual/365 | J22: Actual/365 | K22: Actual/365 | N22: Equipment Appraisal | O22: 0 | P22: 0 | Q22: =O22*P22 -> 0 | R22: $1.5M - $3.5M | AF22: =B45 -> Working Capital - Pre Opening | AG22: =SUM(AH22:AJ22) -> 0 | AH22: 0 | AI22: =IFERROR(INDEX($C45:$K45,MATCH(AI$13,$C$36:$K$36,0)),0) -> 0 | AJ22: =IFERROR(INDEX($C45:$K45,MATCH(AJ$13,$C$36:$K$36,0)),0) -> 0
C23: Term (years) | E23: 10 | F23: 10 | G23: 10 | H23: 7 | I23: 3 | J23: 5 | K23: 0 | N23: Site Visit | O23: 350 | P23: 0 | Q23: =O23*P23 -> 0 | R23: 350 | AF23: =B46 -> Business Acquisition | AG23: =SUM(AH23:AJ23) -> 644000 | AH23: 0 | AI23: =IFERROR(INDEX($C46:$K46,MATCH(AI$13,$C$36:$K$36,0)),0) -> 324000 | AJ23: =IFERROR(INDEX($C46:$K46,MATCH(AJ$13,$C$36:$K$36,0)),0) -> 320000
C24: Amortization (mos) | E24: =E23*12 -> 120 | F24: =F23*12 -> 120 | G24: =G23*12 -> 120 | H24: =H23*12 -> 84 | I24: =I23*12 -> 36 | J24: =J23*12 -> 60 | K24: =K23*12 -> 0 | N24: Construction Monitoring | O24: 0 | P24: 0 | Q24: =O24*P24 -> 0 | R24: See Partner ESI pricing sheet | AF24: =B47 -> Franchise Fees | AG24: =SUM(AH24:AJ24) -> 0 | AH24: 0 | AI24: =IFERROR(INDEX($C47:$K47,MATCH(AI$13,$C$36:$K$36,0)),0) -> 0 | AJ24: =IFERROR(INDEX($C47:$K47,MATCH(AJ$13,$C$36:$K$36,0)),0) -> 0
C25: Estimated Payment | E25: =IFERROR(INDEX(Calculations!$K$4:$K$7,MATCH($E$22,Calculations!$B$4:$B$7,0)),0) -> 7515.7979 | F25: =IFERROR(INDEX(Calculations!$K$10:$K$13,MATCH($F$22,Calculations!$B$10:$B$13,0)),0) -> 30417.001 | G25: =IFERROR(INDEX(Calculations!$K$16:$K$19,MATCH($G$22,Calculations!$B$16:$B$19,0)),0) -> 17474.442 | H25: =IFERROR(INDEX(Calculations!$K$22:$K$25,MATCH($H$22,Calculations!$B$22:$B$25,0)),0) -> 4523.4394 | I25: =IFERROR(INDEX(Calculations!$K$28:$K$31,MATCH($I$22,Calculations!$B$28:$B$31,0)),0) -> 56952.537 | J25: =IFERROR(INDEX(Calculations!$K$34:$K$37,MATCH($J$22,Calculations!$B$34:$B$37,0)),0) -> 0 | K25: =IFERROR(INDEX(Calculations!$K$40:$K$43,MATCH($K$22,Calculations!$B$40:$B$43,0)),0) -> 0 | N25: Loan Packaging Fee | O25: 2500 | P25: 1 | Q25: =O25*P25 -> 2500 | R25: $1.5M - 2.5M | AF25: =B48 -> Construction Hard Costs | AG25: =SUM(AH25:AJ25) -> 0 | AH25: 0 | AI25: =IFERROR(INDEX($C48:$K48,MATCH(AI$13,$C$36:$K$36,0)),0) -> 0 | AJ25: =IFERROR(INDEX($C48:$K48,MATCH(AJ$13,$C$36:$K$36,0)),0) -> 0
C26: SBA 7(a) Guarantee Fee | E26: =IF(E17=Lists!$L$4,Calculations!T7,0) -> 13784 | F26: =IF(F17=Lists!$L$4,Calculations!T13,0) -> 74749 | G26: =IF(G17=Lists!$L$4,Calculations!T19,0) -> 0 | H26: =IF(H17=Lists!$L$4,Calculations!T25,0) -> 0 | I26: =IF(I17=Lists!$L$4,Calculations!T31,0) -> 0 | J26: =IF(J17=Lists!$L$4,Calculations!T37,0) -> 0 | K26: =IF(K17=Lists!$L$4,Calculations!T43,0) -> 0 | N26: Closing Doc Prep | O26: 7000 | P26: 0 | Q26: =O26*P26 -> 0 | R26: $3.5M-$6.0M | AF26: =B49 -> Construction Contingency - 10% | AG26: =SUM(AH26:AJ26) -> 222807 | AH26: 0 | AI26: =IFERROR(INDEX($C49:$K49,MATCH(AI$13,$C$36:$K$36,0)),0) -> 222807 | AJ26: =IFERROR(INDEX($C49:$K49,MATCH(AJ$13,$C$36:$K$36,0)),0) -> 0
C27: USDA Guarantee Fee | E27: =IF(E17=Lists!$L$10,Calculations!Z7,0) -> 0 | F27: =IF(F17=Lists!$L$10,Calculations!Z13,0) -> 0 | G27: =IF(G17=Lists!$L$10,Calculations!Z19,0) -> 0 | H27: =IF(H17=Lists!$L$10,Calculations!Z25,0) -> 0 | I27: =IF(I17=Lists!$L$10,Calculations!Z31,0) -> 0 | J27: =IF(J17=Lists!$L$10,Calculations!Z37,0) -> 0 | K27: =IF(K17=Lists!$L$10,Calculations!Z43,0) -> 0 | N27: Interim Loan Fee / Origination | O27: =Q57-O28 -> 112000 | P27: 1 | Q27: =O27*P27 -> 112000 | R27: 1.0% -2.0% Conv/USDA Loans | AF27: =B50 -> Interest Reserve - 3 Mos | AG27: =SUM(AH27:AJ27) -> 0 | AH27: 0 | AI27: =IFERROR(INDEX($C50:$K50,MATCH(AI$13,$C$36:$K$36,0)),0) -> 0 | AJ27: =IFERROR(INDEX($C50:$K50,MATCH(AJ$13,$C$36:$K$36,0)),0) -> 0
C28: Include Interest Reserve? | E28: No | F28: No | G28: No | H28: No | I28: No | J28: No | K28: No | N28: SBA TPL Fee (Third Party Lender) | O28: 0 | P28: 0 | Q28: =O28*P28 -> 0 | R28: 0.5% of T Bank Perm. Loan (504) | AF28: =B51 -> Construction Soft Costs | AG28: =SUM(AH28:AJ28) -> 0 | AH28: 0 | AI28: =IFERROR(INDEX($C51:$K51,MATCH(AI$13,$C$36:$K$36,0)),0) -> 0 | AJ28: =IFERROR(INDEX($C51:$K51,MATCH(AJ$13,$C$36:$K$36,0)),0) -> 0
N29: Rounding | O29: =Q31-SUM(Q15:Q28)-Q30 -> 200 | P29: 1 | Q29: =O29*P29 -> 200 | AF29: =B52 -> Closing Costs | AG29: =SUM(AH29:AJ29) -> 52000 | AH29: 0 | AI29: =IFERROR(INDEX($C52:$K52,MATCH(AI$13,$C$36:$K$36,0)),0) -> 52000 | AJ29: =IFERROR(INDEX($C52:$K52,MATCH(AJ$13,$C$36:$K$36,0)),0) -> 0
C30: Construction Contingency % | D30: 0.1 | F30: Additional Contingecy $ | G30: 0 | I30: SBA 7a Guarantee % | J30: 0.75 | N30: Other: UCCs and Misc Closing | Q30: =IF('BDO Prequal'!C55=0,0,Q43) -> 800 | AF30: =B53 -> SBA Gty Fee | AG30: =SUM(AH30:AJ30) -> 13784 | AH30: 0 | AI30: =IFERROR(INDEX($C53:$K53,MATCH(AI$13,$C$36:$K$36,0)),0) -> 13784 | AJ30: =IFERROR(INDEX($C53:$K53,MATCH(AJ$13,$C$36:$K$36,0)),0) -> 0
C31: Estimated Construction / Interest Only Period | D31: 3 | F31: Additional Interest Reserve $ | G31: 0 | I31: USDA Guarantee % | J31: 0.8 | N31: Total Estimated Closing Costs | Q31: =ROUNDUP(SUM(Q15,Q16,Q17,Q18,Q19,Q20,Q21,Q22,Q23,Q24,Q25,Q26,Q27,Q28,Q30),-3) -> 118000 | AF31: =B54 -> USDA Gty Fee | AG31: =SUM(AH31:AJ31) -> 0 | AH31: 0 | AI31: =IFERROR(INDEX($C54:$K54,MATCH(AI$13,$C$36:$K$36,0)),0) -> 0 | AJ31: =IFERROR(INDEX($C54:$K54,MATCH(AJ$13,$C$36:$K$36,0)),0) -> 0
N32: =IF(C52<>Q31," ***UOP Closing Costs Do Not Match Above - Ensure Cells C52 and Q31 Match if Using Chart***","") -> ***UOP Closing Costs Do Not Match Above - Ensure Cells C52 and Q31 Match if Using Chart*** | AG32: =SUM(AG15:AG31) -> 932591 | AH32: =SUM(AH15:AH31) -> 0 | AI32: =SUM(AH15:AH31) -> 0 | AJ32: =SUM(AJ15:AJ31) -> 320000
N33: Miscellaneous Closing Costs | O33: Cost | P33: Quantity | Q33: Total | AG33: =IFERROR(AG32/$AG$32,0) -> 1 | AH33: =IFERROR(AH32/$AG$32,0) -> 0 | AI33: =IFERROR(AI32/$AG$32,0) -> 0 | AJ33: =IFERROR(AJ32/$AG$32,0) -> 0.34313005
B34: Sources and Uses of Proceeds | N34: Business Credit Report | O34: 35 | P34: 1 | Q34: =O34*P34 -> 35
N35: Personal Credit Report | O35: 25 | P35: 2 | Q35: =O35*P35 -> 50
C36: Total | D36: =D17 -> Equity | E36: =IF(E17=0,"",E17) -> SBA 7(a) | F36: =IF(F17=0,"",F17) -> SBA 7(a) | G36: =IF(G17=0,"",G17) -> SBA 504 | H36: =IF(H17=0,"",H17) -> Seller Note | I36: =IF(I17=0,"",I17) -> Debenture | J36: =IF(J17=0,"",J17) -> N/A | K36: =IF(K17=0,"",K17) -> N/A | N36: IRS Transcript Service | O36: 65 | P36: 2 | Q36: =O36*P36 -> 130 | W36: Loan Considered | X36: 1 | Z36: Product | AA36: =IF(X36=E15,E36,IF(X36=F15,F36,IF(X36=G15,G36,IF(X36=H15,H36,IF(X36=I15,I36,IF(X36=J15,J36,IF(X36=K15,K36,L15))))))) -> SBA 7(a) | AG36: =C36 -> Total | AH36: =D36 -> Equity | AI36: =Lists!L5 -> SBA 504 | AJ36: =Lists!L6 -> Debenture | AK36: =Lists!L9 -> Seller Note
B37: Direct Project Costs | N37: UCC Searches | O37: 300 | P37: 1 | Q37: =O37*P37 -> 300 | AF37: SBA 504 Project
B38: Real Estate Acquisition | C38: =SUM(D38:K38) -> 0 | E38: 0 | F38: 0 | G38: 0 | H38: 0 | I38: 0 | J38: 0 | K38: 0 | N38: Certificate of Good Standing | O38: 20 | P38: 1 | Q38: =O38*P38 -> 20 | Y38: Term (yrs) | Z38: % | AA38: Wgt | AF38: =B38 -> Real Estate Acquisition | AG38: =SUM(AH38:AK38) -> 0 | AH38: 0 | AI38: =IFERROR(INDEX($C38:$K38,MATCH(AI$36,$C$36:$K$36,0)),0) -> 0 | AJ38: =IFERROR(INDEX($C38:$K38,MATCH(AJ$36,$C$36:$K$36,0)),0) -> 0 | AK38: =IFERROR(INDEX($C38:$K38,MATCH(AK$36,$C$36:$K$36,0)),0) -> 0
B39: Debt Refi - CRE | C39: =SUM(D39:K39) -> 0 | D39: 0 | E39: 0 | F39: 0 | G39: 0 | H39: 0 | I39: 0 | J39: 0 | K39: 0 | N39: Flood Certification | O39: 18 | P39: 1 | Q39: =O39*P39 -> 18 | W39: =B38 -> Real Estate Acquisition | X39: =IF($X$36=$E$15,E38,IF($X$36=$F$15,F38,IF($X$36=$G$15,G38,IF($X$36=$H$15,H38,IF($X$36=$I$15,I38,IF($X$36=$J$15,J38,IF($X$36=$K$15,K38,IF($X$36=$L$15,C38,C38)))))))) -> 0 | Y39: 25 | Z39: =IF($X$53=0,0,X39/$X$53) -> 0 | AA39: =Y39*Z39 -> 0 | AF39: =B39 -> Debt Refi - CRE | AG39: =SUM(AH39:AK39) -> 0 | AH39: 0 | AI39: =IFERROR(INDEX($C39:$K39,MATCH(AI$36,$C$36:$K$36,0)),0) -> 0 | AJ39: =IFERROR(INDEX($C39:$K39,MATCH(AJ$36,$C$36:$K$36,0)),0) -> 0 | AK39: =IFERROR(INDEX($C39:$K39,MATCH(AK$36,$C$36:$K$36,0)),0) -> 0
B40: Debt Refi - Non-CRE | C40: =SUM(D40:K40) -> 0 | D40: 0 | E40: 0 | F40: 0 | G40: 0 | H40: 0 | I40: 0 | J40: 0 | K40: 0 | N40: Filing & Recording Fees | O40: 100 | P40: 1 | Q40: =O40*P40 -> 100 | R40: avg $100 | W40: =B39 -> Debt Refi - CRE | X40: =IF($X$36=$E$15,E39,IF($X$36=$F$15,F39,IF($X$36=$G$15,G39,IF($X$36=$H$15,H39,IF($X$36=$I$15,I39,IF($X$36=$J$15,J39,IF($X$36=$K$15,K39,IF($X$36=$L$15,C39,C39)))))))) -> 0 | Y40: 25 | Z40: =IF($X$53=0,0,X40/$X$53) -> 0 | AA40: =Y40*Z40 -> 0 | AF40: =B40 -> Debt Refi - Non-CRE | AG40: =SUM(AH40:AK40) -> 0 | AH40: 0 | AI40: =IFERROR(INDEX($C40:$K40,MATCH(AI$36,$C$36:$K$36,0)),0) -> 0 | AJ40: =IFERROR(INDEX($C40:$K40,MATCH(AJ$36,$C$36:$K$36,0)),0) -> 0 | AK40: =IFERROR(INDEX($C40:$K40,MATCH(AK$36,$C$36:$K$36,0)),0) -> 0
B41: Machinery & Equipment | C41: =SUM(D41:K41) -> 366285 | D41: 366285 | E41: 0 | F41: 0 | G41: 0 | H41: 0 | I41: 0 | J41: 0 | K41: 0 | N41: FedEx Charges | O41: 50 | P41: 1 | Q41: =O41*P41 -> 50 | R41: avg $50 | W41: =B40 -> Debt Refi - Non-CRE | X41: =IF($X$36=$E$15,E40,IF($X$36=$F$15,F40,IF($X$36=$G$15,G40,IF($X$36=$H$15,H40,IF($X$36=$I$15,I40,IF($X$36=$J$15,J40,IF($X$36=$K$15,K40,IF($X$36=$L$15,C40,C40)))))))) -> 0 | Y41: 10 | Z41: =IF($X$53=0,0,X41/$X$53) -> 0 | AA41: =Y41*Z41 -> 0 | AF41: =B41 -> Machinery & Equipment | AG41: =SUM(AH41:AK41) -> 0 | AH41: 0 | AI41: =IFERROR(INDEX($C41:$K41,MATCH(AI$36,$C$36:$K$36,0)),0) -> 0 | AJ41: =IFERROR(INDEX($C41:$K41,MATCH(AJ$36,$C$36:$K$36,0)),0) -> 0 | AK41: =IFERROR(INDEX($C41:$K41,MATCH(AK$36,$C$36:$K$36,0)),0) -> 0
B42: Furniture & Fixtures | C42: =SUM(D42:K42) -> 600000 | D42: 0 | E42: 0 | F42: 600000 | G42: 0 | H42: 0 | I42: 0 | J42: 0 | K42: 0 | N42: Other: rounding | O42: =Q43-SUM(Q34:Q41) -> 97 | P42: 1 | Q42: =O42*P42 -> 97 | W42: =B41 -> Machinery & Equipment | X42: =IF($X$36=$E$15,E41,IF($X$36=$F$15,F41,IF($X$36=$G$15,G41,IF($X$36=$H$15,H41,IF($X$36=$I$15,I41,IF($X$36=$J$15,J41,IF($X$36=$K$15,K41,IF($X$36=$L$15,C41,C41)))))))) -> 0 | Y42: 10 | Z42: =IF($X$53=0,0,X42/$X$53) -> 0 | AA42: =Y42*Z42 -> 0 | AF42: =B42 -> Furniture & Fixtures | AG42: =SUM(AH42:AK42) -> 0 | AH42: 0 | AI42: =IFERROR(INDEX($C42:$K42,MATCH(AI$36,$C$36:$K$36,0)),0) -> 0 | AJ42: =IFERROR(INDEX($C42:$K42,MATCH(AJ$36,$C$36:$K$36,0)),0) -> 0 | AK42: =IFERROR(INDEX($C42:$K42,MATCH(AK$36,$C$36:$K$36,0)),0) -> 0
B43: Inventory | C43: =SUM(D43:K43) -> 0 | D43: 0 | E43: 0 | F43: 0 | G43: 0 | H43: 0 | I43: 0 | J43: 0 | K43: 0 | N43: Total Misc. Closing Costs | Q43: =ROUNDUP(SUM(Q34,Q35,Q36,Q37,Q38,Q39,Q40,Q41),-2) -> 800 | W43: =B42 -> Furniture & Fixtures | X43: =IF($X$36=$E$15,E42,IF($X$36=$F$15,F42,IF($X$36=$G$15,G42,IF($X$36=$H$15,H42,IF($X$36=$I$15,I42,IF($X$36=$J$15,J42,IF($X$36=$K$15,K42,IF($X$36=$L$15,C42,C42)))))))) -> 0 | Y43: 10 | Z43: =IF($X$53=0,0,X43/$X$53) -> 0 | AA43: =Y43*Z43 -> 0 | AF43: =B43 -> Inventory | AG43: =SUM(AH43:AK43) -> 0 | AH43: 0 | AI43: =IFERROR(INDEX($C43:$K43,MATCH(AI$36,$C$36:$K$36,0)),0) -> 0 | AJ43: =IFERROR(INDEX($C43:$K43,MATCH(AJ$36,$C$36:$K$36,0)),0) -> 0 | AK43: =IFERROR(INDEX($C43:$K43,MATCH(AK$36,$C$36:$K$36,0)),0) -> 0
B44: Working Capital | C44: =SUM(D44:K44) -> 573500 | D44: 573500 | E44: 0 | F44: 0 | G44: 0 | H44: 0 | I44: 0 | J44: 0 | K44: 0 | W44: =B43 -> Inventory | X44: =IF($X$36=$E$15,E43,IF($X$36=$F$15,F43,IF($X$36=$G$15,G43,IF($X$36=$H$15,H43,IF($X$36=$I$15,I43,IF($X$36=$J$15,J43,IF($X$36=$K$15,K43,IF($X$36=$L$15,C43,C43)))))))) -> 0 | Y44: 10 | Z44: =IF($X$53=0,0,X44/$X$53) -> 0 | AA44: =Y44*Z44 -> 0 | AF44: =B44 -> Working Capital | AG44: =SUM(AH44:AK44) -> 0 | AH44: 0 | AI44: =IFERROR(INDEX($C44:$K44,MATCH(AI$36,$C$36:$K$36,0)),0) -> 0 | AJ44: =IFERROR(INDEX($C44:$K44,MATCH(AJ$36,$C$36:$K$36,0)),0) -> 0 | AK44: =IFERROR(INDEX($C44:$K44,MATCH(AK$36,$C$36:$K$36,0)),0) -> 0
B45: Working Capital - Pre Opening | C45: =SUM(D45:K45) -> 77000 | D45: 77000 | E45: 0 | F45: 0 | G45: 0 | H45: 0 | I45: 0 | J45: 0 | K45: 0 | N45: Total Project | O45: =C55 -> 8472925 | P45: =SUM(P46:P48) -> 1 | Q45: (difference) | W45: =B44 -> Working Capital | X45: =IF($X$36=$E$15,E44,IF($X$36=$F$15,F44,IF($X$36=$G$15,G44,IF($X$36=$H$15,H44,IF($X$36=$I$15,I44,IF($X$36=$J$15,J44,IF($X$36=$K$15,K44,IF($X$36=$L$15,C44,C44)))))))) -> 0 | Y45: 10 | Z45: =IF($X$53=0,0,X45/$X$53) -> 0 | AA45: =Y45*Z45 -> 0 | AF45: =B45 -> Working Capital - Pre Opening | AG45: =SUM(AH45:AK45) -> 0 | AH45: 0 | AI45: =IFERROR(INDEX($C45:$K45,MATCH(AI$36,$C$36:$K$36,0)),0) -> 0 | AJ45: =IFERROR(INDEX($C45:$K45,MATCH(AJ$36,$C$36:$K$36,0)),0) -> 0 | AK45: =IFERROR(INDEX($C45:$K45,MATCH(AK$36,$C$36:$K$36,0)),0) -> 0
B46: Business Acquisition | C46: =SUM(D46:K46) -> 2219000 | D46: 225000 | E46: 324000 | F46: 0 | G46: 1350000 | H46: 320000 | I46: 0 | J46: 0 | K46: 0 | N46: Bank Loan % | O46: =O45*P46 -> 4236462.5 | P46: 0.5 | Q46: {=SUMPRODUCT((E17:K17=Lists!$L$5)*E18:K18)-O46} -> -2886462.5 | W46: =B45 -> Working Capital - Pre Opening | X46: =IF($X$36=$E$15,E45,IF($X$36=$F$15,F45,IF($X$36=$G$15,G45,IF($X$36=$H$15,H45,IF($X$36=$I$15,I45,IF($X$36=$J$15,J45,IF($X$36=$K$15,K45,IF($X$36=$L$15,C45,C45)))))))) -> 0 | Y46: 10 | Z46: =IF($X$53=0,0,X46/$X$53) -> 0 | AA46: =Y46*Z46 -> 0 | AF46: =B46 -> Business Acquisition | AG46: =SUM(AH46:AK46) -> 1670000 | AH46: 0 | AI46: =IFERROR(INDEX($C46:$K46,MATCH(AI$36,$C$36:$K$36,0)),0) -> 1350000 | AJ46: =IFERROR(INDEX($C46:$K46,MATCH(AJ$36,$C$36:$K$36,0)),0) -> 0 | AK46: =IFERROR(INDEX($C46:$K46,MATCH(AK$36,$C$36:$K$36,0)),0) -> 320000
B47: Franchise Fees | C47: =SUM(D47:K47) -> 0 | D47: 0 | E47: 0 | F47: 0 | G47: 0 | H47: 0 | I47: 0 | J47: 0 | K47: 0 | N47: CDC Loan % | O47: =O45*P47 -> 2541877.5 | P47: 0.3 | Q47: {=SUMPRODUCT((E17:K17=Lists!$L$6)*E18:K18)-O47} -> -669942.5 | W47: =B46 -> Business Acquisition | X47: =IF($X$36=$E$15,E46,IF($X$36=$F$15,F46,IF($X$36=$G$15,G46,IF($X$36=$H$15,H46,IF($X$36=$I$15,I46,IF($X$36=$J$15,J46,IF($X$36=$K$15,K46,IF($X$36=$L$15,C46,C46)))))))) -> 324000 | Y47: 10 | Z47: =IF($X$53=0,0,X47/$X$53) -> 0.59253082 | AA47: =Y47*Z47 -> 5.9253082 | AF47: =B47 -> Franchise Fees | AG47: =SUM(AH47:AK47) -> 0 | AH47: 0 | AI47: =IFERROR(INDEX($C47:$K47,MATCH(AI$36,$C$36:$K$36,0)),0) -> 0 | AJ47: =IFERROR(INDEX($C47:$K47,MATCH(AJ$36,$C$36:$K$36,0)),0) -> 0 | AK47: =IFERROR(INDEX($C47:$K47,MATCH(AK$36,$C$36:$K$36,0)),0) -> 0
B48: Construction Hard Costs | C48: =SUM(D48:K48) -> 4100000 | D48: 276207 | E48: 0 | F48: 1951858 | G48: 0 | H48: 0 | I48: 1871935 | J48: 0 | K48: 0 | N48: Borrower % | O48: =O45*P48 -> 1694585 | P48: 0.2 | Q48: =D55-O48 -> -122793 | W48: =B47 -> Franchise Fees | X48: =IF($X$36=$E$15,E47,IF($X$36=$F$15,F47,IF($X$36=$G$15,G47,IF($X$36=$H$15,H47,IF($X$36=$I$15,I47,IF($X$36=$J$15,J47,IF($X$36=$K$15,K47,IF($X$36=$L$15,C47,C47)))))))) -> 0 | Y48: 10 | Z48: =IF($X$53=0,0,X48/$X$53) -> 0 | AA48: =Y48*Z48 -> 0 | AF48: =B48 -> Construction Hard Costs | AG48: =SUM(AH48:AK48) -> 1871935 | AH48: 0 | AI48: =IFERROR(INDEX($C48:$K48,MATCH(AI$36,$C$36:$K$36,0)),0) -> 0 | AJ48: =IFERROR(INDEX($C48:$K48,MATCH(AJ$36,$C$36:$K$36,0)),0) -> 1871935 | AK48: =IFERROR(INDEX($C48:$K48,MATCH(AK$36,$C$36:$K$36,0)),0) -> 0
B49: ="Construction Contingency - "&TEXT(D30,"0%") -> Construction Contingency - 10% | C49: =Calculations!$K$47 -> 222807 | D49: 0 | E49: =C49 -> 222807 | F49: 0 | G49: 0 | H49: 0 | I49: 0 | J49: 0 | K49: 0 | W49: =B48 -> Construction Hard Costs | X49: =IF($X$36=$E$15,E48,IF($X$36=$F$15,F48,IF($X$36=$G$15,G48,IF($X$36=$H$15,H48,IF($X$36=$I$15,I48,IF($X$36=$J$15,J48,IF($X$36=$K$15,K48,IF($X$36=$L$15,C48,C48)))))))) -> 0 | Y49: 25 | Z49: =IF($X$53=0,0,X49/$X$53) -> 0 | AA49: =Y49*Z49 -> 0 | AF49: =B49 -> Construction Contingency - 10% | AG49: =SUM(AH49:AK49) -> 0 | AH49: 0 | AI49: =IFERROR(INDEX($C49:$K49,MATCH(AI$36,$C$36:$K$36,0)),0) -> 0 | AJ49: =IFERROR(INDEX($C49:$K49,MATCH(AJ$36,$C$36:$K$36,0)),0) -> 0 | AK49: =IFERROR(INDEX($C49:$K49,MATCH(AK$36,$C$36:$K$36,0)),0) -> 0
B50: ="Interest Reserve - "&D31&" Mos" -> Interest Reserve - 3 Mos | C50: =Calculations!$K$48 -> 0 | D50: 0 | E50: =C50 -> 0 | F50: 0 | G50: 0 | H50: 0 | I50: 0 | J50: 0 | K50: 0 | O50: Bridge / Interim Loan | P50: {=SUMPRODUCT((E17:K17=Lists!$L$5)+(E17:K17=Lists!$L$6),E18:K18)} -> 3221935 | W50: =B49 -> Construction Contingency - 10% | X50: =IF($X$36=$E$15,E49,IF($X$36=$F$15,F49,IF($X$36=$G$15,G49,IF($X$36=$H$15,H49,IF($X$36=$I$15,I49,IF($X$36=$J$15,J49,IF($X$36=$K$15,K49,IF($X$36=$L$15,C49,C49)))))))) -> 222807 | Y50: 25 | Z50: =IF($X$53=0,0,X50/$X$53) -> 0.40746918 | AA50: =Y50*Z50 -> 10.18673 | AF50: =B50 -> Interest Reserve - 3 Mos | AG50: =SUM(AH50:AK50) -> 0 | AH50: 0 | AI50: =IFERROR(INDEX($C50:$K50,MATCH(AI$36,$C$36:$K$36,0)),0) -> 0 | AJ50: =IFERROR(INDEX($C50:$K50,MATCH(AJ$36,$C$36:$K$36,0)),0) -> 0 | AK50: =IFERROR(INDEX($C50:$K50,MATCH(AK$36,$C$36:$K$36,0)),0) -> 0
B51: Construction Soft Costs | C51: =SUM(D51:K51) -> 173800 | D51: 53800 | E51: 0 | F51: 120000 | G51: 0 | H51: 0 | I51: 0 | J51: 0 | K51: 0 | O51: Bank Interim Loan Fee % >>> | P51: 0.015 | W51: =B50 -> Interest Reserve - 3 Mos | X51: =IF($X$36=$E$15,E50,IF($X$36=$F$15,F50,IF($X$36=$G$15,G50,IF($X$36=$H$15,H50,IF($X$36=$I$15,I50,IF($X$36=$J$15,J50,IF($X$36=$K$15,K50,IF($X$36=$L$15,C50,C50)))))))) -> 0 | Y51: 25 | Z51: =IF($X$53=0,0,X51/$X$53) -> 0 | AA51: =Y51*Z51 -> 0 | AF51: =B51 -> Construction Soft Costs | AG51: =SUM(AH51:AK51) -> 0 | AH51: 0 | AI51: =IFERROR(INDEX($C51:$K51,MATCH(AI$36,$C$36:$K$36,0)),0) -> 0 | AJ51: =IFERROR(INDEX($C51:$K51,MATCH(AJ$36,$C$36:$K$36,0)),0) -> 0 | AK51: =IFERROR(INDEX($C51:$K51,MATCH(AK$36,$C$36:$K$36,0)),0) -> 0
B52: Closing Costs | C52: =SUM(D52:K52) -> 52000 | D52: 0 | E52: 52000 | F52: 0 | G52: 0 | H52: 0 | I52: 0 | J52: 0 | K52: 0 | O52: Interim Loan Fee % to Perm Loan | P52: =Q52/O46 -> 0.011407873 | Q52: =P50*P51 -> 48329.025 | W52: =B51 -> Construction Soft Costs | X52: =IF($X$36=$E$15,E51,IF($X$36=$F$15,F51,IF($X$36=$G$15,G51,IF($X$36=$H$15,H51,IF($X$36=$I$15,I51,IF($X$36=$J$15,J51,IF($X$36=$K$15,K51,IF($X$36=$L$15,C51,C51)))))))) -> 0 | Y52: 25 | Z52: =IF($X$53=0,0,X52/$X$53) -> 0 | AA52: =Y52*Z52 -> 0 | AF52: =B52 -> Closing Costs | AG52: =SUM(AH52:AK52) -> 0 | AH52: 0 | AI52: =IFERROR(INDEX($C52:$K52,MATCH(AI$36,$C$36:$K$36,0)),0) -> 0 | AJ52: =IFERROR(INDEX($C52:$K52,MATCH(AJ$36,$C$36:$K$36,0)),0) -> 0 | AK52: =IFERROR(INDEX($C52:$K52,MATCH(AK$36,$C$36:$K$36,0)),0) -> 0
B53: SBA Gty Fee | C53: =SUM(D53:K53) -> 88533 | D53: 0 | E53: =IF(E17<>Lists!$L$4,0, _xlfn.LET( _xlpm.base, SUM(E38:E52)+E54, _xlpm.gty, $J$30, _xlpm.tier1_fee, 0.02*_xlpm.gty*_xlpm.base/(1-0.02*_xlpm.gty), _xlpm.tier2_fee, 0.03*_xlpm.gty*_xlpm.base/(1-0.03*_xlpm.gty), _xlpm.tier3_lowfee, 0.035*_xlpm.gty*_xlpm.base/(1-0.035*_xlpm.gty), _xlpm.tier3_highfee, (-2500+0.0375*_xlpm.gty*_xlpm.base)/(1-0.0375*_xlpm.gty), _xlpm.total1, _xlpm.base+_xlpm.tier1_fee, _xlpm.total2, _xlpm.base+_xlpm.tier2_fee, _xlpm.total3_low, _xlpm.base+_xlpm.tier3_lowfee, _xlpm.total3_high, _xlpm.base+_xlpm.tier3_highfee, _xlpm.result, IF(_xlpm.total1<=150000, _xlpm.tier1_fee, IF(_xlpm.total2<=700000, _xlpm.tier2_fee, IF(_xlpm.total3_low*_xlpm.gty<=1000000, _xlpm.tier3_lowfee, _xlpm.tier3_highfee))), ROUNDUP(_xlpm.result,0) )) -> 13784 | F53: =IF(F17<>Lists!$L$4,0,_xlfn.LET(_xlpm.base,SUM(F38:F52)+F54,_xlpm.gty,$J$30,_xlpm.tier1_fee,0.02*_xlpm.gty*_xlpm.base/(1-0.02*_xlpm.gty),_xlpm.tier2_fee,0.03*_xlpm.gty*_xlpm.base/(1-0.03*_xlpm.gty),_xlpm.tier3_lowfee,0.035*_xlpm.gty*_xlpm.base/(1-0.035*_xlpm.gty),_xlpm.tier3_highfee,(-2500+0.0375*_xlpm.gty*_xlpm.base)/(1-0.0375*_xlpm.gty),_xlpm.total1,_xlpm.base+_xlpm.tier1_fee,_xlpm.total2,_xlpm.base+_xlpm.tier2_fee,_xlpm.total3_low,_xlpm.base+_xlpm.tier3_lowfee,_xlpm.total3_high,_xlpm.base+_xlpm.tier3_highfee,_xlpm.result,IF(_xlpm.total1<=150000,_xlpm.tier1_fee,IF(_xlpm.total2<=700000,_xlpm.tier2_fee,IF(_xlpm.total3_low*_xlpm.gty<=1000000,_xlpm.tier3_lowfee,_xlpm.tier3_highfee))),ROUNDUP(_xlpm.result,0))) -> 74749 | G53: =IF(G17<>Lists!$L$4,0,_xlfn.LET(_xlpm.base,SUM(G38:G52)+G54,_xlpm.gty,$J$30,_xlpm.tier1_fee,0.02*_xlpm.gty*_xlpm.base/(1-0.02*_xlpm.gty),_xlpm.tier2_fee,0.03*_xlpm.gty*_xlpm.base/(1-0.03*_xlpm.gty),_xlpm.tier3_lowfee,0.035*_xlpm.gty*_xlpm.base/(1-0.035*_xlpm.gty),_xlpm.tier3_highfee,(-2500+0.0375*_xlpm.gty*_xlpm.base)/(1-0.0375*_xlpm.gty),_xlpm.total1,_xlpm.base+_xlpm.tier1_fee,_xlpm.total2,_xlpm.base+_xlpm.tier2_fee,_xlpm.total3_low,_xlpm.base+_xlpm.tier3_lowfee,_xlpm.total3_high,_xlpm.base+_xlpm.tier3_highfee,_xlpm.result,IF(_xlpm.total1<=150000,_xlpm.tier1_fee,IF(_xlpm.total2<=700000,_xlpm.tier2_fee,IF(_xlpm.total3_low*_xlpm.gty<=1000000,_xlpm.tier3_lowfee,_xlpm.tier3_highfee))),ROUNDUP(_xlpm.result,0))) -> 0 | H53: =IF(H17<>Lists!$L$4,0,_xlfn.LET(_xlpm.base,SUM(H38:H52)+H54,_xlpm.gty,$J$30,_xlpm.tier1_fee,0.02*_xlpm.gty*_xlpm.base/(1-0.02*_xlpm.gty),_xlpm.tier2_fee,0.03*_xlpm.gty*_xlpm.base/(1-0.03*_xlpm.gty),_xlpm.tier3_lowfee,0.035*_xlpm.gty*_xlpm.base/(1-0.035*_xlpm.gty),_xlpm.tier3_highfee,(-2500+0.0375*_xlpm.gty*_xlpm.base)/(1-0.0375*_xlpm.gty),_xlpm.total1,_xlpm.base+_xlpm.tier1_fee,_xlpm.total2,_xlpm.base+_xlpm.tier2_fee,_xlpm.total3_low,_xlpm.base+_xlpm.tier3_lowfee,_xlpm.total3_high,_xlpm.base+_xlpm.tier3_highfee,_xlpm.result,IF(_xlpm.total1<=150000,_xlpm.tier1_fee,IF(_xlpm.total2<=700000,_xlpm.tier2_fee,IF(_xlpm.total3_low*_xlpm.gty<=1000000,_xlpm.tier3_lowfee,_xlpm.tier3_highfee))),ROUNDUP(_xlpm.result,0))) -> 0 | I53: =IF(I17<>Lists!$L$4,0,_xlfn.LET(_xlpm.base,SUM(I38:I52)+I54,_xlpm.gty,$J$30,_xlpm.tier1_fee,0.02*_xlpm.gty*_xlpm.base/(1-0.02*_xlpm.gty),_xlpm.tier2_fee,0.03*_xlpm.gty*_xlpm.base/(1-0.03*_xlpm.gty),_xlpm.tier3_lowfee,0.035*_xlpm.gty*_xlpm.base/(1-0.035*_xlpm.gty),_xlpm.tier3_highfee,(-2500+0.0375*_xlpm.gty*_xlpm.base)/(1-0.0375*_xlpm.gty),_xlpm.total1,_xlpm.base+_xlpm.tier1_fee,_xlpm.total2,_xlpm.base+_xlpm.tier2_fee,_xlpm.total3_low,_xlpm.base+_xlpm.tier3_lowfee,_xlpm.total3_high,_xlpm.base+_xlpm.tier3_highfee,_xlpm.result,IF(_xlpm.total1<=150000,_xlpm.tier1_fee,IF(_xlpm.total2<=700000,_xlpm.tier2_fee,IF(_xlpm.total3_low*_xlpm.gty<=1000000,_xlpm.tier3_lowfee,_xlpm.tier3_highfee))),ROUNDUP(_xlpm.result,0))) -> 0 | J53: =IF(J17<>Lists!$L$4,0,_xlfn.LET(_xlpm.base,SUM(J38:J52)+J54,_xlpm.gty,$J$30,_xlpm.tier1_fee,0.02*_xlpm.gty*_xlpm.base/(1-0.02*_xlpm.gty),_xlpm.tier2_fee,0.03*_xlpm.gty*_xlpm.base/(1-0.03*_xlpm.gty),_xlpm.tier3_lowfee,0.035*_xlpm.gty*_xlpm.base/(1-0.035*_xlpm.gty),_xlpm.tier3_highfee,(-2500+0.0375*_xlpm.gty*_xlpm.base)/(1-0.0375*_xlpm.gty),_xlpm.total1,_xlpm.base+_xlpm.tier1_fee,_xlpm.total2,_xlpm.base+_xlpm.tier2_fee,_xlpm.total3_low,_xlpm.base+_xlpm.tier3_lowfee,_xlpm.total3_high,_xlpm.base+_xlpm.tier3_highfee,_xlpm.result,IF(_xlpm.total1<=150000,_xlpm.tier1_fee,IF(_xlpm.total2<=700000,_xlpm.tier2_fee,IF(_xlpm.total3_low*_xlpm.gty<=1000000,_xlpm.tier3_lowfee,_xlpm.tier3_highfee))),ROUNDUP(_xlpm.result,0))) -> 0 | K53: =IF(K17<>Lists!$L$4,0,_xlfn.LET(_xlpm.base,SUM(K38:K52)+K54,_xlpm.gty,$J$30,_xlpm.tier1_fee,0.02*_xlpm.gty*_xlpm.base/(1-0.02*_xlpm.gty),_xlpm.tier2_fee,0.03*_xlpm.gty*_xlpm.base/(1-0.03*_xlpm.gty),_xlpm.tier3_lowfee,0.035*_xlpm.gty*_xlpm.base/(1-0.035*_xlpm.gty),_xlpm.tier3_highfee,(-2500+0.0375*_xlpm.gty*_xlpm.base)/(1-0.0375*_xlpm.gty),_xlpm.total1,_xlpm.base+_xlpm.tier1_fee,_xlpm.total2,_xlpm.base+_xlpm.tier2_fee,_xlpm.total3_low,_xlpm.base+_xlpm.tier3_lowfee,_xlpm.total3_high,_xlpm.base+_xlpm.tier3_highfee,_xlpm.result,IF(_xlpm.total1<=150000,_xlpm.tier1_fee,IF(_xlpm.total2<=700000,_xlpm.tier2_fee,IF(_xlpm.total3_low*_xlpm.gty<=1000000,_xlpm.tier3_lowfee,_xlpm.tier3_highfee))),ROUNDUP(_xlpm.result,0))) -> 0 | O53: SBA TPL Fee % | P53: 0.005 | Q53: =O46*P53 -> 21182.312 | W53: Total | X53: =SUM(X39:X52) -> 546807 | Z53: Weighted Term | AA53: =SUM(AA39:AA52) -> 16.112038 | AF53: =B53 -> SBA Gty Fee | AG53: =SUM(AH53:AK53) -> 0 | AH53: 0 | AI53: =IFERROR(INDEX($C53:$K53,MATCH(AI$36,$C$36:$K$36,0)),0) -> 0 | AJ53: =IFERROR(INDEX($C53:$K53,MATCH(AJ$36,$C$36:$K$36,0)),0) -> 0 | AK53: =IFERROR(INDEX($C53:$K53,MATCH(AK$36,$C$36:$K$36,0)),0) -> 0
B54: USDA Gty Fee | C54: =SUM(D54:K54) -> 0 | D54: 0 | E54: =IF(E17<>Lists!$L$10,0,_xlfn.LET(_xlpm.nc,SUM(E38:E47)+E50+SUM(E51:E53),_xlpm.cn,E48+E49,_xlpm.gty,Calculations!$X$3,_xlpm.raw,(_xlpm.gty*0.03*_xlpm.nc+_xlpm.gty*0.035*_xlpm.cn)/(1-_xlpm.gty*0.03),ROUNDUP(_xlpm.raw,0))) -> 0 | F54: =IF(F17<>Lists!$L$10,0,_xlfn.LET(_xlpm.nc,SUM(F38:F47)+F50+SUM(F51:F53),_xlpm.cn,F48+F49,_xlpm.gty,Calculations!$X$3,_xlpm.raw,(_xlpm.gty*0.03*_xlpm.nc+_xlpm.gty*0.035*_xlpm.cn)/(1-_xlpm.gty*0.03),ROUNDUP(_xlpm.raw,0))) -> 0 | G54: =IF(G17<>Lists!$L$10,0,_xlfn.LET(_xlpm.nc,SUM(G38:G47)+G50+SUM(G51:G53),_xlpm.cn,G48+G49,_xlpm.gty,Calculations!$X$3,_xlpm.raw,(_xlpm.gty*0.03*_xlpm.nc+_xlpm.gty*0.035*_xlpm.cn)/(1-_xlpm.gty*0.03),ROUNDUP(_xlpm.raw,0))) -> 0 | H54: =IF(H17<>Lists!$L$10,0,_xlfn.LET(_xlpm.nc,SUM(H38:H47)+H50+SUM(H51:H53),_xlpm.cn,H48+H49,_xlpm.gty,Calculations!$X$3,_xlpm.raw,(_xlpm.gty*0.03*_xlpm.nc+_xlpm.gty*0.035*_xlpm.cn)/(1-_xlpm.gty*0.03),ROUNDUP(_xlpm.raw,0))) -> 0 | I54: =IF(I17<>Lists!$L$10,0,_xlfn.LET(_xlpm.nc,SUM(I38:I47)+I50+SUM(I51:I53),_xlpm.cn,I48+I49,_xlpm.gty,Calculations!$X$3,_xlpm.raw,(_xlpm.gty*0.03*_xlpm.nc+_xlpm.gty*0.035*_xlpm.cn)/(1-_xlpm.gty*0.03),ROUNDUP(_xlpm.raw,0))) -> 0 | J54: =IF(J17<>Lists!$L$10,0,_xlfn.LET(_xlpm.nc,SUM(J38:J47)+J50+SUM(J51:J53),_xlpm.cn,J48+J49,_xlpm.gty,Calculations!$X$3,_xlpm.raw,(_xlpm.gty*0.03*_xlpm.nc+_xlpm.gty*0.035*_xlpm.cn)/(1-_xlpm.gty*0.03),ROUNDUP(_xlpm.raw,0))) -> 0 | K54: 0 | O54: Referral Fee % | P54: 0.01 | Q54: =O46*P54 -> 42364.625 | AF54: =B54 -> USDA Gty Fee | AG54: =SUM(AH54:AK54) -> 0 | AH54: 0 | AI54: =IFERROR(INDEX($C54:$K54,MATCH(AI$36,$C$36:$K$36,0)),0) -> 0 | AJ54: =IFERROR(INDEX($C54:$K54,MATCH(AJ$36,$C$36:$K$36,0)),0) -> 0 | AK54: =IFERROR(INDEX($C54:$K54,MATCH(AK$36,$C$36:$K$36,0)),0) -> 0
C55: =SUM(C38:C53) -> 8472925 | D55: =SUM(D38:D54) -> 1571792 | E55: =SUM(E38:E54) -> 612591 | F55: =SUM(F38:F54) -> 2746607 | G55: =SUM(G38:G54) -> 1350000 | H55: =SUM(H38:H54) -> 320000 | I55: =SUM(I38:I54) -> 1871935 | J55: =SUM(J38:J54) -> 0 | K55: =SUM(K38:K54) -> 0 | O55: Participant Fee % | P55: 0 | Q55: =P55*O46 -> 0 | W55: Blended Term Calculator | AG55: =SUM(AG38:AG54) -> 3541935 | AH55: =SUM(AH38:AH54) -> 0 | AI55: =SUM(AI38:AI54) -> 1350000 | AJ55: =SUM(AJ38:AJ54) -> 1871935 | AK55: =SUM(AK38:AK54) -> 320000
C56: =IFERROR(C55/$C$55,0) -> 1 | D56: =IFERROR(D55/$C$55,0) -> 0.1855076 | E56: =IFERROR(E55/$C$55,0) -> 0.072299826 | F56: =IFERROR(F55/$C$55,0) -> 0.32416279 | G56: =IFERROR(G55/$C$55,0) -> 0.15933105 | H56: =IFERROR(H55/$C$55,0) -> 0.037767359 | I56: =IFERROR(I55/$C$55,0) -> 0.22093138 | J56: =IFERROR(J55/$C$55,0) -> 0 | K56: =IFERROR(K55/$C$55,0) -> 0 | O56: Origination Fee Total | P56: =SUM(P51:P55) -> 0.041407873 | Q56: =SUM(Q52:Q55) -> 111875.96 | AB56: *Guarantee Fees and Closing Costs are excluded from this calculation. | AG56: =IFERROR(AG55/$AG$55,0) -> 1 | AH56: =IFERROR(AH55/$AG$55,0) -> 0 | AI56: =IFERROR(AI55/$AG$55,0) -> 0.38114759 | AJ56: =IFERROR(AJ55/$AG$55,0) -> 0.52850631 | AK56: =IFERROR(AK55/$AG$55,0) -> 0.090346096
O57: Rounded Fee | Q57: =ROUNDUP(Q56,-3) -> 112000 | AF57: ***Any working capital, inventory, or franchise fee is considered ineligible for UOP in 504 loan projects. Please move to SBA 7(a) project.
B58: =IF(SUM(D49:J49)<>C49,"*** Construction contingency does not match total contingency in C49.","") | N58: 504 / USDA Calculations
B59: Liquidity Review | AG59: =C36 -> Total | AH59: =D36 -> Equity | AI59: =Lists!L5 -> SBA 504 | AJ59: =Lists!L6 -> Debenture | AK59: =Lists!L4 -> SBA 7(a) | AL59: =Lists!L9 -> Seller Note
AF60: Hybrid 504-7(a) Chart
C61: Amount | F61: Amount | I61: Amount | AF61: =B38 -> Real Estate Acquisition | AG61: =C38 -> 0 | AH61: 0 | AI61: =IFERROR(INDEX($C38:$K38,MATCH(AI$59,$C$36:$K$36,0)),0) -> 0 | AJ61: =IFERROR(INDEX($C38:$K38,MATCH(AJ$59,$C$36:$K$36,0)),0) -> 0 | AK61: =IFERROR(INDEX($C38:$K38,MATCH(AK$59,$C$36:$K$36,0)),0) -> 0 | AL61: =IFERROR(INDEX($C38:$K38,MATCH(AL$59,$C$36:$K$36,0)),0) -> 0
B62: Operating Company Liquidity | C62: 590000 | E62: =IF(Affiliates!$B$43="{Insert business name which represents Affiliate 1}","Affiliate 1",Affiliates!$B$43) -> Affiliate 1 | F62: 0 | H62: Total Available Liquidity | I62: =SUM(C62:C73,F62:F73) -> 2308100 | AF62: =B39 -> Debt Refi - CRE | AG62: =C39 -> 0 | AH62: 0 | AI62: =IFERROR(INDEX($C39:$K39,MATCH(AI$59,$C$36:$K$36,0)),0) -> 0 | AJ62: =IFERROR(INDEX($C39:$K39,MATCH(AJ$59,$C$36:$K$36,0)),0) -> 0 | AK62: =IFERROR(INDEX($C39:$K39,MATCH(AK$59,$C$36:$K$36,0)),0) -> 0 | AL62: =IFERROR(INDEX($C39:$K39,MATCH(AL$59,$C$36:$K$36,0)),0) -> 0
B63: =IF(Guarantors!B6="Customer 1","Owner/Guarantor 1",Guarantors!B6) -> Jeff Able | C63: =Guarantors!F6 -> 11100 | E63: =IF(Affiliates!$B$99="{Insert business name which represents Affiliate 2}","Affiliate 2",Affiliates!$B$99) -> Affiliate 2 | F63: 0 | AF63: =B40 -> Debt Refi - Non-CRE | AG63: =C40 -> 0 | AH63: 0 | AI63: =IFERROR(INDEX($C40:$K40,MATCH(AI$59,$C$36:$K$36,0)),0) -> 0 | AJ63: =IFERROR(INDEX($C40:$K40,MATCH(AJ$59,$C$36:$K$36,0)),0) -> 0 | AK63: =IFERROR(INDEX($C40:$K40,MATCH(AK$59,$C$36:$K$36,0)),0) -> 0 | AL63: =IFERROR(INDEX($C40:$K40,MATCH(AL$59,$C$36:$K$36,0)),0) -> 0
B64: =IF(Guarantors!B7="Customer 2","Owner/Guarantor 2",Guarantors!B7) -> Lisa McClure | C64: =Guarantors!F7 -> 525000 | E64: =IF(Affiliates!$B$155="{Insert business name which represents Affiliate 3}","Affiliate 3",Affiliates!$B$155) -> Affiliate 3 | F64: 0 | H64: Expected Injection | I64: =D55 -> 1571792 | AF64: =B41 -> Machinery & Equipment | AG64: =C41 -> 366285 | AH64: 0 | AI64: =IFERROR(INDEX($C41:$K41,MATCH(AI$59,$C$36:$K$36,0)),0) -> 0 | AJ64: =IFERROR(INDEX($C41:$K41,MATCH(AJ$59,$C$36:$K$36,0)),0) -> 0 | AK64: =IFERROR(INDEX($C41:$K41,MATCH(AK$59,$C$36:$K$36,0)),0) -> 0 | AL64: =IFERROR(INDEX($C41:$K41,MATCH(AL$59,$C$36:$K$36,0)),0) -> 0
B65: =IF(Guarantors!B8="Customer 3","Owner/Guarantor 3",Guarantors!B8) -> Brandon Johnson | C65: =Guarantors!F8 -> 100000 | E65: =IF(Affiliates!$B$211="{Insert business name which represents Affiliate 4}","Affiliate 4",Affiliates!$B$211) -> Affiliate 4 | F65: 0 | AF65: =B42 -> Furniture & Fixtures | AG65: =C42 -> 600000 | AH65: 0 | AI65: =IFERROR(INDEX($C42:$K42,MATCH(AI$59,$C$36:$K$36,0)),0) -> 0 | AJ65: =IFERROR(INDEX($C42:$K42,MATCH(AJ$59,$C$36:$K$36,0)),0) -> 0 | AK65: =IFERROR(INDEX($C42:$K42,MATCH(AK$59,$C$36:$K$36,0)),0) -> 0 | AL65: =IFERROR(INDEX($C42:$K42,MATCH(AL$59,$C$36:$K$36,0)),0) -> 0
B66: =IF(Guarantors!B9="Customer 4","Owner/Guarantor 4",Guarantors!B9) -> Riku Patel | C66: =Guarantors!F9 -> 425000 | E66: =IF(Affiliates!$B$267="{Insert business name which represents Affiliate 5}","Affiliate 5",Affiliates!$B$267) -> Affiliate 5 | F66: 0 | H66: Working Capital in Loan | I66: =C44+C45 -> 650500 | AF66: =B43 -> Inventory | AG66: =C43 -> 0 | AH66: 0 | AI66: =IFERROR(INDEX($C43:$K43,MATCH(AI$59,$C$36:$K$36,0)),0) -> 0 | AJ66: =IFERROR(INDEX($C43:$K43,MATCH(AJ$59,$C$36:$K$36,0)),0) -> 0 | AK66: =IFERROR(INDEX($C43:$K43,MATCH(AK$59,$C$36:$K$36,0)),0) -> 0 | AL66: =IFERROR(INDEX($C43:$K43,MATCH(AL$59,$C$36:$K$36,0)),0) -> 0
B67: =IF(Guarantors!B10="Customer 5","Owner/Guarantor 5",Guarantors!B10) -> Divy Patel | C67: =Guarantors!F10 -> 657000 | E67: =IF(Affiliates!$B$323="{Insert business name which represents Affiliate 6}","Affiliate 6",Affiliates!$B$323) -> Affiliate 6 | F67: 0 | AF67: =B44 -> Working Capital | AG67: =C44 -> 573500 | AH67: 0 | AI67: =IFERROR(INDEX($C44:$K44,MATCH(AI$59,$C$36:$K$36,0)),0) -> 0 | AJ67: =IFERROR(INDEX($C44:$K44,MATCH(AJ$59,$C$36:$K$36,0)),0) -> 0 | AK67: =IFERROR(INDEX($C44:$K44,MATCH(AK$59,$C$36:$K$36,0)),0) -> 0 | AL67: =IFERROR(INDEX($C44:$K44,MATCH(AL$59,$C$36:$K$36,0)),0) -> 0
B68: =IF(Guarantors!B11="Customer 6","Owner/Guarantor 6",Guarantors!B11) -> Owner/Guarantor 6 | C68: =Guarantors!F11 -> 0 | E68: =IF(Affiliates!$B$379="{Insert business name which represents Affiliate 7}","Affiliate 7",Affiliates!$B$379) -> Affiliate 7 | F68: 0 | H68: Post Close Liquidity | I68: =I62-I64+I66 -> 1386808 | AF68: =B45 -> Working Capital - Pre Opening | AG68: =C45 -> 77000 | AH68: 0 | AI68: =IFERROR(INDEX($C45:$K45,MATCH(AI$59,$C$36:$K$36,0)),0) -> 0 | AJ68: =IFERROR(INDEX($C45:$K45,MATCH(AJ$59,$C$36:$K$36,0)),0) -> 0 | AK68: =IFERROR(INDEX($C45:$K45,MATCH(AK$59,$C$36:$K$36,0)),0) -> 0 | AL68: =IFERROR(INDEX($C45:$K45,MATCH(AL$59,$C$36:$K$36,0)),0) -> 0
B69: =IF(Guarantors!B12="Customer 7","Owner/Guarantor 7",Guarantors!B12) -> Owner/Guarantor 7 | C69: =Guarantors!F12 -> 0 | E69: =IF(Affiliates!$B$435="{Insert business name which represents Affiliate 8}","Affiliate 8",Affiliates!$B$435) -> Affiliate 8 | F69: 0 | AF69: =B46 -> Business Acquisition | AG69: =C46 -> 2219000 | AH69: 0 | AI69: =IFERROR(INDEX($C46:$K46,MATCH(AI$59,$C$36:$K$36,0)),0) -> 1350000 | AJ69: =IFERROR(INDEX($C46:$K46,MATCH(AJ$59,$C$36:$K$36,0)),0) -> 0 | AK69: =IFERROR(INDEX($C46:$K46,MATCH(AK$59,$C$36:$K$36,0)),0) -> 324000 | AL69: =IFERROR(INDEX($C46:$K46,MATCH(AL$59,$C$36:$K$36,0)),0) -> 320000
B70: =IF(Guarantors!B13="Customer 8","Owner/Guarantor 8",Guarantors!B13) -> Owner/Guarantor 8 | C70: =Guarantors!F13 -> 0 | E70: =IF(Affiliates!$B$491="{Insert business name which represents Affiliate 9}","Affiliate 9",Affiliates!$B$491) -> Affiliate 9 | F70: 0 | AF70: =B47 -> Franchise Fees | AG70: =C47 -> 0 | AH70: 0 | AI70: =IFERROR(INDEX($C47:$K47,MATCH(AI$59,$C$36:$K$36,0)),0) -> 0 | AJ70: =IFERROR(INDEX($C47:$K47,MATCH(AJ$59,$C$36:$K$36,0)),0) -> 0 | AK70: =IFERROR(INDEX($C47:$K47,MATCH(AK$59,$C$36:$K$36,0)),0) -> 0 | AL70: =IFERROR(INDEX($C47:$K47,MATCH(AL$59,$C$36:$K$36,0)),0) -> 0
B71: =IF(Guarantors!B14="Customer 9","Owner/Guarantor 9",Guarantors!B14) -> Owner/Guarantor 9 | C71: =Guarantors!F14 -> 0 | E71: =IF(Affiliates!$B$547="{Insert business name which represents Affiliate 10}","Affiliate 10",Affiliates!$B$547) -> Affiliate 10 | F71: 0 | AF71: =B48 -> Construction Hard Costs | AG71: =C48 -> 4100000 | AH71: 0 | AI71: =IFERROR(INDEX($C48:$K48,MATCH(AI$59,$C$36:$K$36,0)),0) -> 0 | AJ71: =IFERROR(INDEX($C48:$K48,MATCH(AJ$59,$C$36:$K$36,0)),0) -> 1871935 | AK71: =IFERROR(INDEX($C48:$K48,MATCH(AK$59,$C$36:$K$36,0)),0) -> 0 | AL71: =IFERROR(INDEX($C48:$K48,MATCH(AL$59,$C$36:$K$36,0)),0) -> 0
B72: =IF(Guarantors!B15="Customer 10","Owner/Guarantor 10",Guarantors!B15) -> Owner/Guarantor 10 | C72: =Guarantors!F15 -> 0 | E72: =IF(Affiliates!$B$603="{Insert business name which represents Affiliate 11}","Affiliate 11",Affiliates!$B$603) -> Affiliate 11 | F72: 0 | AF72: =B49 -> Construction Contingency - 10% | AG72: =C49 -> 222807 | AH72: 0 | AI72: =IFERROR(INDEX($C49:$K49,MATCH(AI$59,$C$36:$K$36,0)),0) -> 0 | AJ72: =IFERROR(INDEX($C49:$K49,MATCH(AJ$59,$C$36:$K$36,0)),0) -> 0 | AK72: =IFERROR(INDEX($C49:$K49,MATCH(AK$59,$C$36:$K$36,0)),0) -> 222807 | AL72: =IFERROR(INDEX($C49:$K49,MATCH(AL$59,$C$36:$K$36,0)),0) -> 0
B73: Other Liquidity | C73: 0 | E73: =IF(Affiliates!$B$659="{Insert business name which represents Affiliate 12}","Affiliate 12",Affiliates!$B$659) -> Affiliate 12 | F73: 0 | AF73: =B50 -> Interest Reserve - 3 Mos | AG73: =C50 -> 0 | AH73: 0 | AI73: =IFERROR(INDEX($C50:$K50,MATCH(AI$59,$C$36:$K$36,0)),0) -> 0 | AJ73: =IFERROR(INDEX($C50:$K50,MATCH(AJ$59,$C$36:$K$36,0)),0) -> 0 | AK73: =IFERROR(INDEX($C50:$K50,MATCH(AK$59,$C$36:$K$36,0)),0) -> 0 | AL73: =IFERROR(INDEX($C50:$K50,MATCH(AL$59,$C$36:$K$36,0)),0) -> 0
AF74: =B51 -> Construction Soft Costs | AG74: =C51 -> 173800 | AH74: 0 | AI74: =IFERROR(INDEX($C51:$K51,MATCH(AI$59,$C$36:$K$36,0)),0) -> 0 | AJ74: =IFERROR(INDEX($C51:$K51,MATCH(AJ$59,$C$36:$K$36,0)),0) -> 0 | AK74: =IFERROR(INDEX($C51:$K51,MATCH(AK$59,$C$36:$K$36,0)),0) -> 0 | AL74: =IFERROR(INDEX($C51:$K51,MATCH(AL$59,$C$36:$K$36,0)),0) -> 0
AF75: =B52 -> Closing Costs | AG75: =C52 -> 52000 | AH75: 0 | AI75: =IFERROR(INDEX($C52:$K52,MATCH(AI$59,$C$36:$K$36,0)),0) -> 0 | AJ75: =IFERROR(INDEX($C52:$K52,MATCH(AJ$59,$C$36:$K$36,0)),0) -> 0 | AK75: =IFERROR(INDEX($C52:$K52,MATCH(AK$59,$C$36:$K$36,0)),0) -> 52000 | AL75: =IFERROR(INDEX($C52:$K52,MATCH(AL$59,$C$36:$K$36,0)),0) -> 0
B76: Business Debt Schedule - Subject Company | AF76: =B53 -> SBA Gty Fee | AG76: =C53 -> 88533 | AH76: 0 | AI76: =IFERROR(INDEX($C53:$K53,MATCH(AI$59,$C$36:$K$36,0)),0) -> 0 | AJ76: =IFERROR(INDEX($C53:$K53,MATCH(AJ$59,$C$36:$K$36,0)),0) -> 0 | AK76: =IFERROR(INDEX($C53:$K53,MATCH(AK$59,$C$36:$K$36,0)),0) -> 13784 | AL76: =IFERROR(INDEX($C53:$K53,MATCH(AL$59,$C$36:$K$36,0)),0) -> 0
AF77: =B54 -> USDA Gty Fee | AG77: =C54 -> 0 | AH77: 0 | AI77: =IFERROR(INDEX($C54:$K54,MATCH(AI$59,$C$36:$K$36,0)),0) -> 0 | AJ77: =IFERROR(INDEX($C54:$K54,MATCH(AJ$59,$C$36:$K$36,0)),0) -> 0 | AK77: =IFERROR(INDEX($C54:$K54,MATCH(AK$59,$C$36:$K$36,0)),0) -> 0 | AL77: =IFERROR(INDEX($C54:$K54,MATCH(AL$59,$C$36:$K$36,0)),0) -> 0
B78: Lender | C78: Current Balance | D78: Monthly Payment | E78: Refinance? | F78: New Rate | G78: New Term (mo.) | H78: Payment After | I78: % Change | AG78: =C55 -> 8472925 | AH78: =SUM(AH61:AH77) -> 0 | AI78: =IFERROR(INDEX($C55:$K55,MATCH(AI$59,$C$36:$K$36,0)),0) -> 1350000 | AJ78: =IFERROR(INDEX($C55:$K55,MATCH(AJ$59,$C$36:$K$36,0)),0) -> 1871935 | AK78: =IFERROR(INDEX($C55:$K55,MATCH(AK$59,$C$36:$K$36,0)),0) -> 612591 | AL78: =IFERROR(INDEX($C55:$K55,MATCH(AL$59,$C$36:$K$36,0)),0) -> 320000
C79: 0 | D79: 0 | E79: No | F79: 0 | G79: 0 | H79: =IFERROR(IF(E79=Lists!$H$3,PMT(F79/12,G79,-C79),D79),D79) -> 0 | I79: =IFERROR((D79-H79)/D79,0) -> 0 | AG79: =IFERROR(AG78/$C$55,0) -> 1 | AH79: =IFERROR(AH78/$C$55,0) -> 0 | AI79: =IFERROR(INDEX($C56:$K56,MATCH(AI$59,$C$36:$K$36,0)),0) -> 0.15933105 | AJ79: =IFERROR(INDEX($C56:$K56,MATCH(AJ$59,$C$36:$K$36,0)),0) -> 0.22093138 | AK79: =IFERROR(INDEX($C56:$K56,MATCH(AK$59,$C$36:$K$36,0)),0) -> 0.072299826 | AL79: =IFERROR(INDEX($C56:$K56,MATCH(AL$59,$C$36:$K$36,0)),0) -> 0.037767359
C80: 0 | D80: 0 | E80: No | F80: 0 | G80: 0 | H80: =IFERROR(IF(E80=Lists!$H$3,PMT(F80/12,G80,-C80),D80),D80) -> 0 | I80: =IFERROR((D80-H80)/D80,0) -> 0
C81: 0 | D81: 0 | E81: No | F81: 0 | G81: 0 | H81: =IFERROR(IF(E81=Lists!$H$3,PMT(F81/12,G81,-C81),D81),D81) -> 0 | I81: =IFERROR((D81-H81)/D81,0) -> 0
C82: 0 | D82: 0 | E82: No | F82: 0 | G82: 0 | H82: =IFERROR(IF(E82=Lists!$H$3,PMT(F82/12,G82,-C82),D82),D82) -> 0 | I82: =IFERROR((D82-H82)/D82,0) -> 0
C83: 0 | D83: 0 | E83: No | F83: 0 | G83: 0 | H83: =IFERROR(IF(E83=Lists!$H$3,PMT(F83/12,G83,-C83),D83),D83) -> 0 | I83: =IFERROR((D83-H83)/D83,0) -> 0
C84: 0 | D84: 0 | E84: No | F84: 0 | G84: 0 | H84: =IFERROR(IF(E84=Lists!$H$3,PMT(F84/12,G84,-C84),D84),D84) -> 0 | I84: =IFERROR((D84-H84)/D84,0) -> 0
C85: 0 | D85: 0 | E85: No | F85: 0 | G85: 0 | H85: =IFERROR(IF(E85=Lists!$H$3,PMT(F85/12,G85,-C85),D85),D85) -> 0 | I85: =IFERROR((D85-H85)/D85,0) -> 0
C86: 0 | D86: 0 | E86: No | F86: 0 | G86: 0 | H86: =IFERROR(IF(E86=Lists!$H$3,PMT(F86/12,G86,-C86),D86),D86) -> 0 | I86: =IFERROR((D86-H86)/D86,0) -> 0
C87: 0 | D87: 0 | E87: No | F87: 0 | G87: 0 | H87: =IFERROR(IF(E87=Lists!$H$3,PMT(F87/12,G87,-C87),D87),D87) -> 0 | I87: =IFERROR((D87-H87)/D87,0) -> 0
C88: 0 | D88: 0 | E88: No | F88: 0 | G88: 0 | H88: =IFERROR(IF(E88=Lists!$H$3,PMT(F88/12,G88,-C88),D88),D88) -> 0 | I88: =IFERROR((D88-H88)/D88,0) -> 0
C89: 0 | D89: 0 | E89: No | F89: 0 | G89: 0 | H89: =IFERROR(IF(E89=Lists!$H$3,PMT(F89/12,G89,-C89),D89),D89) -> 0 | I89: =IFERROR((D89-H89)/D89,0) -> 0
C90: 0 | D90: 0 | E90: No | F90: 0 | G90: 0 | H90: =IFERROR(IF(E90=Lists!$H$3,PMT(F90/12,G90,-C90),D90),D90) -> 0 | I90: =IFERROR((D90-H90)/D90,0) -> 0
C91: 0 | D91: 0 | E91: No | F91: 0 | G91: 0 | H91: =IFERROR(IF(E91=Lists!$H$3,PMT(F91/12,G91,-C91),D91),D91) -> 0 | I91: =IFERROR((D91-H91)/D91,0) -> 0
B92: Total | C92: =SUM(C79:C91) -> 0 | D92: =SUM(D79:D91) -> 0 | G92: Total Existing Debt + Refi Payments | H92: =SUM(H79:H91) -> 0
G93: Total Existing Debt w/o Refi Payments | H93: =SUMIFS(H79:H91,E79:E91,"<>Yes") -> 0
B96: Income Statement Spreads
B97: {Insert business name which represents PSOR}
U98: Projections ---> Expand/Collapse Above --->
B99: Statement Date | D99: 45291 | F99: =EOMONTH(D99,F100) -> 45657 | H99: =EOMONTH(F99,H100) -> 46022 | J99: =EOMONTH(H99,J100) -> 46142 | O99: Projections | Q99: Projections
B100: Months Covered | D100: 12 | F100: 12 | H100: 12 | J100: 4 | O100: Customer | Q100: Customer
B101: Statement Type | D101: Tax Returns | F101: Tax Returns | H101: Internal | J101: Internal | O101: Year | Q101: Year
B102: Revenue Recognition | D102: Cash | F102: Cash | H102: Cash | J102: Accrual | O102: 1 | Q102: 2
J103: =(J104/J100)*12 -> 94004760
C104: Total Revenue | D104: 29649370 | E104: =IF(D$104=0,0,D104/D$104) -> 1 | F104: 43335889 | G104: =IF(F$104=0,0,F104/F$104) -> 1 | H104: 66978891 | I104: =IF(H$104=0,0,H104/H$104) -> 1 | J104: 31334920 | K104: =IF(J$104=0,0,J104/J$104) -> 1 | N104: Total Revenue | O104: 6030320 | P104: =IF(O$104=0,0,O104/O$104) -> 1 | Q104: 7130112 | R104: =IF(Q$104=0,0,Q104/Q$104) -> 1
C105: Total COGS | D105: 26862626 | E105: =IF(D$104=0,0,D105/D$104) -> 0.90601001 | F105: 39325395 | G105: =IF(F$104=0,0,F105/F$104) -> 0.9074556 | H105: 62627088 | I105: =IF(H$104=0,0,H105/H$104) -> 0.93502725 | J105: 27540075 | K105: =IF(J$104=0,0,J105/J$104) -> 0.87889406 | N105: Total COGS | O105: 0 | P105: =IF(O$104=0,0,O105/O$104) -> 0 | Q105: 0 | R105: =IF(Q$104=0,0,Q105/Q$104) -> 0
C106: Total Gross Margin | D106: =D104-D105 -> 2786744 | E106: =IF(D$104=0,0,D106/D$104) -> 0.09398999 | F106: =F104-F105 -> 4010494 | G106: =IF(F$104=0,0,F106/F$104) -> 0.092544404 | H106: =H104-H105 -> 4351803 | I106: =IF(H$104=0,0,H106/H$104) -> 0.064972754 | J106: =J104-J105 -> 3794845 | K106: =IF(J$104=0,0,J106/J$104) -> 0.12110594 | N106: Total Gross Margin | O106: =O104-O105 -> 6030320 | P106: =IF(O$104=0,0,O106/O$104) -> 1 | Q106: =Q104-Q105 -> 7130112 | R106: =IF(Q$104=0,0,Q106/Q$104) -> 1
C108: Officer's Compensation | D108: 437000 | E108: =IF(D$104=0,0,D108/D$104) -> 0.01473893 | F108: 450750 | G108: =IF(F$104=0,0,F108/F$104) -> 0.01040131 | H108: 525000 | I108: =IF(H$104=0,0,H108/H$104) -> 0.0078382904 | J108: 0 | K108: =IF(J$104=0,0,J108/J$104) -> 0 | N108: Officer's Compensation | O108: 0 | P108: =IF(O$104=0,0,O108/O$104) -> 0 | Q108: 0 | R108: =IF(Q$104=0,0,Q108/Q$104) -> 0
...

Sheet Guarantors
B2: Personal Financial Analysis
J4: Outside Annual Income | P4: Monthly Payments | V4: Actuals
D5: Owner % | F5: Personal Liquidity | H5: AVG. FICO | J5: Outside Income | K5: Spouse Income | L5: Interest Income | M5: Rental Income | N5: Total Outside Annual Income | P5: Loan Payments | Q5: Credit Card | R5: Rent | S5: Child Support, Alimony & Other | T5: Total Monthly Liabilities | V5: Annual Liablities | W5: Outside Income | X5: Net Before Living Expenses | Z5: DTI % (Outside Income) | AA5: =_xlfn.CONCAT("Cash after Liablities at 45% DTI") -> Cash after Liablities at 45% DTI | AB5: Draw Needed | AC5: Income from Borrowing Entities | AD5: DTI% (All Income) | AF5: Include Draw? | AG5: Include in Global?
B6: Jeff Able | D6: 0.23 | F6: 11100 | H6: 702.3 | J6: 0 | K6: 126375 | L6: 0 | M6: 0 | N6: =SUM(J6:M6) -> 126375 | P6: 0 | Q6: 0 | R6: 0 | S6: 0 | T6: =SUM(P6:S6) -> 0 | V6: =T6*12 -> 0 | W6: =N6 -> 126375 | X6: =W6-V6 -> 126375 | Z6: =IFERROR((T6*12)/(N6),0) -> 0 | AA6: =N6-((T6*12)/0.45) -> 126375 | AB6: =IF(AF6=Lists!$H$4,0,IF(AA6<0,-AA6,0)) -> 0 | AC6: 0 | AD6: =IFERROR((T6*12)/(N6+AC6),0) -> 0 | AF6: Yes | AG6: Yes
B7: Lisa McClure | D7: 0.27 | F7: 525000 | H7: 800 | J7: 0 | K7: 0 | L7: 0 | M7: 0 | N7: =SUM(J7:M7) -> 0 | P7: 0 | Q7: 0 | R7: 3000 | S7: 0 | T7: =SUM(P7:S7) -> 3000 | V7: =T7*12 -> 36000 | W7: =N7 -> 0 | X7: =W7-V7 -> -36000 | Z7: =IFERROR((T7*12)/(N7),0) -> 0 | AA7: =N7-((T7*12)/0.45) -> -80000 | AB7: =IF(AF7=Lists!$H$4,0,IF(AA7<0,-AA7,0)) -> 80000 | AC7: 0 | AD7: =IFERROR((T7*12)/(N7+AC7),0) -> 0 | AF7: Yes | AG7: Yes
B8: Brandon Johnson | D8: 0.5 | F8: 100000 | H8: 810 | J8: 0 | K8: 0 | L8: 0 | M8: 0 | N8: =SUM(J8:M8) -> 0 | P8: 0 | Q8: 0 | R8: 5211 | S8: 1500 | T8: =SUM(P8:S8) -> 6711 | V8: =T8*12 -> 80532 | W8: =N8 -> 0 | X8: =W8-V8 -> -80532 | Z8: =IFERROR((T8*12)/(N8),0) -> 0 | AA8: =N8-((T8*12)/0.45) -> -178960 | AB8: =IF(AF8=Lists!$H$4,0,IF(AA8<0,-AA8,0)) -> 178960 | AC8: 0 | AD8: =IFERROR((T8*12)/(N8+AC8),0) -> 0 | AF8: Yes | AG8: Yes
B9: Riku Patel | D9: 0 | F9: 425000 | J9: 0 | K9: 64800 | L9: 0 | M9: 0 | N9: =SUM(J9:M9) -> 64800 | P9: 0 | Q9: 400 | R9: 0 | S9: 1183 | T9: =SUM(P9:S9) -> 1583 | V9: =T9*12 -> 18996 | W9: =N9 -> 64800 | X9: =W9-V9 -> 45804 | Z9: =IFERROR((T9*12)/(N9),0) -> 0.29314815 | AA9: =N9-((T9*12)/0.45) -> 22586.667 | AB9: =IF(AF9=Lists!$H$4,0,IF(AA9<0,-AA9,0)) -> 0 | AC9: 0 | AD9: =IFERROR((T9*12)/(N9+AC9),0) -> 0.29314815 | AF9: Yes | AG9: Yes
B10: Divy Patel | D10: 0 | F10: 657000 | J10: 0 | K10: 67200 | L10: 0 | M10: 0 | N10: =SUM(J10:M10) -> 67200 | P10: 0 | Q10: 965 | R10: 0 | S10: 609 | T10: =SUM(P10:S10) -> 1574 | V10: =T10*12 -> 18888 | W10: =N10 -> 67200 | X10: =W10-V10 -> 48312 | Z10: =IFERROR((T10*12)/(N10),0) -> 0.28107143 | AA10: =N10-((T10*12)/0.45) -> 25226.667 | AB10: =IF(AF10=Lists!$H$4,0,IF(AA10<0,-AA10,0)) -> 0 | AC10: 0 | AD10: =IFERROR((T10*12)/(N10+AC10),0) -> 0.28107143 | AF10: Yes | AG10: Yes
B11: Customer 6 | D11: 0 | F11: 0 | J11: 0 | K11: 0 | L11: 0 | M11: 0 | N11: =SUM(J11:M11) -> 0 | P11: 0 | Q11: 0 | R11: 0 | S11: 0 | T11: =SUM(P11:S11) -> 0 | V11: =T11*12 -> 0 | W11: =N11 -> 0 | X11: =W11-V11 -> 0 | Z11: =IFERROR((T11*12)/(N11),0) -> 0 | AA11: =N11-((T11*12)/0.45) -> 0 | AB11: =IF(AF11=Lists!$H$4,0,IF(AA11<0,-AA11,0)) -> 0 | AC11: 0 | AD11: =IFERROR((T11*12)/(N11+AC11),0) -> 0 | AF11: Yes | AG11: Yes
B12: Customer 7 | D12: 0 | F12: 0 | J12: 0 | K12: 0 | L12: 0 | M12: 0 | N12: =SUM(J12:M12) -> 0 | P12: 0 | Q12: 0 | R12: 0 | S12: 0 | T12: =SUM(P12:S12) -> 0 | V12: =T12*12 -> 0 | W12: =N12 -> 0 | X12: =W12-V12 -> 0 | Z12: =IFERROR((T12*12)/(N12),0) -> 0 | AA12: =N12-((T12*12)/0.45) -> 0 | AB12: =IF(AF12=Lists!$H$4,0,IF(AA12<0,-AA12,0)) -> 0 | AC12: 0 | AD12: =IFERROR((T12*12)/(N12+AC12),0) -> 0 | AF12: Yes | AG12: Yes
B13: Customer 8 | D13: 0 | F13: 0 | J13: 0 | K13: 0 | L13: 0 | M13: 0 | N13: =SUM(J13:M13) -> 0 | P13: 0 | Q13: 0 | R13: 0 | S13: 0 | T13: =SUM(P13:S13) -> 0 | V13: =T13*12 -> 0 | W13: =N13 -> 0 | X13: =W13-V13 -> 0 | Z13: =IFERROR((T13*12)/(N13),0) -> 0 | AA13: =N13-((T13*12)/0.45) -> 0 | AB13: =IF(AF13=Lists!$H$4,0,IF(AA13<0,-AA13,0)) -> 0 | AC13: 0 | AD13: =IFERROR((T13*12)/(N13+AC13),0) -> 0 | AF13: Yes | AG13: Yes
B14: Customer 9 | D14: 0 | F14: 0 | J14: 0 | K14: 0 | L14: 0 | M14: 0 | N14: =SUM(J14:M14) -> 0 | P14: 0 | Q14: 0 | R14: 0 | S14: 0 | T14: =SUM(P14:S14) -> 0 | V14: =T14*12 -> 0 | W14: =N14 -> 0 | X14: =W14-V14 -> 0 | Z14: =IFERROR((T14*12)/(N14),0) -> 0 | AA14: =N14-((T14*12)/0.45) -> 0 | AB14: =IF(AF14=Lists!$H$4,0,IF(AA14<0,-AA14,0)) -> 0 | AC14: 0 | AD14: =IFERROR((T14*12)/(N14+AC14),0) -> 0 | AF14: Yes | AG14: Yes
B15: Customer 10 | D15: 0 | F15: 0 | J15: 0 | K15: 0 | L15: 0 | M15: 0 | N15: =SUM(J15:M15) -> 0 | P15: 0 | Q15: 0 | R15: 0 | S15: 0 | T15: =SUM(P15:S15) -> 0 | V15: =T15*12 -> 0 | W15: =N15 -> 0 | X15: =W15-V15 -> 0 | Z15: =IFERROR((T15*12)/(N15),0) -> 0 | AA15: =N15-((T15*12)/0.45) -> 0 | AB15: =IF(AF15=Lists!$H$4,0,IF(AA15<0,-AA15,0)) -> 0 | AC15: 0 | AD15: =IFERROR((T15*12)/(N15+AC15),0) -> 0 | AF15: Yes | AG15: Yes
F16: =SUM(F6:F15) -> 1718100 | H16: =AVERAGE(H6:H15) -> 770.76667 | J16: =SUM(J6:J15) -> 0 | K16: =SUM(K6:K15) -> 258375 | L16: =SUM(L6:L15) -> 0 | M16: =SUM(M6:M15) -> 0 | N16: =SUM(N6:N15) -> 258375 | P16: =SUM(P6:P15) -> 0 | Q16: =SUM(Q6:Q15) -> 1365 | R16: =SUM(R6:R15) -> 8211 | S16: =SUM(S6:S15) -> 3292 | T16: =SUM(T6:T15) -> 12868 | V16: =SUM(V6:V15) -> 154416 | W16: =SUM(W6:W15) -> 258375 | X16: =SUM(X6:X15) -> 103959 | AA16: =SUM(AA6:AA15) -> -84771.667 | AB16: =IF(SUM(AB6:AB15)<AB18,AB18,SUM(AB6:AB15)) -> 258960 | AC16: =SUM(AC6:AC15) -> 0
U18: Include Minimum Draw? | Z18: Yes | AA18: Draw Required | AB18: =IF(Z18=Lists!H3,24000,0) -> 24000

Sheet Affiliates
B2: Affiliate Analysis
B3: <<< click the + to the left to expand sections below
D4: ='BDO Prequal'!D99 -> 45291 | F4: ='BDO Prequal'!F99 -> 45657 | H4: ='BDO Prequal'!H99 -> 46022 | J4: ='BDO Prequal'!J99 -> 46142
C5: Affiliate 1 - Cash Available | D5: =IF(Affiliates!$K$43="Yes",Affiliates!D90,0) -> 0 | F5: =IF(Affiliates!$K$43="Yes",Affiliates!F90,0) -> 0 | H5: =IF(Affiliates!$K$43="Yes",Affiliates!H90,0) -> 0 | J5: =IF(Affiliates!$K$43="Yes",Affiliates!J90,0) -> 0
C6: Affiliate 1 - Debt Service | D6: =IF(Affiliates!$K$43="Yes",Affiliates!D93,0) -> 0 | F6: =IF(Affiliates!$K$43="Yes",Affiliates!F93,0) -> 0 | H6: =IF(Affiliates!$K$43="Yes",Affiliates!H93,0) -> 0 | J6: =IF(Affiliates!$K$43="Yes",Affiliates!J93,0) -> 0
C7: ='BDO Prequal'!C164 -> Affiliate 1 - Net Cashflow | D7: ='BDO Prequal'!D164 -> 0 | F7: ='BDO Prequal'!F164 -> 0 | H7: ='BDO Prequal'!H164 -> 0 | J7: ='BDO Prequal'!J164 -> 0
C8: Affiliate 2 - Cash Available | D8: =IF(Affiliates!$K$99="Yes",Affiliates!D146,0) -> 0 | F8: =IF(Affiliates!$K$99="Yes",Affiliates!F146,0) -> 0 | H8: =IF(Affiliates!$K$99="Yes",Affiliates!H146,0) -> 0 | J8: =IF(Affiliates!$K$99="Yes",Affiliates!J146,0) -> 0
C9: Affiliate 2 - Debt Service | D9: =IF(Affiliates!$K$99="Yes",Affiliates!D149,0) -> 0 | F9: =IF(Affiliates!$K$99="Yes",Affiliates!F149,0) -> 0 | H9: =IF(Affiliates!$K$99="Yes",Affiliates!H149,0) -> 0 | J9: =IF(Affiliates!$K$99="Yes",Affiliates!J149,0) -> 0
C10: ='BDO Prequal'!C165 -> Affiliate 2 - Net Cashflow | D10: ='BDO Prequal'!D165 -> 0 | F10: ='BDO Prequal'!F165 -> 0 | H10: ='BDO Prequal'!H165 -> 0 | J10: ='BDO Prequal'!J165 -> 0
C11: Affiliate 3 - Cash Available | D11: =IF(Affiliates!$K$155="Yes",Affiliates!D202,0) -> 0 | F11: =IF(Affiliates!$K$155="Yes",Affiliates!F202,0) -> 0 | H11: =IF(Affiliates!$K$155="Yes",Affiliates!H202,0) -> 0 | J11: =IF(Affiliates!$K$155="Yes",Affiliates!J202,0) -> 0
C12: Affiliate 3 - Debt Service | D12: =IF(Affiliates!$K$155="Yes",Affiliates!D205,0) -> 0 | F12: =IF(Affiliates!$K$155="Yes",Affiliates!F205,0) -> 0 | H12: =IF(Affiliates!$K$155="Yes",Affiliates!H205,0) -> 0 | J12: =IF(Affiliates!$K$155="Yes",Affiliates!J205,0) -> 0
C13: ='BDO Prequal'!C166 -> Affiliate 3 - Net Cashflow | D13: ='BDO Prequal'!D166 -> 0 | F13: ='BDO Prequal'!F166 -> 0 | H13: ='BDO Prequal'!H166 -> 0 | J13: ='BDO Prequal'!J166 -> 0
C14: Affiliate 4 - Cash Available | D14: =IF(Affiliates!$K$211="Yes",Affiliates!D258,0) -> 0 | F14: =IF(Affiliates!$K$211="Yes",Affiliates!F258,0) -> 0 | H14: =IF(Affiliates!$K$211="Yes",Affiliates!H258,0) -> 0 | J14: =IF(Affiliates!$K$211="Yes",Affiliates!J258,0) -> 0
C15: Affiliate 4 - Debt Service | D15: =IF(Affiliates!$K$211="Yes",Affiliates!D261,0) -> 0 | F15: =IF(Affiliates!$K$211="Yes",Affiliates!F261,0) -> 0 | H15: =IF(Affiliates!$K$211="Yes",Affiliates!H261,0) -> 0 | J15: =IF(Affiliates!$K$211="Yes",Affiliates!J261,0) -> 0
C16: ='BDO Prequal'!C167 -> Affiliate 4 - Net Cashflow | D16: ='BDO Prequal'!D167 -> 0 | F16: ='BDO Prequal'!F167 -> 0 | H16: ='BDO Prequal'!H167 -> 0 | J16: ='BDO Prequal'!J167 -> 0
C17: Affiliate 5 - Cash Available | D17: =IF(Affiliates!$K$267="Yes",Affiliates!D314,0) -> 0 | F17: =IF(Affiliates!$K$267="Yes",Affiliates!F314,0) -> 0 | H17: =IF(Affiliates!$K$267="Yes",Affiliates!H314,0) -> 0 | J17: =IF(Affiliates!$K$267="Yes",Affiliates!J314,0) -> 0
C18: Affiliate 5 - Debt Service | D18: =IF(Affiliates!$K$267="Yes",Affiliates!D317,0) -> 0 | F18: =IF(Affiliates!$K$267="Yes",Affiliates!F317,0) -> 0 | H18: =IF(Affiliates!$K$267="Yes",Affiliates!H317,0) -> 0 | J18: =IF(Affiliates!$K$267="Yes",Affiliates!J317,0) -> 0
C19: ='BDO Prequal'!C168 -> Affiliate 5 - Net Cashflow | D19: ='BDO Prequal'!D168 -> 0 | F19: ='BDO Prequal'!F168 -> 0 | H19: ='BDO Prequal'!H168 -> 0 | J19: ='BDO Prequal'!J168 -> 0
C20: Affiliate 6 - Cash Available | D20: =IF(Affiliates!$K$323="Yes",Affiliates!D370,0) -> 0 | F20: =IF(Affiliates!$K$323="Yes",Affiliates!F370,0) -> 0 | H20: =IF(Affiliates!$K$323="Yes",Affiliates!H370,0) -> 0 | J20: =IF(Affiliates!$K$323="Yes",Affiliates!J370,0) -> 0
C21: Affiliate 6 - Debt Service | D21: =IF(Affiliates!$K$323="Yes",Affiliates!D373,0) -> 0 | F21: =IF(Affiliates!$K$323="Yes",Affiliates!F373,0) -> 0 | H21: =IF(Affiliates!$K$323="Yes",Affiliates!H373,0) -> 0 | J21: =IF(Affiliates!$K$323="Yes",Affiliates!J373,0) -> 0
C22: ='BDO Prequal'!C169 -> Affiliate 6 - Net Cashflow | D22: ='BDO Prequal'!D169 -> 0 | F22: ='BDO Prequal'!F169 -> 0 | H22: ='BDO Prequal'!H169 -> 0 | J22: ='BDO Prequal'!J169 -> 0
C23: Affiliate 7 - Cash Available | D23: =IF(Affiliates!$K$379="Yes",Affiliates!D426,0) -> 0 | F23: =IF(Affiliates!$K$379="Yes",Affiliates!F426,0) -> 0 | H23: =IF(Affiliates!$K$379="Yes",Affiliates!H426,0) -> 0 | J23: =IF(Affiliates!$K$379="Yes",Affiliates!J426,0) -> 0
C24: Affiliate 7 - Debt Service | D24: =IF(Affiliates!$K$379="Yes",D429,0) -> 0 | F24: =IF(Affiliates!$K$379="Yes",Affiliates!F429,0) -> 0 | H24: =IF(Affiliates!$K$379="Yes",Affiliates!H429,0) -> 0 | J24: =IF(Affiliates!$K$379="Yes",Affiliates!J429,0) -> 0
C25: ='BDO Prequal'!C170 -> Affiliate 7 - Net Cashflow | D25: ='BDO Prequal'!D170 -> 0 | F25: ='BDO Prequal'!F170 -> 0 | H25: ='BDO Prequal'!H170 -> 0 | J25: ='BDO Prequal'!J170 -> 0
C26: Affiliate 8 - Cash Available | D26: =IF(Affiliates!$K$435="Yes",Affiliates!D482,0) -> 0 | F26: =IF(Affiliates!$K$435="Yes",Affiliates!F482,0) -> 0 | H26: =IF(Affiliates!$K$435="Yes",Affiliates!H482,0) -> 0 | J26: =IF(Affiliates!$K$435="Yes",Affiliates!J482,0) -> 0
C27: Affiliate 8 - Debt Service | D27: =IF(Affiliates!$K$435="Yes",D485,0) -> 0 | F27: =IF(Affiliates!$K$435="Yes",F485,0) -> 0 | H27: =IF(Affiliates!$K$435="Yes",H485,0) -> 0 | J27: =IF(Affiliates!$K$435="Yes",J485,0) -> 0
C28: ='BDO Prequal'!C171 -> Affiliate 8 - Net Cashflow | D28: ='BDO Prequal'!D171 -> 0 | F28: ='BDO Prequal'!F171 -> 0 | H28: ='BDO Prequal'!H171 -> 0 | J28: ='BDO Prequal'!J171 -> 0
C29: Affiliate 9 - Cash Available | D29: =IF(Affiliates!$K$491="Yes",Affiliates!D538,0) -> 0 | F29: =IF(Affiliates!$K$491="Yes",Affiliates!F538,0) -> 0 | H29: =IF(Affiliates!$K$491="Yes",Affiliates!H538,0) -> 0 | J29: =IF(Affiliates!$K$491="Yes",Affiliates!J538,0) -> 0
C30: Affiliate 9 - Debt Service | D30: =IF(Affiliates!$K$491="Yes",D541,0) -> 0 | F30: =IF(Affiliates!$K$491="Yes",F541,0) -> 0 | H30: =IF(Affiliates!$K$491="Yes",H541,0) -> 0 | J30: =IF(Affiliates!$K$491="Yes",J541,0) -> 0
C31: ='BDO Prequal'!C172 -> Affiliate 9 - Net Cashflow | D31: ='BDO Prequal'!D172 -> 0 | F31: ='BDO Prequal'!F172 -> 0 | H31: ='BDO Prequal'!H172 -> 0 | J31: ='BDO Prequal'!J172 -> 0
C32: Affiliate 10 - Cash Available | D32: =IF($K$547="Yes",D594,0) -> 0 | F32: =IF($K$547="Yes",F594,0) -> 0 | H32: =IF($K$547="Yes",H594,0) -> 0 | J32: =IF($K$547="Yes",J594,0) -> 0
C33: Affiliate 10 - Debt Service | D33: =IF($K$547="Yes",D597,0) -> 0 | F33: =IF($K$547="Yes",F597,0) -> 0 | H33: =IF($K$547="Yes",H597,0) -> 0 | J33: =IF($K$547="Yes",J597,0) -> 0
C34: ='BDO Prequal'!C173 -> Affiliate 10 - Net Cashflow | D34: ='BDO Prequal'!D173 -> 0 | F34: ='BDO Prequal'!F173 -> 0 | H34: ='BDO Prequal'!H173 -> 0 | J34: ='BDO Prequal'!J173 -> 0
C35: Affiliate 11 - Cash Available | D35: =IF($K$603="Yes",D650,0) -> 0 | F35: =IF($K$603="Yes",F650,0) -> 0 | H35: =IF($K$603="Yes",H650,0) -> 0 | J35: =IF($K$603="Yes",J650,0) -> 0
C36: Affiliate 11 - Debt Service | D36: =IF($K$603="Yes",D650,0) -> 0 | F36: =IF($K$603="Yes",F650,0) -> 0 | H36: =IF($K$603="Yes",H650,0) -> 0 | J36: =IF($K$603="Yes",J650,0) -> 0
C37: ='BDO Prequal'!C174 -> Affiliate 11 - Net Cashflow | D37: ='BDO Prequal'!D174 -> 0 | F37: ='BDO Prequal'!F174 -> 0 | H37: ='BDO Prequal'!H174 -> 0 | J37: ='BDO Prequal'!J174 -> 0
C38: Affiliate 12 - Cash Available | D38: =IF($K$659="Yes",D706,0) -> 0 | F38: =IF($K$659="Yes",F706,0) -> 0 | H38: =IF($K$659="Yes",H706,0) -> 0 | J38: =IF($K$659="Yes",J706,0) -> 0
C39: Affiliate 12 - Debt Service | D39: =IF($K$659="Yes",D709,0) -> 0 | F39: =IF($K$659="Yes",F709,0) -> 0 | H39: =IF($K$659="Yes",H709,0) -> 0 | J39: =IF($K$659="Yes",J709,0) -> 0
C40: ='BDO Prequal'!C175 -> Affiliate 12 - Net Cashflow | D40: ='BDO Prequal'!D175 -> 0 | F40: ='BDO Prequal'!F175 -> 0 | H40: ='BDO Prequal'!H175 -> 0 | J40: ='BDO Prequal'!J175 -> 0
B42: Affiliate 1
B43: {Insert business name which represents Affiliate 1} | J43: Include in Global? | K43: No
B45: Statement Date | D45: ='BDO Prequal'!$D$99 -> 45291 | F45: =EOMONTH(D45,F46) -> 45657 | H45: =EOMONTH(F45,H46) -> 46022 | J45: =EOMONTH(H45,J46) -> 46112
B46: Months Covered | D46: 12 | F46: 12 | H46: 12 | J46: 3
B47: Statement Type | D47: Tax Returns | F47: Tax Returns | J47: Internal
B48: Revenue Recognition
J49: =(J50/J46)*12 -> 0
C50: Total Revenue | D50: 0 | E50: =IF(D$50=0,0,D50/D$50) -> 0 | F50: 0 | G50: =IF(F$50=0,0,F50/F$50) -> 0 | H50: 0 | I50: =IF(H$50=0,0,H50/H$50) -> 0 | J50: 0 | K50: =IF(J$50=0,0,J50/J$50) -> 0
C51: Total COGS | D51: 0 | E51: =IF(D$50=0,0,D51/D$50) -> 0 | F51: 0 | G51: =IF(F$50=0,0,F51/F$50) -> 0 | H51: 0 | I51: =IF(H$50=0,0,H51/H$50) -> 0 | J51: 0 | K51: =IF(J$50=0,0,J51/J$50) -> 0
C52: Total Gross Margin | D52: =D50-D51 -> 0 | E52: =IF(D$50=0,0,D52/D$50) -> 0 | F52: =F50-F51 -> 0 | G52: =IF(F$50=0,0,F52/F$50) -> 0 | H52: =H50-H51 -> 0 | I52: =IF(H$50=0,0,H52/H$50) -> 0 | J52: =J50-J51 -> 0 | K52: =IF(J$50=0,0,J52/J$50) -> 0
C54: Officer's Compensation | D54: 0 | E54: =IF(D$50=0,0,D54/D$50) -> 0 | F54: 0 | G54: =IF(F$50=0,0,F54/F$50) -> 0 | H54: 0 | I54: =IF(H$50=0,0,H54/H$50) -> 0 | J54: 0 | K54: =IF(J$50=0,0,J54/J$50) -> 0
C55: Salaries & Wages | D55: 0 | E55: =IF(D$50=0,0,D55/D$50) -> 0 | F55: 0 | G55: =IF(F$50=0,0,F55/F$50) -> 0 | H55: 0 | I55: =IF(H$50=0,0,H55/H$50) -> 0 | J55: 0 | K55: =IF(J$50=0,0,J55/J$50) -> 0
C56: Repairs & Maintenance | D56: 0 | E56: =IF(D$50=0,0,D56/D$50) -> 0 | F56: 0 | G56: =IF(F$50=0,0,F56/F$50) -> 0 | H56: 0 | I56: =IF(H$50=0,0,H56/H$50) -> 0 | J56: 0 | K56: =IF(J$50=0,0,J56/J$50) -> 0
C57: Bad Debts | D57: 0 | E57: =IF(D$50=0,0,D57/D$50) -> 0 | F57: 0 | G57: =IF(F$50=0,0,F57/F$50) -> 0 | H57: 0 | I57: =IF(H$50=0,0,H57/H$50) -> 0 | J57: 0 | K57: =IF(J$50=0,0,J57/J$50) -> 0
C58: Rents | D58: 0 | E58: =IF(D$50=0,0,D58/D$50) -> 0 | F58: 0 | G58: =IF(F$50=0,0,F58/F$50) -> 0 | H58: 0 | I58: =IF(H$50=0,0,H58/H$50) -> 0 | J58: 0 | K58: =IF(J$50=0,0,J58/J$50) -> 0
C59: Taxes & Licenses | D59: 0 | E59: =IF(D$50=0,0,D59/D$50) -> 0 | F59: 0 | G59: =IF(F$50=0,0,F59/F$50) -> 0 | H59: 0 | I59: =IF(H$50=0,0,H59/H$50) -> 0 | J59: 0 | K59: =IF(J$50=0,0,J59/J$50) -> 0
C60: Interest | D60: 0 | E60: =IF(D$50=0,0,D60/D$50) -> 0 | F60: 0 | G60: =IF(F$50=0,0,F60/F$50) -> 0 | H60: 0 | I60: =IF(H$50=0,0,H60/H$50) -> 0 | J60: 0 | K60: =IF(J$50=0,0,J60/J$50) -> 0
C61: Depreciation & Amortization | D61: 0 | E61: =IF(D$50=0,0,D61/D$50) -> 0 | F61: 0 | G61: =IF(F$50=0,0,F61/F$50) -> 0 | H61: 0 | I61: =IF(H$50=0,0,H61/H$50) -> 0 | J61: 0 | K61: =IF(J$50=0,0,J61/J$50) -> 0
C62: Advertising | D62: 0 | E62: =IF(D$50=0,0,D62/D$50) -> 0 | F62: 0 | G62: =IF(F$50=0,0,F62/F$50) -> 0 | H62: 0 | I62: =IF(H$50=0,0,H62/H$50) -> 0 | J62: 0 | K62: =IF(J$50=0,0,J62/J$50) -> 0
C63: Other | D63: 0 | E63: =IF(D$50=0,0,D63/D$50) -> 0 | F63: 0 | G63: =IF(F$50=0,0,F63/F$50) -> 0 | H63: 0 | I63: =IF(H$50=0,0,H63/H$50) -> 0 | J63: 0 | K63: =IF(J$50=0,0,J63/J$50) -> 0
C64: Other | D64: 0 | E64: =IF(D$50=0,0,D64/D$50) -> 0 | F64: 0 | G64: =IF(F$50=0,0,F64/F$50) -> 0 | H64: 0 | I64: =IF(H$50=0,0,H64/H$50) -> 0 | J64: 0 | K64: =IF(J$50=0,0,J64/J$50) -> 0
C65: Other | D65: 0 | E65: =IF(D$50=0,0,D65/D$50) -> 0 | F65: 0 | G65: =IF(F$50=0,0,F65/F$50) -> 0 | H65: 0 | I65: =IF(H$50=0,0,H65/H$50) -> 0 | J65: 0 | K65: =IF(J$50=0,0,J65/J$50) -> 0
C66: Other | D66: 0 | E66: =IF(D$50=0,0,D66/D$50) -> 0 | F66: 0 | G66: =IF(F$50=0,0,F66/F$50) -> 0 | H66: 0 | I66: =IF(H$50=0,0,H66/H$50) -> 0 | J66: 0 | K66: =IF(J$50=0,0,J66/J$50) -> 0
C67: Total Operating Expenses | D67: =SUM(D54:D66) -> 0 | E67: =IF(D$50=0,0,D67/D$50) -> 0 | F67: =SUM(F54:F66) -> 0 | G67: =IF(F$50=0,0,F67/F$50) -> 0 | H67: =SUM(H54:H66) -> 0 | I67: =IF(H$50=0,0,H67/H$50) -> 0 | J67: =SUM(J54:J66) -> 0 | K67: =IF(J$50=0,0,J67/J$50) -> 0
C69: Ordinary Income | D69: =D52-D67 -> 0 | E69: =IF(D$50=0,0,D69/D$50) -> 0 | F69: =F52-F67 -> 0 | G69: =IF(F$50=0,0,F69/F$50) -> 0 | H69: =H52-H67 -> 0 | I69: =IF(H$50=0,0,H69/H$50) -> 0 | J69: =J52-J67 -> 0 | K69: =IF(J$50=0,0,J69/J$50) -> 0
C71: Other Income / Expense | D71: 0 | E71: =IF(D$50=0,0,D71/D$50) -> 0 | F71: 0 | G71: =IF(F$50=0,0,F71/F$50) -> 0 | H71: 0 | I71: =IF(H$50=0,0,H71/H$50) -> 0 | J71: 0 | K71: =IF(J$50=0,0,J71/J$50) -> 0
C72: Other Income / Expense | D72: 0 | E72: =IF(D$50=0,0,D72/D$50) -> 0 | F72: 0 | G72: =IF(F$50=0,0,F72/F$50) -> 0 | H72: 0 | I72: =IF(H$50=0,0,H72/H$50) -> 0 | J72: 0 | K72: =IF(J$50=0,0,J72/J$50) -> 0
C73: Total Other Income (Expenses) | D73: =SUM(D71:D72) -> 0 | E73: =IF(D$50=0,0,D73/D$50) -> 0 | F73: =SUM(F71:F72) -> 0 | G73: =IF(F$50=0,0,F73/F$50) -> 0 | H73: =SUM(H71:H72) -> 0 | I73: =IF(H$50=0,0,H73/H$50) -> 0 | J73: =SUM(J71:J72) -> 0 | K73: =IF(J$50=0,0,J73/J$50) -> 0
C75: Net Income Before Taxes | D75: =D52-D67+D73 -> 0 | E75: =IF(D$50=0,0,D75/D$50) -> 0 | F75: =F52-F67+F73 -> 0 | G75: =IF(F$50=0,0,F75/F$50) -> 0 | H75: =H52-H67+H73 -> 0 | I75: =IF(H$50=0,0,H75/H$50) -> 0 | J75: =J52-J67+J73 -> 0 | K75: =IF(J$50=0,0,J75/J$50) -> 0
C76: Income Taxes | D76: 0 | E76: =IF(D$50=0,0,D76/D$50) -> 0 | F76: 0 | G76: =IF(F$50=0,0,F76/F$50) -> 0 | H76: 0 | I76: =IF(H$50=0,0,H76/H$50) -> 0 | J76: 0 | K76: =IF(J$50=0,0,J76/J$50) -> 0
C78: NET INCOME AFTER TAXES | D78: =D75-D76 -> 0 | E78: =IF(D$50=0,0,D78/D$50) -> 0 | F78: =F75-F76 -> 0 | G78: =IF(F$50=0,0,F78/F$50) -> 0 | H78: =H75-H76 -> 0 | I78: =IF(H$50=0,0,H78/H$50) -> 0 | J78: =J75-J76 -> 0 | K78: =IF(J$50=0,0,J78/J$50) -> 0
C80: ADJUSTMENTS
C81: Compensation of Officers | D81: =D54 -> 0 | F81: =F54 -> 0 | H81: =H54 -> 0 | J81: =J54 -> 0
C82: Depreciation/Amortization | D82: =D61 -> 0 | F82: =F61 -> 0 | H82: =H61 -> 0 | J82: =J61 -> 0
C83: Interest Expense | D83: =D60 -> 0 | F83: =F60 -> 0 | H83: =H60 -> 0 | J83: =J60 -> 0
C84: Rent Adjustment | D84: 0 | F84: 0 | H84: 0 | J84: 0
C85: Other | D85: 0 | F85: 0 | H85: 0 | J85: 0
C86: Other | D86: 0 | F86: 0 | H86: 0 | J86: 0
C87: Estimated Property Tax | D87: 0 | F87: 0 | H87: 0 | J87: 0
C88: Required Owner's Draw | D88: 0 | F88: 0 | H88: 0 | J88: 0
C90: Cash Available | D90: =D78+SUM(D81:D88) -> 0 | F90: =F78+SUM(F81:F88) -> 0 | H90: =H78+SUM(H81:H88) -> 0 | J90: =J78+SUM(J81:J88) -> 0
C92: Existing Monthly Debt | D92: 0 | F92: 0 | H92: 0 | J92: 0
C93: Existing Debt | D93: =D92*D46 -> 0 | F93: =F92*F46 -> 0 | H93: =H92*H46 -> 0 | J93: =J92*J46 -> 0
C95: DCR | D95: =IFERROR(D90/D93,0) -> 0 | F95: =IFERROR(F90/F93,0) -> 0 | H95: =IFERROR(H90/H93,0) -> 0 | J95: =IFERROR(J90/J93,0) -> 0
B98: Affiliate 2
B99: {Insert business name which represents Affiliate 2} | J99: Include in Global? | K99: No
B101: Statement Date | D101: ='BDO Prequal'!$D$99 -> 45291 | F101: =EOMONTH(D101,F102) -> 45657 | H101: =EOMONTH(F101,H102) -> 46022 | J101: =EOMONTH(H101,J102) -> 46112
B102: Months Covered | D102: 12 | F102: 12 | H102: 12 | J102: 3
B103: Statement Type | D103: Tax Returns | F103: Tax Returns | J103: Internal
B104: Revenue Recognition
J105: =(J106/J102)*12 -> 0
C106: Total Revenue | D106: 0 | E106: % | F106: 0 | G106: =IF(F$106=0,0,F106/F$106) -> 0 | H106: 0 | I106: =IF(H$106=0,0,H106/H$106) -> 0 | J106: 0 | K106: =IF(J$106=0,0,J106/J$106) -> 0
C107: Total COGS | D107: 0 | E107: =IF(D$106=0,0,D107/D$106) -> 0 | F107: 0 | G107: =IF(F$106=0,0,F107/F$106) -> 0 | H107: 0 | I107: =IF(H$106=0,0,H107/H$106) -> 0 | J107: 0 | K107: =IF(J$106=0,0,J107/J$106) -> 0
C108: Total Gross Margin | D108: =D106-D107 -> 0 | E108: =IF(D$106=0,0,D108/D$106) -> 0 | F108: =F106-F107 -> 0 | G108: =IF(F$106=0,0,F108/F$106) -> 0 | H108: =H106-H107 -> 0 | I108: =IF(H$106=0,0,H108/H$106) -> 0 | J108: =J106-J107 -> 0 | K108: =IF(J$106=0,0,J108/J$106) -> 0
C110: Officer's Compensation | D110: 0 | E110: =IF(D$106=0,0,D110/D$106) -> 0 | F110: 0 | G110: =IF(F$106=0,0,F110/F$106) -> 0 | H110: 0 | I110: =IF(H$106=0,0,H110/H$106) -> 0 | J110: 0 | K110: =IF(J$106=0,0,J110/J$106) -> 0
C111: Salaries & Wages | D111: 0 | E111: =IF(D$106=0,0,D111/D$106) -> 0 | F111: 0 | G111: =IF(F$106=0,0,F111/F$106) -> 0 | H111: 0 | I111: =IF(H$106=0,0,H111/H$106) -> 0 | J111: 0 | K111: =IF(J$106=0,0,J111/J$106) -> 0
C112: Repairs & Maintenance | D112: 0 | E112: =IF(D$106=0,0,D112/D$106) -> 0 | F112: 0 | G112: =IF(F$106=0,0,F112/F$106) -> 0 | H112: 0 | I112: =IF(H$106=0,0,H112/H$106) -> 0 | J112: 0 | K112: =IF(J$106=0,0,J112/J$106) -> 0
C113: Bad Debts | D113: 0 | E113: =IF(D$106=0,0,D113/D$106) -> 0 | F113: 0 | G113: =IF(F$106=0,0,F113/F$106) -> 0 | H113: 0 | I113: =IF(H$106=0,0,H113/H$106) -> 0 | J113: 0 | K113: =IF(J$106=0,0,J113/J$106) -> 0
C114: Rents | D114: 0 | E114: =IF(D$106=0,0,D114/D$106) -> 0 | F114: 0 | G114: =IF(F$106=0,0,F114/F$106) -> 0 | H114: 0 | I114: =IF(H$106=0,0,H114/H$106) -> 0 | J114: 0 | K114: =IF(J$106=0,0,J114/J$106) -> 0
C115: Taxes & Licenses | D115: 0 | E115: =IF(D$106=0,0,D115/D$106) -> 0 | F115: 0 | G115: =IF(F$106=0,0,F115/F$106) -> 0 | H115: 0 | I115: =IF(H$106=0,0,H115/H$106) -> 0 | J115: 0 | K115: =IF(J$106=0,0,J115/J$106) -> 0
C116: Interest | D116: 0 | E116: =IF(D$106=0,0,D116/D$106) -> 0 | F116: 0 | G116: =IF(F$106=0,0,F116/F$106) -> 0 | H116: 0 | I116: =IF(H$106=0,0,H116/H$106) -> 0 | J116: 0 | K116: =IF(J$106=0,0,J116/J$106) -> 0
...

Sheet Scores
B2: T Bank, N.A. SCORING GRID
B3: Total Score | C3: REPAYMENT | D3: MANAGEMENT | E3: CREDIT | F3: EQUITY | G3: COLLATERAL | H3: Working Capital/Liquidity
B4: =SUM(C4:H4) -> 0
B5: 5 | C5: Pro forma DSC of 1.40x in the most recent year and 1.25x or better for the prior 2 years plus stable/positive trends in the interim. Stable is considered + - 0.05 change in DSC. | D5: 3 or more years ownership in SBC or 3 years as primary responsible employee in SBC or 5 years recent experience in near identical type business as Principal Manager with P&L and HR responsibility. | E5: N/A | F5: 25% cash equity from personal sources Expansions: pro forma tangible D/W of 4:1 or less. | G5: Secured 120% of the loan on a discounted basis with any collateral or 100% secured with 1st lien on RE. 504 1st lien No construction | H5: N/A
B6: 4 | C6: Pro forma DSC of 1.40x or better for most recent years plus 1.25x for the 1 prior year plus stable/positive trends in the interim. Stable is considered + - 0.05 change in DSC. | D6: 2 or more years ownership in SBC or 3 years experience in near identical type business. For startups - this experience, must have been within the last 5 years AND one of the guarantors will devote 100% of time to SBC | E6: FICO Score greater than 750. | F6: 25% cash equity from any source or 20% from personal sources Expansions: pro forma tangible D/W of 5:1 or less. | G6: Secured 100% of the loan on a discounted basis with any collateral or 75% with 1st lien on RE. 504 1st Lien Construction | H6: N/A
B7: 3 | C7: Pro forma DSC of an 1.25x or better in most recent FYE and interim plus stable/positive trends in the interim. Stable is considered + - 0.05 change in DSC. Regardless of DSC declining revenue or profitability trends in the most recent year and/or interim. | D7: 2 years ownership in any industry or 3 years of transferable management experience in any industry, or approved franchise For startups - this experience, must have been within the last 5 years AND one of the guarantors will devote 100% of time to SBC. | E7: FICO Score of 700 to 749. Regardless of any higher FICO score BK between 3 and 5 years in time. Regardless of any higher FICO score expected continuing income of between $5500 and $6000 for every $1000 of CC debt | F7: 20% cash equity from any source or 15% from personal sources Expansions: pro forma tangible D/W of 6:1 or less. | G7: Secured 75% of the loan on a discounted basis with any collateral or 50% with 1st lien on RE. | H7: No or minimal working capital requirement OR Borrower has 1.5X working capital from own liquid resources. Minimal is the lesser of 5% of loan amount or $50K. None is included in loan.
B8: 2 | C8: Pro forma DSC of 1.15x or better in most recent FYE and interim plus positive trends in the interim. Regardless of DSC declining revenue or profitability trends in all periods Projection Based or Start Up with Approved Franchise. | D8: 2 years transferable management experience not specific to this industry or non-approved franchise. For startups - this experience must have been within the last 3 years AND one of the guarantors will 100% of time devoted to SBC | E8: FICO Score 650 to 699 Regardless of any higher FICO score expected continuing income of between $5000 and $5499 for every $1000 of CC debt | F8: 10% cash equity from any source Expansions: pro forma tangible D/W of 8:1 or less. | G8: Secured 50% of the loan on a discounted basis with any collateral or 25% with 1st lien on RE. | H8: Borrower has sufficient documented working Capital to inject from own resources (WC as calculated by U/W). In loan is OK as long as borrower has 1x or greater residual liquidity.
B9: 1 | C9: Projection based or start-up. | D9: Less than 2 years transferable management experience OR reliant on prior owner or franchisor for training. For startups - the experience was over 3 years ago. | E9: FICO Score less than 650 Regardless of any higher FICO score expected continuing income of between $4500 and $4999 for every $1000 of CC debt | F9: Less than 10% injection and/or 50% or more Equity is from Seller note on full standby | G9: < 50% secured with any collateral or less than 25% 1st lien on RE. | H9: All, or substantially all of W/C is included in loan or companion loan and borrower has little or no residual liquidity.
B10: 0 | C10: N/A | D10: Remote management or long distance management with no prior experience of remote management. | E10: BK in the last 3 years. Regardless of any higher FICO score expected continuing income of less than $4500 for every $1000 of CC debt | F10: Any other allowable SBA SOP structure that does not require injection. | G10: No CRE included in collateral or only junior liens on residential. | H10: Working capital included in loan proceeds exceeds 50% of borrower cash injection.
C13: Income | D13: CC Debt | E13: Income Needed $4,500 | F13: Income Needed $4,999 | G13: Income Needed $5,499 | H13: Income Needed $6,000+
B14: =Guarantors!B6 -> Jeff Able | C14: =Guarantors!N6 -> 126375 | D14: 0 | E14: =D14*4.5 -> 0 | F14: =D14*4.999 -> 0 | G14: =D14*5.499 -> 0 | H14: =D14*6 -> 0
B15: =Guarantors!B7 -> Lisa McClure | C15: =Guarantors!N7 -> 0 | D15: 0 | E15: =D15*4.5 -> 0 | F15: =D15*4.999 -> 0 | G15: =D15*5.499 -> 0 | H15: =D15*6 -> 0
B16: =Guarantors!B8 -> Brandon Johnson | C16: =Guarantors!N8 -> 0 | D16: 0 | E16: =D16*4.5 -> 0 | F16: =D16*4.999 -> 0 | G16: =D16*5.499 -> 0 | H16: =D16*6 -> 0
B17: =Guarantors!B9 -> Riku Patel | C17: =Guarantors!N9 -> 64800 | D17: 0 | E17: =D17*4.5 -> 0 | F17: =D17*4.999 -> 0 | G17: =D17*5.499 -> 0 | H17: =D17*6 -> 0
B18: =Guarantors!B10 -> Divy Patel | C18: =Guarantors!N10 -> 67200 | D18: 0 | E18: =D18*4.5 -> 0 | F18: =D18*4.999 -> 0 | G18: =D18*5.499 -> 0 | H18: =D18*6 -> 0
B19: =Guarantors!B11 -> Customer 6 | C19: =Guarantors!N11 -> 0 | D19: 0 | E19: =D19*4.5 -> 0 | F19: =D19*4.999 -> 0 | G19: =D19*5.499 -> 0 | H19: =D19*6 -> 0
B20: =Guarantors!B12 -> Customer 7 | C20: =Guarantors!N12 -> 0 | D20: 0 | E20: =D20*4.5 -> 0 | F20: =D20*4.999 -> 0 | G20: =D20*5.499 -> 0 | H20: =D20*6 -> 0
B21: =Guarantors!B13 -> Customer 8 | C21: =Guarantors!N13 -> 0 | D21: 0 | E21: =D21*4.5 -> 0 | F21: =D21*4.999 -> 0 | G21: =D21*5.499 -> 0 | H21: =D21*6 -> 0
B22: =Guarantors!B14 -> Customer 9 | C22: =Guarantors!N14 -> 0 | D22: 0 | E22: =D22*4.5 -> 0 | F22: =D22*4.999 -> 0 | G22: =D22*5.499 -> 0 | H22: =D22*6 -> 0
B23: =Guarantors!B15 -> Customer 10 | C23: =Guarantors!N15 -> 0 | D23: 0 | E23: =D23*4.5 -> 0 | F23: =D23*4.999 -> 0 | G23: =D23*5.499 -> 0 | H23: =D23*6 -> 0

Sheet Charts
B3: Loan Request | M3: Loan Request
C5: =N5 -> Total | D5: =O5 -> Equity | E5: =P5 -> SBA 7(a) | F5: =Q5 -> SBA 7(a) | G5: =R5 -> SBA 504 | H5: =S5 -> Seller Note | I5: =T5 -> Debenture | J5: =U5 -> N/A | K5: =V5 -> N/A | N5: ='BDO Prequal'!C36 -> Total | O5: ='BDO Prequal'!D36 -> Equity | P5: ='BDO Prequal'!E36 -> SBA 7(a) | Q5: ='BDO Prequal'!F36 -> SBA 7(a) | R5: ='BDO Prequal'!G36 -> SBA 504 | S5: ='BDO Prequal'!H36 -> Seller Note | T5: ='BDO Prequal'!I36 -> Debenture | U5: ='BDO Prequal'!J36 -> N/A | V5: ='BDO Prequal'!K36 -> N/A
B6: {=_xlfn.LET(_xlpm.visRows,_xlfn._xlws.FILTER(ROW($M$6:$M$22),$N$6:$N$22<>0),_xlpm.allRows,_xlfn.VSTACK(_xlpm.visRows,23,24),_xlpm.pos,ROW()-5,IF(_xlpm.pos<=ROWS(_xlpm.allRows),INDEX($M:$M,INDEX(_xlpm.allRows,_xlpm.pos)),""))} -> Machinery & Equipment | C6: {=_xlfn.LET(_xlpm.visRows,_xlfn._xlws.FILTER(ROW($M$6:$M$22),$N$6:$N$22<>0),_xlpm.allRows,_xlfn.VSTACK(_xlpm.visRows,23,24),_xlpm.pos,ROW()-5,IF(_xlpm.pos>ROWS(_xlpm.allRows),"",_xlfn.LET(_xlpm.rn,INDEX(_xlpm.allRows,_xlpm.pos),_xlpm.val,INDEX($N:$N,_xlpm.rn),IF(INDEX($M:$M,_xlpm.rn)="Percentages",IF(_xlpm.val=0,"-",TEXT(_xlpm.val,"0%")),_xlpm.val))))} -> 366285 | D6: {=_xlfn.LET(_xlpm.visRows,_xlfn._xlws.FILTER(ROW($M$6:$M$22),$N$6:$N$22<>0),_xlpm.allRows,_xlfn.VSTACK(_xlpm.visRows,23,24),_xlpm.pos,ROW()-5,IF(_xlpm.pos>ROWS(_xlpm.allRows),"",_xlfn.LET(_xlpm.rn,INDEX(_xlpm.allRows,_xlpm.pos),_xlpm.val,INDEX($O:$O,_xlpm.rn),IF(INDEX($M:$M,_xlpm.rn)="Percentages",IF(_xlpm.val=0,"-",TEXT(_xlpm.val,"0%")),_xlpm.val))))} -> 366285 | E6: {=_xlfn.LET(_xlpm.visRows,_xlfn._xlws.FILTER(ROW($M$6:$M$22),$N$6:$N$22<>0),_xlpm.allRows,_xlfn.VSTACK(_xlpm.visRows,23,24),_xlpm.pos,ROW()-5,IF(_xlpm.pos>ROWS(_xlpm.allRows),"",_xlfn.LET(_xlpm.rn,INDEX(_xlpm.allRows,_xlpm.pos),_xlpm.val,INDEX($P:$P,_xlpm.rn),IF(INDEX($M:$M,_xlpm.rn)="Percentages",IF(_xlpm.val=0,"-",TEXT(_xlpm.val,"0%")),_xlpm.val))))} -> 0 | F6: {=_xlfn.LET(_xlpm.visRows,_xlfn._xlws.FILTER(ROW($M$6:$M$22),$N$6:$N$22<>0),_xlpm.allRows,_xlfn.VSTACK(_xlpm.visRows,23,24),_xlpm.pos,ROW()-5,IF(_xlpm.pos>ROWS(_xlpm.allRows),"",_xlfn.LET(_xlpm.rn,INDEX(_xlpm.allRows,_xlpm.pos),_xlpm.val,INDEX($Q:$Q,_xlpm.rn),IF(INDEX($M:$M,_xlpm.rn)="Percentages",IF(_xlpm.val=0,"-",TEXT(_xlpm.val,"0%")),_xlpm.val))))} -> 0 | G6: {=_xlfn.LET(_xlpm.visRows,_xlfn._xlws.FILTER(ROW($M$6:$M$22),$N$6:$N$22<>0),_xlpm.allRows,_xlfn.VSTACK(_xlpm.visRows,23,24),_xlpm.pos,ROW()-5,IF(_xlpm.pos>ROWS(_xlpm.allRows),"",_xlfn.LET(_xlpm.rn,INDEX(_xlpm.allRows,_xlpm.pos),_xlpm.val,INDEX($R:$R,_xlpm.rn),IF(INDEX($M:$M,_xlpm.rn)="Percentages",IF(_xlpm.val=0,"-",TEXT(_xlpm.val,"0%")),_xlpm.val))))} -> 0 | H6: {=_xlfn.LET(_xlpm.visRows,_xlfn._xlws.FILTER(ROW($M$6:$M$22),$N$6:$N$22<>0),_xlpm.allRows,_xlfn.VSTACK(_xlpm.visRows,23,24),_xlpm.pos,ROW()-5,IF(_xlpm.pos>ROWS(_xlpm.allRows),"",_xlfn.LET(_xlpm.rn,INDEX(_xlpm.allRows,_xlpm.pos),_xlpm.val,INDEX($S:$S,_xlpm.rn),IF(INDEX($M:$M,_xlpm.rn)="Percentages",IF(_xlpm.val=0,"-",TEXT(_xlpm.val,"0%")),_xlpm.val))))} -> 0 | I6: {=_xlfn.LET(_xlpm.visRows,_xlfn._xlws.FILTER(ROW($M$6:$M$22),$N$6:$N$22<>0),_xlpm.allRows,_xlfn.VSTACK(_xlpm.visRows,23,24),_xlpm.pos,ROW()-5,IF(_xlpm.pos>ROWS(_xlpm.allRows),"",_xlfn.LET(_xlpm.rn,INDEX(_xlpm.allRows,_xlpm.pos),_xlpm.val,INDEX($T:$T,_xlpm.rn),IF(INDEX($M:$M,_xlpm.rn)="Percentages",IF(_xlpm.val=0,"-",TEXT(_xlpm.val,"0%")),_xlpm.val))))} -> 0 | J6: {=_xlfn.LET(_xlpm.visRows,_xlfn._xlws.FILTER(ROW($M$6:$M$22),$N$6:$N$22<>0),_xlpm.allRows,_xlfn.VSTACK(_xlpm.visRows,23,24),_xlpm.pos,ROW()-5,IF(_xlpm.pos>ROWS(_xlpm.allRows),"",_xlfn.LET(_xlpm.rn,INDEX(_xlpm.allRows,_xlpm.pos),_xlpm.val,INDEX($U:$U,_xlpm.rn),IF(INDEX($M:$M,_xlpm.rn)="Percentages",IF(_xlpm.val=0,"-",TEXT(_xlpm.val,"0%")),_xlpm.val))))} -> 0 | K6: {=_xlfn.LET(_xlpm.visRows,_xlfn._xlws.FILTER(ROW($M$6:$M$22),$N$6:$N$22<>0),_xlpm.allRows,_xlfn.VSTACK(_xlpm.visRows,23,24),_xlpm.pos,ROW()-5,IF(_xlpm.pos>ROWS(_xlpm.allRows),"",_xlfn.LET(_xlpm.rn,INDEX(_xlpm.allRows,_xlpm.pos),_xlpm.val,INDEX($V:$V,_xlpm.rn),IF(INDEX($M:$M,_xlpm.rn)="Percentages",IF(_xlpm.val=0,"-",TEXT(_xlpm.val,"0%")),_xlpm.val))))} -> 0 | M6: ='BDO Prequal'!B38 -> Real Estate Acquisition | N6: ='BDO Prequal'!C38 -> 0 | O6: ='BDO Prequal'!D38 -> 0 | P6: ='BDO Prequal'!E38 -> 0 | Q6: ='BDO Prequal'!F38 -> 0 | R6: ='BDO Prequal'!G38 -> 0 | S6: ='BDO Prequal'!H38 -> 0 | T6: ='BDO Prequal'!I38 -> 0 | ... V6: ='BDO Prequal'!K38 -> 0
B7: {=_xlfn.LET(_xlpm.visRows,_xlfn._xlws.FILTER(ROW($M$6:$M$22),$N$6:$N$22<>0),_xlpm.allRows,_xlfn.VSTACK(_xlpm.visRows,23,24),_xlpm.pos,ROW()-5,IF(_xlpm.pos<=ROWS(_xlpm.allRows),INDEX($M:$M,INDEX(_xlpm.allRows,_xlpm.pos)),""))} -> Furniture & Fixtures | C7: {=_xlfn.LET(_xlpm.visRows,_xlfn._xlws.FILTER(ROW($M$6:$M$22),$N$6:$N$22<>0),_xlpm.allRows,_xlfn.VSTACK(_xlpm.visRows,23,24),_xlpm.pos,ROW()-5,IF(_xlpm.pos>ROWS(_xlpm.allRows),"",_xlfn.LET(_xlpm.rn,INDEX(_xlpm.allRows,_xlpm.pos),_xlpm.val,INDEX($N:$N,_xlpm.rn),IF(INDEX($M:$M,_xlpm.rn)="Percentages",IF(_xlpm.val=0,"-",TEXT(_xlpm.val,"0%")),_xlpm.val))))} -> 600000 | D7: {=_xlfn.LET(_xlpm.visRows,_xlfn._xlws.FILTER(ROW($M$6:$M$22),$N$6:$N$22<>0),_xlpm.allRows,_xlfn.VSTACK(_xlpm.visRows,23,24),_xlpm.pos,ROW()-5,IF(_xlpm.pos>ROWS(_xlpm.allRows),"",_xlfn.LET(_xlpm.rn,INDEX(_xlpm.allRows,_xlpm.pos),_xlpm.val,INDEX($O:$O,_xlpm.rn),IF(INDEX($M:$M,_xlpm.rn)="Percentages",IF(_xlpm.val=0,"-",TEXT(_xlpm.val,"0%")),_xlpm.val))))} -> 0 | E7: {=_xlfn.LET(_xlpm.visRows,_xlfn._xlws.FILTER(ROW($M$6:$M$22),$N$6:$N$22<>0),_xlpm.allRows,_xlfn.VSTACK(_xlpm.visRows,23,24),_xlpm.pos,ROW()-5,IF(_xlpm.pos>ROWS(_xlpm.allRows),"",_xlfn.LET(_xlpm.rn,INDEX(_xlpm.allRows,_xlpm.pos),_xlpm.val,INDEX($P:$P,_xlpm.rn),IF(INDEX($M:$M,_xlpm.rn)="Percentages",IF(_xlpm.val=0,"-",TEXT(_xlpm.val,"0%")),_xlpm.val))))} -> 0 | F7: {=_xlfn.LET(_xlpm.visRows,_xlfn._xlws.FILTER(ROW($M$6:$M$22),$N$6:$N$22<>0),_xlpm.allRows,_xlfn.VSTACK(_xlpm.visRows,23,24),_xlpm.pos,ROW()-5,IF(_xlpm.pos>ROWS(_xlpm.allRows),"",_xlfn.LET(_xlpm.rn,INDEX(_xlpm.allRows,_xlpm.pos),_xlpm.val,INDEX($Q:$Q,_xlpm.rn),IF(INDEX($M:$M,_xlpm.rn)="Percentages",IF(_xlpm.val=0,"-",TEXT(_xlpm.val,"0%")),_xlpm.val))))} -> 600000 | G7: {=_xlfn.LET(_xlpm.visRows,_xlfn._xlws.FILTER(ROW($M$6:$M$22),$N$6:$N$22<>0),_xlpm.allRows,_xlfn.VSTACK(_xlpm.visRows,23,24),_xlpm.pos,ROW()-5,IF(_xlpm.pos>ROWS(_xlpm.allRows),"",_xlfn.LET(_xlpm.rn,INDEX(_xlpm.allRows,_xlpm.pos),_xlpm.val,INDEX($R:$R,_xlpm.rn),IF(INDEX($M:$M,_xlpm.rn)="Percentages",IF(_xlpm.val=0,"-",TEXT(_xlpm.val,"0%")),_xlpm.val))))} -> 0 | H7: {=_xlfn.LET(_xlpm.visRows,_xlfn._xlws.FILTER(ROW($M$6:$M$22),$N$6:$N$22<>0),_xlpm.allRows,_xlfn.VSTACK(_xlpm.visRows,23,24),_xlpm.pos,ROW()-5,IF(_xlpm.pos>ROWS(_xlpm.allRows),"",_xlfn.LET(_xlpm.rn,INDEX(_xlpm.allRows,_xlpm.pos),_xlpm.val,INDEX($S:$S,_xlpm.rn),IF(INDEX($M:$M,_xlpm.rn)="Percentages",IF(_xlpm.val=0,"-",TEXT(_xlpm.val,"0%")),_xlpm.val))))} -> 0 | I7: {=_xlfn.LET(_xlpm.visRows,_xlfn._xlws.FILTER(ROW($M$6:$M$22),$N$6:$N$22<>0),_xlpm.allRows,_xlfn.VSTACK(_xlpm.visRows,23,24),_xlpm.pos,ROW()-5,IF(_xlpm.pos>ROWS(_xlpm.allRows),"",_xlfn.LET(_xlpm.rn,INDEX(_xlpm.allRows,_xlpm.pos),_xlpm.val,INDEX($T:$T,_xlpm.rn),IF(INDEX($M:$M,_xlpm.rn)="Percentages",IF(_xlpm.val=0,"-",TEXT(_xlpm.val,"0%")),_xlpm.val))))} -> 0 | J7: {=_xlfn.LET(_xlpm.visRows,_xlfn._xlws.FILTER(ROW($M$6:$M$22),$N$6:$N$22<>0),_xlpm.allRows,_xlfn.VSTACK(_xlpm.visRows,23,24),_xlpm.pos,ROW()-5,IF(_xlpm.pos>ROWS(_xlpm.allRows),"",_xlfn.LET(_xlpm.rn,INDEX(_xlpm.allRows,_xlpm.pos),_xlpm.val,INDEX($U:$U,_xlpm.rn),IF(INDEX($M:$M,_xlpm.rn)="Percentages",IF(_xlpm.val=0,"-",TEXT(_xlpm.val,"0%")),_xlpm.val))))} -> 0 | K7: {=_xlfn.LET(_xlpm.visRows,_xlfn._xlws.FILTER(ROW($M$6:$M$22),$N$6:$N$22<>0),_xlpm.allRows,_xlfn.VSTACK(_xlpm.visRows,23,24),_xlpm.pos,ROW()-5,IF(_xlpm.pos>ROWS(_xlpm.allRows),"",_xlfn.LET(_xlpm.rn,INDEX(_xlpm.allRows,_xlpm.pos),_xlpm.val,INDEX($V:$V,_xlpm.rn),IF(INDEX($M:$M,_xlpm.rn)="Percentages",IF(_xlpm.val=0,"-",TEXT(_xlpm.val,"0%")),_xlpm.val))))} -> 0 | M7: ='BDO Prequal'!B39 -> Debt Refi - CRE | N7: ='BDO Prequal'!C39 -> 0 | O7: ='BDO Prequal'!D39 -> 0 | P7: ='BDO Prequal'!E39 -> 0 | Q7: ='BDO Prequal'!F39 -> 0 | R7: ='BDO Prequal'!G39 -> 0 | S7: ='BDO Prequal'!H39 -> 0 | T7: ='BDO Prequal'!I39 -> 0 | ... V7: ='BDO Prequal'!K39 -> 0
B8: {=_xlfn.LET(_xlpm.visRows,_xlfn._xlws.FILTER(ROW($M$6:$M$22),$N$6:$N$22<>0),_xlpm.allRows,_xlfn.VSTACK(_xlpm.visRows,23,24),_xlpm.pos,ROW()-5,IF(_xlpm.pos<=ROWS(_xlpm.allRows),INDEX($M:$M,INDEX(_xlpm.allRows,_xlpm.pos)),""))} -> Working Capital | C8: {=_xlfn.LET(_xlpm.visRows,_xlfn._xlws.FILTER(ROW($M$6:$M$22),$N$6:$N$22<>0),_xlpm.allRows,_xlfn.VSTACK(_xlpm.visRows,23,24),_xlpm.pos,ROW()-5,IF(_xlpm.pos>ROWS(_xlpm.allRows),"",_xlfn.LET(_xlpm.rn,INDEX(_xlpm.allRows,_xlpm.pos),_xlpm.val,INDEX($N:$N,_xlpm.rn),IF(INDEX($M:$M,_xlpm.rn)="Percentages",IF(_xlpm.val=0,"-",TEXT(_xlpm.val,"0%")),_xlpm.val))))} -> 573500 | D8: {=_xlfn.LET(_xlpm.visRows,_xlfn._xlws.FILTER(ROW($M$6:$M$22),$N$6:$N$22<>0),_xlpm.allRows,_xlfn.VSTACK(_xlpm.visRows,23,24),_xlpm.pos,ROW()-5,IF(_xlpm.pos>ROWS(_xlpm.allRows),"",_xlfn.LET(_xlpm.rn,INDEX(_xlpm.allRows,_xlpm.pos),_xlpm.val,INDEX($O:$O,_xlpm.rn),IF(INDEX($M:$M,_xlpm.rn)="Percentages",IF(_xlpm.val=0,"-",TEXT(_xlpm.val,"0%")),_xlpm.val))))} -> 573500 | E8: {=_xlfn.LET(_xlpm.visRows,_xlfn._xlws.FILTER(ROW($M$6:$M$22),$N$6:$N$22<>0),_xlpm.allRows,_xlfn.VSTACK(_xlpm.visRows,23,24),_xlpm.pos,ROW()-5,IF(_xlpm.pos>ROWS(_xlpm.allRows),"",_xlfn.LET(_xlpm.rn,INDEX(_xlpm.allRows,_xlpm.pos),_xlpm.val,INDEX($P:$P,_xlpm.rn),IF(INDEX($M:$M,_xlpm.rn)="Percentages",IF(_xlpm.val=0,"-",TEXT(_xlpm.val,"0%")),_xlpm.val))))} -> 0 | F8: {=_xlfn.LET(_xlpm.visRows,_xlfn._xlws.FILTER(ROW($M$6:$M$22),$N$6:$N$22<>0),_xlpm.allRows,_xlfn.VSTACK(_xlpm.visRows,23,24),_xlpm.pos,ROW()-5,IF(_xlpm.pos>ROWS(_xlpm.allRows),"",_xlfn.LET(_xlpm.rn,INDEX(_xlpm.allRows,_xlpm.pos),_xlpm.val,INDEX($Q:$Q,_xlpm.rn),IF(INDEX($M:$M,_xlpm.rn)="Percentages",IF(_xlpm.val=0,"-",TEXT(_xlpm.val,"0%")),_xlpm.val))))} -> 0 | G8: {=_xlfn.LET(_xlpm.visRows,_xlfn._xlws.FILTER(ROW($M$6:$M$22),$N$6:$N$22<>0),_xlpm.allRows,_xlfn.VSTACK(_xlpm.visRows,23,24),_xlpm.pos,ROW()-5,IF(_xlpm.pos>ROWS(_xlpm.allRows),"",_xlfn.LET(_xlpm.rn,INDEX(_xlpm.allRows,_xlpm.pos),_xlpm.val,INDEX($R:$R,_xlpm.rn),IF(INDEX($M:$M,_xlpm.rn)="Percentages",IF(_xlpm.val=0,"-",TEXT(_xlpm.val,"0%")),_xlpm.val))))} -> 0 | H8: {=_xlfn.LET(_xlpm.visRows,_xlfn._xlws.FILTER(ROW($M$6:$M$22),$N$6:$N$22<>0),_xlpm.allRows,_xlfn.VSTACK(_xlpm.visRows,23,24),_xlpm.pos,ROW()-5,IF(_xlpm.pos>ROWS(_xlpm.allRows),"",_xlfn.LET(_xlpm.rn,INDEX(_xlpm.allRows,_xlpm.pos),_xlpm.val,INDEX($S:$S,_xlpm.rn),IF(INDEX($M:$M,_xlpm.rn)="Percentages",IF(_xlpm.val=0,"-",TEXT(_xlpm.val,"0%")),_xlpm.val))))} -> 0 | I8: {=_xlfn.LET(_xlpm.visRows,_xlfn._xlws.FILTER(ROW($M$6:$M$22),$N$6:$N$22<>0),_xlpm.allRows,_xlfn.VSTACK(_xlpm.visRows,23,24),_xlpm.pos,ROW()-5,IF(_xlpm.pos>ROWS(_xlpm.allRows),"",_xlfn.LET(_xlpm.rn,INDEX(_xlpm.allRows,_xlpm.pos),_xlpm.val,INDEX($T:$T,_xlpm.rn),IF(INDEX($M:$M,_xlpm.rn)="Percentages",IF(_xlpm.val=0,"-",TEXT(_xlpm.val,"0%")),_xlpm.val))))} -> 0 | J8: {=_xlfn.LET(_xlpm.visRows,_xlfn._xlws.FILTER(ROW($M$6:$M$22),$N$6:$N$22<>0),_xlpm.allRows,_xlfn.VSTACK(_xlpm.visRows,23,24),_xlpm.pos,ROW()-5,IF(_xlpm.pos>ROWS(_xlpm.allRows),"",_xlfn.LET(_xlpm.rn,INDEX(_xlpm.allRows,_xlpm.pos),_xlpm.val,INDEX($U:$U,_xlpm.rn),IF(INDEX($M:$M,_xlpm.rn)="Percentages",IF(_xlpm.val=0,"-",TEXT(_xlpm.val,"0%")),_xlpm.val))))} -> 0 | K8: {=_xlfn.LET(_xlpm.visRows,_xlfn._xlws.FILTER(ROW($M$6:$M$22),$N$6:$N$22<>0),_xlpm.allRows,_xlfn.VSTACK(_xlpm.visRows,23,24),_xlpm.pos,ROW()-5,IF(_xlpm.pos>ROWS(_xlpm.allRows),"",_xlfn.LET(_xlpm.rn,INDEX(_xlpm.allRows,_xlpm.pos),_xlpm.val,INDEX($V:$V,_xlpm.rn),IF(INDEX($M:$M,_xlpm.rn)="Percentages",IF(_xlpm.val=0,"-",TEXT(_xlpm.val,"0%")),_xlpm.val))))} -> 0 | M8: ='BDO Prequal'!B40 -> Debt Refi - Non-CRE | N8: ='BDO Prequal'!C40 -> 0 | O8: ='BDO Prequal'!D40 -> 0 | P8: ='BDO Prequal'!E40 -> 0 | Q8: ='BDO Prequal'!F40 -> 0 | R8: ='BDO Prequal'!G40 -> 0 | S8: ='BDO Prequal'!H40 -> 0 | T8: ='BDO Prequal'!I40 -> 0 | ... V8: ='BDO Prequal'!K40 -> 0
B9: {=_xlfn.LET(_xlpm.visRows,_xlfn._xlws.FILTER(ROW($M$6:$M$22),$N$6:$N$22<>0),_xlpm.allRows,_xlfn.VSTACK(_xlpm.visRows,23,24),_xlpm.pos,ROW()-5,IF(_xlpm.pos<=ROWS(_xlpm.allRows),INDEX($M:$M,INDEX(_xlpm.allRows,_xlpm.pos)),""))} -> Working Capital - Pre Opening | C9: {=_xlfn.LET(_xlpm.visRows,_xlfn._xlws.FILTER(ROW($M$6:$M$22),$N$6:$N$22<>0),_xlpm.allRows,_xlfn.VSTACK(_xlpm.visRows,23,24),_xlpm.pos,ROW()-5,IF(_xlpm.pos>ROWS(_xlpm.allRows),"",_xlfn.LET(_xlpm.rn,INDEX(_xlpm.allRows,_xlpm.pos),_xlpm.val,INDEX($N:$N,_xlpm.rn),IF(INDEX($M:$M,_xlpm.rn)="Percentages",IF(_xlpm.val=0,"-",TEXT(_xlpm.val,"0%")),_xlpm.val))))} -> 77000 | D9: {=_xlfn.LET(_xlpm.visRows,_xlfn._xlws.FILTER(ROW($M$6:$M$22),$N$6:$N$22<>0),_xlpm.allRows,_xlfn.VSTACK(_xlpm.visRows,23,24),_xlpm.pos,ROW()-5,IF(_xlpm.pos>ROWS(_xlpm.allRows),"",_xlfn.LET(_xlpm.rn,INDEX(_xlpm.allRows,_xlpm.pos),_xlpm.val,INDEX($O:$O,_xlpm.rn),IF(INDEX($M:$M,_xlpm.rn)="Percentages",IF(_xlpm.val=0,"-",TEXT(_xlpm.val,"0%")),_xlpm.val))))} -> 77000 | E9: {=_xlfn.LET(_xlpm.visRows,_xlfn._xlws.FILTER(ROW($M$6:$M$22),$N$6:$N$22<>0),_xlpm.allRows,_xlfn.VSTACK(_xlpm.visRows,23,24),_xlpm.pos,ROW()-5,IF(_xlpm.pos>ROWS(_xlpm.allRows),"",_xlfn.LET(_xlpm.rn,INDEX(_xlpm.allRows,_xlpm.pos),_xlpm.val,INDEX($P:$P,_xlpm.rn),IF(INDEX($M:$M,_xlpm.rn)="Percentages",IF(_xlpm.val=0,"-",TEXT(_xlpm.val,"0%")),_xlpm.val))))} -> 0 | F9: {=_xlfn.LET(_xlpm.visRows,_xlfn._xlws.FILTER(ROW($M$6:$M$22),$N$6:$N$22<>0),_xlpm.allRows,_xlfn.VSTACK(_xlpm.visRows,23,24),_xlpm.pos,ROW()-5,IF(_xlpm.pos>ROWS(_xlpm.allRows),"",_xlfn.LET(_xlpm.rn,INDEX(_xlpm.allRows,_xlpm.pos),_xlpm.val,INDEX($Q:$Q,_xlpm.rn),IF(INDEX($M:$M,_xlpm.rn)="Percentages",IF(_xlpm.val=0,"-",TEXT(_xlpm.val,"0%")),_xlpm.val))))} -> 0 | G9: {=_xlfn.LET(_xlpm.visRows,_xlfn._xlws.FILTER(ROW($M$6:$M$22),$N$6:$N$22<>0),_xlpm.allRows,_xlfn.VSTACK(_xlpm.visRows,23,24),_xlpm.pos,ROW()-5,IF(_xlpm.pos>ROWS(_xlpm.allRows),"",_xlfn.LET(_xlpm.rn,INDEX(_xlpm.allRows,_xlpm.pos),_xlpm.val,INDEX($R:$R,_xlpm.rn),IF(INDEX($M:$M,_xlpm.rn)="Percentages",IF(_xlpm.val=0,"-",TEXT(_xlpm.val,"0%")),_xlpm.val))))} -> 0 | H9: {=_xlfn.LET(_xlpm.visRows,_xlfn._xlws.FILTER(ROW($M$6:$M$22),$N$6:$N$22<>0),_xlpm.allRows,_xlfn.VSTACK(_xlpm.visRows,23,24),_xlpm.pos,ROW()-5,IF(_xlpm.pos>ROWS(_xlpm.allRows),"",_xlfn.LET(_xlpm.rn,INDEX(_xlpm.allRows,_xlpm.pos),_xlpm.val,INDEX($S:$S,_xlpm.rn),IF(INDEX($M:$M,_xlpm.rn)="Percentages",IF(_xlpm.val=0,"-",TEXT(_xlpm.val,"0%")),_xlpm.val))))} -> 0 | I9: {=_xlfn.LET(_xlpm.visRows,_xlfn._xlws.FILTER(ROW($M$6:$M$22),$N$6:$N$22<>0),_xlpm.allRows,_xlfn.VSTACK(_xlpm.visRows,23,24),_xlpm.pos,ROW()-5,IF(_xlpm.pos>ROWS(_xlpm.allRows),"",_xlfn.LET(_xlpm.rn,INDEX(_xlpm.allRows,_xlpm.pos),_xlpm.val,INDEX($T:$T,_xlpm.rn),IF(INDEX($M:$M,_xlpm.rn)="Percentages",IF(_xlpm.val=0,"-",TEXT(_xlpm.val,"0%")),_xlpm.val))))} -> 0 | J9: {=_xlfn.LET(_xlpm.visRows,_xlfn._xlws.FILTER(ROW($M$6:$M$22),$N$6:$N$22<>0),_xlpm.allRows,_xlfn.VSTACK(_xlpm.visRows,23,24),_xlpm.pos,ROW()-5,IF(_xlpm.pos>ROWS(_xlpm.allRows),"",_xlfn.LET(_xlpm.rn,INDEX(_xlpm.allRows,_xlpm.pos),_xlpm.val,INDEX($U:$U,_xlpm.rn),IF(INDEX($M:$M,_xlpm.rn)="Percentages",IF(_xlpm.val=0,"-",TEXT(_xlpm.val,"0%")),_xlpm.val))))} -> 0 | K9: {=_xlfn.LET(_xlpm.visRows,_xlfn._xlws.FILTER(ROW($M$6:$M$22),$N$6:$N$22<>0),_xlpm.allRows,_xlfn.VSTACK(_xlpm.visRows,23,24),_xlpm.pos,ROW()-5,IF(_xlpm.pos>ROWS(_xlpm.allRows),"",_xlfn.LET(_xlpm.rn,INDEX(_xlpm.allRows,_xlpm.pos),_xlpm.val,INDEX($V:$V,_xlpm.rn),IF(INDEX($M:$M,_xlpm.rn)="Percentages",IF(_xlpm.val=0,"-",TEXT(_xlpm.val,"0%")),_xlpm.val))))} -> 0 | M9: ='BDO Prequal'!B41 -> Machinery & Equipment | N9: ='BDO Prequal'!C41 -> 366285 | O9: ='BDO Prequal'!D41 -> 366285 | P9: ='BDO Prequal'!E41 -> 0 | Q9: ='BDO Prequal'!F41 -> 0 | R9: ='BDO Prequal'!G41 -> 0 | S9: ='BDO Prequal'!H41 -> 0 | T9: ='BDO Prequal'!I41 -> 0 | ... V9: ='BDO Prequal'!K41 -> 0
B10: {=_xlfn.LET(_xlpm.visRows,_xlfn._xlws.FILTER(ROW($M$6:$M$22),$N$6:$N$22<>0),_xlpm.allRows,_xlfn.VSTACK(_xlpm.visRows,23,24),_xlpm.pos,ROW()-5,IF(_xlpm.pos<=ROWS(_xlpm.allRows),INDEX($M:$M,INDEX(_xlpm.allRows,_xlpm.pos)),""))} -> Business Acquisition | C10: {=_xlfn.LET(_xlpm.visRows,_xlfn._xlws.FILTER(ROW($M$6:$M$22),$N$6:$N$22<>0),_xlpm.allRows,_xlfn.VSTACK(_xlpm.visRows,23,24),_xlpm.pos,ROW()-5,IF(_xlpm.pos>ROWS(_xlpm.allRows),"",_xlfn.LET(_xlpm.rn,INDEX(_xlpm.allRows,_xlpm.pos),_xlpm.val,INDEX($N:$N,_xlpm.rn),IF(INDEX($M:$M,_xlpm.rn)="Percentages",IF(_xlpm.val=0,"-",TEXT(_xlpm.val,"0%")),_xlpm.val))))} -> 2219000 | D10: {=_xlfn.LET(_xlpm.visRows,_xlfn._xlws.FILTER(ROW($M$6:$M$22),$N$6:$N$22<>0),_xlpm.allRows,_xlfn.VSTACK(_xlpm.visRows,23,24),_xlpm.pos,ROW()-5,IF(_xlpm.pos>ROWS(_xlpm.allRows),"",_xlfn.LET(_xlpm.rn,INDEX(_xlpm.allRows,_xlpm.pos),_xlpm.val,INDEX($O:$O,_xlpm.rn),IF(INDEX($M:$M,_xlpm.rn)="Percentages",IF(_xlpm.val=0,"-",TEXT(_xlpm.val,"0%")),_xlpm.val))))} -> 225000 | E10: {=_xlfn.LET(_xlpm.visRows,_xlfn._xlws.FILTER(ROW($M$6:$M$22),$N$6:$N$22<>0),_xlpm.allRows,_xlfn.VSTACK(_xlpm.visRows,23,24),_xlpm.pos,ROW()-5,IF(_xlpm.pos>ROWS(_xlpm.allRows),"",_xlfn.LET(_xlpm.rn,INDEX(_xlpm.allRows,_xlpm.pos),_xlpm.val,INDEX($P:$P,_xlpm.rn),IF(INDEX($M:$M,_xlpm.rn)="Percentages",IF(_xlpm.val=0,"-",TEXT(_xlpm.val,"0%")),_xlpm.val))))} -> 324000 | F10: {=_xlfn.LET(_xlpm.visRows,_xlfn._xlws.FILTER(ROW($M$6:$M$22),$N$6:$N$22<>0),_xlpm.allRows,_xlfn.VSTACK(_xlpm.visRows,23,24),_xlpm.pos,ROW()-5,IF(_xlpm.pos>ROWS(_xlpm.allRows),"",_xlfn.LET(_xlpm.rn,INDEX(_xlpm.allRows,_xlpm.pos),_xlpm.val,INDEX($Q:$Q,_xlpm.rn),IF(INDEX($M:$M,_xlpm.rn)="Percentages",IF(_xlpm.val=0,"-",TEXT(_xlpm.val,"0%")),_xlpm.val))))} -> 0 | G10: {=_xlfn.LET(_xlpm.visRows,_xlfn._xlws.FILTER(ROW($M$6:$M$22),$N$6:$N$22<>0),_xlpm.allRows,_xlfn.VSTACK(_xlpm.visRows,23,24),_xlpm.pos,ROW()-5,IF(_xlpm.pos>ROWS(_xlpm.allRows),"",_xlfn.LET(_xlpm.rn,INDEX(_xlpm.allRows,_xlpm.pos),_xlpm.val,INDEX($R:$R,_xlpm.rn),IF(INDEX($M:$M,_xlpm.rn)="Percentages",IF(_xlpm.val=0,"-",TEXT(_xlpm.val,"0%")),_xlpm.val))))} -> 1350000 | H10: {=_xlfn.LET(_xlpm.visRows,_xlfn._xlws.FILTER(ROW($M$6:$M$22),$N$6:$N$22<>0),_xlpm.allRows,_xlfn.VSTACK(_xlpm.visRows,23,24),_xlpm.pos,ROW()-5,IF(_xlpm.pos>ROWS(_xlpm.allRows),"",_xlfn.LET(_xlpm.rn,INDEX(_xlpm.allRows,_xlpm.pos),_xlpm.val,INDEX($S:$S,_xlpm.rn),IF(INDEX($M:$M,_xlpm.rn)="Percentages",IF(_xlpm.val=0,"-",TEXT(_xlpm.val,"0%")),_xlpm.val))))} -> 320000 | I10: {=_xlfn.LET(_xlpm.visRows,_xlfn._xlws.FILTER(ROW($M$6:$M$22),$N$6:$N$22<>0),_xlpm.allRows,_xlfn.VSTACK(_xlpm.visRows,23,24),_xlpm.pos,ROW()-5,IF(_xlpm.pos>ROWS(_xlpm.allRows),"",_xlfn.LET(_xlpm.rn,INDEX(_xlpm.allRows,_xlpm.pos),_xlpm.val,INDEX($T:$T,_xlpm.rn),IF(INDEX($M:$M,_xlpm.rn)="Percentages",IF(_xlpm.val=0,"-",TEXT(_xlpm.val,"0%")),_xlpm.val))))} -> 0 | J10: {=_xlfn.LET(_xlpm.visRows,_xlfn._xlws.FILTER(ROW($M$6:$M$22),$N$6:$N$22<>0),_xlpm.allRows,_xlfn.VSTACK(_xlpm.visRows,23,24),_xlpm.pos,ROW()-5,IF(_xlpm.pos>ROWS(_xlpm.allRows),"",_xlfn.LET(_xlpm.rn,INDEX(_xlpm.allRows,_xlpm.pos),_xlpm.val,INDEX($U:$U,_xlpm.rn),IF(INDEX($M:$M,_xlpm.rn)="Percentages",IF(_xlpm.val=0,"-",TEXT(_xlpm.val,"0%")),_xlpm.val))))} -> 0 | K10: {=_xlfn.LET(_xlpm.visRows,_xlfn._xlws.FILTER(ROW($M$6:$M$22),$N$6:$N$22<>0),_xlpm.allRows,_xlfn.VSTACK(_xlpm.visRows,23,24),_xlpm.pos,ROW()-5,IF(_xlpm.pos>ROWS(_xlpm.allRows),"",_xlfn.LET(_xlpm.rn,INDEX(_xlpm.allRows,_xlpm.pos),_xlpm.val,INDEX($V:$V,_xlpm.rn),IF(INDEX($M:$M,_xlpm.rn)="Percentages",IF(_xlpm.val=0,"-",TEXT(_xlpm.val,"0%")),_xlpm.val))))} -> 0 | M10: ='BDO Prequal'!B42 -> Furniture & Fixtures | N10: ='BDO Prequal'!C42 -> 600000 | O10: ='BDO Prequal'!D42 -> 0 | P10: ='BDO Prequal'!E42 -> 0 | Q10: ='BDO Prequal'!F42 -> 600000 | R10: ='BDO Prequal'!G42 -> 0 | S10: ='BDO Prequal'!H42 -> 0 | T10: ='BDO Prequal'!I42 -> 0 | ... V10: ='BDO Prequal'!K42 -> 0
B11: {=_xlfn.LET(_xlpm.visRows,_xlfn._xlws.FILTER(ROW($M$6:$M$22),$N$6:$N$22<>0),_xlpm.allRows,_xlfn.VSTACK(_xlpm.visRows,23,24),_xlpm.pos,ROW()-5,IF(_xlpm.pos<=ROWS(_xlpm.allRows),INDEX($M:$M,INDEX(_xlpm.allRows,_xlpm.pos)),""))} -> Construction Hard Costs | C11: {=_xlfn.LET(_xlpm.visRows,_xlfn._xlws.FILTER(ROW($M$6:$M$22),$N$6:$N$22<>0),_xlpm.allRows,_xlfn.VSTACK(_xlpm.visRows,23,24),_xlpm.pos,ROW()-5,IF(_xlpm.pos>ROWS(_xlpm.allRows),"",_xlfn.LET(_xlpm.rn,INDEX(_xlpm.allRows,_xlpm.pos),_xlpm.val,INDEX($N:$N,_xlpm.rn),IF(INDEX($M:$M,_xlpm.rn)="Percentages",IF(_xlpm.val=0,"-",TEXT(_xlpm.val,"0%")),_xlpm.val))))} -> 4100000 | D11: {=_xlfn.LET(_xlpm.visRows,_xlfn._xlws.FILTER(ROW($M$6:$M$22),$N$6:$N$22<>0),_xlpm.allRows,_xlfn.VSTACK(_xlpm.visRows,23,24),_xlpm.pos,ROW()-5,IF(_xlpm.pos>ROWS(_xlpm.allRows),"",_xlfn.LET(_xlpm.rn,INDEX(_xlpm.allRows,_xlpm.pos),_xlpm.val,INDEX($O:$O,_xlpm.rn),IF(INDEX($M:$M,_xlpm.rn)="Percentages",IF(_xlpm.val=0,"-",TEXT(_xlpm.val,"0%")),_xlpm.val))))} -> 276207 | E11: {=_xlfn.LET(_xlpm.visRows,_xlfn._xlws.FILTER(ROW($M$6:$M$22),$N$6:$N$22<>0),_xlpm.allRows,_xlfn.VSTACK(_xlpm.visRows,23,24),_xlpm.pos,ROW()-5,IF(_xlpm.pos>ROWS(_xlpm.allRows),"",_xlfn.LET(_xlpm.rn,INDEX(_xlpm.allRows,_xlpm.pos),_xlpm.val,INDEX($P:$P,_xlpm.rn),IF(INDEX($M:$M,_xlpm.rn)="Percentages",IF(_xlpm.val=0,"-",TEXT(_xlpm.val,"0%")),_xlpm.val))))} -> 0 | F11: {=_xlfn.LET(_xlpm.visRows,_xlfn._xlws.FILTER(ROW($M$6:$M$22),$N$6:$N$22<>0),_xlpm.allRows,_xlfn.VSTACK(_xlpm.visRows,23,24),_xlpm.pos,ROW()-5,IF(_xlpm.pos>ROWS(_xlpm.allRows),"",_xlfn.LET(_xlpm.rn,INDEX(_xlpm.allRows,_xlpm.pos),_xlpm.val,INDEX($Q:$Q,_xlpm.rn),IF(INDEX($M:$M,_xlpm.rn)="Percentages",IF(_xlpm.val=0,"-",TEXT(_xlpm.val,"0%")),_xlpm.val))))} -> 1951858 | G11: {=_xlfn.LET(_xlpm.visRows,_xlfn._xlws.FILTER(ROW($M$6:$M$22),$N$6:$N$22<>0),_xlpm.allRows,_xlfn.VSTACK(_xlpm.visRows,23,24),_xlpm.pos,ROW()-5,IF(_xlpm.pos>ROWS(_xlpm.allRows),"",_xlfn.LET(_xlpm.rn,INDEX(_xlpm.allRows,_xlpm.pos),_xlpm.val,INDEX($R:$R,_xlpm.rn),IF(INDEX($M:$M,_xlpm.rn)="Percentages",IF(_xlpm.val=0,"-",TEXT(_xlpm.val,"0%")),_xlpm.val))))} -> 0 | H11: {=_xlfn.LET(_xlpm.visRows,_xlfn._xlws.FILTER(ROW($M$6:$M$22),$N$6:$N$22<>0),_xlpm.allRows,_xlfn.VSTACK(_xlpm.visRows,23,24),_xlpm.pos,ROW()-5,IF(_xlpm.pos>ROWS(_xlpm.allRows),"",_xlfn.LET(_xlpm.rn,INDEX(_xlpm.allRows,_xlpm.pos),_xlpm.val,INDEX($S:$S,_xlpm.rn),IF(INDEX($M:$M,_xlpm.rn)="Percentages",IF(_xlpm.val=0,"-",TEXT(_xlpm.val,"0%")),_xlpm.val))))} -> 0 | I11: {=_xlfn.LET(_xlpm.visRows,_xlfn._xlws.FILTER(ROW($M$6:$M$22),$N$6:$N$22<>0),_xlpm.allRows,_xlfn.VSTACK(_xlpm.visRows,23,24),_xlpm.pos,ROW()-5,IF(_xlpm.pos>ROWS(_xlpm.allRows),"",_xlfn.LET(_xlpm.rn,INDEX(_xlpm.allRows,_xlpm.pos),_xlpm.val,INDEX($T:$T,_xlpm.rn),IF(INDEX($M:$M,_xlpm.rn)="Percentages",IF(_xlpm.val=0,"-",TEXT(_xlpm.val,"0%")),_xlpm.val))))} -> 1871935 | J11: {=_xlfn.LET(_xlpm.visRows,_xlfn._xlws.FILTER(ROW($M$6:$M$22),$N$6:$N$22<>0),_xlpm.allRows,_xlfn.VSTACK(_xlpm.visRows,23,24),_xlpm.pos,ROW()-5,IF(_xlpm.pos>ROWS(_xlpm.allRows),"",_xlfn.LET(_xlpm.rn,INDEX(_xlpm.allRows,_xlpm.pos),_xlpm.val,INDEX($U:$U,_xlpm.rn),IF(INDEX($M:$M,_xlpm.rn)="Percentages",IF(_xlpm.val=0,"-",TEXT(_xlpm.val,"0%")),_xlpm.val))))} -> 0 | K11: {=_xlfn.LET(_xlpm.visRows,_xlfn._xlws.FILTER(ROW($M$6:$M$22),$N$6:$N$22<>0),_xlpm.allRows,_xlfn.VSTACK(_xlpm.visRows,23,24),_xlpm.pos,ROW()-5,IF(_xlpm.pos>ROWS(_xlpm.allRows),"",_xlfn.LET(_xlpm.rn,INDEX(_xlpm.allRows,_xlpm.pos),_xlpm.val,INDEX($V:$V,_xlpm.rn),IF(INDEX($M:$M,_xlpm.rn)="Percentages",IF(_xlpm.val=0,"-",TEXT(_xlpm.val,"0%")),_xlpm.val))))} -> 0 | M11: ='BDO Prequal'!B43 -> Inventory | N11: ='BDO Prequal'!C43 -> 0 | O11: ='BDO Prequal'!D43 -> 0 | P11: ='BDO Prequal'!E43 -> 0 | Q11: ='BDO Prequal'!F43 -> 0 | R11: ='BDO Prequal'!G43 -> 0 | S11: ='BDO Prequal'!H43 -> 0 | T11: ='BDO Prequal'!I43 -> 0 | ... V11: ='BDO Prequal'!K43 -> 0
B12: {=_xlfn.LET(_xlpm.visRows,_xlfn._xlws.FILTER(ROW($M$6:$M$22),$N$6:$N$22<>0),_xlpm.allRows,_xlfn.VSTACK(_xlpm.visRows,23,24),_xlpm.pos,ROW()-5,IF(_xlpm.pos<=ROWS(_xlpm.allRows),INDEX($M:$M,INDEX(_xlpm.allRows,_xlpm.pos)),""))} -> Construction Contingency - 10% | C12: {=_xlfn.LET(_xlpm.visRows,_xlfn._xlws.FILTER(ROW($M$6:$M$22),$N$6:$N$22<>0),_xlpm.allRows,_xlfn.VSTACK(_xlpm.visRows,23,24),_xlpm.pos,ROW()-5,IF(_xlpm.pos>ROWS(_xlpm.allRows),"",_xlfn.LET(_xlpm.rn,INDEX(_xlpm.allRows,_xlpm.pos),_xlpm.val,INDEX($N:$N,_xlpm.rn),IF(INDEX($M:$M,_xlpm.rn)="Percentages",IF(_xlpm.val=0,"-",TEXT(_xlpm.val,"0%")),_xlpm.val))))} -> 222807 | D12: {=_xlfn.LET(_xlpm.visRows,_xlfn._xlws.FILTER(ROW($M$6:$M$22),$N$6:$N$22<>0),_xlpm.allRows,_xlfn.VSTACK(_xlpm.visRows,23,24),_xlpm.pos,ROW()-5,IF(_xlpm.pos>ROWS(_xlpm.allRows),"",_xlfn.LET(_xlpm.rn,INDEX(_xlpm.allRows,_xlpm.pos),_xlpm.val,INDEX($O:$O,_xlpm.rn),IF(INDEX($M:$M,_xlpm.rn)="Percentages",IF(_xlpm.val=0,"-",TEXT(_xlpm.val,"0%")),_xlpm.val))))} -> 0 | E12: {=_xlfn.LET(_xlpm.visRows,_xlfn._xlws.FILTER(ROW($M$6:$M$22),$N$6:$N$22<>0),_xlpm.allRows,_xlfn.VSTACK(_xlpm.visRows,23,24),_xlpm.pos,ROW()-5,IF(_xlpm.pos>ROWS(_xlpm.allRows),"",_xlfn.LET(_xlpm.rn,INDEX(_xlpm.allRows,_xlpm.pos),_xlpm.val,INDEX($P:$P,_xlpm.rn),IF(INDEX($M:$M,_xlpm.rn)="Percentages",IF(_xlpm.val=0,"-",TEXT(_xlpm.val,"0%")),_xlpm.val))))} -> 222807 | F12: {=_xlfn.LET(_xlpm.visRows,_xlfn._xlws.FILTER(ROW($M$6:$M$22),$N$6:$N$22<>0),_xlpm.allRows,_xlfn.VSTACK(_xlpm.visRows,23,24),_xlpm.pos,ROW()-5,IF(_xlpm.pos>ROWS(_xlpm.allRows),"",_xlfn.LET(_xlpm.rn,INDEX(_xlpm.allRows,_xlpm.pos),_xlpm.val,INDEX($Q:$Q,_xlpm.rn),IF(INDEX($M:$M,_xlpm.rn)="Percentages",IF(_xlpm.val=0,"-",TEXT(_xlpm.val,"0%")),_xlpm.val))))} -> 0 | G12: {=_xlfn.LET(_xlpm.visRows,_xlfn._xlws.FILTER(ROW($M$6:$M$22),$N$6:$N$22<>0),_xlpm.allRows,_xlfn.VSTACK(_xlpm.visRows,23,24),_xlpm.pos,ROW()-5,IF(_xlpm.pos>ROWS(_xlpm.allRows),"",_xlfn.LET(_xlpm.rn,INDEX(_xlpm.allRows,_xlpm.pos),_xlpm.val,INDEX($R:$R,_xlpm.rn),IF(INDEX($M:$M,_xlpm.rn)="Percentages",IF(_xlpm.val=0,"-",TEXT(_xlpm.val,"0%")),_xlpm.val))))} -> 0 | H12: {=_xlfn.LET(_xlpm.visRows,_xlfn._xlws.FILTER(ROW($M$6:$M$22),$N$6:$N$22<>0),_xlpm.allRows,_xlfn.VSTACK(_xlpm.visRows,23,24),_xlpm.pos,ROW()-5,IF(_xlpm.pos>ROWS(_xlpm.allRows),"",_xlfn.LET(_xlpm.rn,INDEX(_xlpm.allRows,_xlpm.pos),_xlpm.val,INDEX($S:$S,_xlpm.rn),IF(INDEX($M:$M,_xlpm.rn)="Percentages",IF(_xlpm.val=0,"-",TEXT(_xlpm.val,"0%")),_xlpm.val))))} -> 0 | I12: {=_xlfn.LET(_xlpm.visRows,_xlfn._xlws.FILTER(ROW($M$6:$M$22),$N$6:$N$22<>0),_xlpm.allRows,_xlfn.VSTACK(_xlpm.visRows,23,24),_xlpm.pos,ROW()-5,IF(_xlpm.pos>ROWS(_xlpm.allRows),"",_xlfn.LET(_xlpm.rn,INDEX(_xlpm.allRows,_xlpm.pos),_xlpm.val,INDEX($T:$T,_xlpm.rn),IF(INDEX($M:$M,_xlpm.rn)="Percentages",IF(_xlpm.val=0,"-",TEXT(_xlpm.val,"0%")),_xlpm.val))))} -> 0 | J12: {=_xlfn.LET(_xlpm.visRows,_xlfn._xlws.FILTER(ROW($M$6:$M$22),$N$6:$N$22<>0),_xlpm.allRows,_xlfn.VSTACK(_xlpm.visRows,23,24),_xlpm.pos,ROW()-5,IF(_xlpm.pos>ROWS(_xlpm.allRows),"",_xlfn.LET(_xlpm.rn,INDEX(_xlpm.allRows,_xlpm.pos),_xlpm.val,INDEX($U:$U,_xlpm.rn),IF(INDEX($M:$M,_xlpm.rn)="Percentages",IF(_xlpm.val=0,"-",TEXT(_xlpm.val,"0%")),_xlpm.val))))} -> 0 | K12: {=_xlfn.LET(_xlpm.visRows,_xlfn._xlws.FILTER(ROW($M$6:$M$22),$N$6:$N$22<>0),_xlpm.allRows,_xlfn.VSTACK(_xlpm.visRows,23,24),_xlpm.pos,ROW()-5,IF(_xlpm.pos>ROWS(_xlpm.allRows),"",_xlfn.LET(_xlpm.rn,INDEX(_xlpm.allRows,_xlpm.pos),_xlpm.val,INDEX($V:$V,_xlpm.rn),IF(INDEX($M:$M,_xlpm.rn)="Percentages",IF(_xlpm.val=0,"-",TEXT(_xlpm.val,"0%")),_xlpm.val))))} -> 0 | M12: ='BDO Prequal'!B44 -> Working Capital | N12: ='BDO Prequal'!C44 -> 573500 | O12: ='BDO Prequal'!D44 -> 573500 | P12: ='BDO Prequal'!E44 -> 0 | Q12: ='BDO Prequal'!F44 -> 0 | R12: ='BDO Prequal'!G44 -> 0 | S12: ='BDO Prequal'!H44 -> 0 | T12: ='BDO Prequal'!I44 -> 0 | ... V12: ='BDO Prequal'!K44 -> 0
B13: {=_xlfn.LET(_xlpm.visRows,_xlfn._xlws.FILTER(ROW($M$6:$M$22),$N$6:$N$22<>0),_xlpm.allRows,_xlfn.VSTACK(_xlpm.visRows,23,24),_xlpm.pos,ROW()-5,IF(_xlpm.pos<=ROWS(_xlpm.allRows),INDEX($M:$M,INDEX(_xlpm.allRows,_xlpm.pos)),""))} -> Construction Soft Costs | C13: {=_xlfn.LET(_xlpm.visRows,_xlfn._xlws.FILTER(ROW($M$6:$M$22),$N$6:$N$22<>0),_xlpm.allRows,_xlfn.VSTACK(_xlpm.visRows,23,24),_xlpm.pos,ROW()-5,IF(_xlpm.pos>ROWS(_xlpm.allRows),"",_xlfn.LET(_xlpm.rn,INDEX(_xlpm.allRows,_xlpm.pos),_xlpm.val,INDEX($N:$N,_xlpm.rn),IF(INDEX($M:$M,_xlpm.rn)="Percentages",IF(_xlpm.val=0,"-",TEXT(_xlpm.val,"0%")),_xlpm.val))))} -> 173800 | D13: {=_xlfn.LET(_xlpm.visRows,_xlfn._xlws.FILTER(ROW($M$6:$M$22),$N$6:$N$22<>0),_xlpm.allRows,_xlfn.VSTACK(_xlpm.visRows,23,24),_xlpm.pos,ROW()-5,IF(_xlpm.pos>ROWS(_xlpm.allRows),"",_xlfn.LET(_xlpm.rn,INDEX(_xlpm.allRows,_xlpm.pos),_xlpm.val,INDEX($O:$O,_xlpm.rn),IF(INDEX($M:$M,_xlpm.rn)="Percentages",IF(_xlpm.val=0,"-",TEXT(_xlpm.val,"0%")),_xlpm.val))))} -> 53800 | E13: {=_xlfn.LET(_xlpm.visRows,_xlfn._xlws.FILTER(ROW($M$6:$M$22),$N$6:$N$22<>0),_xlpm.allRows,_xlfn.VSTACK(_xlpm.visRows,23,24),_xlpm.pos,ROW()-5,IF(_xlpm.pos>ROWS(_xlpm.allRows),"",_xlfn.LET(_xlpm.rn,INDEX(_xlpm.allRows,_xlpm.pos),_xlpm.val,INDEX($P:$P,_xlpm.rn),IF(INDEX($M:$M,_xlpm.rn)="Percentages",IF(_xlpm.val=0,"-",TEXT(_xlpm.val,"0%")),_xlpm.val))))} -> 0 | F13: {=_xlfn.LET(_xlpm.visRows,_xlfn._xlws.FILTER(ROW($M$6:$M$22),$N$6:$N$22<>0),_xlpm.allRows,_xlfn.VSTACK(_xlpm.visRows,23,24),_xlpm.pos,ROW()-5,IF(_xlpm.pos>ROWS(_xlpm.allRows),"",_xlfn.LET(_xlpm.rn,INDEX(_xlpm.allRows,_xlpm.pos),_xlpm.val,INDEX($Q:$Q,_xlpm.rn),IF(INDEX($M:$M,_xlpm.rn)="Percentages",IF(_xlpm.val=0,"-",TEXT(_xlpm.val,"0%")),_xlpm.val))))} -> 120000 | G13: {=_xlfn.LET(_xlpm.visRows,_xlfn._xlws.FILTER(ROW($M$6:$M$22),$N$6:$N$22<>0),_xlpm.allRows,_xlfn.VSTACK(_xlpm.visRows,23,24),_xlpm.pos,ROW()-5,IF(_xlpm.pos>ROWS(_xlpm.allRows),"",_xlfn.LET(_xlpm.rn,INDEX(_xlpm.allRows,_xlpm.pos),_xlpm.val,INDEX($R:$R,_xlpm.rn),IF(INDEX($M:$M,_xlpm.rn)="Percentages",IF(_xlpm.val=0,"-",TEXT(_xlpm.val,"0%")),_xlpm.val))))} -> 0 | H13: {=_xlfn.LET(_xlpm.visRows,_xlfn._xlws.FILTER(ROW($M$6:$M$22),$N$6:$N$22<>0),_xlpm.allRows,_xlfn.VSTACK(_xlpm.visRows,23,24),_xlpm.pos,ROW()-5,IF(_xlpm.pos>ROWS(_xlpm.allRows),"",_xlfn.LET(_xlpm.rn,INDEX(_xlpm.allRows,_xlpm.pos),_xlpm.val,INDEX($S:$S,_xlpm.rn),IF(INDEX($M:$M,_xlpm.rn)="Percentages",IF(_xlpm.val=0,"-",TEXT(_xlpm.val,"0%")),_xlpm.val))))} -> 0 | I13: {=_xlfn.LET(_xlpm.visRows,_xlfn._xlws.FILTER(ROW($M$6:$M$22),$N$6:$N$22<>0),_xlpm.allRows,_xlfn.VSTACK(_xlpm.visRows,23,24),_xlpm.pos,ROW()-5,IF(_xlpm.pos>ROWS(_xlpm.allRows),"",_xlfn.LET(_xlpm.rn,INDEX(_xlpm.allRows,_xlpm.pos),_xlpm.val,INDEX($T:$T,_xlpm.rn),IF(INDEX($M:$M,_xlpm.rn)="Percentages",IF(_xlpm.val=0,"-",TEXT(_xlpm.val,"0%")),_xlpm.val))))} -> 0 | J13: {=_xlfn.LET(_xlpm.visRows,_xlfn._xlws.FILTER(ROW($M$6:$M$22),$N$6:$N$22<>0),_xlpm.allRows,_xlfn.VSTACK(_xlpm.visRows,23,24),_xlpm.pos,ROW()-5,IF(_xlpm.pos>ROWS(_xlpm.allRows),"",_xlfn.LET(_xlpm.rn,INDEX(_xlpm.allRows,_xlpm.pos),_xlpm.val,INDEX($U:$U,_xlpm.rn),IF(INDEX($M:$M,_xlpm.rn)="Percentages",IF(_xlpm.val=0,"-",TEXT(_xlpm.val,"0%")),_xlpm.val))))} -> 0 | K13: {=_xlfn.LET(_xlpm.visRows,_xlfn._xlws.FILTER(ROW($M$6:$M$22),$N$6:$N$22<>0),_xlpm.allRows,_xlfn.VSTACK(_xlpm.visRows,23,24),_xlpm.pos,ROW()-5,IF(_xlpm.pos>ROWS(_xlpm.allRows),"",_xlfn.LET(_xlpm.rn,INDEX(_xlpm.allRows,_xlpm.pos),_xlpm.val,INDEX($V:$V,_xlpm.rn),IF(INDEX($M:$M,_xlpm.rn)="Percentages",IF(_xlpm.val=0,"-",TEXT(_xlpm.val,"0%")),_xlpm.val))))} -> 0 | M13: ='BDO Prequal'!B45 -> Working Capital - Pre Opening | N13: ='BDO Prequal'!C45 -> 77000 | O13: ='BDO Prequal'!D45 -> 77000 | P13: ='BDO Prequal'!E45 -> 0 | Q13: ='BDO Prequal'!F45 -> 0 | R13: ='BDO Prequal'!G45 -> 0 | S13: ='BDO Prequal'!H45 -> 0 | T13: ='BDO Prequal'!I45 -> 0 | ... V13: ='BDO Prequal'!K45 -> 0
B14: {=_xlfn.LET(_xlpm.visRows,_xlfn._xlws.FILTER(ROW($M$6:$M$22),$N$6:$N$22<>0),_xlpm.allRows,_xlfn.VSTACK(_xlpm.visRows,23,24),_xlpm.pos,ROW()-5,IF(_xlpm.pos<=ROWS(_xlpm.allRows),INDEX($M:$M,INDEX(_xlpm.allRows,_xlpm.pos)),""))} -> Closing Costs | C14: {=_xlfn.LET(_xlpm.visRows,_xlfn._xlws.FILTER(ROW($M$6:$M$22),$N$6:$N$22<>0),_xlpm.allRows,_xlfn.VSTACK(_xlpm.visRows,23,24),_xlpm.pos,ROW()-5,IF(_xlpm.pos>ROWS(_xlpm.allRows),"",_xlfn.LET(_xlpm.rn,INDEX(_xlpm.allRows,_xlpm.pos),_xlpm.val,INDEX($N:$N,_xlpm.rn),IF(INDEX($M:$M,_xlpm.rn)="Percentages",IF(_xlpm.val=0,"-",TEXT(_xlpm.val,"0%")),_xlpm.val))))} -> 52000 | D14: {=_xlfn.LET(_xlpm.visRows,_xlfn._xlws.FILTER(ROW($M$6:$M$22),$N$6:$N$22<>0),_xlpm.allRows,_xlfn.VSTACK(_xlpm.visRows,23,24),_xlpm.pos,ROW()-5,IF(_xlpm.pos>ROWS(_xlpm.allRows),"",_xlfn.LET(_xlpm.rn,INDEX(_xlpm.allRows,_xlpm.pos),_xlpm.val,INDEX($O:$O,_xlpm.rn),IF(INDEX($M:$M,_xlpm.rn)="Percentages",IF(_xlpm.val=0,"-",TEXT(_xlpm.val,"0%")),_xlpm.val))))} -> 0 | E14: {=_xlfn.LET(_xlpm.visRows,_xlfn._xlws.FILTER(ROW($M$6:$M$22),$N$6:$N$22<>0),_xlpm.allRows,_xlfn.VSTACK(_xlpm.visRows,23,24),_xlpm.pos,ROW()-5,IF(_xlpm.pos>ROWS(_xlpm.allRows),"",_xlfn.LET(_xlpm.rn,INDEX(_xlpm.allRows,_xlpm.pos),_xlpm.val,INDEX($P:$P,_xlpm.rn),IF(INDEX($M:$M,_xlpm.rn)="Percentages",IF(_xlpm.val=0,"-",TEXT(_xlpm.val,"0%")),_xlpm.val))))} -> 52000 | F14: {=_xlfn.LET(_xlpm.visRows,_xlfn._xlws.FILTER(ROW($M$6:$M$22),$N$6:$N$22<>0),_xlpm.allRows,_xlfn.VSTACK(_xlpm.visRows,23,24),_xlpm.pos,ROW()-5,IF(_xlpm.pos>ROWS(_xlpm.allRows),"",_xlfn.LET(_xlpm.rn,INDEX(_xlpm.allRows,_xlpm.pos),_xlpm.val,INDEX($Q:$Q,_xlpm.rn),IF(INDEX($M:$M,_xlpm.rn)="Percentages",IF(_xlpm.val=0,"-",TEXT(_xlpm.val,"0%")),_xlpm.val))))} -> 0 | G14: {=_xlfn.LET(_xlpm.visRows,_xlfn._xlws.FILTER(ROW($M$6:$M$22),$N$6:$N$22<>0),_xlpm.allRows,_xlfn.VSTACK(_xlpm.visRows,23,24),_xlpm.pos,ROW()-5,IF(_xlpm.pos>ROWS(_xlpm.allRows),"",_xlfn.LET(_xlpm.rn,INDEX(_xlpm.allRows,_xlpm.pos),_xlpm.val,INDEX($R:$R,_xlpm.rn),IF(INDEX($M:$M,_xlpm.rn)="Percentages",IF(_xlpm.val=0,"-",TEXT(_xlpm.val,"0%")),_xlpm.val))))} -> 0 | H14: {=_xlfn.LET(_xlpm.visRows,_xlfn._xlws.FILTER(ROW($M$6:$M$22),$N$6:$N$22<>0),_xlpm.allRows,_xlfn.VSTACK(_xlpm.visRows,23,24),_xlpm.pos,ROW()-5,IF(_xlpm.pos>ROWS(_xlpm.allRows),"",_xlfn.LET(_xlpm.rn,INDEX(_xlpm.allRows,_xlpm.pos),_xlpm.val,INDEX($S:$S,_xlpm.rn),IF(INDEX($M:$M,_xlpm.rn)="Percentages",IF(_xlpm.val=0,"-",TEXT(_xlpm.val,"0%")),_xlpm.val))))} -> 0 | I14: {=_xlfn.LET(_xlpm.visRows,_xlfn._xlws.FILTER(ROW($M$6:$M$22),$N$6:$N$22<>0),_xlpm.allRows,_xlfn.VSTACK(_xlpm.visRows,23,24),_xlpm.pos,ROW()-5,IF(_xlpm.pos>ROWS(_xlpm.allRows),"",_xlfn.LET(_xlpm.rn,INDEX(_xlpm.allRows,_xlpm.pos),_xlpm.val,INDEX($T:$T,_xlpm.rn),IF(INDEX($M:$M,_xlpm.rn)="Percentages",IF(_xlpm.val=0,"-",TEXT(_xlpm.val,"0%")),_xlpm.val))))} -> 0 | J14: {=_xlfn.LET(_xlpm.visRows,_xlfn._xlws.FILTER(ROW($M$6:$M$22),$N$6:$N$22<>0),_xlpm.allRows,_xlfn.VSTACK(_xlpm.visRows,23,24),_xlpm.pos,ROW()-5,IF(_xlpm.pos>ROWS(_xlpm.allRows),"",_xlfn.LET(_xlpm.rn,INDEX(_xlpm.allRows,_xlpm.pos),_xlpm.val,INDEX($U:$U,_xlpm.rn),IF(INDEX($M:$M,_xlpm.rn)="Percentages",IF(_xlpm.val=0,"-",TEXT(_xlpm.val,"0%")),_xlpm.val))))} -> 0 | K14: {=_xlfn.LET(_xlpm.visRows,_xlfn._xlws.FILTER(ROW($M$6:$M$22),$N$6:$N$22<>0),_xlpm.allRows,_xlfn.VSTACK(_xlpm.visRows,23,24),_xlpm.pos,ROW()-5,IF(_xlpm.pos>ROWS(_xlpm.allRows),"",_xlfn.LET(_xlpm.rn,INDEX(_xlpm.allRows,_xlpm.pos),_xlpm.val,INDEX($V:$V,_xlpm.rn),IF(INDEX($M:$M,_xlpm.rn)="Percentages",IF(_xlpm.val=0,"-",TEXT(_xlpm.val,"0%")),_xlpm.val))))} -> 0 | M14: ='BDO Prequal'!B46 -> Business Acquisition | N14: ='BDO Prequal'!C46 -> 2219000 | O14: ='BDO Prequal'!D46 -> 225000 | P14: ='BDO Prequal'!E46 -> 324000 | Q14: ='BDO Prequal'!F46 -> 0 | R14: ='BDO Prequal'!G46 -> 1350000 | S14: ='BDO Prequal'!H46 -> 320000 | T14: ='BDO Prequal'!I46 -> 0 | ... V14: ='BDO Prequal'!K46 -> 0
B15: {=_xlfn.LET(_xlpm.visRows,_xlfn._xlws.FILTER(ROW($M$6:$M$22),$N$6:$N$22<>0),_xlpm.allRows,_xlfn.VSTACK(_xlpm.visRows,23,24),_xlpm.pos,ROW()-5,IF(_xlpm.pos<=ROWS(_xlpm.allRows),INDEX($M:$M,INDEX(_xlpm.allRows,_xlpm.pos)),""))} -> SBA Gty Fee | C15: {=_xlfn.LET(_xlpm.visRows,_xlfn._xlws.FILTER(ROW($M$6:$M$22),$N$6:$N$22<>0),_xlpm.allRows,_xlfn.VSTACK(_xlpm.visRows,23,24),_xlpm.pos,ROW()-5,IF(_xlpm.pos>ROWS(_xlpm.allRows),"",_xlfn.LET(_xlpm.rn,INDEX(_xlpm.allRows,_xlpm.pos),_xlpm.val,INDEX($N:$N,_xlpm.rn),IF(INDEX($M:$M,_xlpm.rn)="Percentages",IF(_xlpm.val=0,"-",TEXT(_xlpm.val,"0%")),_xlpm.val))))} -> 88533 | D15: {=_xlfn.LET(_xlpm.visRows,_xlfn._xlws.FILTER(ROW($M$6:$M$22),$N$6:$N$22<>0),_xlpm.allRows,_xlfn.VSTACK(_xlpm.visRows,23,24),_xlpm.pos,ROW()-5,IF(_xlpm.pos>ROWS(_xlpm.allRows),"",_xlfn.LET(_xlpm.rn,INDEX(_xlpm.allRows,_xlpm.pos),_xlpm.val,INDEX($O:$O,_xlpm.rn),IF(INDEX($M:$M,_xlpm.rn)="Percentages",IF(_xlpm.val=0,"-",TEXT(_xlpm.val,"0%")),_xlpm.val))))} -> 0 | E15: {=_xlfn.LET(_xlpm.visRows,_xlfn._xlws.FILTER(ROW($M$6:$M$22),$N$6:$N$22<>0),_xlpm.allRows,_xlfn.VSTACK(_xlpm.visRows,23,24),_xlpm.pos,ROW()-5,IF(_xlpm.pos>ROWS(_xlpm.allRows),"",_xlfn.LET(_xlpm.rn,INDEX(_xlpm.allRows,_xlpm.pos),_xlpm.val,INDEX($P:$P,_xlpm.rn),IF(INDEX($M:$M,_xlpm.rn)="Percentages",IF(_xlpm.val=0,"-",TEXT(_xlpm.val,"0%")),_xlpm.val))))} -> 13784 | F15: {=_xlfn.LET(_xlpm.visRows,_xlfn._xlws.FILTER(ROW($M$6:$M$22),$N$6:$N$22<>0),_xlpm.allRows,_xlfn.VSTACK(_xlpm.visRows,23,24),_xlpm.pos,ROW()-5,IF(_xlpm.pos>ROWS(_xlpm.allRows),"",_xlfn.LET(_xlpm.rn,INDEX(_xlpm.allRows,_xlpm.pos),_xlpm.val,INDEX($Q:$Q,_xlpm.rn),IF(INDEX($M:$M,_xlpm.rn)="Percentages",IF(_xlpm.val=0,"-",TEXT(_xlpm.val,"0%")),_xlpm.val))))} -> 74749 | G15: {=_xlfn.LET(_xlpm.visRows,_xlfn._xlws.FILTER(ROW($M$6:$M$22),$N$6:$N$22<>0),_xlpm.allRows,_xlfn.VSTACK(_xlpm.visRows,23,24),_xlpm.pos,ROW()-5,IF(_xlpm.pos>ROWS(_xlpm.allRows),"",_xlfn.LET(_xlpm.rn,INDEX(_xlpm.allRows,_xlpm.pos),_xlpm.val,INDEX($R:$R,_xlpm.rn),IF(INDEX($M:$M,_xlpm.rn)="Percentages",IF(_xlpm.val=0,"-",TEXT(_xlpm.val,"0%")),_xlpm.val))))} -> 0 | H15: {=_xlfn.LET(_xlpm.visRows,_xlfn._xlws.FILTER(ROW($M$6:$M$22),$N$6:$N$22<>0),_xlpm.allRows,_xlfn.VSTACK(_xlpm.visRows,23,24),_xlpm.pos,ROW()-5,IF(_xlpm.pos>ROWS(_xlpm.allRows),"",_xlfn.LET(_xlpm.rn,INDEX(_xlpm.allRows,_xlpm.pos),_xlpm.val,INDEX($S:$S,_xlpm.rn),IF(INDEX($M:$M,_xlpm.rn)="Percentages",IF(_xlpm.val=0,"-",TEXT(_xlpm.val,"0%")),_xlpm.val))))} -> 0 | I15: {=_xlfn.LET(_xlpm.visRows,_xlfn._xlws.FILTER(ROW($M$6:$M$22),$N$6:$N$22<>0),_xlpm.allRows,_xlfn.VSTACK(_xlpm.visRows,23,24),_xlpm.pos,ROW()-5,IF(_xlpm.pos>ROWS(_xlpm.allRows),"",_xlfn.LET(_xlpm.rn,INDEX(_xlpm.allRows,_xlpm.pos),_xlpm.val,INDEX($T:$T,_xlpm.rn),IF(INDEX($M:$M,_xlpm.rn)="Percentages",IF(_xlpm.val=0,"-",TEXT(_xlpm.val,"0%")),_xlpm.val))))} -> 0 | J15: {=_xlfn.LET(_xlpm.visRows,_xlfn._xlws.FILTER(ROW($M$6:$M$22),$N$6:$N$22<>0),_xlpm.allRows,_xlfn.VSTACK(_xlpm.visRows,23,24),_xlpm.pos,ROW()-5,IF(_xlpm.pos>ROWS(_xlpm.allRows),"",_xlfn.LET(_xlpm.rn,INDEX(_xlpm.allRows,_xlpm.pos),_xlpm.val,INDEX($U:$U,_xlpm.rn),IF(INDEX($M:$M,_xlpm.rn)="Percentages",IF(_xlpm.val=0,"-",TEXT(_xlpm.val,"0%")),_xlpm.val))))} -> 0 | K15: {=_xlfn.LET(_xlpm.visRows,_xlfn._xlws.FILTER(ROW($M$6:$M$22),$N$6:$N$22<>0),_xlpm.allRows,_xlfn.VSTACK(_xlpm.visRows,23,24),_xlpm.pos,ROW()-5,IF(_xlpm.pos>ROWS(_xlpm.allRows),"",_xlfn.LET(_xlpm.rn,INDEX(_xlpm.allRows,_xlpm.pos),_xlpm.val,INDEX($V:$V,_xlpm.rn),IF(INDEX($M:$M,_xlpm.rn)="Percentages",IF(_xlpm.val=0,"-",TEXT(_xlpm.val,"0%")),_xlpm.val))))} -> 0 | M15: ='BDO Prequal'!B47 -> Franchise Fees | N15: ='BDO Prequal'!C47 -> 0 | O15: ='BDO Prequal'!D47 -> 0 | P15: ='BDO Prequal'!E47 -> 0 | Q15: ='BDO Prequal'!F47 -> 0 | R15: ='BDO Prequal'!G47 -> 0 | S15: ='BDO Prequal'!H47 -> 0 | T15: ='BDO Prequal'!I47 -> 0 | ... V15: ='BDO Prequal'!K47 -> 0
B16: {=_xlfn.LET(_xlpm.visRows,_xlfn._xlws.FILTER(ROW($M$6:$M$22),$N$6:$N$22<>0),_xlpm.allRows,_xlfn.VSTACK(_xlpm.visRows,23,24),_xlpm.pos,ROW()-5,IF(_xlpm.pos<=ROWS(_xlpm.allRows),INDEX($M:$M,INDEX(_xlpm.allRows,_xlpm.pos)),""))} -> Project Total | C16: {=_xlfn.LET(_xlpm.visRows,_xlfn._xlws.FILTER(ROW($M$6:$M$22),$N$6:$N$22<>0),_xlpm.allRows,_xlfn.VSTACK(_xlpm.visRows,23,24),_xlpm.pos,ROW()-5,IF(_xlpm.pos>ROWS(_xlpm.allRows),"",_xlfn.LET(_xlpm.rn,INDEX(_xlpm.allRows,_xlpm.pos),_xlpm.val,INDEX($N:$N,_xlpm.rn),IF(INDEX($M:$M,_xlpm.rn)="Percentages",IF(_xlpm.val=0,"-",TEXT(_xlpm.val,"0%")),_xlpm.val))))} -> 8472925 | D16: {=_xlfn.LET(_xlpm.visRows,_xlfn._xlws.FILTER(ROW($M$6:$M$22),$N$6:$N$22<>0),_xlpm.allRows,_xlfn.VSTACK(_xlpm.visRows,23,24),_xlpm.pos,ROW()-5,IF(_xlpm.pos>ROWS(_xlpm.allRows),"",_xlfn.LET(_xlpm.rn,INDEX(_xlpm.allRows,_xlpm.pos),_xlpm.val,INDEX($O:$O,_xlpm.rn),IF(INDEX($M:$M,_xlpm.rn)="Percentages",IF(_xlpm.val=0,"-",TEXT(_xlpm.val,"0%")),_xlpm.val))))} -> 1571792 | E16: {=_xlfn.LET(_xlpm.visRows,_xlfn._xlws.FILTER(ROW($M$6:$M$22),$N$6:$N$22<>0),_xlpm.allRows,_xlfn.VSTACK(_xlpm.visRows,23,24),_xlpm.pos,ROW()-5,IF(_xlpm.pos>ROWS(_xlpm.allRows),"",_xlfn.LET(_xlpm.rn,INDEX(_xlpm.allRows,_xlpm.pos),_xlpm.val,INDEX($P:$P,_xlpm.rn),IF(INDEX($M:$M,_xlpm.rn)="Percentages",IF(_xlpm.val=0,"-",TEXT(_xlpm.val,"0%")),_xlpm.val))))} -> 612591 | F16: {=_xlfn.LET(_xlpm.visRows,_xlfn._xlws.FILTER(ROW($M$6:$M$22),$N$6:$N$22<>0),_xlpm.allRows,_xlfn.VSTACK(_xlpm.visRows,23,24),_xlpm.pos,ROW()-5,IF(_xlpm.pos>ROWS(_xlpm.allRows),"",_xlfn.LET(_xlpm.rn,INDEX(_xlpm.allRows,_xlpm.pos),_xlpm.val,INDEX($Q:$Q,_xlpm.rn),IF(INDEX($M:$M,_xlpm.rn)="Percentages",IF(_xlpm.val=0,"-",TEXT(_xlpm.val,"0%")),_xlpm.val))))} -> 2746607 | G16: {=_xlfn.LET(_xlpm.visRows,_xlfn._xlws.FILTER(ROW($M$6:$M$22),$N$6:$N$22<>0),_xlpm.allRows,_xlfn.VSTACK(_xlpm.visRows,23,24),_xlpm.pos,ROW()-5,IF(_xlpm.pos>ROWS(_xlpm.allRows),"",_xlfn.LET(_xlpm.rn,INDEX(_xlpm.allRows,_xlpm.pos),_xlpm.val,INDEX($R:$R,_xlpm.rn),IF(INDEX($M:$M,_xlpm.rn)="Percentages",IF(_xlpm.val=0,"-",TEXT(_xlpm.val,"0%")),_xlpm.val))))} -> 1350000 | H16: {=_xlfn.LET(_xlpm.visRows,_xlfn._xlws.FILTER(ROW($M$6:$M$22),$N$6:$N$22<>0),_xlpm.allRows,_xlfn.VSTACK(_xlpm.visRows,23,24),_xlpm.pos,ROW()-5,IF(_xlpm.pos>ROWS(_xlpm.allRows),"",_xlfn.LET(_xlpm.rn,INDEX(_xlpm.allRows,_xlpm.pos),_xlpm.val,INDEX($S:$S,_xlpm.rn),IF(INDEX($M:$M,_xlpm.rn)="Percentages",IF(_xlpm.val=0,"-",TEXT(_xlpm.val,"0%")),_xlpm.val))))} -> 320000 | I16: {=_xlfn.LET(_xlpm.visRows,_xlfn._xlws.FILTER(ROW($M$6:$M$22),$N$6:$N$22<>0),_xlpm.allRows,_xlfn.VSTACK(_xlpm.visRows,23,24),_xlpm.pos,ROW()-5,IF(_xlpm.pos>ROWS(_xlpm.allRows),"",_xlfn.LET(_xlpm.rn,INDEX(_xlpm.allRows,_xlpm.pos),_xlpm.val,INDEX($T:$T,_xlpm.rn),IF(INDEX($M:$M,_xlpm.rn)="Percentages",IF(_xlpm.val=0,"-",TEXT(_xlpm.val,"0%")),_xlpm.val))))} -> 1871935 | J16: {=_xlfn.LET(_xlpm.visRows,_xlfn._xlws.FILTER(ROW($M$6:$M$22),$N$6:$N$22<>0),_xlpm.allRows,_xlfn.VSTACK(_xlpm.visRows,23,24),_xlpm.pos,ROW()-5,IF(_xlpm.pos>ROWS(_xlpm.allRows),"",_xlfn.LET(_xlpm.rn,INDEX(_xlpm.allRows,_xlpm.pos),_xlpm.val,INDEX($U:$U,_xlpm.rn),IF(INDEX($M:$M,_xlpm.rn)="Percentages",IF(_xlpm.val=0,"-",TEXT(_xlpm.val,"0%")),_xlpm.val))))} -> 0 | K16: {=_xlfn.LET(_xlpm.visRows,_xlfn._xlws.FILTER(ROW($M$6:$M$22),$N$6:$N$22<>0),_xlpm.allRows,_xlfn.VSTACK(_xlpm.visRows,23,24),_xlpm.pos,ROW()-5,IF(_xlpm.pos>ROWS(_xlpm.allRows),"",_xlfn.LET(_xlpm.rn,INDEX(_xlpm.allRows,_xlpm.pos),_xlpm.val,INDEX($V:$V,_xlpm.rn),IF(INDEX($M:$M,_xlpm.rn)="Percentages",IF(_xlpm.val=0,"-",TEXT(_xlpm.val,"0%")),_xlpm.val))))} -> 0 | M16: ='BDO Prequal'!B48 -> Construction Hard Costs | N16: ='BDO Prequal'!C48 -> 4100000 | O16: ='BDO Prequal'!D48 -> 276207 | P16: ='BDO Prequal'!E48 -> 0 | Q16: ='BDO Prequal'!F48 -> 1951858 | R16: ='BDO Prequal'!G48 -> 0 | S16: ='BDO Prequal'!H48 -> 0 | T16: ='BDO Prequal'!I48 -> 1871935 | ... V16: ='BDO Prequal'!K48 -> 0
B17: {=_xlfn.LET(_xlpm.visRows,_xlfn._xlws.FILTER(ROW($M$6:$M$22),$N$6:$N$22<>0),_xlpm.allRows,_xlfn.VSTACK(_xlpm.visRows,23,24),_xlpm.pos,ROW()-5,IF(_xlpm.pos<=ROWS(_xlpm.allRows),INDEX($M:$M,INDEX(_xlpm.allRows,_xlpm.pos)),""))} -> Percentages | C17: {=_xlfn.LET(_xlpm.visRows,_xlfn._xlws.FILTER(ROW($M$6:$M$22),$N$6:$N$22<>0),_xlpm.allRows,_xlfn.VSTACK(_xlpm.visRows,23,24),_xlpm.pos,ROW()-5,IF(_xlpm.pos>ROWS(_xlpm.allRows),"",_xlfn.LET(_xlpm.rn,INDEX(_xlpm.allRows,_xlpm.pos),_xlpm.val,INDEX($N:$N,_xlpm.rn),IF(INDEX($M:$M,_xlpm.rn)="Percentages",IF(_xlpm.val=0,"-",TEXT(_xlpm.val,"0%")),_xlpm.val))))} -> 100% | D17: {=_xlfn.LET(_xlpm.visRows,_xlfn._xlws.FILTER(ROW($M$6:$M$22),$N$6:$N$22<>0),_xlpm.allRows,_xlfn.VSTACK(_xlpm.visRows,23,24),_xlpm.pos,ROW()-5,IF(_xlpm.pos>ROWS(_xlpm.allRows),"",_xlfn.LET(_xlpm.rn,INDEX(_xlpm.allRows,_xlpm.pos),_xlpm.val,INDEX($O:$O,_xlpm.rn),IF(INDEX($M:$M,_xlpm.rn)="Percentages",IF(_xlpm.val=0,"-",TEXT(_xlpm.val,"0%")),_xlpm.val))))} -> 19% | E17: {=_xlfn.LET(_xlpm.visRows,_xlfn._xlws.FILTER(ROW($M$6:$M$22),$N$6:$N$22<>0),_xlpm.allRows,_xlfn.VSTACK(_xlpm.visRows,23,24),_xlpm.pos,ROW()-5,IF(_xlpm.pos>ROWS(_xlpm.allRows),"",_xlfn.LET(_xlpm.rn,INDEX(_xlpm.allRows,_xlpm.pos),_xlpm.val,INDEX($P:$P,_xlpm.rn),IF(INDEX($M:$M,_xlpm.rn)="Percentages",IF(_xlpm.val=0,"-",TEXT(_xlpm.val,"0%")),_xlpm.val))))} -> 7% | F17: {=_xlfn.LET(_xlpm.visRows,_xlfn._xlws.FILTER(ROW($M$6:$M$22),$N$6:$N$22<>0),_xlpm.allRows,_xlfn.VSTACK(_xlpm.visRows,23,24),_xlpm.pos,ROW()-5,IF(_xlpm.pos>ROWS(_xlpm.allRows),"",_xlfn.LET(_xlpm.rn,INDEX(_xlpm.allRows,_xlpm.pos),_xlpm.val,INDEX($Q:$Q,_xlpm.rn),IF(INDEX($M:$M,_xlpm.rn)="Percentages",IF(_xlpm.val=0,"-",TEXT(_xlpm.val,"0%")),_xlpm.val))))} -> 32% | G17: {=_xlfn.LET(_xlpm.visRows,_xlfn._xlws.FILTER(ROW($M$6:$M$22),$N$6:$N$22<>0),_xlpm.allRows,_xlfn.VSTACK(_xlpm.visRows,23,24),_xlpm.pos,ROW()-5,IF(_xlpm.pos>ROWS(_xlpm.allRows),"",_xlfn.LET(_xlpm.rn,INDEX(_xlpm.allRows,_xlpm.pos),_xlpm.val,INDEX($R:$R,_xlpm.rn),IF(INDEX($M:$M,_xlpm.rn)="Percentages",IF(_xlpm.val=0,"-",TEXT(_xlpm.val,"0%")),_xlpm.val))))} -> 16% | H17: {=_xlfn.LET(_xlpm.visRows,_xlfn._xlws.FILTER(ROW($M$6:$M$22),$N$6:$N$22<>0),_xlpm.allRows,_xlfn.VSTACK(_xlpm.visRows,23,24),_xlpm.pos,ROW()-5,IF(_xlpm.pos>ROWS(_xlpm.allRows),"",_xlfn.LET(_xlpm.rn,INDEX(_xlpm.allRows,_xlpm.pos),_xlpm.val,INDEX($S:$S,_xlpm.rn),IF(INDEX($M:$M,_xlpm.rn)="Percentages",IF(_xlpm.val=0,"-",TEXT(_xlpm.val,"0%")),_xlpm.val))))} -> 4% | I17: {=_xlfn.LET(_xlpm.visRows,_xlfn._xlws.FILTER(ROW($M$6:$M$22),$N$6:$N$22<>0),_xlpm.allRows,_xlfn.VSTACK(_xlpm.visRows,23,24),_xlpm.pos,ROW()-5,IF(_xlpm.pos>ROWS(_xlpm.allRows),"",_xlfn.LET(_xlpm.rn,INDEX(_xlpm.allRows,_xlpm.pos),_xlpm.val,INDEX($T:$T,_xlpm.rn),IF(INDEX($M:$M,_xlpm.rn)="Percentages",IF(_xlpm.val=0,"-",TEXT(_xlpm.val,"0%")),_xlpm.val))))} -> 22% | J17: {=_xlfn.LET(_xlpm.visRows,_xlfn._xlws.FILTER(ROW($M$6:$M$22),$N$6:$N$22<>0),_xlpm.allRows,_xlfn.VSTACK(_xlpm.visRows,23,24),_xlpm.pos,ROW()-5,IF(_xlpm.pos>ROWS(_xlpm.allRows),"",_xlfn.LET(_xlpm.rn,INDEX(_xlpm.allRows,_xlpm.pos),_xlpm.val,INDEX($U:$U,_xlpm.rn),IF(INDEX($M:$M,_xlpm.rn)="Percentages",IF(_xlpm.val=0,"-",TEXT(_xlpm.val,"0%")),_xlpm.val))))} -> - | K17: {=_xlfn.LET(_xlpm.visRows,_xlfn._xlws.FILTER(ROW($M$6:$M$22),$N$6:$N$22<>0),_xlpm.allRows,_xlfn.VSTACK(_xlpm.visRows,23,24),_xlpm.pos,ROW()-5,IF(_xlpm.pos>ROWS(_xlpm.allRows),"",_xlfn.LET(_xlpm.rn,INDEX(_xlpm.allRows,_xlpm.pos),_xlpm.val,INDEX($V:$V,_xlpm.rn),IF(INDEX($M:$M,_xlpm.rn)="Percentages",IF(_xlpm.val=0,"-",TEXT(_xlpm.val,"0%")),_xlpm.val))))} -> - | M17: ='BDO Prequal'!B49 -> Construction Contingency - 10% | N17: ='BDO Prequal'!C49 -> 222807 | O17: ='BDO Prequal'!D49 -> 0 | P17: ='BDO Prequal'!E49 -> 222807 | Q17: ='BDO Prequal'!F49 -> 0 | R17: ='BDO Prequal'!G49 -> 0 | S17: ='BDO Prequal'!H49 -> 0 | T17: ='BDO Prequal'!I49 -> 0 | ... V17: ='BDO Prequal'!K49 -> 0
... B22: {=_xlfn.LET(_xlpm.visRows,_xlfn._xlws.FILTER(ROW($M$6:$M$22),$N$6:$N$22<>0),_xlpm.allRows,_xlfn.VSTACK(_xlpm.visRows,23,24),_xlpm.pos,ROW()-5,IF(_xlpm.pos<=ROWS(_xlpm.allRows),INDEX($M:$M,INDEX(_xlpm.allRows,_xlpm.pos)),""))} | C22: {=_xlfn.LET(_xlpm.visRows,_xlfn._xlws.FILTER(ROW($M$6:$M$22),$N$6:$N$22<>0),_xlpm.allRows,_xlfn.VSTACK(_xlpm.visRows,23,24),_xlpm.pos,ROW()-5,IF(_xlpm.pos>ROWS(_xlpm.allRows),"",_xlfn.LET(_xlpm.rn,INDEX(_xlpm.allRows,_xlpm.pos),_xlpm.val,INDEX($N:$N,_xlpm.rn),IF(INDEX($M:$M,_xlpm.rn)="Percentages",IF(_xlpm.val=0,"-",TEXT(_xlpm.val,"0%")),_xlpm.val))))} | D22: {=_xlfn.LET(_xlpm.visRows,_xlfn._xlws.FILTER(ROW($M$6:$M$22),$N$6:$N$22<>0),_xlpm.allRows,_xlfn.VSTACK(_xlpm.visRows,23,24),_xlpm.pos,ROW()-5,IF(_xlpm.pos>ROWS(_xlpm.allRows),"",_xlfn.LET(_xlpm.rn,INDEX(_xlpm.allRows,_xlpm.pos),_xlpm.val,INDEX($O:$O,_xlpm.rn),IF(INDEX($M:$M,_xlpm.rn)="Percentages",IF(_xlpm.val=0,"-",TEXT(_xlpm.val,"0%")),_xlpm.val))))} | E22: {=_xlfn.LET(_xlpm.visRows,_xlfn._xlws.FILTER(ROW($M$6:$M$22),$N$6:$N$22<>0),_xlpm.allRows,_xlfn.VSTACK(_xlpm.visRows,23,24),_xlpm.pos,ROW()-5,IF(_xlpm.pos>ROWS(_xlpm.allRows),"",_xlfn.LET(_xlpm.rn,INDEX(_xlpm.allRows,_xlpm.pos),_xlpm.val,INDEX($P:$P,_xlpm.rn),IF(INDEX($M:$M,_xlpm.rn)="Percentages",IF(_xlpm.val=0,"-",TEXT(_xlpm.val,"0%")),_xlpm.val))))} | F22: {=_xlfn.LET(_xlpm.visRows,_xlfn._xlws.FILTER(ROW($M$6:$M$22),$N$6:$N$22<>0),_xlpm.allRows,_xlfn.VSTACK(_xlpm.visRows,23,24),_xlpm.pos,ROW()-5,IF(_xlpm.pos>ROWS(_xlpm.allRows),"",_xlfn.LET(_xlpm.rn,INDEX(_xlpm.allRows,_xlpm.pos),_xlpm.val,INDEX($Q:$Q,_xlpm.rn),IF(INDEX($M:$M,_xlpm.rn)="Percentages",IF(_xlpm.val=0,"-",TEXT(_xlpm.val,"0%")),_xlpm.val))))} | G22: {=_xlfn.LET(_xlpm.visRows,_xlfn._xlws.FILTER(ROW($M$6:$M$22),$N$6:$N$22<>0),_xlpm.allRows,_xlfn.VSTACK(_xlpm.visRows,23,24),_xlpm.pos,ROW()-5,IF(_xlpm.pos>ROWS(_xlpm.allRows),"",_xlfn.LET(_xlpm.rn,INDEX(_xlpm.allRows,_xlpm.pos),_xlpm.val,INDEX($R:$R,_xlpm.rn),IF(INDEX($M:$M,_xlpm.rn)="Percentages",IF(_xlpm.val=0,"-",TEXT(_xlpm.val,"0%")),_xlpm.val))))} | H22: {=_xlfn.LET(_xlpm.visRows,_xlfn._xlws.FILTER(ROW($M$6:$M$22),$N$6:$N$22<>0),_xlpm.allRows,_xlfn.VSTACK(_xlpm.visRows,23,24),_xlpm.pos,ROW()-5,IF(_xlpm.pos>ROWS(_xlpm.allRows),"",_xlfn.LET(_xlpm.rn,INDEX(_xlpm.allRows,_xlpm.pos),_xlpm.val,INDEX($S:$S,_xlpm.rn),IF(INDEX($M:$M,_xlpm.rn)="Percentages",IF(_xlpm.val=0,"-",TEXT(_xlpm.val,"0%")),_xlpm.val))))} | I22: {=_xlfn.LET(_xlpm.visRows,_xlfn._xlws.FILTER(ROW($M$6:$M$22),$N$6:$N$22<>0),_xlpm.allRows,_xlfn.VSTACK(_xlpm.visRows,23,24),_xlpm.pos,ROW()-5,IF(_xlpm.pos>ROWS(_xlpm.allRows),"",_xlfn.LET(_xlpm.rn,INDEX(_xlpm.allRows,_xlpm.pos),_xlpm.val,INDEX($T:$T,_xlpm.rn),IF(INDEX($M:$M,_xlpm.rn)="Percentages",IF(_xlpm.val=0,"-",TEXT(_xlpm.val,"0%")),_xlpm.val))))} | J22: {=_xlfn.LET(_xlpm.visRows,_xlfn._xlws.FILTER(ROW($M$6:$M$22),$N$6:$N$22<>0),_xlpm.allRows,_xlfn.VSTACK(_xlpm.visRows,23,24),_xlpm.pos,ROW()-5,IF(_xlpm.pos>ROWS(_xlpm.allRows),"",_xlfn.LET(_xlpm.rn,INDEX(_xlpm.allRows,_xlpm.pos),_xlpm.val,INDEX($U:$U,_xlpm.rn),IF(INDEX($M:$M,_xlpm.rn)="Percentages",IF(_xlpm.val=0,"-",TEXT(_xlpm.val,"0%")),_xlpm.val))))} | K22: {=_xlfn.LET(_xlpm.visRows,_xlfn._xlws.FILTER(ROW($M$6:$M$22),$N$6:$N$22<>0),_xlpm.allRows,_xlfn.VSTACK(_xlpm.visRows,23,24),_xlpm.pos,ROW()-5,IF(_xlpm.pos>ROWS(_xlpm.allRows),"",_xlfn.LET(_xlpm.rn,INDEX(_xlpm.allRows,_xlpm.pos),_xlpm.val,INDEX($V:$V,_xlpm.rn),IF(INDEX($M:$M,_xlpm.rn)="Percentages",IF(_xlpm.val=0,"-",TEXT(_xlpm.val,"0%")),_xlpm.val))))} | M22: ='BDO Prequal'!B54 -> USDA Gty Fee | N22: ='BDO Prequal'!C54 -> 0 | O22: ='BDO Prequal'!D54 -> 0 | P22: ='BDO Prequal'!E54 -> 0 | Q22: ='BDO Prequal'!F54 -> 0 | R22: ='BDO Prequal'!G54 -> 0 | S22: ='BDO Prequal'!H54 -> 0 | T22: ='BDO Prequal'!I54 -> 0 | ... V22: ='BDO Prequal'!K54 -> 0
B23: {=_xlfn.LET(_xlpm.visRows,_xlfn._xlws.FILTER(ROW($M$6:$M$22),$N$6:$N$22<>0),_xlpm.allRows,_xlfn.VSTACK(_xlpm.visRows,23,24),_xlpm.pos,ROW()-5,IF(_xlpm.pos<=ROWS(_xlpm.allRows),INDEX($M:$M,INDEX(_xlpm.allRows,_xlpm.pos)),""))} | C23: {=_xlfn.LET(_xlpm.visRows,_xlfn._xlws.FILTER(ROW($M$6:$M$22),$N$6:$N$22<>0),_xlpm.allRows,_xlfn.VSTACK(_xlpm.visRows,23,24),_xlpm.pos,ROW()-5,IF(_xlpm.pos>ROWS(_xlpm.allRows),"",_xlfn.LET(_xlpm.rn,INDEX(_xlpm.allRows,_xlpm.pos),_xlpm.val,INDEX($N:$N,_xlpm.rn),IF(INDEX($M:$M,_xlpm.rn)="Percentages",IF(_xlpm.val=0,"-",TEXT(_xlpm.val,"0%")),_xlpm.val))))} | D23: {=_xlfn.LET(_xlpm.visRows,_xlfn._xlws.FILTER(ROW($M$6:$M$22),$N$6:$N$22<>0),_xlpm.allRows,_xlfn.VSTACK(_xlpm.visRows,23,24),_xlpm.pos,ROW()-5,IF(_xlpm.pos>ROWS(_xlpm.allRows),"",_xlfn.LET(_xlpm.rn,INDEX(_xlpm.allRows,_xlpm.pos),_xlpm.val,INDEX($O:$O,_xlpm.rn),IF(INDEX($M:$M,_xlpm.rn)="Percentages",IF(_xlpm.val=0,"-",TEXT(_xlpm.val,"0%")),_xlpm.val))))} | E23: {=_xlfn.LET(_xlpm.visRows,_xlfn._xlws.FILTER(ROW($M$6:$M$22),$N$6:$N$22<>0),_xlpm.allRows,_xlfn.VSTACK(_xlpm.visRows,23,24),_xlpm.pos,ROW()-5,IF(_xlpm.pos>ROWS(_xlpm.allRows),"",_xlfn.LET(_xlpm.rn,INDEX(_xlpm.allRows,_xlpm.pos),_xlpm.val,INDEX($P:$P,_xlpm.rn),IF(INDEX($M:$M,_xlpm.rn)="Percentages",IF(_xlpm.val=0,"-",TEXT(_xlpm.val,"0%")),_xlpm.val))))} | F23: {=_xlfn.LET(_xlpm.visRows,_xlfn._xlws.FILTER(ROW($M$6:$M$22),$N$6:$N$22<>0),_xlpm.allRows,_xlfn.VSTACK(_xlpm.visRows,23,24),_xlpm.pos,ROW()-5,IF(_xlpm.pos>ROWS(_xlpm.allRows),"",_xlfn.LET(_xlpm.rn,INDEX(_xlpm.allRows,_xlpm.pos),_xlpm.val,INDEX($Q:$Q,_xlpm.rn),IF(INDEX($M:$M,_xlpm.rn)="Percentages",IF(_xlpm.val=0,"-",TEXT(_xlpm.val,"0%")),_xlpm.val))))} | G23: {=_xlfn.LET(_xlpm.visRows,_xlfn._xlws.FILTER(ROW($M$6:$M$22),$N$6:$N$22<>0),_xlpm.allRows,_xlfn.VSTACK(_xlpm.visRows,23,24),_xlpm.pos,ROW()-5,IF(_xlpm.pos>ROWS(_xlpm.allRows),"",_xlfn.LET(_xlpm.rn,INDEX(_xlpm.allRows,_xlpm.pos),_xlpm.val,INDEX($R:$R,_xlpm.rn),IF(INDEX($M:$M,_xlpm.rn)="Percentages",IF(_xlpm.val=0,"-",TEXT(_xlpm.val,"0%")),_xlpm.val))))} | H23: {=_xlfn.LET(_xlpm.visRows,_xlfn._xlws.FILTER(ROW($M$6:$M$22),$N$6:$N$22<>0),_xlpm.allRows,_xlfn.VSTACK(_xlpm.visRows,23,24),_xlpm.pos,ROW()-5,IF(_xlpm.pos>ROWS(_xlpm.allRows),"",_xlfn.LET(_xlpm.rn,INDEX(_xlpm.allRows,_xlpm.pos),_xlpm.val,INDEX($S:$S,_xlpm.rn),IF(INDEX($M:$M,_xlpm.rn)="Percentages",IF(_xlpm.val=0,"-",TEXT(_xlpm.val,"0%")),_xlpm.val))))} | I23: {=_xlfn.LET(_xlpm.visRows,_xlfn._xlws.FILTER(ROW($M$6:$M$22),$N$6:$N$22<>0),_xlpm.allRows,_xlfn.VSTACK(_xlpm.visRows,23,24),_xlpm.pos,ROW()-5,IF(_xlpm.pos>ROWS(_xlpm.allRows),"",_xlfn.LET(_xlpm.rn,INDEX(_xlpm.allRows,_xlpm.pos),_xlpm.val,INDEX($T:$T,_xlpm.rn),IF(INDEX($M:$M,_xlpm.rn)="Percentages",IF(_xlpm.val=0,"-",TEXT(_xlpm.val,"0%")),_xlpm.val))))} | J23: {=_xlfn.LET(_xlpm.visRows,_xlfn._xlws.FILTER(ROW($M$6:$M$22),$N$6:$N$22<>0),_xlpm.allRows,_xlfn.VSTACK(_xlpm.visRows,23,24),_xlpm.pos,ROW()-5,IF(_xlpm.pos>ROWS(_xlpm.allRows),"",_xlfn.LET(_xlpm.rn,INDEX(_xlpm.allRows,_xlpm.pos),_xlpm.val,INDEX($U:$U,_xlpm.rn),IF(INDEX($M:$M,_xlpm.rn)="Percentages",IF(_xlpm.val=0,"-",TEXT(_xlpm.val,"0%")),_xlpm.val))))} | K23: {=_xlfn.LET(_xlpm.visRows,_xlfn._xlws.FILTER(ROW($M$6:$M$22),$N$6:$N$22<>0),_xlpm.allRows,_xlfn.VSTACK(_xlpm.visRows,23,24),_xlpm.pos,ROW()-5,IF(_xlpm.pos>ROWS(_xlpm.allRows),"",_xlfn.LET(_xlpm.rn,INDEX(_xlpm.allRows,_xlpm.pos),_xlpm.val,INDEX($V:$V,_xlpm.rn),IF(INDEX($M:$M,_xlpm.rn)="Percentages",IF(_xlpm.val=0,"-",TEXT(_xlpm.val,"0%")),_xlpm.val))))} | M23: Project Total | N23: ='BDO Prequal'!C55 -> 8472925 | O23: ='BDO Prequal'!D55 -> 1571792 | P23: ='BDO Prequal'!E55 -> 612591 | Q23: ='BDO Prequal'!F55 -> 2746607 | R23: ='BDO Prequal'!G55 -> 1350000 | S23: ='BDO Prequal'!H55 -> 320000 | T23: ='BDO Prequal'!I55 -> 1871935 | U23: ='BDO Prequal'!J55 -> 0 | V23: ='BDO Prequal'!K55 -> 0
B24: {=_xlfn.LET(_xlpm.visRows,_xlfn._xlws.FILTER(ROW($M$6:$M$22),$N$6:$N$22<>0),_xlpm.allRows,_xlfn.VSTACK(_xlpm.visRows,23,24),_xlpm.pos,ROW()-5,IF(_xlpm.pos<=ROWS(_xlpm.allRows),INDEX($M:$M,INDEX(_xlpm.allRows,_xlpm.pos)),""))} | C24: {=_xlfn.LET(_xlpm.visRows,_xlfn._xlws.FILTER(ROW($M$6:$M$22),$N$6:$N$22<>0),_xlpm.allRows,_xlfn.VSTACK(_xlpm.visRows,23,24),_xlpm.pos,ROW()-5,IF(_xlpm.pos>ROWS(_xlpm.allRows),"",_xlfn.LET(_xlpm.rn,INDEX(_xlpm.allRows,_xlpm.pos),_xlpm.val,INDEX($N:$N,_xlpm.rn),IF(INDEX($M:$M,_xlpm.rn)="Percentages",IF(_xlpm.val=0,"-",TEXT(_xlpm.val,"0%")),_xlpm.val))))} | D24: {=_xlfn.LET(_xlpm.visRows,_xlfn._xlws.FILTER(ROW($M$6:$M$22),$N$6:$N$22<>0),_xlpm.allRows,_xlfn.VSTACK(_xlpm.visRows,23,24),_xlpm.pos,ROW()-5,IF(_xlpm.pos>ROWS(_xlpm.allRows),"",_xlfn.LET(_xlpm.rn,INDEX(_xlpm.allRows,_xlpm.pos),_xlpm.val,INDEX($O:$O,_xlpm.rn),IF(INDEX($M:$M,_xlpm.rn)="Percentages",IF(_xlpm.val=0,"-",TEXT(_xlpm.val,"0%")),_xlpm.val))))} | E24: {=_xlfn.LET(_xlpm.visRows,_xlfn._xlws.FILTER(ROW($M$6:$M$22),$N$6:$N$22<>0),_xlpm.allRows,_xlfn.VSTACK(_xlpm.visRows,23,24),_xlpm.pos,ROW()-5,IF(_xlpm.pos>ROWS(_xlpm.allRows),"",_xlfn.LET(_xlpm.rn,INDEX(_xlpm.allRows,_xlpm.pos),_xlpm.val,INDEX($P:$P,_xlpm.rn),IF(INDEX($M:$M,_xlpm.rn)="Percentages",IF(_xlpm.val=0,"-",TEXT(_xlpm.val,"0%")),_xlpm.val))))} | F24: {=_xlfn.LET(_xlpm.visRows,_xlfn._xlws.FILTER(ROW($M$6:$M$22),$N$6:$N$22<>0),_xlpm.allRows,_xlfn.VSTACK(_xlpm.visRows,23,24),_xlpm.pos,ROW()-5,IF(_xlpm.pos>ROWS(_xlpm.allRows),"",_xlfn.LET(_xlpm.rn,INDEX(_xlpm.allRows,_xlpm.pos),_xlpm.val,INDEX($Q:$Q,_xlpm.rn),IF(INDEX($M:$M,_xlpm.rn)="Percentages",IF(_xlpm.val=0,"-",TEXT(_xlpm.val,"0%")),_xlpm.val))))} | G24: {=_xlfn.LET(_xlpm.visRows,_xlfn._xlws.FILTER(ROW($M$6:$M$22),$N$6:$N$22<>0),_xlpm.allRows,_xlfn.VSTACK(_xlpm.visRows,23,24),_xlpm.pos,ROW()-5,IF(_xlpm.pos>ROWS(_xlpm.allRows),"",_xlfn.LET(_xlpm.rn,INDEX(_xlpm.allRows,_xlpm.pos),_xlpm.val,INDEX($R:$R,_xlpm.rn),IF(INDEX($M:$M,_xlpm.rn)="Percentages",IF(_xlpm.val=0,"-",TEXT(_xlpm.val,"0%")),_xlpm.val))))} | H24: {=_xlfn.LET(_xlpm.visRows,_xlfn._xlws.FILTER(ROW($M$6:$M$22),$N$6:$N$22<>0),_xlpm.allRows,_xlfn.VSTACK(_xlpm.visRows,23,24),_xlpm.pos,ROW()-5,IF(_xlpm.pos>ROWS(_xlpm.allRows),"",_xlfn.LET(_xlpm.rn,INDEX(_xlpm.allRows,_xlpm.pos),_xlpm.val,INDEX($S:$S,_xlpm.rn),IF(INDEX($M:$M,_xlpm.rn)="Percentages",IF(_xlpm.val=0,"-",TEXT(_xlpm.val,"0%")),_xlpm.val))))} | I24: {=_xlfn.LET(_xlpm.visRows,_xlfn._xlws.FILTER(ROW($M$6:$M$22),$N$6:$N$22<>0),_xlpm.allRows,_xlfn.VSTACK(_xlpm.visRows,23,24),_xlpm.pos,ROW()-5,IF(_xlpm.pos>ROWS(_xlpm.allRows),"",_xlfn.LET(_xlpm.rn,INDEX(_xlpm.allRows,_xlpm.pos),_xlpm.val,INDEX($T:$T,_xlpm.rn),IF(INDEX($M:$M,_xlpm.rn)="Percentages",IF(_xlpm.val=0,"-",TEXT(_xlpm.val,"0%")),_xlpm.val))))} | J24: {=_xlfn.LET(_xlpm.visRows,_xlfn._xlws.FILTER(ROW($M$6:$M$22),$N$6:$N$22<>0),_xlpm.allRows,_xlfn.VSTACK(_xlpm.visRows,23,24),_xlpm.pos,ROW()-5,IF(_xlpm.pos>ROWS(_xlpm.allRows),"",_xlfn.LET(_xlpm.rn,INDEX(_xlpm.allRows,_xlpm.pos),_xlpm.val,INDEX($U:$U,_xlpm.rn),IF(INDEX($M:$M,_xlpm.rn)="Percentages",IF(_xlpm.val=0,"-",TEXT(_xlpm.val,"0%")),_xlpm.val))))} | K24: {=_xlfn.LET(_xlpm.visRows,_xlfn._xlws.FILTER(ROW($M$6:$M$22),$N$6:$N$22<>0),_xlpm.allRows,_xlfn.VSTACK(_xlpm.visRows,23,24),_xlpm.pos,ROW()-5,IF(_xlpm.pos>ROWS(_xlpm.allRows),"",_xlfn.LET(_xlpm.rn,INDEX(_xlpm.allRows,_xlpm.pos),_xlpm.val,INDEX($V:$V,_xlpm.rn),IF(INDEX($M:$M,_xlpm.rn)="Percentages",IF(_xlpm.val=0,"-",TEXT(_xlpm.val,"0%")),_xlpm.val))))} | M24: Percentages | N24: ='BDO Prequal'!C56 -> 1 | O24: ='BDO Prequal'!D56 -> 0.1855076 | P24: ='BDO Prequal'!E56 -> 0.072299826 | Q24: ='BDO Prequal'!F56 -> 0.32416279 | R24: ='BDO Prequal'!G56 -> 0.15933105 | S24: ='BDO Prequal'!H56 -> 0.037767359 | T24: ='BDO Prequal'!I56 -> 0.22093138 | U24: ='BDO Prequal'!J56 -> 0 | V24: ='BDO Prequal'!K56 -> 0
B27: Structure Table
C29: ='BDO Prequal'!E17 -> SBA 7(a) | D29: ='BDO Prequal'!F17 -> SBA 7(a) | E29: ='BDO Prequal'!G17 -> SBA 504 | F29: ='BDO Prequal'!H17 -> Seller Note | G29: ='BDO Prequal'!I17 -> Debenture | H29: ='BDO Prequal'!J17 -> N/A | I29: ='BDO Prequal'!K17 -> N/A
B30: Loan Amount | C30: ='BDO Prequal'!E18 -> 612591 | D30: ='BDO Prequal'!F18 -> 2746607 | E30: ='BDO Prequal'!G18 -> 1350000 | F30: ='BDO Prequal'!H18 -> 320000 | G30: ='BDO Prequal'!I18 -> 1871935 | H30: ='BDO Prequal'!J18 -> 0 | I30: ='BDO Prequal'!K18 -> 0 | M30: ↑↑↑↑↑↑↑↑↑↑↑↑↑↑↑↑↑↑↑↑↑↑↑↑↑↑↑↑↑↑↑↑↑↑↑↑↑↑↑↑↑↑↑↑↑↑↑↑↑↑↑↑↑
B31: ='BDO Prequal'!C19 -> Base Rate | C31: ='BDO Prequal'!E19 -> 0.0675 | D31: ='BDO Prequal'!F19 -> 0.0594 | E31: ='BDO Prequal'!G19 -> 0.0675 | F31: ='BDO Prequal'!H19 -> 0.05 | G31: ='BDO Prequal'!I19 -> 0.05 | H31: ='BDO Prequal'!J19 -> 0.0675 | I31: ='BDO Prequal'!K19 -> 0 | M31: REFERENCE CHARTS
B32: ='BDO Prequal'!C20 -> Spread | C32: ='BDO Prequal'!E20 -> 0.015 | D32: ='BDO Prequal'!F20 -> 0 | E32: ='BDO Prequal'!G20 -> 0.0275 | F32: ='BDO Prequal'!H20 -> 0 | G32: ='BDO Prequal'!I20 -> 0.01 | H32: ='BDO Prequal'!J20 -> 0.03 | I32: ='BDO Prequal'!K20 -> 0
B33: ='BDO Prequal'!C21 -> Indicative Rate | C33: ='BDO Prequal'!E21 -> 0.0825 | D33: ='BDO Prequal'!F21 -> 0.0594 | E33: ='BDO Prequal'!G21 -> 0.095 | F33: ='BDO Prequal'!H21 -> 0.05 | G33: ='BDO Prequal'!I21 -> 0.06 | H33: ='BDO Prequal'!J21 -> 0.0975 | I33: ='BDO Prequal'!K21 -> 0 | M33: ↓↓↓↓↓↓↓↓↓↓↓↓↓↓↓↓↓↓↓↓↓↓↓↓↓↓↓↓↓↓↓↓↓↓↓↓↓↓↓↓↓↓↓↓↓↓↓↓↓↓↓↓↓
B34: Adjustment / Fix | C34: Quarterly | D34: Fixed | E34: Fixed | F34: Fixed | G34: Fixed | H34: Fixed | I34: Fixed
B35: ='BDO Prequal'!C23 -> Term (years) | C35: ='BDO Prequal'!E23 -> 10 | D35: ='BDO Prequal'!F23 -> 10 | E35: ='BDO Prequal'!G23 -> 10 | F35: ='BDO Prequal'!H23 -> 7 | G35: ='BDO Prequal'!I23 -> 3 | H35: ='BDO Prequal'!J23 -> 5 | I35: ='BDO Prequal'!K23 -> 0
B36: ='BDO Prequal'!C25 -> Estimated Payment | C36: ='BDO Prequal'!E25 -> 7515.7979 | D36: ='BDO Prequal'!F25 -> 30417.001 | E36: ='BDO Prequal'!G25 -> 17474.442 | F36: ='BDO Prequal'!H25 -> 4523.4394 | G36: ='BDO Prequal'!I25 -> 56952.537 | H36: ='BDO Prequal'!J25 -> 0 | I36: ='BDO Prequal'!K25 -> 0
B39: Estimated Closing Costs | M39: Estimated Closing Costs
C41: =N41 -> Cost | D41: =O41 -> Quantity | E41: =P41 -> Total | N41: ='BDO Prequal'!O14 -> Cost | O41: ='BDO Prequal'!P14 -> Quantity | P41: ='BDO Prequal'!Q14 -> Total
B42: {=_xlfn.LET(_xlpm.visRows,_xlfn._xlws.FILTER(ROW($M$42:$M$57),$P$42:$P$57<>0),_xlpm.allRows,_xlfn.VSTACK(_xlpm.visRows,58),_xlpm.pos,ROW()-41,IF(_xlpm.pos<=ROWS(_xlpm.allRows),INDEX($M:$M,INDEX(_xlpm.allRows,_xlpm.pos)),""))} -> Business Valuation | C42: {=_xlfn.LET(_xlpm.visRows,_xlfn._xlws.FILTER(ROW($M$42:$M$57),$P$42:$P$57<>0),_xlpm.allRows,_xlfn.VSTACK(_xlpm.visRows,58),_xlpm.pos,ROW()-41,IF(_xlpm.pos>ROWS(_xlpm.allRows),"",INDEX($N:$N,INDEX(_xlpm.allRows,_xlpm.pos))))} -> 2500 | D42: {=_xlfn.LET(_xlpm.visRows,_xlfn._xlws.FILTER(ROW($M$42:$M$57),$P$42:$P$57<>0),_xlpm.allRows,_xlfn.VSTACK(_xlpm.visRows,58),_xlpm.pos,ROW()-41,IF(_xlpm.pos>ROWS(_xlpm.allRows),"",INDEX($O:$O,INDEX(_xlpm.allRows,_xlpm.pos))))} -> 1 | E42: {=_xlfn.LET(_xlpm.visRows,_xlfn._xlws.FILTER(ROW($M$42:$M$57),$P$42:$P$57<>0),_xlpm.allRows,_xlfn.VSTACK(_xlpm.visRows,58),_xlpm.pos,ROW()-41,IF(_xlpm.pos>ROWS(_xlpm.allRows),"",INDEX($P:$P,INDEX(_xlpm.allRows,_xlpm.pos))))} -> 2500 | M42: ='BDO Prequal'!N15 -> Title Insurance | N42: ='BDO Prequal'!O15 -> 0 | O42: ='BDO Prequal'!P15 -> 0 | P42: ='BDO Prequal'!Q15 -> 0
B43: {=_xlfn.LET(_xlpm.visRows,_xlfn._xlws.FILTER(ROW($M$42:$M$57),$P$42:$P$57<>0),_xlpm.allRows,_xlfn.VSTACK(_xlpm.visRows,58),_xlpm.pos,ROW()-41,IF(_xlpm.pos<=ROWS(_xlpm.allRows),INDEX($M:$M,INDEX(_xlpm.allRows,_xlpm.pos)),""))} -> Loan Packaging Fee | C43: {=_xlfn.LET(_xlpm.visRows,_xlfn._xlws.FILTER(ROW($M$42:$M$57),$P$42:$P$57<>0),_xlpm.allRows,_xlfn.VSTACK(_xlpm.visRows,58),_xlpm.pos,ROW()-41,IF(_xlpm.pos>ROWS(_xlpm.allRows),"",INDEX($N:$N,INDEX(_xlpm.allRows,_xlpm.pos))))} -> 2500 | D43: {=_xlfn.LET(_xlpm.visRows,_xlfn._xlws.FILTER(ROW($M$42:$M$57),$P$42:$P$57<>0),_xlpm.allRows,_xlfn.VSTACK(_xlpm.visRows,58),_xlpm.pos,ROW()-41,IF(_xlpm.pos>ROWS(_xlpm.allRows),"",INDEX($O:$O,INDEX(_xlpm.allRows,_xlpm.pos))))} -> 1 | E43: {=_xlfn.LET(_xlpm.visRows,_xlfn._xlws.FILTER(ROW($M$42:$M$57),$P$42:$P$57<>0),_xlpm.allRows,_xlfn.VSTACK(_xlpm.visRows,58),_xlpm.pos,ROW()-41,IF(_xlpm.pos>ROWS(_xlpm.allRows),"",INDEX($P:$P,INDEX(_xlpm.allRows,_xlpm.pos))))} -> 2500 | M43: ='BDO Prequal'!N16 -> Real Estate Tax Fee | N43: ='BDO Prequal'!O16 -> 0 | O43: ='BDO Prequal'!P16 -> 0 | P43: ='BDO Prequal'!Q16 -> 0
B44: {=_xlfn.LET(_xlpm.visRows,_xlfn._xlws.FILTER(ROW($M$42:$M$57),$P$42:$P$57<>0),_xlpm.allRows,_xlfn.VSTACK(_xlpm.visRows,58),_xlpm.pos,ROW()-41,IF(_xlpm.pos<=ROWS(_xlpm.allRows),INDEX($M:$M,INDEX(_xlpm.allRows,_xlpm.pos)),""))} -> Interim Loan Fee / Origination | C44: {=_xlfn.LET(_xlpm.visRows,_xlfn._xlws.FILTER(ROW($M$42:$M$57),$P$42:$P$57<>0),_xlpm.allRows,_xlfn.VSTACK(_xlpm.visRows,58),_xlpm.pos,ROW()-41,IF(_xlpm.pos>ROWS(_xlpm.allRows),"",INDEX($N:$N,INDEX(_xlpm.allRows,_xlpm.pos))))} -> 112000 | D44: {=_xlfn.LET(_xlpm.visRows,_xlfn._xlws.FILTER(ROW($M$42:$M$57),$P$42:$P$57<>0),_xlpm.allRows,_xlfn.VSTACK(_xlpm.visRows,58),_xlpm.pos,ROW()-41,IF(_xlpm.pos>ROWS(_xlpm.allRows),"",INDEX($O:$O,INDEX(_xlpm.allRows,_xlpm.pos))))} -> 1 | E44: {=_xlfn.LET(_xlpm.visRows,_xlfn._xlws.FILTER(ROW($M$42:$M$57),$P$42:$P$57<>0),_xlpm.allRows,_xlfn.VSTACK(_xlpm.visRows,58),_xlpm.pos,ROW()-41,IF(_xlpm.pos>ROWS(_xlpm.allRows),"",INDEX($P:$P,INDEX(_xlpm.allRows,_xlpm.pos))))} -> 112000 | M44: ='BDO Prequal'!N17 -> Survey Charges | N44: ='BDO Prequal'!O17 -> 3000 | O44: ='BDO Prequal'!P17 -> 0 | P44: ='BDO Prequal'!Q17 -> 0
B45: {=_xlfn.LET(_xlpm.visRows,_xlfn._xlws.FILTER(ROW($M$42:$M$57),$P$42:$P$57<>0),_xlpm.allRows,_xlfn.VSTACK(_xlpm.visRows,58),_xlpm.pos,ROW()-41,IF(_xlpm.pos<=ROWS(_xlpm.allRows),INDEX($M:$M,INDEX(_xlpm.allRows,_xlpm.pos)),""))} -> Rounding | C45: {=_xlfn.LET(_xlpm.visRows,_xlfn._xlws.FILTER(ROW($M$42:$M$57),$P$42:$P$57<>0),_xlpm.allRows,_xlfn.VSTACK(_xlpm.visRows,58),_xlpm.pos,ROW()-41,IF(_xlpm.pos>ROWS(_xlpm.allRows),"",INDEX($N:$N,INDEX(_xlpm.allRows,_xlpm.pos))))} -> 200 | D45: {=_xlfn.LET(_xlpm.visRows,_xlfn._xlws.FILTER(ROW($M$42:$M$57),$P$42:$P$57<>0),_xlpm.allRows,_xlfn.VSTACK(_xlpm.visRows,58),_xlpm.pos,ROW()-41,IF(_xlpm.pos>ROWS(_xlpm.allRows),"",INDEX($O:$O,INDEX(_xlpm.allRows,_xlpm.pos))))} -> 1 | E45: {=_xlfn.LET(_xlpm.visRows,_xlfn._xlws.FILTER(ROW($M$42:$M$57),$P$42:$P$57<>0),_xlpm.allRows,_xlfn.VSTACK(_xlpm.visRows,58),_xlpm.pos,ROW()-41,IF(_xlpm.pos>ROWS(_xlpm.allRows),"",INDEX($P:$P,INDEX(_xlpm.allRows,_xlpm.pos))))} -> 200 | M45: ='BDO Prequal'!N18 -> CRE Appraisal | N45: ='BDO Prequal'!O18 -> 3500 | O45: ='BDO Prequal'!P18 -> 0 | P45: ='BDO Prequal'!Q18 -> 0
B46: {=_xlfn.LET(_xlpm.visRows,_xlfn._xlws.FILTER(ROW($M$42:$M$57),$P$42:$P$57<>0),_xlpm.allRows,_xlfn.VSTACK(_xlpm.visRows,58),_xlpm.pos,ROW()-41,IF(_xlpm.pos<=ROWS(_xlpm.allRows),INDEX($M:$M,INDEX(_xlpm.allRows,_xlpm.pos)),""))} -> Other: UCCs and Misc Closing | C46: {=_xlfn.LET(_xlpm.visRows,_xlfn._xlws.FILTER(ROW($M$42:$M$57),$P$42:$P$57<>0),_xlpm.allRows,_xlfn.VSTACK(_xlpm.visRows,58),_xlpm.pos,ROW()-41,IF(_xlpm.pos>ROWS(_xlpm.allRows),"",INDEX($N:$N,INDEX(_xlpm.allRows,_xlpm.pos))))} -> 0 | D46: {=_xlfn.LET(_xlpm.visRows,_xlfn._xlws.FILTER(ROW($M$42:$M$57),$P$42:$P$57<>0),_xlpm.allRows,_xlfn.VSTACK(_xlpm.visRows,58),_xlpm.pos,ROW()-41,IF(_xlpm.pos>ROWS(_xlpm.allRows),"",INDEX($O:$O,INDEX(_xlpm.allRows,_xlpm.pos))))} -> 0 | E46: {=_xlfn.LET(_xlpm.visRows,_xlfn._xlws.FILTER(ROW($M$42:$M$57),$P$42:$P$57<>0),_xlpm.allRows,_xlfn.VSTACK(_xlpm.visRows,58),_xlpm.pos,ROW()-41,IF(_xlpm.pos>ROWS(_xlpm.allRows),"",INDEX($P:$P,INDEX(_xlpm.allRows,_xlpm.pos))))} -> 800 | M46: ='BDO Prequal'!N19 -> Environmental Investigation | N46: ='BDO Prequal'!O19 -> 2500 | O46: ='BDO Prequal'!P19 -> 0 | P46: ='BDO Prequal'!Q19 -> 0
B47: {=_xlfn.LET(_xlpm.visRows,_xlfn._xlws.FILTER(ROW($M$42:$M$57),$P$42:$P$57<>0),_xlpm.allRows,_xlfn.VSTACK(_xlpm.visRows,58),_xlpm.pos,ROW()-41,IF(_xlpm.pos<=ROWS(_xlpm.allRows),INDEX($M:$M,INDEX(_xlpm.allRows,_xlpm.pos)),""))} -> Total Estimated Closing Costs | C47: {=_xlfn.LET(_xlpm.visRows,_xlfn._xlws.FILTER(ROW($M$42:$M$57),$P$42:$P$57<>0),_xlpm.allRows,_xlfn.VSTACK(_xlpm.visRows,58),_xlpm.pos,ROW()-41,IF(_xlpm.pos>ROWS(_xlpm.allRows),"",INDEX($N:$N,INDEX(_xlpm.allRows,_xlpm.pos))))} -> 0 | D47: {=_xlfn.LET(_xlpm.visRows,_xlfn._xlws.FILTER(ROW($M$42:$M$57),$P$42:$P$57<>0),_xlpm.allRows,_xlfn.VSTACK(_xlpm.visRows,58),_xlpm.pos,ROW()-41,IF(_xlpm.pos>ROWS(_xlpm.allRows),"",INDEX($O:$O,INDEX(_xlpm.allRows,_xlpm.pos))))} -> 0 | E47: {=_xlfn.LET(_xlpm.visRows,_xlfn._xlws.FILTER(ROW($M$42:$M$57),$P$42:$P$57<>0),_xlpm.allRows,_xlfn.VSTACK(_xlpm.visRows,58),_xlpm.pos,ROW()-41,IF(_xlpm.pos>ROWS(_xlpm.allRows),"",INDEX($P:$P,INDEX(_xlpm.allRows,_xlpm.pos))))} -> 118000 | M47: ='BDO Prequal'!N20 -> Residential Appr / Valuation | N47: ='BDO Prequal'!O20 -> 500 | O47: ='BDO Prequal'!P20 -> 0 | P47: ='BDO Prequal'!Q20 -> 0
B48: {=_xlfn.LET(_xlpm.visRows,_xlfn._xlws.FILTER(ROW($M$42:$M$57),$P$42:$P$57<>0),_xlpm.allRows,_xlfn.VSTACK(_xlpm.visRows,58),_xlpm.pos,ROW()-41,IF(_xlpm.pos<=ROWS(_xlpm.allRows),INDEX($M:$M,INDEX(_xlpm.allRows,_xlpm.pos)),""))} | C48: {=_xlfn.LET(_xlpm.visRows,_xlfn._xlws.FILTER(ROW($M$42:$M$57),$P$42:$P$57<>0),_xlpm.allRows,_xlfn.VSTACK(_xlpm.visRows,58),_xlpm.pos,ROW()-41,IF(_xlpm.pos>ROWS(_xlpm.allRows),"",INDEX($N:$N,INDEX(_xlpm.allRows,_xlpm.pos))))} | D48: {=_xlfn.LET(_xlpm.visRows,_xlfn._xlws.FILTER(ROW($M$42:$M$57),$P$42:$P$57<>0),_xlpm.allRows,_xlfn.VSTACK(_xlpm.visRows,58),_xlpm.pos,ROW()-41,IF(_xlpm.pos>ROWS(_xlpm.allRows),"",INDEX($O:$O,INDEX(_xlpm.allRows,_xlpm.pos))))} | E48: {=_xlfn.LET(_xlpm.visRows,_xlfn._xlws.FILTER(ROW($M$42:$M$57),$P$42:$P$57<>0),_xlpm.allRows,_xlfn.VSTACK(_xlpm.visRows,58),_xlpm.pos,ROW()-41,IF(_xlpm.pos>ROWS(_xlpm.allRows),"",INDEX($P:$P,INDEX(_xlpm.allRows,_xlpm.pos))))} | M48: ='BDO Prequal'!N21 -> Business Valuation | N48: ='BDO Prequal'!O21 -> 2500 | O48: ='BDO Prequal'!P21 -> 1 | P48: ='BDO Prequal'!Q21 -> 2500
B49: {=_xlfn.LET(_xlpm.visRows,_xlfn._xlws.FILTER(ROW($M$42:$M$57),$P$42:$P$57<>0),_xlpm.allRows,_xlfn.VSTACK(_xlpm.visRows,58),_xlpm.pos,ROW()-41,IF(_xlpm.pos<=ROWS(_xlpm.allRows),INDEX($M:$M,INDEX(_xlpm.allRows,_xlpm.pos)),""))} | C49: {=_xlfn.LET(_xlpm.visRows,_xlfn._xlws.FILTER(ROW($M$42:$M$57),$P$42:$P$57<>0),_xlpm.allRows,_xlfn.VSTACK(_xlpm.visRows,58),_xlpm.pos,ROW()-41,IF(_xlpm.pos>ROWS(_xlpm.allRows),"",INDEX($N:$N,INDEX(_xlpm.allRows,_xlpm.pos))))} | D49: {=_xlfn.LET(_xlpm.visRows,_xlfn._xlws.FILTER(ROW($M$42:$M$57),$P$42:$P$57<>0),_xlpm.allRows,_xlfn.VSTACK(_xlpm.visRows,58),_xlpm.pos,ROW()-41,IF(_xlpm.pos>ROWS(_xlpm.allRows),"",INDEX($O:$O,INDEX(_xlpm.allRows,_xlpm.pos))))} | E49: {=_xlfn.LET(_xlpm.visRows,_xlfn._xlws.FILTER(ROW($M$42:$M$57),$P$42:$P$57<>0),_xlpm.allRows,_xlfn.VSTACK(_xlpm.visRows,58),_xlpm.pos,ROW()-41,IF(_xlpm.pos>ROWS(_xlpm.allRows),"",INDEX($P:$P,INDEX(_xlpm.allRows,_xlpm.pos))))} | M49: ='BDO Prequal'!N22 -> Equipment Appraisal | N49: ='BDO Prequal'!O22 -> 0 | O49: ='BDO Prequal'!P22 -> 0 | P49: ='BDO Prequal'!Q22 -> 0
B50: {=_xlfn.LET(_xlpm.visRows,_xlfn._xlws.FILTER(ROW($M$42:$M$57),$P$42:$P$57<>0),_xlpm.allRows,_xlfn.VSTACK(_xlpm.visRows,58),_xlpm.pos,ROW()-41,IF(_xlpm.pos<=ROWS(_xlpm.allRows),INDEX($M:$M,INDEX(_xlpm.allRows,_xlpm.pos)),""))} | C50: {=_xlfn.LET(_xlpm.visRows,_xlfn._xlws.FILTER(ROW($M$42:$M$57),$P$42:$P$57<>0),_xlpm.allRows,_xlfn.VSTACK(_xlpm.visRows,58),_xlpm.pos,ROW()-41,IF(_xlpm.pos>ROWS(_xlpm.allRows),"",INDEX($N:$N,INDEX(_xlpm.allRows,_xlpm.pos))))} | D50: {=_xlfn.LET(_xlpm.visRows,_xlfn._xlws.FILTER(ROW($M$42:$M$57),$P$42:$P$57<>0),_xlpm.allRows,_xlfn.VSTACK(_xlpm.visRows,58),_xlpm.pos,ROW()-41,IF(_xlpm.pos>ROWS(_xlpm.allRows),"",INDEX($O:$O,INDEX(_xlpm.allRows,_xlpm.pos))))} | E50: {=_xlfn.LET(_xlpm.visRows,_xlfn._xlws.FILTER(ROW($M$42:$M$57),$P$42:$P$57<>0),_xlpm.allRows,_xlfn.VSTACK(_xlpm.visRows,58),_xlpm.pos,ROW()-41,IF(_xlpm.pos>ROWS(_xlpm.allRows),"",INDEX($P:$P,INDEX(_xlpm.allRows,_xlpm.pos))))} | M50: ='BDO Prequal'!N23 -> Site Visit | N50: ='BDO Prequal'!O23 -> 350 | O50: ='BDO Prequal'!P23 -> 0 | P50: ='BDO Prequal'!Q23 -> 0
B51: {=_xlfn.LET(_xlpm.visRows,_xlfn._xlws.FILTER(ROW($M$42:$M$57),$P$42:$P$57<>0),_xlpm.allRows,_xlfn.VSTACK(_xlpm.visRows,58),_xlpm.pos,ROW()-41,IF(_xlpm.pos<=ROWS(_xlpm.allRows),INDEX($M:$M,INDEX(_xlpm.allRows,_xlpm.pos)),""))} | C51: {=_xlfn.LET(_xlpm.visRows,_xlfn._xlws.FILTER(ROW($M$42:$M$57),$P$42:$P$57<>0),_xlpm.allRows,_xlfn.VSTACK(_xlpm.visRows,58),_xlpm.pos,ROW()-41,IF(_xlpm.pos>ROWS(_xlpm.allRows),"",INDEX($N:$N,INDEX(_xlpm.allRows,_xlpm.pos))))} | D51: {=_xlfn.LET(_xlpm.visRows,_xlfn._xlws.FILTER(ROW($M$42:$M$57),$P$42:$P$57<>0),_xlpm.allRows,_xlfn.VSTACK(_xlpm.visRows,58),_xlpm.pos,ROW()-41,IF(_xlpm.pos>ROWS(_xlpm.allRows),"",INDEX($O:$O,INDEX(_xlpm.allRows,_xlpm.pos))))} | E51: {=_xlfn.LET(_xlpm.visRows,_xlfn._xlws.FILTER(ROW($M$42:$M$57),$P$42:$P$57<>0),_xlpm.allRows,_xlfn.VSTACK(_xlpm.visRows,58),_xlpm.pos,ROW()-41,IF(_xlpm.pos>ROWS(_xlpm.allRows),"",INDEX($P:$P,INDEX(_xlpm.allRows,_xlpm.pos))))} | M51: ='BDO Prequal'!N24 -> Construction Monitoring | N51: ='BDO Prequal'!O24 -> 0 | O51: ='BDO Prequal'!P24 -> 0 | P51: ='BDO Prequal'!Q24 -> 0
B52: {=_xlfn.LET(_xlpm.visRows,_xlfn._xlws.FILTER(ROW($M$42:$M$57),$P$42:$P$57<>0),_xlpm.allRows,_xlfn.VSTACK(_xlpm.visRows,58),_xlpm.pos,ROW()-41,IF(_xlpm.pos<=ROWS(_xlpm.allRows),INDEX($M:$M,INDEX(_xlpm.allRows,_xlpm.pos)),""))} | C52: {=_xlfn.LET(_xlpm.visRows,_xlfn._xlws.FILTER(ROW($M$42:$M$57),$P$42:$P$57<>0),_xlpm.allRows,_xlfn.VSTACK(_xlpm.visRows,58),_xlpm.pos,ROW()-41,IF(_xlpm.pos>ROWS(_xlpm.allRows),"",INDEX($N:$N,INDEX(_xlpm.allRows,_xlpm.pos))))} | D52: {=_xlfn.LET(_xlpm.visRows,_xlfn._xlws.FILTER(ROW($M$42:$M$57),$P$42:$P$57<>0),_xlpm.allRows,_xlfn.VSTACK(_xlpm.visRows,58),_xlpm.pos,ROW()-41,IF(_xlpm.pos>ROWS(_xlpm.allRows),"",INDEX($O:$O,INDEX(_xlpm.allRows,_xlpm.pos))))} | E52: {=_xlfn.LET(_xlpm.visRows,_xlfn._xlws.FILTER(ROW($M$42:$M$57),$P$42:$P$57<>0),_xlpm.allRows,_xlfn.VSTACK(_xlpm.visRows,58),_xlpm.pos,ROW()-41,IF(_xlpm.pos>ROWS(_xlpm.allRows),"",INDEX($P:$P,INDEX(_xlpm.allRows,_xlpm.pos))))} | M52: ='BDO Prequal'!N25 -> Loan Packaging Fee | N52: ='BDO Prequal'!O25 -> 2500 | O52: ='BDO Prequal'!P25 -> 1 | P52: ='BDO Prequal'!Q25 -> 2500
B53: {=_xlfn.LET(_xlpm.visRows,_xlfn._xlws.FILTER(ROW($M$42:$M$57),$P$42:$P$57<>0),_xlpm.allRows,_xlfn.VSTACK(_xlpm.visRows,58),_xlpm.pos,ROW()-41,IF(_xlpm.pos<=ROWS(_xlpm.allRows),INDEX($M:$M,INDEX(_xlpm.allRows,_xlpm.pos)),""))} | C53: {=_xlfn.LET(_xlpm.visRows,_xlfn._xlws.FILTER(ROW($M$42:$M$57),$P$42:$P$57<>0),_xlpm.allRows,_xlfn.VSTACK(_xlpm.visRows,58),_xlpm.pos,ROW()-41,IF(_xlpm.pos>ROWS(_xlpm.allRows),"",INDEX($N:$N,INDEX(_xlpm.allRows,_xlpm.pos))))} | D53: {=_xlfn.LET(_xlpm.visRows,_xlfn._xlws.FILTER(ROW($M$42:$M$57),$P$42:$P$57<>0),_xlpm.allRows,_xlfn.VSTACK(_xlpm.visRows,58),_xlpm.pos,ROW()-41,IF(_xlpm.pos>ROWS(_xlpm.allRows),"",INDEX($O:$O,INDEX(_xlpm.allRows,_xlpm.pos))))} | E53: {=_xlfn.LET(_xlpm.visRows,_xlfn._xlws.FILTER(ROW($M$42:$M$57),$P$42:$P$57<>0),_xlpm.allRows,_xlfn.VSTACK(_xlpm.visRows,58),_xlpm.pos,ROW()-41,IF(_xlpm.pos>ROWS(_xlpm.allRows),"",INDEX($P:$P,INDEX(_xlpm.allRows,_xlpm.pos))))} | M53: ='BDO Prequal'!N26 -> Closing Doc Prep | N53: ='BDO Prequal'!O26 -> 7000 | O53: ='BDO Prequal'!P26 -> 0 | P53: ='BDO Prequal'!Q26 -> 0
... B56: {=_xlfn.LET(_xlpm.visRows,_xlfn._xlws.FILTER(ROW($M$42:$M$57),$P$42:$P$57<>0),_xlpm.allRows,_xlfn.VSTACK(_xlpm.visRows,58),_xlpm.pos,ROW()-41,IF(_xlpm.pos<=ROWS(_xlpm.allRows),INDEX($M:$M,INDEX(_xlpm.allRows,_xlpm.pos)),""))} | C56: {=_xlfn.LET(_xlpm.visRows,_xlfn._xlws.FILTER(ROW($M$42:$M$57),$P$42:$P$57<>0),_xlpm.allRows,_xlfn.VSTACK(_xlpm.visRows,58),_xlpm.pos,ROW()-41,IF(_xlpm.pos>ROWS(_xlpm.allRows),"",INDEX($N:$N,INDEX(_xlpm.allRows,_xlpm.pos))))} | D56: {=_xlfn.LET(_xlpm.visRows,_xlfn._xlws.FILTER(ROW($M$42:$M$57),$P$42:$P$57<>0),_xlpm.allRows,_xlfn.VSTACK(_xlpm.visRows,58),_xlpm.pos,ROW()-41,IF(_xlpm.pos>ROWS(_xlpm.allRows),"",INDEX($O:$O,INDEX(_xlpm.allRows,_xlpm.pos))))} | E56: {=_xlfn.LET(_xlpm.visRows,_xlfn._xlws.FILTER(ROW($M$42:$M$57),$P$42:$P$57<>0),_xlpm.allRows,_xlfn.VSTACK(_xlpm.visRows,58),_xlpm.pos,ROW()-41,IF(_xlpm.pos>ROWS(_xlpm.allRows),"",INDEX($P:$P,INDEX(_xlpm.allRows,_xlpm.pos))))} | M56: ='BDO Prequal'!N29 -> Rounding | N56: ='BDO Prequal'!O29 -> 200 | O56: ='BDO Prequal'!P29 -> 1 | P56: ='BDO Prequal'!Q29 -> 200
B57: {=_xlfn.LET(_xlpm.visRows,_xlfn._xlws.FILTER(ROW($M$42:$M$57),$P$42:$P$57<>0),_xlpm.allRows,_xlfn.VSTACK(_xlpm.visRows,58),_xlpm.pos,ROW()-41,IF(_xlpm.pos<=ROWS(_xlpm.allRows),INDEX($M:$M,INDEX(_xlpm.allRows,_xlpm.pos)),""))} | C57: {=_xlfn.LET(_xlpm.visRows,_xlfn._xlws.FILTER(ROW($M$42:$M$57),$P$42:$P$57<>0),_xlpm.allRows,_xlfn.VSTACK(_xlpm.visRows,58),_xlpm.pos,ROW()-41,IF(_xlpm.pos>ROWS(_xlpm.allRows),"",INDEX($N:$N,INDEX(_xlpm.allRows,_xlpm.pos))))} | D57: {=_xlfn.LET(_xlpm.visRows,_xlfn._xlws.FILTER(ROW($M$42:$M$57),$P$42:$P$57<>0),_xlpm.allRows,_xlfn.VSTACK(_xlpm.visRows,58),_xlpm.pos,ROW()-41,IF(_xlpm.pos>ROWS(_xlpm.allRows),"",INDEX($O:$O,INDEX(_xlpm.allRows,_xlpm.pos))))} | E57: {=_xlfn.LET(_xlpm.visRows,_xlfn._xlws.FILTER(ROW($M$42:$M$57),$P$42:$P$57<>0),_xlpm.allRows,_xlfn.VSTACK(_xlpm.visRows,58),_xlpm.pos,ROW()-41,IF(_xlpm.pos>ROWS(_xlpm.allRows),"",INDEX($P:$P,INDEX(_xlpm.allRows,_xlpm.pos))))} | M57: ='BDO Prequal'!N30 -> Other: UCCs and Misc Closing | P57: ='BDO Prequal'!Q30 -> 800
B58: {=_xlfn.LET(_xlpm.visRows,_xlfn._xlws.FILTER(ROW($M$42:$M$57),$P$42:$P$57<>0),_xlpm.allRows,_xlfn.VSTACK(_xlpm.visRows,58),_xlpm.pos,ROW()-41,IF(_xlpm.pos<=ROWS(_xlpm.allRows),INDEX($M:$M,INDEX(_xlpm.allRows,_xlpm.pos)),""))} | C58: {=_xlfn.LET(_xlpm.visRows,_xlfn._xlws.FILTER(ROW($M$42:$M$57),$P$42:$P$57<>0),_xlpm.allRows,_xlfn.VSTACK(_xlpm.visRows,58),_xlpm.pos,ROW()-41,IF(_xlpm.pos>ROWS(_xlpm.allRows),"",INDEX($N:$N,INDEX(_xlpm.allRows,_xlpm.pos))))} | D58: {=_xlfn.LET(_xlpm.visRows,_xlfn._xlws.FILTER(ROW($M$42:$M$57),$P$42:$P$57<>0),_xlpm.allRows,_xlfn.VSTACK(_xlpm.visRows,58),_xlpm.pos,ROW()-41,IF(_xlpm.pos>ROWS(_xlpm.allRows),"",INDEX($O:$O,INDEX(_xlpm.allRows,_xlpm.pos))))} | E58: {=_xlfn.LET(_xlpm.visRows,_xlfn._xlws.FILTER(ROW($M$42:$M$57),$P$42:$P$57<>0),_xlpm.allRows,_xlfn.VSTACK(_xlpm.visRows,58),_xlpm.pos,ROW()-41,IF(_xlpm.pos>ROWS(_xlpm.allRows),"",INDEX($P:$P,INDEX(_xlpm.allRows,_xlpm.pos))))} | M58: ='BDO Prequal'!N31 -> Total Estimated Closing Costs | P58: ='BDO Prequal'!Q31 -> 118000
D61: Blended Rate Table
D62: Bank Loan with CDC Loan
E63: Loan | F63: Est. Payment | G63: Rate
B64: Loan #1 Considered | C64: 1 | D64: =IF(C64='BDO Prequal'!E15,'BDO Prequal'!E17,IF(C64='BDO Prequal'!F15,'BDO Prequal'!F17,IF(C64='BDO Prequal'!G15,'BDO Prequal'!G17,IF(C64='BDO Prequal'!H15,'BDO Prequal'!H17,IF(C64='BDO Prequal'!I15,'BDO Prequal'!I17,IF(C64='BDO Prequal'!J15,'BDO Prequal'!J17,IF(C64='BDO Prequal'!K15,'BDO Prequal'!K17,'BDO Prequal'!E17))))))) -> SBA 7(a) | E64: =IF(C64='BDO Prequal'!E15,'BDO Prequal'!E18,IF(C64='BDO Prequal'!F15,'BDO Prequal'!F18,IF(C64='BDO Prequal'!G15,'BDO Prequal'!G18,IF(C64='BDO Prequal'!H15,'BDO Prequal'!H18,IF(C64='BDO Prequal'!I15,'BDO Prequal'!I18,IF(C64='BDO Prequal'!J15,'BDO Prequal'!J18,IF(C64='BDO Prequal'!K15,'BDO Prequal'!K18,'BDO Prequal'!E18))))))) -> 612591 | F64: =IF(C64='BDO Prequal'!E15,'BDO Prequal'!E25,IF(C64='BDO Prequal'!F15,'BDO Prequal'!F25,IF(C64='BDO Prequal'!G15,'BDO Prequal'!G25,IF(C64='BDO Prequal'!H15,'BDO Prequal'!H25,IF(C64='BDO Prequal'!I15,'BDO Prequal'!I25,IF(C64='BDO Prequal'!J15,'BDO Prequal'!J25,IF(C64='BDO Prequal'!K15,'BDO Prequal'!K25,'BDO Prequal'!E25))))))) -> 7515.7979 | G64: =IF(C64='BDO Prequal'!E15,'BDO Prequal'!E21,IF(C64='BDO Prequal'!F15,'BDO Prequal'!F21,IF(C64='BDO Prequal'!G15,'BDO Prequal'!G21,IF(C64='BDO Prequal'!H15,'BDO Prequal'!H21,IF(C64='BDO Prequal'!I15,'BDO Prequal'!I21,IF(C64='BDO Prequal'!J15,'BDO Prequal'!J21,IF(C64='BDO Prequal'!K15,'BDO Prequal'!K21,'BDO Prequal'!E21))))))) -> 0.0825
B65: Loan #2 Considered | C65: 2 | D65: =IF(C65='BDO Prequal'!E15,'BDO Prequal'!E17,IF(C65='BDO Prequal'!F15,'BDO Prequal'!F17,IF(C65='BDO Prequal'!G15,'BDO Prequal'!G17,IF(C65='BDO Prequal'!H15,'BDO Prequal'!H17,IF(C65='BDO Prequal'!I15,'BDO Prequal'!I17,IF(C65='BDO Prequal'!J15,'BDO Prequal'!J17,IF(C65='BDO Prequal'!K15,'BDO Prequal'!K17,'BDO Prequal'!E17))))))) -> SBA 7(a) | E65: =IF(C65='BDO Prequal'!E15,'BDO Prequal'!E18,IF(C65='BDO Prequal'!F15,'BDO Prequal'!F18,IF(C65='BDO Prequal'!G15,'BDO Prequal'!G18,IF(C65='BDO Prequal'!H15,'BDO Prequal'!H18,IF(C65='BDO Prequal'!I15,'BDO Prequal'!I18,IF(C65='BDO Prequal'!J15,'BDO Prequal'!J18,IF(C65='BDO Prequal'!K15,'BDO Prequal'!K18,'BDO Prequal'!F18))))))) -> 2746607 | F65: =IF(C65='BDO Prequal'!E15,'BDO Prequal'!E25,IF(C65='BDO Prequal'!F15,'BDO Prequal'!F25,IF(C65='BDO Prequal'!G15,'BDO Prequal'!G25,IF(C65='BDO Prequal'!H15,'BDO Prequal'!H25,IF(C65='BDO Prequal'!I15,'BDO Prequal'!I25,IF(C65='BDO Prequal'!J15,'BDO Prequal'!J25,IF(C65='BDO Prequal'!K15,'BDO Prequal'!K25,'BDO Prequal'!F25))))))) -> 30417.001 | G65: =IF(C65='BDO Prequal'!E15,'BDO Prequal'!E21,IF(C65='BDO Prequal'!F15,'BDO Prequal'!F21,IF(C65='BDO Prequal'!G15,'BDO Prequal'!G21,IF(C65='BDO Prequal'!H15,'BDO Prequal'!H21,IF(C65='BDO Prequal'!I15,'BDO Prequal'!I21,IF(C65='BDO Prequal'!J15,'BDO Prequal'!J21,IF(C65='BDO Prequal'!K15,'BDO Prequal'!K21,'BDO Prequal'!F21))))))) -> 0.0594
D66: Total/Blend | E66: =E64+E65 -> 3359198 | F66: =F64+F65 -> 37932.799 | G66: =(E64*G64+E65*G65)/E66 -> 0.063612569
B69: Origination / TPL / Referral Chart
C71: % Factor | D71: $
B72: ='BDO Prequal'!O50 -> Bridge / Interim Loan | C72: ='BDO Prequal'!P51 -> 0.015 | D72: ='BDO Prequal'!P50 -> 3221935
B73: ='BDO Prequal'!O52 -> Interim Loan Fee % to Perm Loan | C73: ='BDO Prequal'!P52 -> 0.011407873 | D73: ='BDO Prequal'!Q52 -> 48329.025 | M73: ↑↑↑↑↑↑↑↑↑↑↑↑↑↑↑↑↑↑↑↑↑↑↑↑↑↑↑↑↑↑↑↑↑↑↑↑↑↑↑↑↑↑↑↑↑↑↑↑↑↑↑↑↑
B74: ='BDO Prequal'!O53 -> SBA TPL Fee % | C74: ='BDO Prequal'!P53 -> 0.005 | D74: ='BDO Prequal'!Q53 -> 21182.312 | M74: REFERENCE CHARTS
B75: ='BDO Prequal'!O54 -> Referral Fee % | C75: ='BDO Prequal'!P54 -> 0.01 | D75: ='BDO Prequal'!Q54 -> 42364.625
B76: ='BDO Prequal'!O55 -> Participant Fee % | C76: ='BDO Prequal'!P55 -> 0 | D76: ='BDO Prequal'!Q55 -> 0 | M76: ↓↓↓↓↓↓↓↓↓↓↓↓↓↓↓↓↓↓↓↓↓↓↓↓↓↓↓↓↓↓↓↓↓↓↓↓↓↓↓↓↓↓↓↓↓↓↓↓↓↓↓↓↓
B77: ='BDO Prequal'!O56 -> Origination Fee Total | C77: ='BDO Prequal'!P56 -> 0.041407873 | D77: ='BDO Prequal'!Q56 -> 111875.96
B78: ='BDO Prequal'!O57 -> Rounded Fee | D78: ='BDO Prequal'!Q57 -> 112000
B81: Collateral Analysis
B83: Address | D83: Gross Value | E83: Advance Rate | F83: Discounted Value | G83: Senior Liens | H83: Liquidation Value
B84: =IF('BDO Prequal'!C197="","",'BDO Prequal'!C197) | D84: ='BDO Prequal'!G197 -> 0 | E84: ='BDO Prequal'!H197 -> 0.85 | F84: ='BDO Prequal'!I197 -> 0 | G84: ='BDO Prequal'!J197 -> 0 | H84: ='BDO Prequal'!K197 -> 0
B85: =IF('BDO Prequal'!C198="","",'BDO Prequal'!C198) | D85: ='BDO Prequal'!G198 -> 0 | E85: ='BDO Prequal'!H198 -> 0.85 | F85: ='BDO Prequal'!I198 -> 0 | G85: ='BDO Prequal'!J198 -> 0 | H85: ='BDO Prequal'!K198 -> 0
B86: =IF('BDO Prequal'!C199="","",'BDO Prequal'!C199) | D86: ='BDO Prequal'!G199 -> 0 | E86: ='BDO Prequal'!H199 -> 0.85 | F86: ='BDO Prequal'!I199 -> 0 | G86: ='BDO Prequal'!J199 -> 0 | H86: ='BDO Prequal'!K199 -> 0
B87: =IF('BDO Prequal'!C200="","",'BDO Prequal'!C200) | D87: ='BDO Prequal'!G200 -> 0 | E87: ='BDO Prequal'!H200 -> 0.5 | F87: ='BDO Prequal'!I200 -> 0 | G87: ='BDO Prequal'!J200 -> 0 | H87: ='BDO Prequal'!K200 -> 0
B88: =IF('BDO Prequal'!C201="","",'BDO Prequal'!C201) | D88: ='BDO Prequal'!G201 -> 0 | E88: ='BDO Prequal'!H201 -> 0.5 | F88: ='BDO Prequal'!I201 -> 0 | G88: ='BDO Prequal'!J201 -> 0 | H88: ='BDO Prequal'!K201 -> 0
B89: =IF('BDO Prequal'!C202="","",'BDO Prequal'!C202) | D89: ='BDO Prequal'!G202 -> 0 | E89: ='BDO Prequal'!H202 -> 0.1 | F89: ='BDO Prequal'!I202 -> 0 | G89: ='BDO Prequal'!J202 -> 0 | H89: ='BDO Prequal'!K202 -> 0
B90: =IF('BDO Prequal'!C203="","",'BDO Prequal'!C203) | D90: ='BDO Prequal'!G203 -> 0 | E90: ='BDO Prequal'!H203 -> 0.1 | F90: ='BDO Prequal'!I203 -> 0 | G90: ='BDO Prequal'!J203 -> 0 | H90: ='BDO Prequal'!K203 -> 0
B91: =IF('BDO Prequal'!C204="","",'BDO Prequal'!C204) | D91: ='BDO Prequal'!G204 -> 0 | E91: ='BDO Prequal'!H204 -> 0.1 | F91: ='BDO Prequal'!I204 -> 0 | G91: ='BDO Prequal'!J204 -> 0 | H91: ='BDO Prequal'!K204 -> 0
B92: =IF('BDO Prequal'!C205="","",'BDO Prequal'!C205) | D92: ='BDO Prequal'!G205 -> 0 | E92: ='BDO Prequal'!H205 -> 0.05 | F92: ='BDO Prequal'!I205 -> 0 | G92: ='BDO Prequal'!J205 -> 0 | H92: ='BDO Prequal'!K205 -> 0
C93: Totals | D93: ='BDO Prequal'!G206 -> 0 | F93: ='BDO Prequal'!I206 -> 0 | G93: ='BDO Prequal'!J206 -> 0 | H93: ='BDO Prequal'!K206 -> 0
B95: Gross LTV | D95: ='BDO Prequal'!H208 -> 0 | E95: Net LTV | G95: Net LTV | H95: ='BDO Prequal'!K208 -> 0
B96: Gross Coverage | D96: ='BDO Prequal'!H209 -> 0 | E96: Net Coverage | G96: Net Coverage | H96: ='BDO Prequal'!K209 -> 0
B99: Liquidity Analysis | M99: Liquidity Analysis
B101: {=IF(ROW()-ROW($B$101)+1<=SUMPRODUCT(($N$101:$N$124<>0)*1),INDEX($M$101:$M$124,_xlfn.AGGREGATE(15,6,(ROW($M$101:$M$124)-ROW($M$101)+1)/($N$101:$N$124<>0),ROW()-ROW($B$101)+1)),IF(ROW()-ROW($B$101)+1=SUMPRODUCT(($N$101:$N$124<>0)*1)+1,$M$125,IF(ROW()-ROW($B$101)+1=SUMPRODUCT(($N$101:$N$124<>0)*1)+2,$M$126,IF(ROW()-ROW($B$101)+1=SUMPRODUCT(($N$101:$N$124<>0)*1)+3,$M$127,IF(ROW()-ROW($B$101)+1=SUMPRODUCT(($N$101:$N$124<>0)*1)+4,$M$128,"")))))} -> Operating Company Liquidity | C101: {=IF(ROW()-ROW($C$101)+1<=SUMPRODUCT(($N$101:$N$124<>0)*1),INDEX($N$101:$N$124,_xlfn.AGGREGATE(15,6,(ROW($N$101:$N$124)-ROW($N$101)+1)/($N$101:$N$124<>0),ROW()-ROW($C$101)+1)),IF(ROW()-ROW($C$101)+1=SUMPRODUCT(($N$101:$N$124<>0)*1)+1,$N$125,IF(ROW()-ROW($C$101)+1=SUMPRODUCT(($N$101:$N$124<>0)*1)+2,$N$126,IF(ROW()-ROW($C$101)+1=SUMPRODUCT(($N$101:$N$124<>0)*1)+3,$N$127,IF(ROW()-ROW($C$101)+1=SUMPRODUCT(($N$101:$N$124<>0)*1)+4,$N$128,"")))))} -> 590000 | M101: ='BDO Prequal'!B62 -> Operating Company Liquidity | N101: ='BDO Prequal'!C62 -> 590000
B102: {=IF(ROW()-ROW($B$101)+1<=SUMPRODUCT(($N$101:$N$124<>0)*1),INDEX($M$101:$M$124,_xlfn.AGGREGATE(15,6,(ROW($M$101:$M$124)-ROW($M$101)+1)/($N$101:$N$124<>0),ROW()-ROW($B$101)+1)),IF(ROW()-ROW($B$101)+1=SUMPRODUCT(($N$101:$N$124<>0)*1)+1,$M$125,IF(ROW()-ROW($B$101)+1=SUMPRODUCT(($N$101:$N$124<>0)*1)+2,$M$126,IF(ROW()-ROW($B$101)+1=SUMPRODUCT(($N$101:$N$124<>0)*1)+3,$M$127,IF(ROW()-ROW($B$101)+1=SUMPRODUCT(($N$101:$N$124<>0)*1)+4,$M$128,"")))))} -> Jeff Able | C102: {=IF(ROW()-ROW($C$101)+1<=SUMPRODUCT(($N$101:$N$124<>0)*1),INDEX($N$101:$N$124,_xlfn.AGGREGATE(15,6,(ROW($N$101:$N$124)-ROW($N$101)+1)/($N$101:$N$124<>0),ROW()-ROW($C$101)+1)),IF(ROW()-ROW($C$101)+1=SUMPRODUCT(($N$101:$N$124<>0)*1)+1,$N$125,IF(ROW()-ROW($C$101)+1=SUMPRODUCT(($N$101:$N$124<>0)*1)+2,$N$126,IF(ROW()-ROW($C$101)+1=SUMPRODUCT(($N$101:$N$124<>0)*1)+3,$N$127,IF(ROW()-ROW($C$101)+1=SUMPRODUCT(($N$101:$N$124<>0)*1)+4,$N$128,"")))))} -> 11100 | M102: ='BDO Prequal'!B63 -> Jeff Able | N102: ='BDO Prequal'!C63 -> 11100
B103: {=IF(ROW()-ROW($B$101)+1<=SUMPRODUCT(($N$101:$N$124<>0)*1),INDEX($M$101:$M$124,_xlfn.AGGREGATE(15,6,(ROW($M$101:$M$124)-ROW($M$101)+1)/($N$101:$N$124<>0),ROW()-ROW($B$101)+1)),IF(ROW()-ROW($B$101)+1=SUMPRODUCT(($N$101:$N$124<>0)*1)+1,$M$125,IF(ROW()-ROW($B$101)+1=SUMPRODUCT(($N$101:$N$124<>0)*1)+2,$M$126,IF(ROW()-ROW($B$101)+1=SUMPRODUCT(($N$101:$N$124<>0)*1)+3,$M$127,IF(ROW()-ROW($B$101)+1=SUMPRODUCT(($N$101:$N$124<>0)*1)+4,$M$128,"")))))} -> Lisa McClure | C103: {=IF(ROW()-ROW($C$101)+1<=SUMPRODUCT(($N$101:$N$124<>0)*1),INDEX($N$101:$N$124,_xlfn.AGGREGATE(15,6,(ROW($N$101:$N$124)-ROW($N$101)+1)/($N$101:$N$124<>0),ROW()-ROW($C$101)+1)),IF(ROW()-ROW($C$101)+1=SUMPRODUCT(($N$101:$N$124<>0)*1)+1,$N$125,IF(ROW()-ROW($C$101)+1=SUMPRODUCT(($N$101:$N$124<>0)*1)+2,$N$126,IF(ROW()-ROW($C$101)+1=SUMPRODUCT(($N$101:$N$124<>0)*1)+3,$N$127,IF(ROW()-ROW($C$101)+1=SUMPRODUCT(($N$101:$N$124<>0)*1)+4,$N$128,"")))))} -> 525000 | M103: ='BDO Prequal'!B64 -> Lisa McClure | N103: ='BDO Prequal'!C64 -> 525000
B104: {=IF(ROW()-ROW($B$101)+1<=SUMPRODUCT(($N$101:$N$124<>0)*1),INDEX($M$101:$M$124,_xlfn.AGGREGATE(15,6,(ROW($M$101:$M$124)-ROW($M$101)+1)/($N$101:$N$124<>0),ROW()-ROW($B$101)+1)),IF(ROW()-ROW($B$101)+1=SUMPRODUCT(($N$101:$N$124<>0)*1)+1,$M$125,IF(ROW()-ROW($B$101)+1=SUMPRODUCT(($N$101:$N$124<>0)*1)+2,$M$126,IF(ROW()-ROW($B$101)+1=SUMPRODUCT(($N$101:$N$124<>0)*1)+3,$M$127,IF(ROW()-ROW($B$101)+1=SUMPRODUCT(($N$101:$N$124<>0)*1)+4,$M$128,"")))))} -> Brandon Johnson | C104: {=IF(ROW()-ROW($C$101)+1<=SUMPRODUCT(($N$101:$N$124<>0)*1),INDEX($N$101:$N$124,_xlfn.AGGREGATE(15,6,(ROW($N$101:$N$124)-ROW($N$101)+1)/($N$101:$N$124<>0),ROW()-ROW($C$101)+1)),IF(ROW()-ROW($C$101)+1=SUMPRODUCT(($N$101:$N$124<>0)*1)+1,$N$125,IF(ROW()-ROW($C$101)+1=SUMPRODUCT(($N$101:$N$124<>0)*1)+2,$N$126,IF(ROW()-ROW($C$101)+1=SUMPRODUCT(($N$101:$N$124<>0)*1)+3,$N$127,IF(ROW()-ROW($C$101)+1=SUMPRODUCT(($N$101:$N$124<>0)*1)+4,$N$128,"")))))} -> 100000 | M104: ='BDO Prequal'!B65 -> Brandon Johnson | N104: ='BDO Prequal'!C65 -> 100000
B105: {=IF(ROW()-ROW($B$101)+1<=SUMPRODUCT(($N$101:$N$124<>0)*1),INDEX($M$101:$M$124,_xlfn.AGGREGATE(15,6,(ROW($M$101:$M$124)-ROW($M$101)+1)/($N$101:$N$124<>0),ROW()-ROW($B$101)+1)),IF(ROW()-ROW($B$101)+1=SUMPRODUCT(($N$101:$N$124<>0)*1)+1,$M$125,IF(ROW()-ROW($B$101)+1=SUMPRODUCT(($N$101:$N$124<>0)*1)+2,$M$126,IF(ROW()-ROW($B$101)+1=SUMPRODUCT(($N$101:$N$124<>0)*1)+3,$M$127,IF(ROW()-ROW($B$101)+1=SUMPRODUCT(($N$101:$N$124<>0)*1)+4,$M$128,"")))))} -> Riku Patel | C105: {=IF(ROW()-ROW($C$101)+1<=SUMPRODUCT(($N$101:$N$124<>0)*1),INDEX($N$101:$N$124,_xlfn.AGGREGATE(15,6,(ROW($N$101:$N$124)-ROW($N$101)+1)/($N$101:$N$124<>0),ROW()-ROW($C$101)+1)),IF(ROW()-ROW($C$101)+1=SUMPRODUCT(($N$101:$N$124<>0)*1)+1,$N$125,IF(ROW()-ROW($C$101)+1=SUMPRODUCT(($N$101:$N$124<>0)*1)+2,$N$126,IF(ROW()-ROW($C$101)+1=SUMPRODUCT(($N$101:$N$124<>0)*1)+3,$N$127,IF(ROW()-ROW($C$101)+1=SUMPRODUCT(($N$101:$N$124<>0)*1)+4,$N$128,"")))))} -> 425000 | M105: ='BDO Prequal'!B66 -> Riku Patel | N105: ='BDO Prequal'!C66 -> 425000
B106: {=IF(ROW()-ROW($B$101)+1<=SUMPRODUCT(($N$101:$N$124<>0)*1),INDEX($M$101:$M$124,_xlfn.AGGREGATE(15,6,(ROW($M$101:$M$124)-ROW($M$101)+1)/($N$101:$N$124<>0),ROW()-ROW($B$101)+1)),IF(ROW()-ROW($B$101)+1=SUMPRODUCT(($N$101:$N$124<>0)*1)+1,$M$125,IF(ROW()-ROW($B$101)+1=SUMPRODUCT(($N$101:$N$124<>0)*1)+2,$M$126,IF(ROW()-ROW($B$101)+1=SUMPRODUCT(($N$101:$N$124<>0)*1)+3,$M$127,IF(ROW()-ROW($B$101)+1=SUMPRODUCT(($N$101:$N$124<>0)*1)+4,$M$128,"")))))} -> Divy Patel | C106: {=IF(ROW()-ROW($C$101)+1<=SUMPRODUCT(($N$101:$N$124<>0)*1),INDEX($N$101:$N$124,_xlfn.AGGREGATE(15,6,(ROW($N$101:$N$124)-ROW($N$101)+1)/($N$101:$N$124<>0),ROW()-ROW($C$101)+1)),IF(ROW()-ROW($C$101)+1=SUMPRODUCT(($N$101:$N$124<>0)*1)+1,$N$125,IF(ROW()-ROW($C$101)+1=SUMPRODUCT(($N$101:$N$124<>0)*1)+2,$N$126,IF(ROW()-ROW($C$101)+1=SUMPRODUCT(($N$101:$N$124<>0)*1)+3,$N$127,IF(ROW()-ROW($C$101)+1=SUMPRODUCT(($N$101:$N$124<>0)*1)+4,$N$128,"")))))} -> 657000 | M106: ='BDO Prequal'!B67 -> Divy Patel | N106: ='BDO Prequal'!C67 -> 657000
B107: {=IF(ROW()-ROW($B$101)+1<=SUMPRODUCT(($N$101:$N$124<>0)*1),INDEX($M$101:$M$124,_xlfn.AGGREGATE(15,6,(ROW($M$101:$M$124)-ROW($M$101)+1)/($N$101:$N$124<>0),ROW()-ROW($B$101)+1)),IF(ROW()-ROW($B$101)+1=SUMPRODUCT(($N$101:$N$124<>0)*1)+1,$M$125,IF(ROW()-ROW($B$101)+1=SUMPRODUCT(($N$101:$N$124<>0)*1)+2,$M$126,IF(ROW()-ROW($B$101)+1=SUMPRODUCT(($N$101:$N$124<>0)*1)+3,$M$127,IF(ROW()-ROW($B$101)+1=SUMPRODUCT(($N$101:$N$124<>0)*1)+4,$M$128,"")))))} -> Total Available Liquidity | C107: {=IF(ROW()-ROW($C$101)+1<=SUMPRODUCT(($N$101:$N$124<>0)*1),INDEX($N$101:$N$124,_xlfn.AGGREGATE(15,6,(ROW($N$101:$N$124)-ROW($N$101)+1)/($N$101:$N$124<>0),ROW()-ROW($C$101)+1)),IF(ROW()-ROW($C$101)+1=SUMPRODUCT(($N$101:$N$124<>0)*1)+1,$N$125,IF(ROW()-ROW($C$101)+1=SUMPRODUCT(($N$101:$N$124<>0)*1)+2,$N$126,IF(ROW()-ROW($C$101)+1=SUMPRODUCT(($N$101:$N$124<>0)*1)+3,$N$127,IF(ROW()-ROW($C$101)+1=SUMPRODUCT(($N$101:$N$124<>0)*1)+4,$N$128,"")))))} -> 2308100 | M107: ='BDO Prequal'!B68 -> Owner/Guarantor 6 | N107: ='BDO Prequal'!C68 -> 0
B108: {=IF(ROW()-ROW($B$101)+1<=SUMPRODUCT(($N$101:$N$124<>0)*1),INDEX($M$101:$M$124,_xlfn.AGGREGATE(15,6,(ROW($M$101:$M$124)-ROW($M$101)+1)/($N$101:$N$124<>0),ROW()-ROW($B$101)+1)),IF(ROW()-ROW($B$101)+1=SUMPRODUCT(($N$101:$N$124<>0)*1)+1,$M$125,IF(ROW()-ROW($B$101)+1=SUMPRODUCT(($N$101:$N$124<>0)*1)+2,$M$126,IF(ROW()-ROW($B$101)+1=SUMPRODUCT(($N$101:$N$124<>0)*1)+3,$M$127,IF(ROW()-ROW($B$101)+1=SUMPRODUCT(($N$101:$N$124<>0)*1)+4,$M$128,"")))))} -> Expected Injection | C108: {=IF(ROW()-ROW($C$101)+1<=SUMPRODUCT(($N$101:$N$124<>0)*1),INDEX($N$101:$N$124,_xlfn.AGGREGATE(15,6,(ROW($N$101:$N$124)-ROW($N$101)+1)/($N$101:$N$124<>0),ROW()-ROW($C$101)+1)),IF(ROW()-ROW($C$101)+1=SUMPRODUCT(($N$101:$N$124<>0)*1)+1,$N$125,IF(ROW()-ROW($C$101)+1=SUMPRODUCT(($N$101:$N$124<>0)*1)+2,$N$126,IF(ROW()-ROW($C$101)+1=SUMPRODUCT(($N$101:$N$124<>0)*1)+3,$N$127,IF(ROW()-ROW($C$101)+1=SUMPRODUCT(($N$101:$N$124<>0)*1)+4,$N$128,"")))))} -> -1571792 | M108: ='BDO Prequal'!B69 -> Owner/Guarantor 7 | N108: ='BDO Prequal'!C69 -> 0
B109: {=IF(ROW()-ROW($B$101)+1<=SUMPRODUCT(($N$101:$N$124<>0)*1),INDEX($M$101:$M$124,_xlfn.AGGREGATE(15,6,(ROW($M$101:$M$124)-ROW($M$101)+1)/($N$101:$N$124<>0),ROW()-ROW($B$101)+1)),IF(ROW()-ROW($B$101)+1=SUMPRODUCT(($N$101:$N$124<>0)*1)+1,$M$125,IF(ROW()-ROW($B$101)+1=SUMPRODUCT(($N$101:$N$124<>0)*1)+2,$M$126,IF(ROW()-ROW($B$101)+1=SUMPRODUCT(($N$101:$N$124<>0)*1)+3,$M$127,IF(ROW()-ROW($B$101)+1=SUMPRODUCT(($N$101:$N$124<>0)*1)+4,$M$128,"")))))} -> Working Capital in Loan | C109: {=IF(ROW()-ROW($C$101)+1<=SUMPRODUCT(($N$101:$N$124<>0)*1),INDEX($N$101:$N$124,_xlfn.AGGREGATE(15,6,(ROW($N$101:$N$124)-ROW($N$101)+1)/($N$101:$N$124<>0),ROW()-ROW($C$101)+1)),IF(ROW()-ROW($C$101)+1=SUMPRODUCT(($N$101:$N$124<>0)*1)+1,$N$125,IF(ROW()-ROW($C$101)+1=SUMPRODUCT(($N$101:$N$124<>0)*1)+2,$N$126,IF(ROW()-ROW($C$101)+1=SUMPRODUCT(($N$101:$N$124<>0)*1)+3,$N$127,IF(ROW()-ROW($C$101)+1=SUMPRODUCT(($N$101:$N$124<>0)*1)+4,$N$128,"")))))} -> 650500 | M109: ='BDO Prequal'!B70 -> Owner/Guarantor 8 | N109: ='BDO Prequal'!C70 -> 0
B110: {=IF(ROW()-ROW($B$101)+1<=SUMPRODUCT(($N$101:$N$124<>0)*1),INDEX($M$101:$M$124,_xlfn.AGGREGATE(15,6,(ROW($M$101:$M$124)-ROW($M$101)+1)/($N$101:$N$124<>0),ROW()-ROW($B$101)+1)),IF(ROW()-ROW($B$101)+1=SUMPRODUCT(($N$101:$N$124<>0)*1)+1,$M$125,IF(ROW()-ROW($B$101)+1=SUMPRODUCT(($N$101:$N$124<>0)*1)+2,$M$126,IF(ROW()-ROW($B$101)+1=SUMPRODUCT(($N$101:$N$124<>0)*1)+3,$M$127,IF(ROW()-ROW($B$101)+1=SUMPRODUCT(($N$101:$N$124<>0)*1)+4,$M$128,"")))))} -> Post Close Liquidity | C110: {=IF(ROW()-ROW($C$101)+1<=SUMPRODUCT(($N$101:$N$124<>0)*1),INDEX($N$101:$N$124,_xlfn.AGGREGATE(15,6,(ROW($N$101:$N$124)-ROW($N$101)+1)/($N$101:$N$124<>0),ROW()-ROW($C$101)+1)),IF(ROW()-ROW($C$101)+1=SUMPRODUCT(($N$101:$N$124<>0)*1)+1,$N$125,IF(ROW()-ROW($C$101)+1=SUMPRODUCT(($N$101:$N$124<>0)*1)+2,$N$126,IF(ROW()-ROW($C$101)+1=SUMPRODUCT(($N$101:$N$124<>0)*1)+3,$N$127,IF(ROW()-ROW($C$101)+1=SUMPRODUCT(($N$101:$N$124<>0)*1)+4,$N$128,"")))))} -> 1386808 | M110: ='BDO Prequal'!B71 -> Owner/Guarantor 9 | N110: ='BDO Prequal'!C71 -> 0
B111: {=IF(ROW()-ROW($B$101)+1<=SUMPRODUCT(($N$101:$N$124<>0)*1),INDEX($M$101:$M$124,_xlfn.AGGREGATE(15,6,(ROW($M$101:$M$124)-ROW($M$101)+1)/($N$101:$N$124<>0),ROW()-ROW($B$101)+1)),IF(ROW()-ROW($B$101)+1=SUMPRODUCT(($N$101:$N$124<>0)*1)+1,$M$125,IF(ROW()-ROW($B$101)+1=SUMPRODUCT(($N$101:$N$124<>0)*1)+2,$M$126,IF(ROW()-ROW($B$101)+1=SUMPRODUCT(($N$101:$N$124<>0)*1)+3,$M$127,IF(ROW()-ROW($B$101)+1=SUMPRODUCT(($N$101:$N$124<>0)*1)+4,$M$128,"")))))} | C111: {=IF(ROW()-ROW($C$101)+1<=SUMPRODUCT(($N$101:$N$124<>0)*1),INDEX($N$101:$N$124,_xlfn.AGGREGATE(15,6,(ROW($N$101:$N$124)-ROW($N$101)+1)/($N$101:$N$124<>0),ROW()-ROW($C$101)+1)),IF(ROW()-ROW($C$101)+1=SUMPRODUCT(($N$101:$N$124<>0)*1)+1,$N$125,IF(ROW()-ROW($C$101)+1=SUMPRODUCT(($N$101:$N$124<>0)*1)+2,$N$126,IF(ROW()-ROW($C$101)+1=SUMPRODUCT(($N$101:$N$124<>0)*1)+3,$N$127,IF(ROW()-ROW($C$101)+1=SUMPRODUCT(($N$101:$N$124<>0)*1)+4,$N$128,"")))))} | M111: ='BDO Prequal'!B72 -> Owner/Guarantor 10 | N111: ='BDO Prequal'!C72 -> 0
B112: {=IF(ROW()-ROW($B$101)+1<=SUMPRODUCT(($N$101:$N$124<>0)*1),INDEX($M$101:$M$124,_xlfn.AGGREGATE(15,6,(ROW($M$101:$M$124)-ROW($M$101)+1)/($N$101:$N$124<>0),ROW()-ROW($B$101)+1)),IF(ROW()-ROW($B$101)+1=SUMPRODUCT(($N$101:$N$124<>0)*1)+1,$M$125,IF(ROW()-ROW($B$101)+1=SUMPRODUCT(($N$101:$N$124<>0)*1)+2,$M$126,IF(ROW()-ROW($B$101)+1=SUMPRODUCT(($N$101:$N$124<>0)*1)+3,$M$127,IF(ROW()-ROW($B$101)+1=SUMPRODUCT(($N$101:$N$124<>0)*1)+4,$M$128,"")))))} | C112: {=IF(ROW()-ROW($C$101)+1<=SUMPRODUCT(($N$101:$N$124<>0)*1),INDEX($N$101:$N$124,_xlfn.AGGREGATE(15,6,(ROW($N$101:$N$124)-ROW($N$101)+1)/($N$101:$N$124<>0),ROW()-ROW($C$101)+1)),IF(ROW()-ROW($C$101)+1=SUMPRODUCT(($N$101:$N$124<>0)*1)+1,$N$125,IF(ROW()-ROW($C$101)+1=SUMPRODUCT(($N$101:$N$124<>0)*1)+2,$N$126,IF(ROW()-ROW($C$101)+1=SUMPRODUCT(($N$101:$N$124<>0)*1)+3,$N$127,IF(ROW()-ROW($C$101)+1=SUMPRODUCT(($N$101:$N$124<>0)*1)+4,$N$128,"")))))} | M112: ='BDO Prequal'!E62 -> Affiliate 1 | N112: ='BDO Prequal'!F62 -> 0
B113: {=IF(ROW()-ROW($B$101)+1<=SUMPRODUCT(($N$101:$N$124<>0)*1),INDEX($M$101:$M$124,_xlfn.AGGREGATE(15,6,(ROW($M$101:$M$124)-ROW($M$101)+1)/($N$101:$N$124<>0),ROW()-ROW($B$101)+1)),IF(ROW()-ROW($B$101)+1=SUMPRODUCT(($N$101:$N$124<>0)*1)+1,$M$125,IF(ROW()-ROW($B$101)+1=SUMPRODUCT(($N$101:$N$124<>0)*1)+2,$M$126,IF(ROW()-ROW($B$101)+1=SUMPRODUCT(($N$101:$N$124<>0)*1)+3,$M$127,IF(ROW()-ROW($B$101)+1=SUMPRODUCT(($N$101:$N$124<>0)*1)+4,$M$128,"")))))} | C113: {=IF(ROW()-ROW($C$101)+1<=SUMPRODUCT(($N$101:$N$124<>0)*1),INDEX($N$101:$N$124,_xlfn.AGGREGATE(15,6,(ROW($N$101:$N$124)-ROW($N$101)+1)/($N$101:$N$124<>0),ROW()-ROW($C$101)+1)),IF(ROW()-ROW($C$101)+1=SUMPRODUCT(($N$101:$N$124<>0)*1)+1,$N$125,IF(ROW()-ROW($C$101)+1=SUMPRODUCT(($N$101:$N$124<>0)*1)+2,$N$126,IF(ROW()-ROW($C$101)+1=SUMPRODUCT(($N$101:$N$124<>0)*1)+3,$N$127,IF(ROW()-ROW($C$101)+1=SUMPRODUCT(($N$101:$N$124<>0)*1)+4,$N$128,"")))))} | M113: ='BDO Prequal'!E63 -> Affiliate 2 | N113: ='BDO Prequal'!F63 -> 0
B114: {=IF(ROW()-ROW($B$101)+1<=SUMPRODUCT(($N$101:$N$124<>0)*1),INDEX($M$101:$M$124,_xlfn.AGGREGATE(15,6,(ROW($M$101:$M$124)-ROW($M$101)+1)/($N$101:$N$124<>0),ROW()-ROW($B$101)+1)),IF(ROW()-ROW($B$101)+1=SUMPRODUCT(($N$101:$N$124<>0)*1)+1,$M$125,IF(ROW()-ROW($B$101)+1=SUMPRODUCT(($N$101:$N$124<>0)*1)+2,$M$126,IF(ROW()-ROW($B$101)+1=SUMPRODUCT(($N$101:$N$124<>0)*1)+3,$M$127,IF(ROW()-ROW($B$101)+1=SUMPRODUCT(($N$101:$N$124<>0)*1)+4,$M$128,"")))))} | C114: {=IF(ROW()-ROW($C$101)+1<=SUMPRODUCT(($N$101:$N$124<>0)*1),INDEX($N$101:$N$124,_xlfn.AGGREGATE(15,6,(ROW($N$101:$N$124)-ROW($N$101)+1)/($N$101:$N$124<>0),ROW()-ROW($C$101)+1)),IF(ROW()-ROW($C$101)+1=SUMPRODUCT(($N$101:$N$124<>0)*1)+1,$N$125,IF(ROW()-ROW($C$101)+1=SUMPRODUCT(($N$101:$N$124<>0)*1)+2,$N$126,IF(ROW()-ROW($C$101)+1=SUMPRODUCT(($N$101:$N$124<>0)*1)+3,$N$127,IF(ROW()-ROW($C$101)+1=SUMPRODUCT(($N$101:$N$124<>0)*1)+4,$N$128,"")))))} | M114: ='BDO Prequal'!E64 -> Affiliate 3 | N114: ='BDO Prequal'!F64 -> 0
B115: {=IF(ROW()-ROW($B$101)+1<=SUMPRODUCT(($N$101:$N$124<>0)*1),INDEX($M$101:$M$124,_xlfn.AGGREGATE(15,6,(ROW($M$101:$M$124)-ROW($M$101)+1)/($N$101:$N$124<>0),ROW()-ROW($B$101)+1)),IF(ROW()-ROW($B$101)+1=SUMPRODUCT(($N$101:$N$124<>0)*1)+1,$M$125,IF(ROW()-ROW($B$101)+1=SUMPRODUCT(($N$101:$N$124<>0)*1)+2,$M$126,IF(ROW()-ROW($B$101)+1=SUMPRODUCT(($N$101:$N$124<>0)*1)+3,$M$127,IF(ROW()-ROW($B$101)+1=SUMPRODUCT(($N$101:$N$124<>0)*1)+4,$M$128,"")))))} | C115: {=IF(ROW()-ROW($C$101)+1<=SUMPRODUCT(($N$101:$N$124<>0)*1),INDEX($N$101:$N$124,_xlfn.AGGREGATE(15,6,(ROW($N$101:$N$124)-ROW($N$101)+1)/($N$101:$N$124<>0),ROW()-ROW($C$101)+1)),IF(ROW()-ROW($C$101)+1=SUMPRODUCT(($N$101:$N$124<>0)*1)+1,$N$125,IF(ROW()-ROW($C$101)+1=SUMPRODUCT(($N$101:$N$124<>0)*1)+2,$N$126,IF(ROW()-ROW($C$101)+1=SUMPRODUCT(($N$101:$N$124<>0)*1)+3,$N$127,IF(ROW()-ROW($C$101)+1=SUMPRODUCT(($N$101:$N$124<>0)*1)+4,$N$128,"")))))} | M115: ='BDO Prequal'!E65 -> Affiliate 4 | N115: ='BDO Prequal'!F65 -> 0
B116: {=IF(ROW()-ROW($B$101)+1<=SUMPRODUCT(($N$101:$N$124<>0)*1),INDEX($M$101:$M$124,_xlfn.AGGREGATE(15,6,(ROW($M$101:$M$124)-ROW($M$101)+1)/($N$101:$N$124<>0),ROW()-ROW($B$101)+1)),IF(ROW()-ROW($B$101)+1=SUMPRODUCT(($N$101:$N$124<>0)*1)+1,$M$125,IF(ROW()-ROW($B$101)+1=SUMPRODUCT(($N$101:$N$124<>0)*1)+2,$M$126,IF(ROW()-ROW($B$101)+1=SUMPRODUCT(($N$101:$N$124<>0)*1)+3,$M$127,IF(ROW()-ROW($B$101)+1=SUMPRODUCT(($N$101:$N$124<>0)*1)+4,$M$128,"")))))} | C116: {=IF(ROW()-ROW($C$101)+1<=SUMPRODUCT(($N$101:$N$124<>0)*1),INDEX($N$101:$N$124,_xlfn.AGGREGATE(15,6,(ROW($N$101:$N$124)-ROW($N$101)+1)/($N$101:$N$124<>0),ROW()-ROW($C$101)+1)),IF(ROW()-ROW($C$101)+1=SUMPRODUCT(($N$101:$N$124<>0)*1)+1,$N$125,IF(ROW()-ROW($C$101)+1=SUMPRODUCT(($N$101:$N$124<>0)*1)+2,$N$126,IF(ROW()-ROW($C$101)+1=SUMPRODUCT(($N$101:$N$124<>0)*1)+3,$N$127,IF(ROW()-ROW($C$101)+1=SUMPRODUCT(($N$101:$N$124<>0)*1)+4,$N$128,"")))))} | M116: ='BDO Prequal'!E66 -> Affiliate 5 | N116: ='BDO Prequal'!F66 -> 0
B117: {=IF(ROW()-ROW($B$101)+1<=SUMPRODUCT(($N$101:$N$124<>0)*1),INDEX($M$101:$M$124,_xlfn.AGGREGATE(15,6,(ROW($M$101:$M$124)-ROW($M$101)+1)/($N$101:$N$124<>0),ROW()-ROW($B$101)+1)),IF(ROW()-ROW($B$101)+1=SUMPRODUCT(($N$101:$N$124<>0)*1)+1,$M$125,IF(ROW()-ROW($B$101)+1=SUMPRODUCT(($N$101:$N$124<>0)*1)+2,$M$126,IF(ROW()-ROW($B$101)+1=SUMPRODUCT(($N$101:$N$124<>0)*1)+3,$M$127,IF(ROW()-ROW($B$101)+1=SUMPRODUCT(($N$101:$N$124<>0)*1)+4,$M$128,"")))))} | C117: {=IF(ROW()-ROW($C$101)+1<=SUMPRODUCT(($N$101:$N$124<>0)*1),INDEX($N$101:$N$124,_xlfn.AGGREGATE(15,6,(ROW($N$101:$N$124)-ROW($N$101)+1)/($N$101:$N$124<>0),ROW()-ROW($C$101)+1)),IF(ROW()-ROW($C$101)+1=SUMPRODUCT(($N$101:$N$124<>0)*1)+1,$N$125,IF(ROW()-ROW($C$101)+1=SUMPRODUCT(($N$101:$N$124<>0)*1)+2,$N$126,IF(ROW()-ROW($C$101)+1=SUMPRODUCT(($N$101:$N$124<>0)*1)+3,$N$127,IF(ROW()-ROW($C$101)+1=SUMPRODUCT(($N$101:$N$124<>0)*1)+4,$N$128,"")))))} | M117: ='BDO Prequal'!E67 -> Affiliate 6 | N117: ='BDO Prequal'!F67 -> 0
B118: {=IF(ROW()-ROW($B$101)+1<=SUMPRODUCT(($N$101:$N$124<>0)*1),INDEX($M$101:$M$124,_xlfn.AGGREGATE(15,6,(ROW($M$101:$M$124)-ROW($M$101)+1)/($N$101:$N$124<>0),ROW()-ROW($B$101)+1)),IF(ROW()-ROW($B$101)+1=SUMPRODUCT(($N$101:$N$124<>0)*1)+1,$M$125,IF(ROW()-ROW($B$101)+1=SUMPRODUCT(($N$101:$N$124<>0)*1)+2,$M$126,IF(ROW()-ROW($B$101)+1=SUMPRODUCT(($N$101:$N$124<>0)*1)+3,$M$127,IF(ROW()-ROW($B$101)+1=SUMPRODUCT(($N$101:$N$124<>0)*1)+4,$M$128,"")))))} | C118: {=IF(ROW()-ROW($C$101)+1<=SUMPRODUCT(($N$101:$N$124<>0)*1),INDEX($N$101:$N$124,_xlfn.AGGREGATE(15,6,(ROW($N$101:$N$124)-ROW($N$101)+1)/($N$101:$N$124<>0),ROW()-ROW($C$101)+1)),IF(ROW()-ROW($C$101)+1=SUMPRODUCT(($N$101:$N$124<>0)*1)+1,$N$125,IF(ROW()-ROW($C$101)+1=SUMPRODUCT(($N$101:$N$124<>0)*1)+2,$N$126,IF(ROW()-ROW($C$101)+1=SUMPRODUCT(($N$101:$N$124<>0)*1)+3,$N$127,IF(ROW()-ROW($C$101)+1=SUMPRODUCT(($N$101:$N$124<>0)*1)+4,$N$128,"")))))} | M118: ='BDO Prequal'!E68 -> Affiliate 7 | N118: ='BDO Prequal'!F68 -> 0
B119: {=IF(ROW()-ROW($B$101)+1<=SUMPRODUCT(($N$101:$N$124<>0)*1),INDEX($M$101:$M$124,_xlfn.AGGREGATE(15,6,(ROW($M$101:$M$124)-ROW($M$101)+1)/($N$101:$N$124<>0),ROW()-ROW($B$101)+1)),IF(ROW()-ROW($B$101)+1=SUMPRODUCT(($N$101:$N$124<>0)*1)+1,$M$125,IF(ROW()-ROW($B$101)+1=SUMPRODUCT(($N$101:$N$124<>0)*1)+2,$M$126,IF(ROW()-ROW($B$101)+1=SUMPRODUCT(($N$101:$N$124<>0)*1)+3,$M$127,IF(ROW()-ROW($B$101)+1=SUMPRODUCT(($N$101:$N$124<>0)*1)+4,$M$128,"")))))} | C119: {=IF(ROW()-ROW($C$101)+1<=SUMPRODUCT(($N$101:$N$124<>0)*1),INDEX($N$101:$N$124,_xlfn.AGGREGATE(15,6,(ROW($N$101:$N$124)-ROW($N$101)+1)/($N$101:$N$124<>0),ROW()-ROW($C$101)+1)),IF(ROW()-ROW($C$101)+1=SUMPRODUCT(($N$101:$N$124<>0)*1)+1,$N$125,IF(ROW()-ROW($C$101)+1=SUMPRODUCT(($N$101:$N$124<>0)*1)+2,$N$126,IF(ROW()-ROW($C$101)+1=SUMPRODUCT(($N$101:$N$124<>0)*1)+3,$N$127,IF(ROW()-ROW($C$101)+1=SUMPRODUCT(($N$101:$N$124<>0)*1)+4,$N$128,"")))))} | M119: ='BDO Prequal'!E69 -> Affiliate 8 | N119: ='BDO Prequal'!F69 -> 0
B120: {=IF(ROW()-ROW($B$101)+1<=SUMPRODUCT(($N$101:$N$124<>0)*1),INDEX($M$101:$M$124,_xlfn.AGGREGATE(15,6,(ROW($M$101:$M$124)-ROW($M$101)+1)/($N$101:$N$124<>0),ROW()-ROW($B$101)+1)),IF(ROW()-ROW($B$101)+1=SUMPRODUCT(($N$101:$N$124<>0)*1)+1,$M$125,IF(ROW()-ROW($B$101)+1=SUMPRODUCT(($N$101:$N$124<>0)*1)+2,$M$126,IF(ROW()-ROW($B$101)+1=SUMPRODUCT(($N$101:$N$124<>0)*1)+3,$M$127,IF(ROW()-ROW($B$101)+1=SUMPRODUCT(($N$101:$N$124<>0)*1)+4,$M$128,"")))))} | C120: {=IF(ROW()-ROW($C$101)+1<=SUMPRODUCT(($N$101:$N$124<>0)*1),INDEX($N$101:$N$124,_xlfn.AGGREGATE(15,6,(ROW($N$101:$N$124)-ROW($N$101)+1)/($N$101:$N$124<>0),ROW()-ROW($C$101)+1)),IF(ROW()-ROW($C$101)+1=SUMPRODUCT(($N$101:$N$124<>0)*1)+1,$N$125,IF(ROW()-ROW($C$101)+1=SUMPRODUCT(($N$101:$N$124<>0)*1)+2,$N$126,IF(ROW()-ROW($C$101)+1=SUMPRODUCT(($N$101:$N$124<>0)*1)+3,$N$127,IF(ROW()-ROW($C$101)+1=SUMPRODUCT(($N$101:$N$124<>0)*1)+4,$N$128,"")))))} | M120: ='BDO Prequal'!E70 -> Affiliate 9 | N120: ='BDO Prequal'!F70 -> 0
B121: {=IF(ROW()-ROW($B$101)+1<=SUMPRODUCT(($N$101:$N$124<>0)*1),INDEX($M$101:$M$124,_xlfn.AGGREGATE(15,6,(ROW($M$101:$M$124)-ROW($M$101)+1)/($N$101:$N$124<>0),ROW()-ROW($B$101)+1)),IF(ROW()-ROW($B$101)+1=SUMPRODUCT(($N$101:$N$124<>0)*1)+1,$M$125,IF(ROW()-ROW($B$101)+1=SUMPRODUCT(($N$101:$N$124<>0)*1)+2,$M$126,IF(ROW()-ROW($B$101)+1=SUMPRODUCT(($N$101:$N$124<>0)*1)+3,$M$127,IF(ROW()-ROW($B$101)+1=SUMPRODUCT(($N$101:$N$124<>0)*1)+4,$M$128,"")))))} | C121: {=IF(ROW()-ROW($C$101)+1<=SUMPRODUCT(($N$101:$N$124<>0)*1),INDEX($N$101:$N$124,_xlfn.AGGREGATE(15,6,(ROW($N$101:$N$124)-ROW($N$101)+1)/($N$101:$N$124<>0),ROW()-ROW($C$101)+1)),IF(ROW()-ROW($C$101)+1=SUMPRODUCT(($N$101:$N$124<>0)*1)+1,$N$125,IF(ROW()-ROW($C$101)+1=SUMPRODUCT(($N$101:$N$124<>0)*1)+2,$N$126,IF(ROW()-ROW($C$101)+1=SUMPRODUCT(($N$101:$N$124<>0)*1)+3,$N$127,IF(ROW()-ROW($C$101)+1=SUMPRODUCT(($N$101:$N$124<>0)*1)+4,$N$128,"")))))} | M121: ='BDO Prequal'!E71 -> Affiliate 10 | N121: ='BDO Prequal'!F71 -> 0
B122: {=IF(ROW()-ROW($B$101)+1<=SUMPRODUCT(($N$101:$N$124<>0)*1),INDEX($M$101:$M$124,_xlfn.AGGREGATE(15,6,(ROW($M$101:$M$124)-ROW($M$101)+1)/($N$101:$N$124<>0),ROW()-ROW($B$101)+1)),IF(ROW()-ROW($B$101)+1=SUMPRODUCT(($N$101:$N$124<>0)*1)+1,$M$125,IF(ROW()-ROW($B$101)+1=SUMPRODUCT(($N$101:$N$124<>0)*1)+2,$M$126,IF(ROW()-ROW($B$101)+1=SUMPRODUCT(($N$101:$N$124<>0)*1)+3,$M$127,IF(ROW()-ROW($B$101)+1=SUMPRODUCT(($N$101:$N$124<>0)*1)+4,$M$128,"")))))} | C122: {=IF(ROW()-ROW($C$101)+1<=SUMPRODUCT(($N$101:$N$124<>0)*1),INDEX($N$101:$N$124,_xlfn.AGGREGATE(15,6,(ROW($N$101:$N$124)-ROW($N$101)+1)/($N$101:$N$124<>0),ROW()-ROW($C$101)+1)),IF(ROW()-ROW($C$101)+1=SUMPRODUCT(($N$101:$N$124<>0)*1)+1,$N$125,IF(ROW()-ROW($C$101)+1=SUMPRODUCT(($N$101:$N$124<>0)*1)+2,$N$126,IF(ROW()-ROW($C$101)+1=SUMPRODUCT(($N$101:$N$124<>0)*1)+3,$N$127,IF(ROW()-ROW($C$101)+1=SUMPRODUCT(($N$101:$N$124<>0)*1)+4,$N$128,"")))))} | M122: ='BDO Prequal'!E72 -> Affiliate 11 | N122: ='BDO Prequal'!F72 -> 0
B123: {=IF(ROW()-ROW($B$101)+1<=SUMPRODUCT(($N$101:$N$124<>0)*1),INDEX($M$101:$M$124,_xlfn.AGGREGATE(15,6,(ROW($M$101:$M$124)-ROW($M$101)+1)/($N$101:$N$124<>0),ROW()-ROW($B$101)+1)),IF(ROW()-ROW($B$101)+1=SUMPRODUCT(($N$101:$N$124<>0)*1)+1,$M$125,IF(ROW()-ROW($B$101)+1=SUMPRODUCT(($N$101:$N$124<>0)*1)+2,$M$126,IF(ROW()-ROW($B$101)+1=SUMPRODUCT(($N$101:$N$124<>0)*1)+3,$M$127,IF(ROW()-ROW($B$101)+1=SUMPRODUCT(($N$101:$N$124<>0)*1)+4,$M$128,"")))))} | C123: {=IF(ROW()-ROW($C$101)+1<=SUMPRODUCT(($N$101:$N$124<>0)*1),INDEX($N$101:$N$124,_xlfn.AGGREGATE(15,6,(ROW($N$101:$N$124)-ROW($N$101)+1)/($N$101:$N$124<>0),ROW()-ROW($C$101)+1)),IF(ROW()-ROW($C$101)+1=SUMPRODUCT(($N$101:$N$124<>0)*1)+1,$N$125,IF(ROW()-ROW($C$101)+1=SUMPRODUCT(($N$101:$N$124<>0)*1)+2,$N$126,IF(ROW()-ROW($C$101)+1=SUMPRODUCT(($N$101:$N$124<>0)*1)+3,$N$127,IF(ROW()-ROW($C$101)+1=SUMPRODUCT(($N$101:$N$124<>0)*1)+4,$N$128,"")))))} | M123: ='BDO Prequal'!E73 -> Affiliate 12 | N123: ='BDO Prequal'!F73 -> 0
B124: {=IF(ROW()-ROW($B$101)+1<=SUMPRODUCT(($N$101:$N$124<>0)*1),INDEX($M$101:$M$124,_xlfn.AGGREGATE(15,6,(ROW($M$101:$M$124)-ROW($M$101)+1)/($N$101:$N$124<>0),ROW()-ROW($B$101)+1)),IF(ROW()-ROW($B$101)+1=SUMPRODUCT(($N$101:$N$124<>0)*1)+1,$M$125,IF(ROW()-ROW($B$101)+1=SUMPRODUCT(($N$101:$N$124<>0)*1)+2,$M$126,IF(ROW()-ROW($B$101)+1=SUMPRODUCT(($N$101:$N$124<>0)*1)+3,$M$127,IF(ROW()-ROW($B$101)+1=SUMPRODUCT(($N$101:$N$124<>0)*1)+4,$M$128,"")))))} | C124: {=IF(ROW()-ROW($C$101)+1<=SUMPRODUCT(($N$101:$N$124<>0)*1),INDEX($N$101:$N$124,_xlfn.AGGREGATE(15,6,(ROW($N$101:$N$124)-ROW($N$101)+1)/($N$101:$N$124<>0),ROW()-ROW($C$101)+1)),IF(ROW()-ROW($C$101)+1=SUMPRODUCT(($N$101:$N$124<>0)*1)+1,$N$125,IF(ROW()-ROW($C$101)+1=SUMPRODUCT(($N$101:$N$124<>0)*1)+2,$N$126,IF(ROW()-ROW($C$101)+1=SUMPRODUCT(($N$101:$N$124<>0)*1)+3,$N$127,IF(ROW()-ROW($C$101)+1=SUMPRODUCT(($N$101:$N$124<>0)*1)+4,$N$128,"")))))} | M124: ='BDO Prequal'!B73 -> Other Liquidity | N124: ='BDO Prequal'!C73 -> 0
B125: {=IF(ROW()-ROW($B$101)+1<=SUMPRODUCT(($N$101:$N$124<>0)*1),INDEX($M$101:$M$124,_xlfn.AGGREGATE(15,6,(ROW($M$101:$M$124)-ROW($M$101)+1)/($N$101:$N$124<>0),ROW()-ROW($B$101)+1)),IF(ROW()-ROW($B$101)+1=SUMPRODUCT(($N$101:$N$124<>0)*1)+1,$M$125,IF(ROW()-ROW($B$101)+1=SUMPRODUCT(($N$101:$N$124<>0)*1)+2,$M$126,IF(ROW()-ROW($B$101)+1=SUMPRODUCT(($N$101:$N$124<>0)*1)+3,$M$127,IF(ROW()-ROW($B$101)+1=SUMPRODUCT(($N$101:$N$124<>0)*1)+4,$M$128,"")))))} | C125: {=IF(ROW()-ROW($C$101)+1<=SUMPRODUCT(($N$101:$N$124<>0)*1),INDEX($N$101:$N$124,_xlfn.AGGREGATE(15,6,(ROW($N$101:$N$124)-ROW($N$101)+1)/($N$101:$N$124<>0),ROW()-ROW($C$101)+1)),IF(ROW()-ROW($C$101)+1=SUMPRODUCT(($N$101:$N$124<>0)*1)+1,$N$125,IF(ROW()-ROW($C$101)+1=SUMPRODUCT(($N$101:$N$124<>0)*1)+2,$N$126,IF(ROW()-ROW($C$101)+1=SUMPRODUCT(($N$101:$N$124<>0)*1)+3,$N$127,IF(ROW()-ROW($C$101)+1=SUMPRODUCT(($N$101:$N$124<>0)*1)+4,$N$128,"")))))} | M125: ='BDO Prequal'!H62 -> Total Available Liquidity | N125: ='BDO Prequal'!I62 -> 2308100
B126: {=IF(ROW()-ROW($B$101)+1<=SUMPRODUCT(($N$101:$N$124<>0)*1),INDEX($M$101:$M$124,_xlfn.AGGREGATE(15,6,(ROW($M$101:$M$124)-ROW($M$101)+1)/($N$101:$N$124<>0),ROW()-ROW($B$101)+1)),IF(ROW()-ROW($B$101)+1=SUMPRODUCT(($N$101:$N$124<>0)*1)+1,$M$125,IF(ROW()-ROW($B$101)+1=SUMPRODUCT(($N$101:$N$124<>0)*1)+2,$M$126,IF(ROW()-ROW($B$101)+1=SUMPRODUCT(($N$101:$N$124<>0)*1)+3,$M$127,IF(ROW()-ROW($B$101)+1=SUMPRODUCT(($N$101:$N$124<>0)*1)+4,$M$128,"")))))} | C126: {=IF(ROW()-ROW($C$101)+1<=SUMPRODUCT(($N$101:$N$124<>0)*1),INDEX($N$101:$N$124,_xlfn.AGGREGATE(15,6,(ROW($N$101:$N$124)-ROW($N$101)+1)/($N$101:$N$124<>0),ROW()-ROW($C$101)+1)),IF(ROW()-ROW($C$101)+1=SUMPRODUCT(($N$101:$N$124<>0)*1)+1,$N$125,IF(ROW()-ROW($C$101)+1=SUMPRODUCT(($N$101:$N$124<>0)*1)+2,$N$126,IF(ROW()-ROW($C$101)+1=SUMPRODUCT(($N$101:$N$124<>0)*1)+3,$N$127,IF(ROW()-ROW($C$101)+1=SUMPRODUCT(($N$101:$N$124<>0)*1)+4,$N$128,"")))))} | M126: ='BDO Prequal'!H64 -> Expected Injection | N126: ='BDO Prequal'!I64*-1 -> -1571792
B127: {=IF(ROW()-ROW($B$101)+1<=SUMPRODUCT(($N$101:$N$124<>0)*1),INDEX($M$101:$M$124,_xlfn.AGGREGATE(15,6,(ROW($M$101:$M$124)-ROW($M$101)+1)/($N$101:$N$124<>0),ROW()-ROW($B$101)+1)),IF(ROW()-ROW($B$101)+1=SUMPRODUCT(($N$101:$N$124<>0)*1)+1,$M$125,IF(ROW()-ROW($B$101)+1=SUMPRODUCT(($N$101:$N$124<>0)*1)+2,$M$126,IF(ROW()-ROW($B$101)+1=SUMPRODUCT(($N$101:$N$124<>0)*1)+3,$M$127,IF(ROW()-ROW($B$101)+1=SUMPRODUCT(($N$101:$N$124<>0)*1)+4,$M$128,"")))))} | C127: {=IF(ROW()-ROW($C$101)+1<=SUMPRODUCT(($N$101:$N$124<>0)*1),INDEX($N$101:$N$124,_xlfn.AGGREGATE(15,6,(ROW($N$101:$N$124)-ROW($N$101)+1)/($N$101:$N$124<>0),ROW()-ROW($C$101)+1)),IF(ROW()-ROW($C$101)+1=SUMPRODUCT(($N$101:$N$124<>0)*1)+1,$N$125,IF(ROW()-ROW($C$101)+1=SUMPRODUCT(($N$101:$N$124<>0)*1)+2,$N$126,IF(ROW()-ROW($C$101)+1=SUMPRODUCT(($N$101:$N$124<>0)*1)+3,$N$127,IF(ROW()-ROW($C$101)+1=SUMPRODUCT(($N$101:$N$124<>0)*1)+4,$N$128,"")))))} | M127: ='BDO Prequal'!H66 -> Working Capital in Loan | N127: ='BDO Prequal'!I66 -> 650500
...

Sheet Lists
A1: Color Scheme | D1: X/O | F1: True/False | H1: Basics | J1: Party | L1: Loan Type | N1: BDO | P1: Statement Type | R1: Amortization Basis | T1: Revenue Recognition | V1: Collateral Types | W1: Advance Rates | Y1: Adjust/Fix
A3: Title Bar | B3: Title Bar | D3: x | F3: True | H3: Yes | J3: T Bank | L3: N/A | N3: Audrey Wendel | P3: Tax Returns | R3: 30/360 | T3: Cash | V3: Primary Real Estate | W3: 0.85 | Y3: Monthly
A4: Drop Down | B4: Drop Down | F4: False | H4: No | J4: Borrower | L4: SBA 7(a) | N4: Becca Gilson | P4: Audited | R4: Actual/365 | T4: Accrual | V4: Secondary Real Estate | W4: 0.85 | Y4: Quarterly
A5: Calculated Cell | B5: Calculated Cell | H5: N/A | J5: Seller | L5: SBA 504 | N5: Ben Eakin | P5: Reviewed | R5: Actual/360 | T5: Hybrid | V5: Machinery & Equipment | W5: 0.5 | Y5: Annual
A6: Background | J6: CDC | L6: Debenture | N6: Glenn Giro | P6: Compiled | R6: Interest-Only | T6: Other | V6: Rolling Stock | W6: 0.5 | Y6: Fixed
A7: Module Backing | B7: Module Backing | J7: 3rd Party | L7: SBA Express Line | N7: Greg Swett | P7: Schedule C | R7: Full Standby | V7: Accounts Receivable | W7: 0.1
J8: Investor | L8: SBA CAPLine | N8: Kandace Moon | P8: Internal | V8: Inventory | W8: 0.1
J9: N/A | L9: Seller Note | N9: Kevin Coffman | P9: Form 10K | V9: Furniture and Fixtures | W9: 0.1
L10: USDA | N10: Marc Gilson | P10: Form 10Q | V10: Leasehold Improvements | W10: 0.05
L11: P&E | N11: Matthew Alm | P11: Other | V11: Miscellaneous | W11: 0
L12: Conventional | N12: Mike Ramsay
L13: Contribution | N13: Patrick Phillips
N14: Rod Rodriguez
N15: Steve Jones

Sheet Calculations
B2: ='BDO Prequal'!E16 -> T Bank | N2: Loan Amount | Q2: =IF(U2="SBA 7a",'BDO Prequal'!E55,0) -> 612591 | T2: Type | U2: =IF('BDO Prequal'!E17="SBA 7(a)","SBA 7a","Not 7a") -> SBA 7a | W2: Type: | X2: =IF('BDO Prequal'!E17=Lists!$L$10,"USDA","Not USDA") -> Not USDA | Y2: =B2 -> T Bank
B3: Basis | C3: Loan Amount | D3: Interest Rate | E3: Term (mo) | F3: Amo (mo) | G3: Start Month | H3: End Month | I3: # days | J3: Interest Rate Conversion | K3: Pmt | N3: Guaranteed Portion | Q3: =Q2*U3 -> 459443.25 | T3: Guarantee % | U3: ='BDO Prequal'!$J$30 -> 0.75 | W3: Guarantee %: | X3: ='BDO Prequal'!J31 -> 0.8
B4: 30/360 | C4: =IF('BDO Prequal'!$E$55>0,'BDO Prequal'!$E$55,'BDO Prequal'!$E$18) -> 612591 | D4: ='BDO Prequal'!$E$21 -> 0.0825 | E4: ='BDO Prequal'!$E$23*12 -> 120 | F4: ='BDO Prequal'!$E$24 -> 120 | G4: =TODAY()+45 -> 46205 | H4: =DATE(YEAR(G4)+F4/12,MONTH(G4),DAY(G4)) -> 49858 | I4: =H4-G4 -> 3653 | J4: =IFERROR((D4/360)*30*12,0) -> 0.0825 | K4: =IFERROR(PMT(J4/12,F4,-C4),0) -> 7513.5894 | N4: < | O4: 150000 | P4: 0.02 | Q4: =IF(Q2<=150000,Q3*0.02,0) -> 0 | X4: From UOP | Y4: =X3 -> 0.8 | Z4: Sum
B5: Actual/365 | C5: =IF('BDO Prequal'!$E$55>0,'BDO Prequal'!$E$55,'BDO Prequal'!$E$18) -> 612591 | D5: ='BDO Prequal'!$E$21 -> 0.0825 | E5: ='BDO Prequal'!$E$23*12 -> 120 | F5: ='BDO Prequal'!$E$24 -> 120 | G5: =TODAY()+45 -> 46205 | H5: =DATE(YEAR(G5)+F5/12,MONTH(G5),DAY(G5)) -> 49858 | I5: =H5-G5 -> 3653 | J5: =IFERROR((D5/(365*F5/12))*I5,0) -> 0.082567808 | K5: =IFERROR(PMT(J5/12,F5,-C5),0) -> 7515.7979 | N5: 150001 | O5: 700000 | P5: 0.03 | Q5: =IF(AND(Q2>150000,Q2<=700000),Q3*0.03,0) -> 13783.297 | W5: Guaranty Fee @ 3.0% | X5: ='BDO Prequal'!E55-'BDO Prequal'!E48-'BDO Prequal'!E49 -> 389784 | Y5: =X5*Y4 -> 311827.2 | Z5: =Y5*0.03 -> 9354.816
B6: Actual/360 | C6: =IF('BDO Prequal'!$E$55>0,'BDO Prequal'!$E$55,'BDO Prequal'!$E$18) -> 612591 | D6: ='BDO Prequal'!$E$21 -> 0.0825 | E6: ='BDO Prequal'!$E$23*12 -> 120 | F6: ='BDO Prequal'!$E$24 -> 120 | G6: =TODAY()+45 -> 46205 | H6: =DATE(YEAR(G6)+F6/12,MONTH(G6),DAY(G6)) -> 49858 | I6: =H6-G6 -> 3653 | J6: =IFERROR((D6/(360*F6/12))*I6,0) -> 0.083714583 | K6: =IFERROR(PMT(J6/12,F6,-C6),0) -> 7553.2024 | N6: 700001 | O6: 5000000 | P6: 0.035 | Q6: =IF(Q2>700000,MIN(Q3,1000000)*0.035,0) -> 0 | R6: Guaranty Fee | U6: =SUM(Q4:Q7) -> 13783.297 | W6: Guaranty Fee @ 3.5% - Const. | X6: ='BDO Prequal'!E48+'BDO Prequal'!E49 -> 222807 | Y6: =X6*Y4 -> 178245.6 | Z6: =Y6*0.035 -> 6238.596
B7: Interest-Only | C7: =IF('BDO Prequal'!$E$55>0,'BDO Prequal'!$E$55,'BDO Prequal'!$E$18) -> 612591 | D7: ='BDO Prequal'!$E$21 -> 0.0825 | E7: ='BDO Prequal'!$E$23*12 -> 120 | F7: ='BDO Prequal'!$E$24 -> 120 | G7: =TODAY()+45 -> 46205 | H7: =DATE(YEAR(G7)+F7/12,MONTH(G7),DAY(G7)) -> 49858 | I7: =H7-G7 -> 3653 | J7: =IFERROR((D7/(360*F7/12))*I7,0) -> 0.083714583 | K7: =IFERROR(C7*J7/12,0) -> 4273.5667 | P7: 0.0375 | Q7: =IF(AND(Q2>700000,Q3>1000000),(Q3-1000000)*0.0375,0) -> 0 | R7: Total Gty Fee (Rounded) | T7: =ROUNDUP(U6,-0.1) -> 13784 | W7: Total USDA Guaranty Fee | Z7: =ROUNDUP(Z5+Z6,0) -> 15594
B8: ='BDO Prequal'!F17 -> SBA 7(a) | N8: Loan Amount | Q8: =IF(U8="SBA 7a",'BDO Prequal'!F55,0) -> 2746607 | T8: Type | U8: =IF('BDO Prequal'!F17="SBA 7(a)","SBA 7a","Not 7a") -> SBA 7a | W8: Type: | X8: =IF('BDO Prequal'!F17=Lists!$L$10,"USDA","Not USDA") -> Not USDA | Y8: =B8 -> SBA 7(a)
B9: Basis | C9: Loan Amount | D9: Interest Rate | E9: Term (mo) | F9: Amo (mo) | G9: Start Month | H9: End Month | I9: # days | J9: Interest Rate Conversion | K9: Pmt | N9: Guaranteed Portion | Q9: =Q8*U9 -> 2059955.2 | T9: Guarantee % | U9: ='BDO Prequal'!$J$30 -> 0.75 | W9: Guarantee %: | X9: ='BDO Prequal'!J31 -> 0.8
B10: 30/360 | C10: =IF('BDO Prequal'!$F$55>0,'BDO Prequal'!$F$55,'BDO Prequal'!$F$18) -> 2746607 | D10: ='BDO Prequal'!$F$21 -> 0.0594 | E10: ='BDO Prequal'!$F$23*12 -> 120 | F10: ='BDO Prequal'!$F$24 -> 120 | G10: =TODAY()+45 -> 46205 | H10: =DATE(YEAR(G10)+F10/12,MONTH(G10),DAY(G10)) -> 49858 | I10: =H10-G10 -> 3653 | J10: =IFERROR((D10/360)*30*12,0) -> 0.0594 | K10: =IFERROR(PMT(J10/12,F10,-C10),0) -> 30410.278 | N10: < | O10: 150000 | P10: 0.02 | Q10: =IF(Q8<=150000,Q9*0.02,0) -> 0 | X10: From UOP | Y10: =X9 -> 0.8 | Z10: Sum
B11: Actual/365 | C11: =IF('BDO Prequal'!$F$55>0,'BDO Prequal'!$F$55,'BDO Prequal'!$F$18) -> 2746607 | D11: ='BDO Prequal'!$F$21 -> 0.0594 | E11: ='BDO Prequal'!$F$23*12 -> 120 | F11: ='BDO Prequal'!$F$24 -> 120 | G11: =TODAY()+45 -> 46205 | H11: =DATE(YEAR(G11)+F11/12,MONTH(G11),DAY(G11)) -> 49858 | I11: =H11-G11 -> 3653 | J11: =IFERROR((D11/(365*F11/12))*I11,0) -> 0.059448822 | K11: =IFERROR(PMT(J11/12,F11,-C11),0) -> 30417.001 | N11: 150001 | O11: 700000 | P11: 0.03 | Q11: =IF(AND(Q8>150000,Q8<=700000),Q9*0.03,0) -> 0 | W11: Guaranty Fee @ 3.0% | X11: ='BDO Prequal'!F55-'BDO Prequal'!F48-'BDO Prequal'!F49 -> 794749 | Y11: =X11*Y10 -> 635799.2 | Z11: =Y11*0.03 -> 19073.976
B12: Actual/360 | C12: =IF('BDO Prequal'!$F$55>0,'BDO Prequal'!$F$55,'BDO Prequal'!$F$18) -> 2746607 | D12: ='BDO Prequal'!$F$21 -> 0.0594 | E12: ='BDO Prequal'!$F$23*12 -> 120 | F12: ='BDO Prequal'!$F$24 -> 120 | G12: =TODAY()+45 -> 46205 | H12: =DATE(YEAR(G12)+F12/12,MONTH(G12),DAY(G12)) -> 49858 | I12: =H12-G12 -> 3653 | J12: =IFERROR((D12/(360*F12/12))*I12,0) -> 0.0602745 | K12: =IFERROR(PMT(J12/12,F12,-C12),0) -> 30530.844 | N12: 700001 | O12: 5000000 | P12: 0.035 | Q12: =IF(Q8>700000,MIN(Q9,1000000)*0.035,0) -> 35000 | R12: Guaranty Fee | U12: =SUM(Q10:Q13) -> 74748.322 | W12: Guaranty Fee @ 3.5% - Const. | X12: ='BDO Prequal'!F48+'BDO Prequal'!F49 -> 1951858 | Y12: =X12*Y10 -> 1561486.4 | Z12: =Y12*0.035 -> 54652.024
B13: Interest-Only | C13: =IF('BDO Prequal'!$F$55>0,'BDO Prequal'!$F$55,'BDO Prequal'!$F$18) -> 2746607 | D13: ='BDO Prequal'!$F$21 -> 0.0594 | E13: ='BDO Prequal'!$F$23*12 -> 120 | F13: ='BDO Prequal'!$F$24 -> 120 | G13: =TODAY()+45 -> 46205 | H13: =DATE(YEAR(G13)+F13/12,MONTH(G13),DAY(G13)) -> 49858 | I13: =H13-G13 -> 3653 | J13: =IFERROR((D13/(360*F13/12))*I13,0) -> 0.0602745 | K13: =IFERROR(C13*J13/12,0) -> 13795.864 | P13: 0.0375 | Q13: =IF(AND(Q8>700000,Q9>1000000),(Q9-1000000)*0.0375,0) -> 39748.322 | R13: Total Gty Fee (Rounded) | T13: =ROUNDUP(U12,-0.1) -> 74749 | W13: Total USDA Guaranty Fee | Z13: =ROUNDUP(Z11+Z12,0) -> 73726
B14: ='BDO Prequal'!G17 -> SBA 504 | N14: Loan Amount | Q14: =IF(U14="SBA 7a",'BDO Prequal'!G55,0) -> 0 | T14: Type | U14: =IF('BDO Prequal'!G17="SBA 7(a)","SBA 7a","Not 7a") -> Not 7a | W14: Type: | X14: =IF('BDO Prequal'!G17=Lists!$L$10,"USDA","Not USDA") -> Not USDA | Z14: =B14 -> SBA 504
B15: Basis | C15: Loan Amount | D15: Interest Rate | E15: Term (mo) | F15: Amo (mo) | G15: Start Month | H15: End Month | I15: # days | J15: Interest Rate Conversion | K15: Pmt | N15: Guaranteed Portion | Q15: =Q14*U15 -> 0 | T15: Guarantee % | U15: ='BDO Prequal'!$J$30 -> 0.75 | W15: Guarantee %: | X15: ='BDO Prequal'!J31 -> 0.8
B16: 30/360 | C16: =IF('BDO Prequal'!$G$55>0,'BDO Prequal'!$G$55,'BDO Prequal'!$G$18) -> 1350000 | D16: ='BDO Prequal'!$G$21 -> 0.095 | E16: ='BDO Prequal'!$G$23*12 -> 120 | F16: ='BDO Prequal'!$G$24 -> 120 | G16: =TODAY()+45 -> 46205 | H16: =DATE(YEAR(G16)+F16/12,MONTH(G16),DAY(G16)) -> 49858 | I16: =H16-G16 -> 3653 | J16: =IFERROR((D16/360)*30*12,0) -> 0.095 | K16: =IFERROR(PMT(J16/12,F16,-C16),0) -> 17468.67 | N16: < | O16: 150000 | P16: 0.02 | Q16: =IF(Q14<=150000,Q15*0.02,0) -> 0 | X16: From UOP | Y16: =X15 -> 0.8 | Z16: Sum
B17: Actual/365 | C17: =IF('BDO Prequal'!$G$55>0,'BDO Prequal'!$G$55,'BDO Prequal'!$G$18) -> 1350000 | D17: ='BDO Prequal'!$G$21 -> 0.095 | E17: ='BDO Prequal'!$G$23*12 -> 120 | F17: ='BDO Prequal'!$G$24 -> 120 | G17: =TODAY()+45 -> 46205 | H17: =DATE(YEAR(G17)+F17/12,MONTH(G17),DAY(G17)) -> 49858 | I17: =H17-G17 -> 3653 | J17: =IFERROR((D17/(365*F17/12))*I17,0) -> 0.095078082 | K17: =IFERROR(PMT(J17/12,F17,-C17),0) -> 17474.442 | N17: 150001 | O17: 700000 | P17: 0.03 | Q17: =IF(AND(Q14>150000,Q14<=700000),Q15*0.03,0) -> 0 | W17: Guaranty Fee @ 3.0% | X17: ='BDO Prequal'!G55-'BDO Prequal'!G48-'BDO Prequal'!G49 -> 1350000 | Y17: =X17*Y16 -> 1080000 | Z17: =Y17*0.03 -> 32400
B18: Actual/360 | C18: =IF('BDO Prequal'!$G$55>0,'BDO Prequal'!$G$55,'BDO Prequal'!$G$18) -> 1350000 | D18: ='BDO Prequal'!$G$21 -> 0.095 | E18: ='BDO Prequal'!$G$23*12 -> 120 | F18: ='BDO Prequal'!$G$24 -> 120 | G18: =TODAY()+45 -> 46205 | H18: =DATE(YEAR(G18)+F18/12,MONTH(G18),DAY(G18)) -> 49858 | I18: =H18-G18 -> 3653 | J18: =IFERROR((D18/(360*F18/12))*I18,0) -> 0.096398611 | K18: =IFERROR(PMT(J18/12,F18,-C18),0) -> 17572.212 | N18: 700001 | O18: 5000000 | P18: 0.035 | Q18: =IF(Q14>700000,MIN(Q15,1000000)*0.035,0) -> 0 | R18: Guaranty Fee | U18: =SUM(Q16:Q19) -> 0 | W18: Guaranty Fee @ 3.5% - Const. | X18: ='BDO Prequal'!G48+'BDO Prequal'!G49 -> 0 | Y18: =X18*Y16 -> 0 | Z18: =Y18*0.035 -> 0
B19: Interest-Only | C19: =IF('BDO Prequal'!$G$55>0,'BDO Prequal'!$G$55,'BDO Prequal'!$G$18) -> 1350000 | D19: ='BDO Prequal'!$G$21 -> 0.095 | E19: ='BDO Prequal'!$G$23*12 -> 120 | F19: ='BDO Prequal'!$G$24 -> 120 | G19: =TODAY()+45 -> 46205 | H19: =DATE(YEAR(G19)+F19/12,MONTH(G19),DAY(G19)) -> 49858 | I19: =H19-G19 -> 3653 | J19: =IFERROR((D19/(360*F19/12))*I19,0) -> 0.096398611 | K19: =IFERROR(C19*J19/12,0) -> 10844.844 | P19: 0.0375 | Q19: =IF(AND(Q14>700000,Q15>1000000),(Q15-1000000)*0.0375,0) -> 0 | R19: Total Gty Fee (Rounded) | T19: =ROUNDUP(U18,-0.1) -> 0 | W19: Total USDA Guaranty Fee | Z19: =ROUNDUP(Z17+Z18,0) -> 32400
