Workbook
Name Beg_Bal: #REF!
Name Beg_Bal: #REF!
Name Cum_Int: #REF!
Name Data: #REF!
Name DisbursementType: #REF!
Name DisbursementType: #REF!
Name End_Bal: #REF!
Name End_Bal: #REF!
Name EXPENSES: #REF!
Name EXPENSES: #REF!
Name Extra_Pay: #REF!
Name Extra_Pay: #REF!
Name Full_Print: #REF!
Name Full_Print: #REF!
Name Header_Row: _xlfn.ROW(#REF!)
Name Header_Row: _xlfn.ROW(#REF!)
Name Int: #REF!
Name Int: #REF!
Name Interest_Rate: #REF!
Name Interest_Rate: #REF!
Name Last_Row: IF(#REF!_Entered,Header_Row+#REF!_of_Payments,Header_Row)
Name Last_Row: IF(Scores!Values_Entered,Scores!Header_Row+Scores!Number_of_Payments,Scores!Header_Row)
Name Last_Row: IF(Values_Entered,Header_Row+Number_of_Payments,Header_Row)
Name Loan_Amount: #REF!
Name Loan_Amount: #REF!
Name Loan_Start: #REF!
Name Loan_Start: #REF!
Name Loan_Years: #REF!
Name Loan_Years: #REF!
Name MajorExpensesList: #REF!
Name MajorExpensesList: #REF!
Name Num_Pmt_Per_Year: #REF!
Name Num_Pmt_Per_Year: #REF!
Name Number_of_Payments: MATCH(0.01,End_Bal,-1)+1
Name Number_of_Payments: MATCH(0.01,Scores!End_Bal,-1)+1
Name Number_of_Payments: MATCH(0.01,End_Bal,-1)+1
Name Pay_Date: #REF!
Name Pay_Num: #REF!
Name Pay_Num: #REF!
Name Payment_Date: "DATE(YEAR(#REF!_Start);MONTH(#REF!_Start)+Payment_Number;DAY(#REF!_Start))"
Name Payment_Date: DATE(YEAR(Scores!Loan_Start),MONTH(Scores!Loan_Start)+Payment_Number,DAY(Scores!Loan_Start))
Name Payment_Date: DATE(YEAR(Loan_Start),MONTH(Loan_Start)+Payment_Number,DAY(Loan_Start))
Name Periodic_rate: Annual_interest_rate/Payments_per_year
Name Periodic_rate: Annual_interest_rate/Payments_per_year
Name Periodic_rate: Annual_interest_rate/Payments_per_year
Name Princ: #REF!
Name Princ: #REF!
Name Print_Area_Reset: OFFSET(Full_Print,0,0,#REF!_Row)
Name Print_Area_Reset: OFFSET(Scores!Full_Print,0,0,Scores!Last_Row)
Name Print_Area_Reset: OFFSET(Full_Print,0,0,Last_Row)
Name Sched_Pay: #REF!
Name Sched_Pay: #REF!
Name Scheduled_Extra_Payments: #REF!
Name Scheduled_Extra_Payments: #REF!
Name Scheduled_Interest_Rate: #REF!
Name Scheduled_Monthly_Payment: #REF!
Name Scheduled_Monthly_Payment: #REF!
Name Total_Interest: #REF!
Name Total_Pay: #REF!
Name Total_Pay: #REF!

Sheet Proposed Changes
B1: Tab 1 | C1: Tab 2 | D1: Tab 3 | E1: Tab 4 | F1: Tab 5 | G1: Tab 6 | H1: Tab 7 | I1: Tab 8
B2: Project Structure | C2: Sources & Uses | D2: Financials | E2: PFS | F2: Debt and Liquidity? | G2: Affiliates? | H2: Scores
B4: Sections
B5: Project Description | C5: Sources & Uses | D5: Income Statement | E5: 4) Personal Financial Analysis | F5: Global Debt Coverage? | G5: Income Statement Spreads | H5: Scores | I5: Charts?
B6: Loan Terms | C6: Total Project Cost | D6: Business Debt Schedule | F6: Business Debt Schedule ?
B7: Sources & Uses | C7: Closing Cost | F7: Liquidity Review?
C8: Misc Closing Cost
B10: Ben's Sections:
B11: 1) Loan Structure
B12: Loan Terms
B13: 2) Sources and Uses
B14: Liquidity Review
B15: 3) Income Statement
B16: Global Debt Coverage
B17: Business Debt Schedule
B18: 4) Affiliate Analysis
B19: Income Statement Spreads
B21: 4) Personal Financial Analysis
B22: 5) Collateral Summary

Sheet 1. Project Structure
B4: Project Description
B9: Loan Terms | M9: Loan Terms
C11: T Bank Loan | D11: Borrower | E11: Seller Note | F11: 3rd Party | N11: T Bank 7(a) | O11: Borrower | P11: Seller Note | Q11: T Bank 504 | R11: CDC 504
B12: Product Type | I12: SBA Gty % | J12: 0.75 | M12: Base Rate | N12: 0.075 | P12: 0.08 | Q12: 0.075 | R12: 0.0624
B13: Loan Amount/Injection | C13: =C45 -> 0 | D13: =D45 -> 0 | E13: =E45 -> 0 | F13: 0 | I13: Est. Appraisal Costs | J13: =SUM('2. Sources and Uses'!E43,'2. Sources and Uses'!E44,'2. Sources and Uses'!E45,'2. Sources and Uses'!E49) -> 0 | M13: Spread | N13: 0.015 | P13: 0 | Q13: 0.015 | R13: 0
B14: Base Rate | C14: 0.075 | E14: 0.08 | F14: 0.0624 | I14: Est. Environmental Report Costs | J14: =SUM('2. Sources and Uses'!E46,'2. Sources and Uses'!E47) -> 0 | M14: Indicative Rate | N14: =N12+N13 -> 0.09 | P14: =P12+P13 -> 0.08 | Q14: =Q12+Q13 -> 0.09 | R14: =R12+R13 -> 0.0624
B15: Spread | C15: 0.015 | E15: 0 | F15: 0 | I15: Packaging Fee | J15: =SUM('2. Sources and Uses'!E39) -> 2500 | M15: Amortization Basis | N15: Actual/365 | Q15: Actual/365
B16: Indicative Rate | C16: =C14+C15 -> 0.09 | E16: =E14+E15 -> 0.08 | F16: =F14+F15 -> 0.0624 | I16: Survey | J16: =SUM('2. Sources and Uses'!E42) -> 0 | M16: Term (years) | N16: 10 | P16: 10 | Q16: 10 | R16: 25
B17: Amortization Basis | C17: Actual/365 | I17: Business Valuation | J17: =SUM('2. Sources and Uses'!E48) -> 0 | M17: Amortization (mos) | N17: =N16*12 -> 120 | P17: =P16*12 -> 120 | Q17: =Q16*12 -> 120 | R17: =R16*12 -> 300
B18: Term (years) | C18: 10 | E18: 10 | F18: 25 | I18: Title / Escrow / Closing | J18: =SUM('2. Sources and Uses'!E40,'2. Sources and Uses'!E41) -> 0 | M18: Est Const Period (mths) | N18: 0
B19: Amortization (mos) | C19: =C18*12 -> 120 | E19: =E18*12 -> 120 | F19: =F18*12 -> 300 | I19: SBA GTY Fee | J19: ='2. Sources and Uses'!D80 -> 0
B20: Estimated Payment | C20: =IFERROR(INDEX('2. Sources and Uses'!K92:K94,MATCH($C$17,#REF!,0)),0) -> 0 | E20: =IFERROR(PMT(E16/12,E19,-E13),0) -> 0 | F20: =IFERROR(PMT(F16/12,F19,-F13),0) -> 0 | I20: Other Costs | J20: =E55-SUM(J13:K18) -> -2500
B21: Est Const Period (mths) | C21: 0 | I21: Total SBA Fees & Closing Costs | J21: =SUM(J13:K20) -> 0
B22: Are there funded SBA Loans in last 90 days? | D22: Amount? | E22: 0 | F22: Guarantee %? | G22: 0
B25: Sources and Uses of Proceeds | M25: Sources and Uses of Proceeds - 504
C27: T Bank Loan | D27: Borrower | E27: Seller Note | F27: 3rd Party | G27: Total | H27: SBA Term (yrs) | I27: % | J27: Wgt | N27: T Bank 504 | O27: Borrower | P27: Seller Note | Q27: CDC 504 | R27: Total
B28: Direct Project Costs | M28: Direct Project Costs
B29: Real Estate Acquisition | C29: ='2. Sources and Uses'!C6 -> 0 | D29: ='2. Sources and Uses'!D6 -> 0 | E29: ='2. Sources and Uses'!E6 -> 0 | F29: ='2. Sources and Uses'!F6 -> 0 | G29: ='2. Sources and Uses'!G6 -> 0 | H29: ='2. Sources and Uses'!H6 -> 25 | I29: ='2. Sources and Uses'!I6 -> 0 | J29: ='2. Sources and Uses'!J6 -> 0 | M29: Real Estate Acquisition | N29: ='2. Sources and Uses'!N6 -> 0 | O29: ='2. Sources and Uses'!O6 -> 0 | P29: ='2. Sources and Uses'!P6 -> 0 | Q29: ='2. Sources and Uses'!Q6 -> 0 | R29: ='2. Sources and Uses'!R6 -> 0
B30: Debt Refi - CRE | C30: ='2. Sources and Uses'!C7 -> 0 | D30: ='2. Sources and Uses'!D7 -> 0 | E30: ='2. Sources and Uses'!E7 -> 0 | F30: ='2. Sources and Uses'!F7 -> 0 | G30: ='2. Sources and Uses'!G7 -> 0 | H30: ='2. Sources and Uses'!H7 -> 25 | I30: ='2. Sources and Uses'!I7 -> 0 | J30: ='2. Sources and Uses'!J7 -> 0 | M30: Debt Refi - CRE | N30: ='2. Sources and Uses'!N7 -> 0 | O30: ='2. Sources and Uses'!O7 -> 0 | P30: ='2. Sources and Uses'!P7 -> 0 | Q30: ='2. Sources and Uses'!Q7 -> 0 | R30: ='2. Sources and Uses'!R7 -> 0
B31: Debt Refi - Non-CRE | C31: ='2. Sources and Uses'!C8 -> 0 | D31: ='2. Sources and Uses'!D8 -> 0 | E31: ='2. Sources and Uses'!E8 -> 0 | F31: ='2. Sources and Uses'!F8 -> 0 | G31: ='2. Sources and Uses'!G8 -> 0 | H31: ='2. Sources and Uses'!H8 -> 10 | I31: ='2. Sources and Uses'!I8 -> 0 | J31: ='2. Sources and Uses'!J8 -> 0 | M31: Debt Refi - Non-CRE | N31: ='2. Sources and Uses'!N8 -> 0 | O31: ='2. Sources and Uses'!O8 -> 0 | P31: ='2. Sources and Uses'!P8 -> 0 | Q31: ='2. Sources and Uses'!Q8 -> 0 | R31: ='2. Sources and Uses'!R8 -> 0
B32: Machinery & Equipment | C32: ='2. Sources and Uses'!C9 -> 0 | D32: ='2. Sources and Uses'!D9 -> 0 | E32: ='2. Sources and Uses'!E9 -> 0 | F32: ='2. Sources and Uses'!F9 -> 0 | G32: ='2. Sources and Uses'!G9 -> 0 | H32: ='2. Sources and Uses'!H9 -> 10 | I32: ='2. Sources and Uses'!I9 -> 0 | J32: ='2. Sources and Uses'!J9 -> 0 | M32: Machinery & Equipment | N32: ='2. Sources and Uses'!N9 -> 0 | O32: ='2. Sources and Uses'!O9 -> 0 | P32: ='2. Sources and Uses'!P9 -> 0 | Q32: ='2. Sources and Uses'!Q9 -> 0 | R32: ='2. Sources and Uses'!R9 -> 0
B33: Furniture & Fixtures (TIs) | C33: ='2. Sources and Uses'!C10 -> 0 | D33: ='2. Sources and Uses'!D10 -> 0 | E33: ='2. Sources and Uses'!E10 -> 0 | F33: ='2. Sources and Uses'!F10 -> 0 | G33: ='2. Sources and Uses'!G10 -> 0 | H33: ='2. Sources and Uses'!H10 -> 10 | I33: ='2. Sources and Uses'!I10 -> 0 | J33: ='2. Sources and Uses'!J10 -> 0 | M33: Furniture & Fixtures (TIs) | N33: ='2. Sources and Uses'!N10 -> 0 | O33: ='2. Sources and Uses'!O10 -> 0 | P33: ='2. Sources and Uses'!P10 -> 0 | Q33: ='2. Sources and Uses'!Q10 -> 0 | R33: ='2. Sources and Uses'!R10 -> 0
B34: Inventory | C34: ='2. Sources and Uses'!C11 -> 0 | D34: ='2. Sources and Uses'!D11 -> 0 | E34: ='2. Sources and Uses'!E11 -> 0 | F34: ='2. Sources and Uses'!F11 -> 0 | G34: ='2. Sources and Uses'!G11 -> 0 | H34: ='2. Sources and Uses'!H11 -> 10 | I34: ='2. Sources and Uses'!I11 -> 0 | J34: ='2. Sources and Uses'!J11 -> 0 | M34: Inventory | N34: ='2. Sources and Uses'!N11 -> 0 | O34: ='2. Sources and Uses'!O11 -> 0 | P34: ='2. Sources and Uses'!P11 -> 0 | Q34: ='2. Sources and Uses'!Q11 -> 0 | R34: ='2. Sources and Uses'!R11 -> 0
B35: Working Capital | C35: ='2. Sources and Uses'!C12 -> 0 | D35: ='2. Sources and Uses'!D12 -> 0 | E35: ='2. Sources and Uses'!E12 -> 0 | F35: ='2. Sources and Uses'!F12 -> 0 | G35: ='2. Sources and Uses'!G12 -> 0 | H35: ='2. Sources and Uses'!H12 -> 10 | I35: ='2. Sources and Uses'!I12 -> 0 | J35: ='2. Sources and Uses'!J12 -> 0 | M35: Working Capital | N35: ='2. Sources and Uses'!N12 -> 0 | O35: ='2. Sources and Uses'!O12 -> 0 | P35: ='2. Sources and Uses'!P12 -> 0 | Q35: ='2. Sources and Uses'!Q12 -> 0 | R35: ='2. Sources and Uses'!R12 -> 0
B36: Working Capital - Pre Opening | C36: ='2. Sources and Uses'!C13 -> 0 | D36: ='2. Sources and Uses'!D13 -> 0 | E36: ='2. Sources and Uses'!E13 -> 0 | F36: ='2. Sources and Uses'!F13 -> 0 | G36: ='2. Sources and Uses'!G13 -> 0 | H36: ='2. Sources and Uses'!H13 -> 10 | I36: ='2. Sources and Uses'!I13 -> 0 | J36: ='2. Sources and Uses'!J13 -> 0 | M36: Working Capital - Pre Opening | N36: ='2. Sources and Uses'!N13 -> 0 | O36: ='2. Sources and Uses'!O13 -> 0 | P36: ='2. Sources and Uses'!P13 -> 0 | Q36: ='2. Sources and Uses'!Q13 -> 0 | R36: ='2. Sources and Uses'!R13 -> 0
B37: Business Acquisition | C37: ='2. Sources and Uses'!C14 -> 0 | D37: ='2. Sources and Uses'!D14 -> 0 | E37: ='2. Sources and Uses'!E14 -> 0 | F37: ='2. Sources and Uses'!F14 -> 0 | G37: ='2. Sources and Uses'!G14 -> 0 | H37: ='2. Sources and Uses'!H14 -> 10 | I37: ='2. Sources and Uses'!I14 -> 0 | J37: ='2. Sources and Uses'!J14 -> 0 | M37: Business Acquisition | N37: ='2. Sources and Uses'!N14 -> 0 | O37: ='2. Sources and Uses'!O14 -> 0 | P37: ='2. Sources and Uses'!P14 -> 0 | Q37: ='2. Sources and Uses'!Q14 -> 0 | R37: ='2. Sources and Uses'!R14 -> 0
B38: Franchise Fees | C38: ='2. Sources and Uses'!C15 -> 0 | D38: ='2. Sources and Uses'!D15 -> 0 | E38: ='2. Sources and Uses'!E15 -> 0 | F38: ='2. Sources and Uses'!F15 -> 0 | G38: ='2. Sources and Uses'!G15 -> 0 | H38: ='2. Sources and Uses'!H15 -> 10 | I38: ='2. Sources and Uses'!I15 -> 0 | J38: ='2. Sources and Uses'!J15 -> 0 | M38: Franchise Fees | N38: ='2. Sources and Uses'!N15 -> 0 | O38: ='2. Sources and Uses'!O15 -> 0 | P38: ='2. Sources and Uses'!P15 -> 0 | Q38: ='2. Sources and Uses'!Q15 -> 0 | R38: ='2. Sources and Uses'!R15 -> 0
B39: Construction Hard Costs | C39: ='2. Sources and Uses'!C16 -> 0 | D39: ='2. Sources and Uses'!D16 -> 0 | E39: ='2. Sources and Uses'!E16 -> 0 | F39: ='2. Sources and Uses'!F16 -> 0 | G39: ='2. Sources and Uses'!G16 -> 0 | H39: ='2. Sources and Uses'!H16 -> 25 | I39: ='2. Sources and Uses'!I16 -> 0 | J39: ='2. Sources and Uses'!J16 -> 0 | M39: Construction Hard Costs | N39: ='2. Sources and Uses'!N16 -> 0 | O39: ='2. Sources and Uses'!O16 -> 0 | P39: ='2. Sources and Uses'!P16 -> 0 | Q39: ='2. Sources and Uses'!Q16 -> 0 | R39: ='2. Sources and Uses'!R16 -> 0
B40: Interim Interest Reserve | C40: ='2. Sources and Uses'!C17 -> 0 | D40: ='2. Sources and Uses'!D17 -> 0 | E40: ='2. Sources and Uses'!E17 -> 0 | F40: ='2. Sources and Uses'!F17 -> 0 | G40: ='2. Sources and Uses'!G17 -> 0 | H40: ='2. Sources and Uses'!H17 -> 25 | I40: ='2. Sources and Uses'!I17 -> 0 | J40: ='2. Sources and Uses'!J17 -> 0 | K40: Const Contigency | M40: Interim Interest Reserve | N40: ='2. Sources and Uses'!N17 -> 0 | O40: ='2. Sources and Uses'!O17 -> 0 | P40: ='2. Sources and Uses'!P17 -> 0 | Q40: ='2. Sources and Uses'!Q17 -> 0 | R40: ='2. Sources and Uses'!R17 -> 0 | S40: Const Contigency
B41: Construction Contingency | C41: ='2. Sources and Uses'!C18 -> 0 | D41: ='2. Sources and Uses'!D18 -> 0 | E41: ='2. Sources and Uses'!E18 -> 0 | F41: ='2. Sources and Uses'!F18 -> 0 | G41: ='2. Sources and Uses'!G18 -> 0 | H41: ='2. Sources and Uses'!H18 -> 25 | I41: ='2. Sources and Uses'!I18 -> 0 | J41: ='2. Sources and Uses'!J18 -> 0 | K41: 0.1 | M41: Construction Contingency | N41: ='2. Sources and Uses'!N18 -> 0 | O41: ='2. Sources and Uses'!O18 -> 0 | P41: ='2. Sources and Uses'!P18 -> 0 | Q41: ='2. Sources and Uses'!Q18 -> 0 | R41: ='2. Sources and Uses'!R18 -> 0 | S41: ='2. Sources and Uses'!S18 -> 0.1
B42: Other Construction Soft Costs | C42: ='2. Sources and Uses'!C19 -> 0 | D42: ='2. Sources and Uses'!D19 -> 0 | E42: ='2. Sources and Uses'!E19 -> 0 | F42: ='2. Sources and Uses'!F19 -> 0 | G42: ='2. Sources and Uses'!G19 -> 0 | H42: ='2. Sources and Uses'!H19 -> 25 | I42: ='2. Sources and Uses'!I19 -> 0 | J42: ='2. Sources and Uses'!J19 -> 0 | M42: Other Construction Soft Costs | N42: ='2. Sources and Uses'!N19 -> 0 | O42: ='2. Sources and Uses'!O19 -> 0 | P42: ='2. Sources and Uses'!P19 -> 0 | Q42: ='2. Sources and Uses'!Q19 -> 0 | R42: ='2. Sources and Uses'!R19 -> 0
B43: Closing Costs | C43: ='2. Sources and Uses'!C20 -> 0 | D43: ='2. Sources and Uses'!D20 -> 0 | E43: ='2. Sources and Uses'!E20 -> 0 | F43: ='2. Sources and Uses'!F20 -> 0 | G43: ='2. Sources and Uses'!G20 -> 0 | H43: ='2. Sources and Uses'!H20 -> 10 | I43: ='2. Sources and Uses'!I20 -> 0 | J43: ='2. Sources and Uses'!J20 -> 0 | M43: Closing Costs | N43: ='2. Sources and Uses'!N20 -> 0 | O43: ='2. Sources and Uses'!O20 -> 0 | P43: ='2. Sources and Uses'!P20 -> 0 | Q43: ='2. Sources and Uses'!Q20 -> 0 | R43: ='2. Sources and Uses'!R20 -> 0
B44: SBA Gty Fee | C44: ='2. Sources and Uses'!C21 -> 0 | D44: ='2. Sources and Uses'!D21 -> 0 | E44: ='2. Sources and Uses'!E21 | F44: ='2. Sources and Uses'!F21 | G44: ='2. Sources and Uses'!G21 -> 0 | H44: ='2. Sources and Uses'!H21 -> 10 | I44: ='2. Sources and Uses'!I21 -> 0 | J44: ='2. Sources and Uses'!J21 -> 0 | M44: SBA Gty Fee | N44: ='2. Sources and Uses'!N21 -> 0 | O44: ='2. Sources and Uses'!O21 -> 0 | P44: ='2. Sources and Uses'!P21 | Q44: ='2. Sources and Uses'!Q21 | R44: ='2. Sources and Uses'!R21
C45: ='2. Sources and Uses'!C22 -> 0 | D45: ='2. Sources and Uses'!D22 -> 0 | E45: ='2. Sources and Uses'!E22 -> 0 | F45: ='2. Sources and Uses'!F22 -> 0 | G45: ='2. Sources and Uses'!G22 -> 0 | H45: ='2. Sources and Uses'!H22 | I45: ='2. Sources and Uses'!I22 -> Weighted Term | J45: ='2. Sources and Uses'!J22 -> 0 | N45: ='2. Sources and Uses'!N22 -> 0 | O45: ='2. Sources and Uses'!O22 -> 0 | P45: ='2. Sources and Uses'!P22 -> 0 | Q45: ='2. Sources and Uses'!Q22 -> 0 | R45: ='2. Sources and Uses'!R22 -> 0
C46: ='2. Sources and Uses'!C23 -> 0 | D46: ='2. Sources and Uses'!D23 -> 0 | E46: ='2. Sources and Uses'!E23 -> 0 | F46: ='2. Sources and Uses'!F23 -> 0 | G46: ='2. Sources and Uses'!G23 -> 0 | N46: ='2. Sources and Uses'!N23 -> 0 | O46: ='2. Sources and Uses'!O23 -> 0 | P46: ='2. Sources and Uses'!P23 -> 0 | Q46: ='2. Sources and Uses'!Q23 -> 0 | R46: ='2. Sources and Uses'!R23 -> 0

Sheet 2. Sources and Uses
B2: Sources and Uses of Proceeds | M2: Sources and Uses of Proceeds - 504
C4: T Bank Loan | D4: Borrower | E4: Seller Note | F4: 3rd Party | G4: Total | H4: SBA Term (yrs) | I4: % | J4: Wgt | N4: T Bank 504 | O4: Borrower | P4: Seller Note | Q4: CDC 504 | R4: Total
B5: Direct Project Costs | M5: Direct Project Costs
B6: Real Estate Acquisition | C6: =G6-SUM(D6:F6) -> 0 | D6: 0 | E6: 0 | F6: 0 | G6: 0 | H6: 25 | I6: =IF($C$22=0,0,C6/$C$22) -> 0 | J6: =H6*I6 -> 0 | M6: Real Estate Acquisition | N6: =R6-SUM(O6:Q6) -> 0 | O6: 0 | P6: 0 | Q6: 0 | R6: 0
B7: Debt Refi - CRE | C7: =G7-SUM(D7:F7) -> 0 | D7: 0 | E7: 0 | F7: 0 | G7: 0 | H7: 25 | I7: =IF($C$22=0,0,C7/$C$22) -> 0 | J7: =H7*I7 -> 0 | M7: Debt Refi - CRE | N7: =R7-SUM(O7:Q7) -> 0 | O7: 0 | P7: 0 | Q7: 0 | R7: 0
B8: Debt Refi - Non-CRE | C8: =G8-SUM(D8:F8) -> 0 | D8: 0 | E8: 0 | F8: 0 | G8: 0 | H8: 10 | I8: =IF($C$22=0,0,C8/$C$22) -> 0 | J8: =H8*I8 -> 0 | M8: Debt Refi - Non-CRE | N8: =R8-SUM(O8:Q8) -> 0 | O8: 0 | P8: 0 | Q8: 0 | R8: 0
B9: Machinery & Equipment | C9: =G9-SUM(D9:F9) -> 0 | D9: 0 | E9: 0 | F9: 0 | G9: 0 | H9: 10 | I9: =IF($C$22=0,0,C9/$C$22) -> 0 | J9: =H9*I9 -> 0 | M9: Machinery & Equipment | N9: =R9-SUM(O9:Q9) -> 0 | O9: 0 | P9: 0 | Q9: 0 | R9: 0
B10: Furniture & Fixtures (TIs) | C10: =G10-SUM(D10:F10) -> 0 | D10: 0 | E10: 0 | F10: 0 | G10: 0 | H10: 10 | I10: =IF($C$22=0,0,C10/$C$22) -> 0 | J10: =H10*I10 -> 0 | M10: Furniture & Fixtures (TIs) | N10: =R10-SUM(O10:Q10) -> 0 | O10: 0 | P10: 0 | Q10: 0 | R10: 0
B11: Inventory | C11: =G11-SUM(D11:F11) -> 0 | D11: 0 | E11: 0 | F11: 0 | G11: 0 | H11: 10 | I11: =IF($C$22=0,0,C11/$C$22) -> 0 | J11: =H11*I11 -> 0 | M11: Inventory | N11: =R11-SUM(O11:Q11) -> 0 | O11: 0 | P11: 0 | Q11: 0 | R11: 0
B12: Working Capital | C12: =G12-SUM(D12:F12) -> 0 | D12: 0 | E12: 0 | F12: 0 | G12: 0 | H12: 10 | I12: =IF($C$22=0,0,C12/$C$22) -> 0 | J12: =H12*I12 -> 0 | M12: Working Capital | N12: =R12-SUM(O12:Q12) -> 0 | O12: 0 | P12: 0 | Q12: 0 | R12: 0
B13: Working Capital - Pre Opening | C13: =G13-SUM(D13:F13) -> 0 | D13: 0 | E13: 0 | F13: 0 | G13: 0 | H13: 10 | I13: =IF($C$22=0,0,C13/$C$22) -> 0 | J13: =H13*I13 -> 0 | M13: Working Capital - Pre Opening | N13: =R13-SUM(O13:Q13) -> 0 | O13: 0 | P13: 0 | Q13: 0 | R13: 0
B14: Business Acquisition | C14: =G14-SUM(D14:F14) -> 0 | D14: 0 | E14: 0 | F14: 0 | G14: 0 | H14: 10 | I14: =IF($C$22=0,0,C14/$C$22) -> 0 | J14: =H14*I14 -> 0 | M14: Business Acquisition | N14: =R14-SUM(O14:Q14) -> 0 | O14: 0 | P14: 0 | Q14: 0 | R14: 0
B15: Franchise Fees | C15: =G15-SUM(D15:F15) -> 0 | D15: 0 | E15: 0 | F15: 0 | G15: 0 | H15: 10 | I15: =IF($C$22=0,0,C15/$C$22) -> 0 | J15: =H15*I15 -> 0 | M15: Franchise Fees | N15: =R15-SUM(O15:Q15) -> 0 | O15: 0 | P15: 0 | Q15: 0 | R15: 0
B16: Construction Hard Costs | C16: =G16-SUM(D16:F16) -> 0 | D16: 0 | E16: 0 | F16: 0 | G16: 0 | H16: 25 | I16: =IF($C$22=0,0,C16/$C$22) -> 0 | J16: =H16*I16 -> 0 | M16: Construction Hard Costs | N16: =R16-SUM(O16:Q16) -> 0 | O16: 0 | P16: 0 | Q16: 0 | R16: 0
B17: Interim Interest Reserve | C17: 0 | D17: =G17-C17 -> 0 | E17: 0 | F17: 0 | G17: =ROUND(((C6+F6)*'1. Project Structure'!C16/12)*'1. Project Structure'!C21+((C22-C6+F22-F6)*'1. Project Structure'!C16*0.6/12)*'1. Project Structure'!C21,0) -> 0 | H17: 25 | I17: =IF($C$22=0,0,C17/$C$22) -> 0 | J17: =H17*I17 -> 0 | K17: Const Contigency | M17: Interim Interest Reserve | N17: 0 | O17: =R17-N17 -> 0 | P17: 0 | Q17: 0 | R17: =ROUND(((N6+Q6)*'1. Project Structure'!N14/12)*'1. Project Structure'!N18+((N22-N6+Q22-Q6)*'1. Project Structure'!N14*0.6/12)*'1. Project Structure'!N18,0) -> 0 | S17: Const Contigency
B18: Construction Contingency | C18: =G18-D18-E18-F18 -> 0 | D18: 0 | E18: 0 | F18: 0 | G18: =ROUND(G17*K18,0) -> 0 | H18: 25 | I18: =IF($C$22=0,0,C18/$C$22) -> 0 | J18: =H18*I18 -> 0 | K18: 0.1 | M18: Construction Contingency | N18: =R18-O18-P18-Q18 -> 0 | O18: 0 | P18: 0 | Q18: 0 | R18: =ROUND(R17*V18,0) -> 0 | S18: 0.1
B19: Other Construction Soft Costs | C19: =G19-SUM(D19:F19) -> 0 | D19: 0 | E19: 0 | F19: 0 | G19: 0 | H19: 25 | I19: =IF($C$22=0,0,C19/$C$22) -> 0 | J19: =H19*I19 -> 0 | M19: Other Construction Soft Costs | N19: =R19-SUM(O19:Q19) -> 0 | O19: 0 | P19: 0 | Q19: 0 | R19: 0
B20: Closing Costs | C20: =G20-SUM(D20:F20) -> 0 | D20: 0 | E20: 0 | F20: 0 | G20: 0 | H20: 10 | I20: =IF($C$22=0,0,C20/$C$22) -> 0 | J20: =H20*I20 -> 0 | M20: Closing Costs | N20: =R20-SUM(O20:Q20) -> 0 | O20: 0 | P20: 0 | Q20: 0 | R20: 0
B21: SBA Gty Fee | C21: 0 | D21: =G21-C21 -> 0 | G21: =D80 -> 0 | H21: 10 | I21: =IF($C$22=0,0,C21/$C$22) -> 0 | J21: =H21*I21 -> 0 | M21: SBA Gty Fee | N21: 0 | O21: =R21-N21 -> 0 | R21: =O80
C22: 0 | D22: =SUM(D6:D21) -> 0 | E22: =SUM(E6:E21) -> 0 | F22: =SUM(F6:F21) -> 0 | G22: =SUM(G6:G21) -> 0 | I22: Weighted Term | J22: =SUM(J6:J21) -> 0 | N22: 0 | O22: =SUM(O6:O21) -> 0 | P22: =SUM(P6:P21) -> 0 | Q22: =SUM(Q6:Q21) -> 0 | R22: =SUM(R6:R21) -> 0
C23: =IFERROR(C22/$G$22,0) -> 0 | D23: =IFERROR(D22/$G$22,0) -> 0 | E23: =IFERROR(E22/$G$22,0) -> 0 | F23: =IFERROR(F22/$G$22,0) -> 0 | G23: =IFERROR(G22/$G$22,0) -> 0 | N23: =IFERROR(N22/$R$22,0) -> 0 | O23: =IFERROR(O22/$R$22,0) -> 0 | P23: =IFERROR(P22/$R$22,0) -> 0 | Q23: =IFERROR(Q22/$R$22,0) -> 0 | R23: =IFERROR(R22/$R$22,0) -> 0
B26: Total Project | C26: =SUM(C27:C29) -> 1 | D26: =G22 -> 0 | E26: (difference)
B27: Bank Loan % | C27: 0.5 | D27: =D26*C27 -> 0 | E27: =C22-D27 -> 0
B28: CDC Loan % | C28: 0.4 | D28: =D26*C28 -> 0 | E28: =F22-D28 -> 0
B29: Borrower % | C29: 0.1 | D29: =D26*C29 -> 0 | E29: =D22-D29 -> 0
B31: Bank Interim Loan Fee % | C31: 0.025 | D31: =D27*C31 -> 0 | E31: Blended Rate | F31: (C22*'1. Project Structure'.c16 + F22*'1. Project Structure'.f16)/SUM('1. Project Structure'.c13+'1. Project Structure'.F13)
B32: SBA TPL Fee % | C32: 0.005 | D32: =D27*C32 -> 0
B33: Referral Fee % | C33: 0 | D33: =D27*C33 -> 0 | E33: Interim Loan | F33: =C22+F22 -> 0
B34: Participant Fee % | C34: 0 | D34: =C22*C34 -> 0 | E34: Rounded Fee | F34: =ROUNDUP(D35,-3) -> 1000
B35: Origination Fee Total | C35: =SUM(C31:C34) -> 0.03 | D35: =SUM(D31:D34) -> 0 | E35: Fee % to Interim | F35: =F34/F33 -> #DIV/0!
B36: 504 Loan Project
B38: Closing Costs | C38: Cost | D38: Quantity | E38: Total
B39: Loan Packaging Fee | C39: 2500 | D39: 1 | E39: =C39*D39 -> 2500
B40: Title Insurance | C40: 0 | D40: 0 | E40: =C40*D40 -> 0
B41: Real Estate Tax Fee | C41: 0 | D41: 0 | E41: =C41*D41 -> 0
B42: Survey Charges | C42: 3000 | D42: 0 | E42: =C42*D42 -> 0
B43: CRE Appraisal | C43: 3500 | D43: 0 | E43: =C43*D43 -> 0
B44: Equipment Appraisal | C44: 0 | D44: 0 | E44: =C44*D44 -> 0
B45: Appraisal Review | C45: 0 | D45: 0 | E45: =C45*D45 -> 0
B46: Site Visit | C46: 350 | D46: 0 | E46: =C46*D46 -> 0
B47: Environmental Investigation | C47: 2500 | D47: 0 | E47: =C47*D47 -> 0
B48: Business Valuation | C48: 2500 | D48: 0 | E48: =C48*D48 -> 0
B49: Residential Appr/Valuation | C49: 0 | D49: 0 | E49: =C49*D49 -> 0
B50: Attorney Doc Prep | C50: 6000 | D50: 1 | E50: =C50*D50 -> 6000
... B53: Rounding | C53: 700 | D53: 1 | E53: =C53*D53 -> 700
B54: Other: UCCs and Misc Closing | E54: =E67 -> 800
B55: Total Estimated Closing Costs | E55: =SUM(E39:E54) -> 10000
B57: Miscellaneous Closing Costs | C57: Cost | D57: Quantity | E57: Total
B58: Business Credit Report | C58: 35 | D58: 1 | E58: =C58*D58 -> 35
B59: Personal Credit Report | C59: 25 | D59: 2 | E59: =C59*D59 -> 50
B60: IRS Transcript Service | C60: 65 | D60: 2 | E60: =C60*D60 -> 130
B61: UCC Searches | C61: 300 | D61: 1 | E61: =C61*D61 -> 300
B62: Certificate of Good Standing | C62: 20 | D62: 1 | E62: =C62*D62 -> 20
B63: Flood Certification | C63: 18 | D63: 1 | E63: =C63*D63 -> 18
B64: Filing & Recording Fees | C64: 100 | D64: 1 | E64: =C64*D64 -> 100
B65: FedEx Charges | C65: 50 | D65: 1 | E65: =C65*D65 -> 50
B66: Other: rounding | C66: 97 | D66: 1 | E66: =C66*D66 -> 97
B67: Total Misc. Closing Costs | E67: =SUM(E58:E66) -> 800
B69: =IF('1. Project Structure'!C12="SBA 7a","SBA 7a","Not 7a, Guaranty Calculation not applicable") -> Not 7a, Guaranty Calculation not applicable
E70: SBA Guaranty % | G70: ='1. Project Structure'!J12 -> 0.75
B71: If there has been a previous SBA 7a loan funded within the last 90 days, enter loan amount and guaranty %.
B72: Previous Loan Amount | F72: ='1. Project Structure'!E22 -> 0
B73: Previous Guaranty % | F73: ='1. Project Structure'!G22 -> 0
B74: SBA Guaranty Fee Calculation
B75: T Bank SBA Loan | F75: Previous SBA Loan Within 90 Days | I75: Two Loans Combined
B76: Loan Amount | E76: =IF(B69="SBA 7a",'1. Project Structure'!C12,0) -> 0 | F76: Loan Amount | H76: =F72 -> 0 | I76: Loan Amount | K76: =H76+E76 -> 0
B77: Guaranteed Portion | E77: =E76*G70 -> 0 | F77: Guaranteed Portion | H77: =H76*F73 -> 0 | I77: Guaranteed Portion | K77: =E77+H77 -> 0
B78: Guaranty Fee | E78: =SUM(E83:E87) -> 0 | F78: Guaranty Fee | H78: =SUM(F83:G87) -> #REF! | I78: Guaranty Fee | K78: =SUM(J83:J87) -> 0
B79: Add'l Gty Fee | E79: =IF(F72>0,K78-H78-E78,0) -> 0
B80: Total Gty Fee (Rounded) | D80: =ROUNDUP(E78+E79,-0.1) -> 0 | F80: Total Gty Fee (Rounded) | H80: =ROUNDUP(H78+H79,-0.1) -> #REF! | I80: Total Gty Fee (Rounded) | K80: =ROUNDUP(K78+K79,-0.1) -> 0
B82: Proposed Loan Amount | C82: Fee % | F82: Prior Loan Amount Calc | I82: Total Combined | J82: Fee %
B83: < | C83: 150000 | D83: 0.02 | E83: =IF(E76<=C83,E77*D83,0) -> 0 | F83: =IF(H76<=$C$83,H77*$D$83,0) -> 0 | J83: =IF(K76<=C83,K77*D83,0) -> 0
B84: 150001 | C84: 700000 | D84: 0.03 | E84: =IF(E76>=C84+1,0,IF(E76>=B84,E77*D84,0)) -> 0 | F84: =IF($H$76>=$C$84+1,0,IF($H$76>=$B$84,$H$77*$D$84,0)) -> 0 | G84: =IF(#REF!>=#REF!+1,0,IF(#REF!>=#REF!,#REF!*#REF!,0)) -> #REF! | J84: =IF(K76>=C84+1,0,IF(K76>=B84,K77*D84,0)) -> 0
D85: 0 | E85: =IF(E76>=$C$84+1,0,IF(E76>=$B$84,IF(E77>1000000,(E77-1000000)*D85,0),0)) -> 0 | F85: =IF(H76>=C84+1,0,IF(H76>=B84,IF(H77>1000000,(H77-1000000)*D85,0),0)) -> 0 | J85: =IF(K76>=C84+1,0,IF(K76>=B84,IF(K77>1000000,(K77-1000000)*D85,0),0)) -> 0
B86: 700001 | C86: 5000000 | D86: 0.035 | E86: =IF(E76>=$B$86,1000000*$D$86,0) -> 0 | F86: =MIN(35000,IF(H76>=$C$86+1,1000000*$D$86,0)) -> 0 | J86: =MIN(35000,IF(K76>=C86+1,1000000*D86,0)) -> 0
D87: 0.0375 | E87: =IF(E76>=$B$86,(E77-1000000)*$D$87,0) -> 0 | F87: =IF((H77-$B$86)*$D$87<=0,0,(H77-1000000)*$D$87) -> 0 | J87: =IF((K76-B86)*D87<=0,0,(K76-1000000)*D87) -> 0
B90: Request 1 | D90: 504 Perm 1st
B91: Basis | C91: Loan Amount | D91: Interest Rate | E91: Term (mo) | F91: Amo (mo) | G91: Start Month | H91: End Month | I91: # days | J91: Interest Rate Conversion | K91: Pmt
B92: 30/360 | C92: =IF($E$90>0,$E$90,IF($C$22>0,$C$22,'1. Project Structure'!$C$13)) -> 0 | D92: ='1. Project Structure'!$C$16 -> 0.09 | E92: ='1. Project Structure'!$C$18*12 -> 120 | F92: ='1. Project Structure'!$C$19 -> 120 | G92: =TODAY()+45 -> 46044 | H92: =DATE(YEAR(G92)+F92/12,MONTH(G92),DAY(G92)) -> 49696 | I92: =H92-G92 -> 3652 | J92: =IFERROR((D92/360)*30*12,0) -> 0.09 | K92: =IFERROR(PMT(J92/12,F92,-C92),"Incomplete Data") -> 0
B93: Actual/365 | C93: =IF($E$90>0,$E$90,IF($C$22>0,$C$22,'1. Project Structure'!$C$13)) -> 0 | D93: ='1. Project Structure'!$C$16 -> 0.09 | E93: ='1. Project Structure'!$C$18*12 -> 120 | F93: ='1. Project Structure'!$C$19 -> 120 | G93: =TODAY()+45 -> 46044 | H93: =DATE(YEAR(G93)+F93/12,MONTH(G93),DAY(G93)) -> 49696 | I93: =H93-G93 -> 3652 | J93: =IFERROR((D93/(365*F93/12))*I93,0) -> 0.090049315 | K93: =IFERROR(PMT(J93/12,F93,-C93),"Incomplete Data") -> 0
B94: Actual/360 | C94: =IF($E$90>0,$E$90,IF($C$22>0,$C$22,'1. Project Structure'!$C$13)) -> 0 | D94: ='1. Project Structure'!$C$16 -> 0.09 | E94: ='1. Project Structure'!$C$18*12 -> 120 | F94: ='1. Project Structure'!$C$19 -> 120 | G94: =TODAY()+45 -> 46044 | H94: =DATE(YEAR(G94)+F94/12,MONTH(G94),DAY(G94)) -> 49696 | I94: =H94-G94 -> 3652 | J94: =IFERROR((D94/(360*F94/12))*I94,0) -> 0.0913 | K94: =IFERROR(PMT(J94/12,F94,-C94),"Incomplete Data") -> 0
B96: Plus 1%
B97: Basis | C97: Loan Amount | D97: Interest Rate | E97: Term (mo) | F97: Amo (mo) | G97: Start Month | H97: End Month | I97: # days | J97: Interest Rate Conversion | K97: Pmt
B98: 30/360 | C98: =IF($E$90>0,$E$90,IF($C$22>0,$C$22,'1. Project Structure'!$C$13)) -> 0 | D98: ='1. Project Structure'!$C$16+1% -> 0.1 | E98: ='1. Project Structure'!$C$18*12 -> 120 | F98: ='1. Project Structure'!$C$19 -> 120 | G98: =TODAY()+45 -> 46044 | H98: =DATE(YEAR(G98)+F98/12,MONTH(G98),DAY(G98)) -> 49696 | I98: =H98-G98 -> 3652 | J98: =IFERROR((D98/360)*30*12,0) -> 0.1 | K98: =IFERROR(PMT(J98/12,F98,-C98),"Incomplete Data") -> 0
B99: Actual/365 | C99: =IF($E$90>0,$E$90,IF($C$22>0,$C$22,'1. Project Structure'!$C$13)) -> 0 | D99: ='1. Project Structure'!$C$16+1% -> 0.1 | E99: ='1. Project Structure'!$C$18*12 -> 120 | F99: ='1. Project Structure'!$C$19 -> 120 | G99: =TODAY()+45 -> 46044 | H99: =DATE(YEAR(G99)+F99/12,MONTH(G99),DAY(G99)) -> 49696 | I99: =H99-G99 -> 3652 | J99: =IFERROR((D99/(365*F99/12))*I99,0) -> 0.10005479 | K99: =IFERROR(PMT(J99/12,F99,-C99),"Incomplete Data") -> 0
B100: Actual/360 | C100: =IF($E$90>0,$E$90,IF($C$22>0,$C$22,'1. Project Structure'!$C$13)) -> 0 | D100: ='1. Project Structure'!$C$16+1% -> 0.1 | E100: ='1. Project Structure'!$C$18*12 -> 120 | F100: ='1. Project Structure'!$C$19 -> 120 | G100: =TODAY()+45 -> 46044 | H100: =DATE(YEAR(G100)+F100/12,MONTH(G100),DAY(G100)) -> 49696 | I100: =H100-G100 -> 3652 | J100: =IFERROR((D100/(360*F100/12))*I100,0) -> 0.10144444 | K100: =IFERROR(PMT(J100/12,F100,-C100),"Incomplete Data") -> 0
B102: Plus 2%
B103: Basis | C103: Loan Amount | D103: Interest Rate | E103: Term (mo) | F103: Amo (mo) | G103: Start Month | H103: End Month | I103: # days | J103: Interest Rate Conversion | K103: Pmt
B104: 30/360 | C104: =IF($E$90>0,$E$90,IF($C$22>0,$C$22,'1. Project Structure'!$C$13)) -> 0 | D104: ='1. Project Structure'!$C$16+2% -> 0.11 | E104: ='1. Project Structure'!$C$18*12 -> 120 | F104: ='1. Project Structure'!$C$19 -> 120 | G104: =TODAY()+45 -> 46044 | H104: =DATE(YEAR(G104)+F104/12,MONTH(G104),DAY(G104)) -> 49696 | I104: =H104-G104 -> 3652 | J104: =IFERROR((D104/360)*30*12,0) -> 0.11 | K104: =IFERROR(PMT(J104/12,F104,-C104),"Incomplete Data") -> 0
B105: Actual/365 | C105: =IF($E$90>0,$E$90,IF($C$22>0,$C$22,'1. Project Structure'!$C$13)) -> 0 | D105: ='1. Project Structure'!$C$16+2% -> 0.11 | E105: ='1. Project Structure'!$C$18*12 -> 120 | F105: ='1. Project Structure'!$C$19 -> 120 | G105: =TODAY()+45 -> 46044 | H105: =DATE(YEAR(G105)+F105/12,MONTH(G105),DAY(G105)) -> 49696 | I105: =H105-G105 -> 3652 | J105: =IFERROR((D105/(365*F105/12))*I105,0) -> 0.11006027 | K105: =IFERROR(PMT(J105/12,F105,-C105),"Incomplete Data") -> 0
B106: Actual/360 | C106: =IF($E$90>0,$E$90,IF($C$22>0,$C$22,'1. Project Structure'!$C$13)) -> 0 | D106: ='1. Project Structure'!$C$16+2% -> 0.11 | E106: ='1. Project Structure'!$C$18*12 -> 120 | F106: ='1. Project Structure'!$C$19 -> 120 | G106: =TODAY()+45 -> 46044 | H106: =DATE(YEAR(G106)+F106/12,MONTH(G106),DAY(G106)) -> 49696 | I106: =H106-G106 -> 3652 | J106: =IFERROR((D106/(360*F106/12))*I106,0) -> 0.11158889 | K106: =IFERROR(PMT(J106/12,F106,-C106),"Incomplete Data") -> 0
B108: Plus 3%
B109: Basis | C109: Loan Amount | D109: Interest Rate | E109: Term (mo) | F109: Amo (mo) | G109: Start Month | H109: End Month | I109: # days | J109: Interest Rate Conversion | K109: Pmt
B110: 30/360 | C110: =IF($E$90>0,$E$90,IF($C$22>0,$C$22,'1. Project Structure'!$C$13)) -> 0 | D110: ='1. Project Structure'!$C$16+3% -> 0.12 | E110: ='1. Project Structure'!$C$18*12 -> 120 | F110: ='1. Project Structure'!$C$19 -> 120 | G110: =TODAY()+45 -> 46044 | H110: =DATE(YEAR(G110)+F110/12,MONTH(G110),DAY(G110)) -> 49696 | I110: =H110-G110 -> 3652 | J110: =IFERROR((D110/360)*30*12,0) -> 0.12 | K110: =IFERROR(PMT(J110/12,F110,-C110),"Incomplete Data") -> 0
B111: Actual/365 | C111: =IF($E$90>0,$E$90,IF($C$22>0,$C$22,'1. Project Structure'!$C$13)) -> 0 | D111: ='1. Project Structure'!$C$16+3% -> 0.12 | E111: ='1. Project Structure'!$C$18*12 -> 120 | F111: ='1. Project Structure'!$C$19 -> 120 | G111: =TODAY()+45 -> 46044 | H111: =DATE(YEAR(G111)+F111/12,MONTH(G111),DAY(G111)) -> 49696 | I111: =H111-G111 -> 3652 | J111: =IFERROR((D111/(365*F111/12))*I111,0) -> 0.12006575 | K111: =IFERROR(PMT(J111/12,F111,-C111),"Incomplete Data") -> 0
B112: Actual/360 | C112: =IF($E$90>0,$E$90,IF($C$22>0,$C$22,'1. Project Structure'!$C$13)) -> 0 | D112: ='1. Project Structure'!$C$16+3% -> 0.12 | E112: ='1. Project Structure'!$C$18*12 -> 120 | F112: ='1. Project Structure'!$C$19 -> 120 | G112: =TODAY()+45 -> 46044 | H112: =DATE(YEAR(G112)+F112/12,MONTH(G112),DAY(G112)) -> 49696 | I112: =H112-G112 -> 3652 | J112: =IFERROR((D112/(360*F112/12))*I112,0) -> 0.12173333 | K112: =IFERROR(PMT(J112/12,F112,-C112),"Incomplete Data") -> 0
B114: Plus 4%
B115: Basis | C115: Loan Amount | D115: Interest Rate | E115: Term (mo) | F115: Amo (mo) | G115: Start Month | H115: End Month | I115: # days | J115: Interest Rate Conversion | K115: Pmt
B116: 30/360 | C116: =IF($E$90>0,$E$90,IF($C$22>0,$C$22,'1. Project Structure'!$C$13)) -> 0 | D116: ='1. Project Structure'!$C$16+4% -> 0.13 | E116: ='1. Project Structure'!$C$18*12 -> 120 | F116: ='1. Project Structure'!$C$19 -> 120 | G116: =TODAY()+45 -> 46044 | H116: =DATE(YEAR(G116)+F116/12,MONTH(G116),DAY(G116)) -> 49696 | I116: =H116-G116 -> 3652 | J116: =IFERROR((D116/360)*30*12,0) -> 0.13 | K116: =IFERROR(PMT(J116/12,F116,-C116),"Incomplete Data") -> 0
B117: Actual/365 | C117: =IF($E$90>0,$E$90,IF($C$22>0,$C$22,'1. Project Structure'!$C$13)) -> 0 | D117: ='1. Project Structure'!$C$16+4% -> 0.13 | E117: ='1. Project Structure'!$C$18*12 -> 120 | F117: ='1. Project Structure'!$C$19 -> 120 | G117: =TODAY()+45 -> 46044 | H117: =DATE(YEAR(G117)+F117/12,MONTH(G117),DAY(G117)) -> 49696 | I117: =H117-G117 -> 3652 | J117: =IFERROR((D117/(365*F117/12))*I117,0) -> 0.13007123 | K117: =IFERROR(PMT(J117/12,F117,-C117),"Incomplete Data") -> 0
...

Sheet 3. Financials
B3: Income Statement Spreads
B4: {Insert business name which represents PSOR}
B5: Include in Global? | C5: Yes
B6: Statement Date | D6: 44926 | F6: =EOMONTH(D6,F7) -> 45291 | H6: =EOMONTH(F6,H7) -> 45657 | J6: =EOMONTH(H6,J7) -> 45747 | N6: Projections | P6: Projections
B7: Months Covered | D7: 12 | F7: 12 | H7: 12 | J7: 3 | N7: Customer | P7: Customer
B8: Statement Type | D8: Tax Returns | F8: Tax Returns | J8: Internal | N8: Year | P8: Year
B9: Revenue Recognition | N9: 1 | P9: 2
B10: REVENUE
B11: Revenue | C11: (Product Line #1) | D11: 1 | E11: =IF(D$14=0,0,D11/D$14) -> 0 | F11: 0 | G11: =IF(F$14=0,0,F11/F$14) -> 0 | H11: 0 | I11: =IF(H$14=0,0,H11/H$14) -> 0 | J11: 0 | K11: =IF(J$14=0,0,J11/J$14) -> 0 | M11: Revenue (Product Line #1) | N11: 0 | O11: =IF(N$14=0,0,N11/N$14) -> 0 | P11: 0 | Q11: =IF(P$14=0,0,P11/P$14) -> 0
B12: COGS | C12: (Product Line #1) | D12: 0 | E12: =IF(D$14=0,0,D12/D$14) -> 0 | F12: 0 | G12: =IF(F$14=0,0,F12/F$14) -> 0 | H12: 0 | I12: =IF(H$14=0,0,H12/H$14) -> 0 | J12: 0 | K12: =IF(J$14=0,0,J12/J$14) -> 0 | M12: COGS (Product Line #1) | N12: 0 | O12: =IF(N$14=0,0,N12/N$14) -> 0 | P12: 0 | Q12: =IF(P$14=0,0,P12/P$14) -> 0
B13: Gross Margin | C13: (Product Line #1) | D13: =D11-D12 -> 1 | E13: =IF(D$14=0,0,D13/D$14) -> 0 | F13: =F11-F12 -> 0 | G13: =IF(F$14=0,0,F13/F$14) -> 0 | H13: =H11-H12 -> 0 | I13: =IF(H$14=0,0,H13/H$14) -> 0 | J13: =J11-J12 -> 0 | K13: =IF(J$14=0,0,J13/J$14) -> 0 | M13: Gross Margin (Product Line #1) | N13: =N11-N12 -> 0 | O13: =IF(N$14=0,0,N13/N$14) -> 0 | P13: =P11-P12 -> 0 | Q13: =IF(P$14=0,0,P13/P$14) -> 0
C14: Total Revenue | D14: 0 | E14: =IF(D$14=0,0,D14/D$14) -> 0 | F14: 0 | G14: =IF(F$14=0,0,F14/F$14) -> 0 | H14: 0 | I14: =IF(H$14=0,0,H14/H$14) -> 0 | J14: 0 | K14: =IF(J$14=0,0,J14/J$14) -> 0 | M14: Total Revenue | N14: =N11 -> 0 | O14: =IF(N$14=0,0,N14/N$14) -> 0 | P14: =P11 -> 0 | Q14: =IF(P$14=0,0,P14/P$14) -> 0
C15: Total COGS | D15: 0 | E15: =IF(D$14=0,0,D15/D$14) -> 0 | F15: 0 | G15: =IF(F$14=0,0,F15/F$14) -> 0 | H15: 0 | I15: =IF(H$14=0,0,H15/H$14) -> 0 | J15: 0 | K15: =IF(J$14=0,0,J15/J$14) -> 0 | M15: Total COGS | N15: =N12 -> 0 | O15: =IF(N$14=0,0,N15/N$14) -> 0 | P15: =P12 -> 0 | Q15: =IF(P$14=0,0,P15/P$14) -> 0
C16: Total Gross Margin | D16: =D14-D15 -> 0 | E16: =IF(D$14=0,0,D16/D$14) -> 0 | F16: =F14-F15 -> 0 | G16: =IF(F$14=0,0,F16/F$14) -> 0 | H16: =H14-H15 -> 0 | I16: =IF(H$14=0,0,H16/H$14) -> 0 | J16: =J14-J15 -> 0 | K16: =IF(J$14=0,0,J16/J$14) -> 0 | M16: Total Gross Margin | N16: =N14-N15 -> 0 | O16: =IF(N$14=0,0,N16/N$14) -> 0 | P16: =P14-P15 -> 0 | Q16: =IF(P$14=0,0,P16/P$14) -> 0
C18: OPERATING EXPENSES | M18: OPERATING EXPENSES
C19: Officer's Compensation | D19: 0 | E19: =IF(D$14=0,0,D19/D$14) -> 0 | F19: 0 | G19: =IF(F$14=0,0,F19/F$14) -> 0 | H19: 0 | I19: =IF(H$14=0,0,H19/H$14) -> 0 | J19: 0 | K19: =IF(J$14=0,0,J19/J$14) -> 0 | M19: Officer's Compensation | N19: 0 | O19: =IF(N$14=0,0,N19/N$14) -> 0 | P19: 0 | Q19: =IF(P$14=0,0,P19/P$14) -> 0
C20: Salaries & Wages | D20: 0 | E20: =IF(D$14=0,0,D20/D$14) -> 0 | F20: 0 | G20: =IF(F$14=0,0,F20/F$14) -> 0 | H20: 0 | I20: =IF(H$14=0,0,H20/H$14) -> 0 | J20: 0 | K20: =IF(J$14=0,0,J20/J$14) -> 0 | M20: Salaries & Wages | N20: 0 | O20: =IF(N$14=0,0,N20/N$14) -> 0 | P20: 0 | Q20: =IF(P$14=0,0,P20/P$14) -> 0
C21: Repairs & Maintenance | D21: 0 | E21: =IF(D$14=0,0,D21/D$14) -> 0 | F21: 0 | G21: =IF(F$14=0,0,F21/F$14) -> 0 | H21: 0 | I21: =IF(H$14=0,0,H21/H$14) -> 0 | J21: 0 | K21: =IF(J$14=0,0,J21/J$14) -> 0 | M21: Repairs & Maintenance | N21: 0 | O21: =IF(N$14=0,0,N21/N$14) -> 0 | P21: 0 | Q21: =IF(P$14=0,0,P21/P$14) -> 0
C22: Bad Debts | D22: 0 | E22: =IF(D$14=0,0,D22/D$14) -> 0 | F22: 0 | G22: =IF(F$14=0,0,F22/F$14) -> 0 | H22: 0 | I22: =IF(H$14=0,0,H22/H$14) -> 0 | J22: 0 | K22: =IF(J$14=0,0,J22/J$14) -> 0 | M22: Bad Debts | N22: 0 | O22: =IF(N$14=0,0,N22/N$14) -> 0 | P22: 0 | Q22: =IF(P$14=0,0,P22/P$14) -> 0
C23: Rents | D23: 0 | E23: =IF(D$14=0,0,D23/D$14) -> 0 | F23: 0 | G23: =IF(F$14=0,0,F23/F$14) -> 0 | H23: 0 | I23: =IF(H$14=0,0,H23/H$14) -> 0 | J23: 0 | K23: =IF(J$14=0,0,J23/J$14) -> 0 | M23: Rents | N23: 0 | O23: =IF(N$14=0,0,N23/N$14) -> 0 | P23: 0 | Q23: =IF(P$14=0,0,P23/P$14) -> 0
C24: Taxes & Licenses | D24: 0 | E24: =IF(D$14=0,0,D24/D$14) -> 0 | F24: 0 | G24: =IF(F$14=0,0,F24/F$14) -> 0 | H24: 0 | I24: =IF(H$14=0,0,H24/H$14) -> 0 | J24: 0 | K24: =IF(J$14=0,0,J24/J$14) -> 0 | M24: Taxes & Licenses | N24: 0 | O24: =IF(N$14=0,0,N24/N$14) -> 0 | P24: 0 | Q24: =IF(P$14=0,0,P24/P$14) -> 0
C25: Interest | D25: 0 | E25: =IF(D$14=0,0,D25/D$14) -> 0 | F25: 0 | G25: =IF(F$14=0,0,F25/F$14) -> 0 | H25: 0 | I25: =IF(H$14=0,0,H25/H$14) -> 0 | J25: 0 | K25: =IF(J$14=0,0,J25/J$14) -> 0 | M25: Interest | N25: 0 | O25: =IF(N$14=0,0,N25/N$14) -> 0 | P25: 0 | Q25: =IF(P$14=0,0,P25/P$14) -> 0
C26: Depreciation & Amortization | D26: 0 | E26: =IF(D$14=0,0,D26/D$14) -> 0 | F26: 0 | G26: =IF(F$14=0,0,F26/F$14) -> 0 | H26: 0 | I26: =IF(H$14=0,0,H26/H$14) -> 0 | J26: 0 | K26: =IF(J$14=0,0,J26/J$14) -> 0 | M26: Depreciation & Amortization | N26: 0 | O26: =IF(N$14=0,0,N26/N$14) -> 0 | P26: 0 | Q26: =IF(P$14=0,0,P26/P$14) -> 0
C27: Advertising | D27: 0 | E27: =IF(D$14=0,0,D27/D$14) -> 0 | F27: 0 | G27: =IF(F$14=0,0,F27/F$14) -> 0 | H27: 0 | I27: =IF(H$14=0,0,H27/H$14) -> 0 | J27: 0 | K27: =IF(J$14=0,0,J27/J$14) -> 0 | M27: Advertising | N27: 0 | O27: =IF(N$14=0,0,N27/N$14) -> 0 | P27: 0 | Q27: =IF(P$14=0,0,P27/P$14) -> 0
C28: Other | D28: 0 | E28: =IF(D$14=0,0,D28/D$14) -> 0 | F28: 0 | G28: =IF(F$14=0,0,F28/F$14) -> 0 | H28: 0 | I28: =IF(H$14=0,0,H28/H$14) -> 0 | J28: 0 | K28: =IF(J$14=0,0,J28/J$14) -> 0 | M28: Other | N28: 0 | O28: =IF(N$14=0,0,N28/N$14) -> 0 | P28: 0 | Q28: =IF(P$14=0,0,P28/P$14) -> 0
C29: Other | D29: 0 | E29: =IF(D$14=0,0,D29/D$14) -> 0 | F29: 0 | G29: =IF(F$14=0,0,F29/F$14) -> 0 | H29: 0 | I29: =IF(H$14=0,0,H29/H$14) -> 0 | J29: 0 | K29: =IF(J$14=0,0,J29/J$14) -> 0 | M29: Other | N29: =0-SUM(N19:N28) -> 0 | O29: =IF(N$14=0,0,N29/N$14) -> 0 | P29: =0-SUM(P19:P28) -> 0 | Q29: =IF(P$14=0,0,P29/P$14) -> 0
C30: Total Operating Expenses | D30: =SUM(D19:D29) -> 0 | E30: =IF(D$14=0,0,D30/D$14) -> 0 | F30: =SUM(F19:F29) -> 0 | G30: =IF(F$14=0,0,F30/F$14) -> 0 | H30: =SUM(H19:H29) -> 0 | I30: =IF(H$14=0,0,H30/H$14) -> 0 | J30: =SUM(J19:J29) -> 0 | K30: =IF(J$14=0,0,J30/J$14) -> 0 | M30: Total Operating Expenses | N30: =SUM(N19:N29) -> 0 | O30: =IF(N$14=0,0,N30/N$14) -> 0 | P30: =SUM(P19:P29) -> 0 | Q30: =IF(P$14=0,0,P30/P$14) -> 0
C32: Ordinary Income | D32: =D16-D30 -> 0 | E32: =IF(D$14=0,0,D32/D$14) -> 0 | F32: =F16-F30 -> 0 | G32: =IF(F$14=0,0,F32/F$14) -> 0 | H32: =H16-H30 -> 0 | I32: =IF(H$14=0,0,H32/H$14) -> 0 | J32: =J16-J30 -> 0 | K32: =IF(J$14=0,0,J32/J$14) -> 0 | M32: Ordinary Income | N32: =N16-N30 -> 0 | O32: =IF(N$14=0,0,N32/N$14) -> 0 | P32: =P16-P30 -> 0 | Q32: =IF(P$14=0,0,P32/P$14) -> 0
C34: Other Income | D34: 0 | E34: =IF(D$14=0,0,D34/D$14) -> 0 | F34: 0 | G34: =IF(F$14=0,0,F34/F$14) -> 0 | H34: 0 | I34: =IF(H$14=0,0,H34/H$14) -> 0 | J34: 0 | K34: =IF(J$14=0,0,J34/J$14) -> 0 | M34: Other Income | N34: 0 | O34: =IF(N$14=0,0,N34/N$14) -> 0 | P34: 0 | Q34: =IF(P$14=0,0,P34/P$14) -> 0
C35: Other Income | D35: 0 | E35: =IF(D$14=0,0,D35/D$14) -> 0 | F35: 0 | G35: =IF(F$14=0,0,F35/F$14) -> 0 | H35: 0 | I35: =IF(H$14=0,0,H35/H$14) -> 0 | J35: 0 | K35: =IF(J$14=0,0,J35/J$14) -> 0 | M35: Other Income | N35: 0 | O35: =IF(N$14=0,0,N35/N$14) -> 0 | P35: 0 | Q35: =IF(P$14=0,0,P35/P$14) -> 0
C36: Other Expense | D36: 0 | E36: =IF(D$14=0,0,D36/D$14) -> 0 | F36: 0 | G36: =IF(F$14=0,0,F36/F$14) -> 0 | H36: 0 | I36: =IF(H$14=0,0,H36/H$14) -> 0 | J36: 0 | K36: =IF(J$14=0,0,J36/J$14) -> 0 | M36: Other Expense | N36: 0 | O36: =IF(N$14=0,0,N36/N$14) -> 0 | P36: 0 | Q36: =IF(P$14=0,0,P36/P$14) -> 0
C37: Other Expense | D37: 0 | E37: =IF(D$14=0,0,D37/D$14) -> 0 | F37: 0 | G37: =IF(F$14=0,0,F37/F$14) -> 0 | H37: 0 | I37: =IF(H$14=0,0,H37/H$14) -> 0 | J37: 0 | K37: =IF(J$14=0,0,J37/J$14) -> 0 | M37: Other Expense | N37: 0 | O37: =IF(N$14=0,0,N37/N$14) -> 0 | P37: 0 | Q37: =IF(P$14=0,0,P37/P$14) -> 0
C38: Total Other Income (Expenses) | D38: =SUM(D34:D37) -> 0 | E38: =IF(D$14=0,0,D38/D$14) -> 0 | F38: =SUM(F34:F37) -> 0 | G38: =IF(F$14=0,0,F38/F$14) -> 0 | H38: =SUM(H34:H37) -> 0 | I38: =IF(H$14=0,0,H38/H$14) -> 0 | J38: =SUM(J34:J37) -> 0 | K38: =IF(J$14=0,0,J38/J$14) -> 0 | M38: Total Other Income (Expenses) | N38: =SUM(N34:N37) -> 0 | O38: =IF(N$14=0,0,N38/N$14) -> 0 | P38: =SUM(P34:P37) -> 0 | Q38: =IF(P$14=0,0,P38/P$14) -> 0
C40: Net Income Before Taxes | D40: =D16-D30+D38 -> 0 | E40: =IF(D$14=0,0,D40/D$14) -> 0 | F40: =F16-F30+F38 -> 0 | G40: =IF(F$14=0,0,F40/F$14) -> 0 | H40: =H16-H30+H38 -> 0 | I40: =IF(H$14=0,0,H40/H$14) -> 0 | J40: =J16-J30+J38 -> 0 | K40: =IF(J$14=0,0,J40/J$14) -> 0 | M40: Net Income Before Taxes | N40: =N16-N30+N38 -> 0 | O40: =IF(N$14=0,0,N40/N$14) -> 0 | P40: =P16-P30+P38 -> 0 | Q40: =IF(P$14=0,0,P40/P$14) -> 0
C41: Income Taxes | D41: 0 | E41: =IF(D$14=0,0,D41/D$14) -> 0 | F41: 0 | G41: =IF(F$14=0,0,F41/F$14) -> 0 | H41: 0 | I41: =IF(H$14=0,0,H41/H$14) -> 0 | J41: 0 | K41: =IF(J$14=0,0,J41/J$14) -> 0 | M41: Income Taxes | N41: 0 | O41: =IF(N$14=0,0,N41/N$14) -> 0 | P41: 0 | Q41: =IF(P$14=0,0,P41/P$14) -> 0
C43: NET INCOME AFTER TAXES | D43: =D40-D41 -> 0 | E43: =IF(D$14=0,0,D43/D$14) -> 0 | F43: =F40-F41 -> 0 | G43: =IF(F$14=0,0,F43/F$14) -> 0 | H43: =H40-H41 -> 0 | I43: =IF(H$14=0,0,H43/H$14) -> 0 | J43: =J40-J41 -> 0 | K43: =IF(J$14=0,0,J43/J$14) -> 0 | M43: NET INCOME AFTER TAXES | N43: =N40-N41 -> 0 | O43: =IF(N$14=0,0,N43/N$14) -> 0 | P43: =P40-P41 -> 0 | Q43: =IF(P$14=0,0,P43/P$14) -> 0
C45: Add Backs : | M45: Add Backs :
C46: + Compensation of Officers | D46: =D19 -> 0 | F46: =F19 -> 0 | H46: =H19 -> 0 | J46: =J19 -> 0 | M46: + Compensation of Officers | N46: =N19 -> 0 | O46: =IF(N$14=0,0,N46/N$14) -> 0 | P46: =P19 -> 0 | Q46: =IF(P$14=0,0,P46/P$14) -> 0
C47: + Depreciation/Amortization | D47: =D26 -> 0 | F47: =F26 -> 0 | H47: =H26 -> 0 | J47: =J26 -> 0 | M47: + Depreciation/Amortization | N47: =N26 -> 0 | O47: =IF(N$14=0,0,N47/N$14) -> 0 | P47: =P26 -> 0 | Q47: =IF(P$14=0,0,P47/P$14) -> 0
C48: + Interest Expense | D48: =D25 -> 0 | F48: =F25 -> 0 | H48: =H25 -> 0 | J48: =J25 -> 0 | M48: + Interest Expense | N48: =N25 -> 0 | O48: =IF(N$14=0,0,N48/N$14) -> 0 | P48: =P25 -> 0 | Q48: =IF(P$14=0,0,P48/P$14) -> 0
C49: + Rent Add Back | D49: 0 | F49: 0 | H49: 0 | J49: 0 | M49: + Rent Add Back | N49: =N23 -> 0 | O49: =IF(N$14=0,0,N49/N$14) -> 0 | P49: =P23 -> 0 | Q49: =IF(P$14=0,0,P49/P$14) -> 0
C50: + - Other | D50: 0 | F50: 0 | H50: 0 | J50: 0 | M50: + - Other | N50: 0 | O50: =IF(N$14=0,0,N50/N$14) -> 0 | P50: 0 | Q50: =IF(P$14=0,0,P50/P$14) -> 0
C51: + - Other | D51: 0 | F51: 0 | H51: 0 | J51: 0 | M51: + - Other | N51: 0 | O51: =IF(N$14=0,0,N51/N$14) -> 0 | P51: 0 | Q51: =IF(P$14=0,0,P51/P$14) -> 0
C52: - Estimated Property Tax | D52: 0 | F52: 0 | H52: 0 | J52: 0 | M52: - Estimated Property Tax | N52: 0 | O52: =IF(N$14=0,0,N52/N$14) -> 0 | P52: 0 | Q52: =IF(P$14=0,0,P52/P$14) -> 0
C53: - Required Owner's Draw | D53: 0 | F53: 0 | H53: 0 | J53: 0 | M53: - Required Owner's Draw | N53: =H53 -> 0 | O53: =IF(N$14=0,0,N53/N$14) -> 0 | P53: =H53 -> 0 | Q53: =IF(P$14=0,0,P53/P$14) -> 0
C55: Cash Available | D55: =D43+SUM(D46:D53) -> 0 | F55: =F43+SUM(F46:F53) -> 0 | H55: =H43+SUM(H46:H53) -> 0 | J55: =J43+SUM(J46:J53) -> 0 | M55: Cash Available | N55: =N40+SUM(N46:N53) -> 0 | O55: =IF(N$14=0,0,N55/N$14) -> 0 | P55: =P40+SUM(P46:P53) -> 0 | Q55: =IF(P$14=0,0,P55/P$14) -> 0
C57: Existing Debt | D57: =Table211[[#Totals],[CF Debt Svc]]*D7 -> 0 | F57: =Table211[[#Totals],[CF Debt Svc]]*F7 -> 0 | H57: =Table211[[#Totals],[CF Debt Svc]]*H7 -> 0 | J57: =Table211[[#Totals],[CF Debt Svc]]*J7 -> 0 | M57: Existing Debt | N57: =SUMIF(K$68:K$77,"No",E68:F77)*$D$7 -> 0 | O57: =IF(N$14=0,0,N57/N$14) -> 0 | P57: =SUMIF(K$68:K$77,"No",E68:F77)*$D$7 -> 0 | Q57: =IF(P$14=0,0,P57/P$14) -> 0
C58: Proposed Loan 1 | D58: =IFERROR(INDEX('2. Sources and Uses'!$K$92:$K$94,MATCH('1. Project Structure'!$C$17,'2. Sources and Uses'!B$92:$B$94,0))*D$7,0) -> 0 | F58: =IFERROR(INDEX('2. Sources and Uses'!$K$92:$K$94,MATCH('1. Project Structure'!$C$17,'2. Sources and Uses'!$B$92:D$94,0))*F$7,0) -> 0 | H58: =IFERROR(INDEX('2. Sources and Uses'!$K$92:$K$94,MATCH('1. Project Structure'!$C$17,'2. Sources and Uses'!$B$92:F$94,0))*H$7,0) -> 0 | J58: =IFERROR(INDEX('2. Sources and Uses'!$K$92:$K$94,MATCH('1. Project Structure'!$C$17,'2. Sources and Uses'!$B$92:H$94,0))*J$7,0) -> 0 | M58: =_xlfn.CONCAT('1. Project Structure'!C$11) -> T Bank Loan | N58: ='1. Project Structure'!C20*D7 -> 0 | O58: =IF(N$14=0,0,N58/N$14) -> 0 | P58: ='1. Project Structure'!C20*D7 -> 0 | Q58: =IF(P$14=0,0,P58/P$14) -> 0
C59: Seller Carry Note | D59: =IFERROR(PMT('1. Project Structure'!$E$16/12,'1. Project Structure'!$E$19,-'1. Project Structure'!$E$22),0)*D$7 -> 0 | F59: =IFERROR(PMT('1. Project Structure'!$E$16/12,'1. Project Structure'!$E$19,-'1. Project Structure'!$E$22),0)*F$7 -> 0 | H59: =IFERROR(PMT('1. Project Structure'!$E$16/12,'1. Project Structure'!$E$19,-'1. Project Structure'!$E$22),0)*H$7 -> 0 | J59: =IFERROR(PMT('1. Project Structure'!$E$16/12,'1. Project Structure'!$E$19,-'1. Project Structure'!$E$22),0)*J$7 -> 0 | M59: =_xlfn.CONCAT('1. Project Structure'!E$11) -> Seller Note | N59: =IFERROR(PMT('1. Project Structure'!C14/12,'1. Project Structure'!E17,-'2. Sources and Uses'!E20),0)*12 -> 0 | O59: =IF(N$14=0,0,N59/N$14) -> 0 | P59: =IFERROR(PMT('1. Project Structure'!C14/12,'1. Project Structure'!E17,-'2. Sources and Uses'!EE20),0)*12 -> 0 | Q59: =IF(P$14=0,0,P59/P$14) -> 0
C60: 3rd Party Financing | D60: =IFERROR(PMT('1. Project Structure'!$F$16/12,'1. Project Structure'!$F$19,-'2. Sources and Uses'!$F$22),0)*D$7 -> 0 | F60: =IFERROR(PMT('1. Project Structure'!$F$16/12,'1. Project Structure'!$F$19,-'2. Sources and Uses'!$F$22),0)*F$7 -> 0 | H60: =IFERROR(PMT('1. Project Structure'!$F$16/12,'1. Project Structure'!$F$19,-'2. Sources and Uses'!$F$22),0)*H$7 -> 0 | J60: =IFERROR(PMT('1. Project Structure'!$F$16/12,'1. Project Structure'!$F$19,-'2. Sources and Uses'!$F$22),0)*J$7 -> 0 | M60: =_xlfn.CONCAT('1. Project Structure'!F$11) -> 3rd Party | N60: =IFERROR(PMT('1. Project Structure'!F14/12,'1. Project Structure'!F17,-'2. Sources and Uses'!F20),0)*12 -> 0 | O60: =IF(N$14=0,0,N60/N$14) -> 0 | P60: =IFERROR(PMT('1. Project Structure'!F14/12,'1. Project Structure'!F17,-'2. Sources and Uses'!F20),0)*12 -> 0 | Q60: =IF(P$14=0,0,P60/P$14) -> 0
C61: Total Debt | D61: =SUM(D$57:D$60) -> 0 | F61: =SUM(F$57:F$60) -> 0 | H61: =SUM(H$57:H$60) -> 0 | J61: =SUM(J$57:J$60) -> 0 | M61: Total Debt | N61: =SUM(N57:N60) -> 0 | O61: =IF(N$14=0,0,N61/N$14) -> 0 | P61: =SUM(P56:P60) -> 0 | Q61: =IF(P$14=0,0,P61/P$14) -> 0
C63: DCR | D63: =IFERROR(D$55/D$61,0) -> 0 | F63: =IFERROR(F$55/F$61,0) -> 0 | H63: =IFERROR(H$55/H$61,0) -> 0 | J63: =IFERROR(J$55/J$61,0) -> 0 | M63: DCR | N63: =IFERROR(N55/N61,0) -> 0 | O63: =IF(N$14=0,0,N63/N$14) -> 0 | P63: =IFERROR(P55/P61,0) -> 0 | Q63: =IF(P$14=0,0,P63/P$14) -> 0
B66: Business Debt Schedule
B67: Lender | C67: Current Balance | D67: Mthly Pmt | E67: Collateral | F67: Refinance? | G67: % of Loan | H67: Refi Pmt | I67: % Chg | J67: CF Debt Svc | K67: Reserved
C68: 0 | D68: 0 | G68: =IFERROR(@Table211[[#This Row],[Current Balance]]/'2. Sources and Uses'!$C$22,0) -> 0 | H68: =IFERROR(IF(@Table211[[#This Row],[Refinance?]]="Yes",PMT('1. Project Structure'!$C$16/12,'1. Project Structure'!$C$19,-(@Table211[[#This Row],[Current Balance]])),0),0) -> 0 | I68: =IFERROR((@Table211[[#This Row],[Mthly Pmt]]-@Table211[[#This Row],[Refi Pmt]])/@Table211[[#This Row],[Mthly Pmt]],0) -> 0 | J68: =IF(@Table211[[#This Row],[Refinance?]]="Yes",0,@Table211[[#This Row],[Mthly Pmt]]) -> 0
C69: 0 | D69: 0 | G69: =IFERROR(@Table211[[#This Row],[Current Balance]]/'2. Sources and Uses'!$C$22,0) -> 0 | H69: =IFERROR(IF(@Table211[[#This Row],[Refinance?]]="Yes",PMT('1. Project Structure'!$C$16/12,'1. Project Structure'!$C$19,-(@Table211[[#This Row],[Current Balance]])),0),0) -> 0 | I69: =IFERROR((@Table211[[#This Row],[Mthly Pmt]]-@Table211[[#This Row],[Refi Pmt]])/@Table211[[#This Row],[Mthly Pmt]],0) -> 0 | J69: =IF(@Table211[[#This Row],[Refinance?]]="Yes",0,@Table211[[#This Row],[Mthly Pmt]]) -> 0
C70: 0 | D70: 0 | G70: =IFERROR(@Table211[[#This Row],[Current Balance]]/'2. Sources and Uses'!$C$22,0) -> 0 | H70: =IFERROR(IF(@Table211[[#This Row],[Refinance?]]="Yes",PMT('1. Project Structure'!$C$16/12,'1. Project Structure'!$C$19,-(@Table211[[#This Row],[Current Balance]])),0),0) -> 0 | I70: =IFERROR((@Table211[[#This Row],[Mthly Pmt]]-@Table211[[#This Row],[Refi Pmt]])/@Table211[[#This Row],[Mthly Pmt]],0) -> 0 | J70: =IF(@Table211[[#This Row],[Refinance?]]="Yes",0,@Table211[[#This Row],[Mthly Pmt]]) -> 0
C71: 0 | D71: 0 | G71: =IFERROR(@Table211[[#This Row],[Current Balance]]/'2. Sources and Uses'!$C$22,0) -> 0 | H71: =IFERROR(IF(@Table211[[#This Row],[Refinance?]]="Yes",PMT('1. Project Structure'!$C$16/12,'1. Project Structure'!$C$19,-(@Table211[[#This Row],[Current Balance]])),0),0) -> 0 | I71: =IFERROR((@Table211[[#This Row],[Mthly Pmt]]-@Table211[[#This Row],[Refi Pmt]])/@Table211[[#This Row],[Mthly Pmt]],0) -> 0 | J71: =IF(@Table211[[#This Row],[Refinance?]]="Yes",0,@Table211[[#This Row],[Mthly Pmt]]) -> 0
C72: 0 | D72: 0 | G72: =IFERROR(@Table211[[#This Row],[Current Balance]]/'2. Sources and Uses'!$C$22,0) -> 0 | H72: =IFERROR(IF(@Table211[[#This Row],[Refinance?]]="Yes",PMT('1. Project Structure'!$C$16/12,'1. Project Structure'!$C$19,-(@Table211[[#This Row],[Current Balance]])),0),0) -> 0 | I72: =IFERROR((@Table211[[#This Row],[Mthly Pmt]]-@Table211[[#This Row],[Refi Pmt]])/@Table211[[#This Row],[Mthly Pmt]],0) -> 0 | J72: =IF(@Table211[[#This Row],[Refinance?]]="Yes",0,@Table211[[#This Row],[Mthly Pmt]]) -> 0
C73: 0 | D73: 0 | G73: =IFERROR(@Table211[[#This Row],[Current Balance]]/'2. Sources and Uses'!$C$22,0) -> 0 | H73: =IFERROR(IF(@Table211[[#This Row],[Refinance?]]="Yes",PMT('1. Project Structure'!$C$16/12,'1. Project Structure'!$C$19,-(@Table211[[#This Row],[Current Balance]])),0),0) -> 0 | I73: =IFERROR((@Table211[[#This Row],[Mthly Pmt]]-@Table211[[#This Row],[Refi Pmt]])/@Table211[[#This Row],[Mthly Pmt]],0) -> 0 | J73: =IF(@Table211[[#This Row],[Refinance?]]="Yes",0,@Table211[[#This Row],[Mthly Pmt]]) -> 0
C74: 0 | D74: 0 | G74: =IFERROR(@Table211[[#This Row],[Current Balance]]/'2. Sources and Uses'!$C$22,0) -> 0 | H74: =IFERROR(IF(@Table211[[#This Row],[Refinance?]]="Yes",PMT('1. Project Structure'!$C$16/12,'1. Project Structure'!$C$19,-(@Table211[[#This Row],[Current Balance]])),0),0) -> 0 | I74: =IFERROR((@Table211[[#This Row],[Mthly Pmt]]-@Table211[[#This Row],[Refi Pmt]])/@Table211[[#This Row],[Mthly Pmt]],0) -> 0 | J74: =IF(@Table211[[#This Row],[Refinance?]]="Yes",0,@Table211[[#This Row],[Mthly Pmt]]) -> 0
C75: 0 | D75: 0 | G75: =IFERROR(@Table211[[#This Row],[Current Balance]]/'2. Sources and Uses'!$C$22,0) -> 0 | H75: =IFERROR(IF(@Table211[[#This Row],[Refinance?]]="Yes",PMT('1. Project Structure'!$C$16/12,'1. Project Structure'!$C$19,-(@Table211[[#This Row],[Current Balance]])),0),0) -> 0 | I75: =IFERROR((@Table211[[#This Row],[Mthly Pmt]]-@Table211[[#This Row],[Refi Pmt]])/@Table211[[#This Row],[Mthly Pmt]],0) -> 0 | J75: =IF(@Table211[[#This Row],[Refinance?]]="Yes",0,@Table211[[#This Row],[Mthly Pmt]]) -> 0
C76: 0 | D76: 0 | G76: =IFERROR(@Table211[[#This Row],[Current Balance]]/'2. Sources and Uses'!$C$22,0) -> 0 | H76: =IFERROR(IF(@Table211[[#This Row],[Refinance?]]="Yes",PMT('1. Project Structure'!$C$16/12,'1. Project Structure'!$C$19,-(@Table211[[#This Row],[Current Balance]])),0),0) -> 0 | I76: =IFERROR((@Table211[[#This Row],[Mthly Pmt]]-@Table211[[#This Row],[Refi Pmt]])/@Table211[[#This Row],[Mthly Pmt]],0) -> 0 | J76: =IF(@Table211[[#This Row],[Refinance?]]="Yes",0,@Table211[[#This Row],[Mthly Pmt]]) -> 0
C77: 0 | D77: 0 | G77: =IFERROR(@Table211[[#This Row],[Current Balance]]/'2. Sources and Uses'!$C$22,0) -> 0 | H77: =IFERROR(IF(@Table211[[#This Row],[Refinance?]]="Yes",PMT('1. Project Structure'!$C$16/12,'1. Project Structure'!$C$19,-(@Table211[[#This Row],[Current Balance]])),0),0) -> 0 | I77: =IFERROR((@Table211[[#This Row],[Mthly Pmt]]-@Table211[[#This Row],[Refi Pmt]])/@Table211[[#This Row],[Mthly Pmt]],0) -> 0 | J77: =IF(@Table211[[#This Row],[Refinance?]]="Yes",0,@Table211[[#This Row],[Mthly Pmt]]) -> 0
B78: Total | C78: =SUBTOTAL(109,Table211[Current Balance]) -> 0 | H78: =SUBTOTAL(109,Table211[Refi Pmt]) -> 0 | J78: =SUBTOTAL(109,Table211[CF Debt Svc]) -> 0
B80: Curr Pmts on Debt to Be Refinanced | C80: =SUMIF(Table211[Refinance?],"Yes",Table211[Mthly Pmt]) -> 0 | D80: Proposed Pmt: | E80: =@Table211[[#Totals],[Refi Pmt]] -> 0 | F80: % Savings: | G80: =IFERROR(C80-E80/C80,0) -> 0

Sheet 4. PFS 
B1: Loan Structure
B2: Purchase and Sale Close Date, if known, otherwise Target Closing Date
B5: Entity Name: - Financials | D5: Role | F5: Yrs. In Bus. | G5: Guarantor?
I6: BDO:
I7: Cooperating BDO:
I8: Broker Name:
I9: Broker Fee:
B11: * List entities in the following order (as applicable): Borrower, Co-Borrower, Operating Entity, Corp. Guarantor, Affiliate.
B12: Individual Guarantor Info: | C12: Ownership Exp. (yrs) | D12: Ownership % | E12: FICO | F12: Prior BK? | G12: Prior Loss to Gov't | H12: Debarred by SBA? | I12: Pending Legal Action? | J12: Criminal History?
B20: Business / Property Address:
C21: (Street) | F21: (City) (State) (ZIP)
B23: Personal Financial Analysis | M23: + Collapse /Expand (Additional Individuals)
B25: Last Name, First Initial
B27: Liquid Assets* | C27: 0 | E27: 0 | G27: 0 | I27: 0 | N27: 0 | P27: 0 | R27: 0 | T27: 0
B28: Include in Global?
B29: Annual Income Sources other than SBC:
B30: Spouses salary/pension | C30: 0 | E30: 0 | G30: 0 | I30: 0 | N30: 0 | P30: 0 | R30: 0 | T30: 0
B31: Interest and Dividends | C31: 0 | E31: 0 | G31: 0 | I31: 0 | N31: 0 | P31: 0 | R31: 0 | T31: 0
B32: Business Income (Sch C) | C32: 0 | E32: 0 | G32: 0 | I32: 0 | N32: 0 | P32: 0 | R32: 0 | T32: 0
B33: Net Rental Income (Sch E) | C33: 0 | E33: 0 | G33: 0 | I33: 0 | N33: 0 | P33: 0 | R33: 0 | T33: 0
B34: Social Security Income | C34: 0 | E34: 0 | G34: 0 | I34: 0 | N34: 0 | P34: 0 | R34: 0 | T34: 0
B35: Other: (Income from Affiliate) | C35: 0 | E35: 0 | G35: 0 | I35: 0 | N35: 0 | P35: 0 | R35: 0 | T35: 0
B36: Other: (alimony, ongoing capital gains) | C36: 0 | E36: 0 | G36: 0 | I36: 0 | N36: 0 | P36: 0 | R36: 0 | T36: 0
B37: Total Annual Outside Income | C37: =SUM(C30:C36) -> 0 | E37: =SUM(E30:E36) -> 0 | G37: =SUM(G30:G36) -> 0 | I37: =SUM(I30:I36) -> 0 | N37: =SUM(N30:N36) -> 0 | P37: =SUM(P30:P36) -> 0 | R37: =SUM(R30:R36) -> 0 | T37: =SUM(T30:T36) -> 0
B39: Fixed Monthly Expenses:
B40: Home/Primary Residence | C40: 0 | E40: 0 | G40: 0 | I40: 0 | N40: 0 | P40: 0 | R40: 0 | T40: 0
B41: Other Mortgages | C41: 0 | E41: 0 | G41: 0 | I41: 0 | N41: 0 | P41: 0 | R41: 0 | T41: 0
B42: Other Installment Loans | C42: 0 | E42: 0 | G42: 0 | I42: 0 | N42: 0 | P42: 0 | R42: 0 | T42: 0
B43: Vehicle Loans | C43: 0 | E43: 0 | G43: 0 | I43: 0 | N43: 0 | P43: 0 | R43: 0 | T43: 0
B44: Credit Cards | C44: 0 | E44: 0 | G44: 0 | I44: 0 | N44: 0 | P44: 0 | R44: 0 | T44: 0
B45: Other: | C45: 0 | E45: 0 | G45: 0 | I45: 0 | N45: 0 | P45: 0 | R45: 0 | T45: 0
B46: Total Fixed Monthly Expenses | C46: =SUM(C40:C45) -> 0 | E46: =SUM(E40:E45) -> 0 | G46: =SUM(G40:G45) -> 0 | I46: =SUM(I40:I45) -> 0 | N46: =SUM(N40:N45) -> 0 | P46: =SUM(P40:P45) -> 0 | R46: =SUM(R40:R45) -> 0 | T46: =SUM(T40:T45) -> 0
B48: Annualized Monthly Fixed Expenses | C48: =C46*12 -> 0 | E48: =E46*12 -> 0 | G48: =G46*12 -> 0 | I48: =I46*12 -> 0 | N48: =N46*12 -> 0 | P48: =P46*12 -> 0 | R48: =R46*12 -> 0 | T48: =T46*12 -> 0
B49: Debt Ratio prior to draw | C49: =IF(C37=0,0,C48/C37) -> 0 | E49: =IF(E37=0,0,E48/E37) -> 0 | G49: =IF(G37=0,0,G48/G37) -> 0 | I49: =IF(I37=0,0,I48/I37) -> 0 | N49: =IF(N37=0,0,N48/N37) -> 0 | P49: =IF(P37=0,0,P48/P37) -> 0 | R49: =IF(R37=0,0,R48/R37) -> 0 | T49: =IF(T37=0,0,T48/T37) -> 0
B50: Calculated draw (Mo. Exp x2) | C50: =(C46*12/50)*100 -> 0 | E50: =(E46*12/50)*100 -> 0 | G50: =(G46*12/50)*100 -> 0 | I50: =(I46*12/50)*100 -> 0 | N50: =(N46*12/50)*100 -> 0 | P50: =(P46*12/50)*100 -> 0 | R50: =(R46*12/50)*100 -> 0 | T50: =(T46*12/50)*100 -> 0
B52: Monthly Expenses not Doubled
B53: Lifestyle Adjustment | C53: =C61 -> 0 | E53: =E61 -> 0 | G53: =G61 -> 0 | I53: =I61 -> 0 | N53: =N61 -> 0 | P53: =P61 -> 0 | R53: =R61 -> 0 | T53: =T61 -> 0
B54: Alimony Payments | C54: 0 | E54: 0 | G54: 0 | I54: 0 | N54: 0 | P54: 0 | R54: 0 | T54: 0
B55: Rental/Other Property Payments | C55: 0 | E55: 0 | G55: 0 | I55: 0 | N55: 0 | P55: 0 | R55: 0 | T55: 0
B56: Other | C56: 0 | E56: 0 | G56: 0 | I56: 0 | N56: 0 | P56: 0 | R56: 0 | T56: 0
C57: =SUM(C53:C56) -> 0 | E57: =SUM(E53:E56) -> 0 | G57: =SUM(G53:G56) -> 0 | I57: =SUM(I53:I56) -> 0 | N57: =SUM(N53:N56) -> 0 | P57: =SUM(P53:P56) -> 0 | R57: =SUM(R53:R56) -> 0 | T57: =SUM(T53:T56) -> 0
B59: Personal Expenses per PIE | C59: 0 | E59: 0 | G59: 0 | I59: 0 | N59: 0 | P59: 0 | R59: 0 | T59: 0
B60: Diff between calculated draw and PIE | C60: =C59-C50 -> 0 | E60: =E59-E50 -> 0 | G60: =G59-G50 -> 0 | I60: =I59-I50 -> 0 | N60: =N59-N50 -> 0 | P60: =P59-P50 -> 0 | R60: =R59-R50 -> 0 | T60: =T59-T50 -> 0
B61: Monthly Difference, included in cell D32 | C61: =IF(C50>C59,0,C60/12) -> 0 | E61: =IF(E50>E59,0,E60/12) -> 0 | G61: =IF(G50>G59,0,G60/12) -> 0 | I61: =IF(I50>I59,0,I60/12) -> 0 | N61: =IF(N50>N59,0,N60/12) -> 0 | P61: =IF(P50>P59,0,P60/12) -> 0 | R61: =IF(R50>R59,0,R60/12) -> 0 | T61: =IF(T50>T59,0,T60/12) -> 0
B64: Total Annual Need | C64: =C50+C57*12 -> 0 | E64: =E50+E57*12 -> 0 | G64: =G50+G57*12 -> 0 | I64: =I50+I57*12 -> 0 | N64: =N50+N57*12 -> 0 | P64: =P50+P57*12 -> 0 | R64: =R50+R57*12 -> 0 | T64: =T50+T57*12 -> 0
B65: Less Income from Outside Sources | C65: =C37 -> 0 | E65: =E37 -> 0 | G65: =G37 -> 0 | I65: =I37 -> 0 | N65: =N37 -> 0 | P65: =P37 -> 0 | R65: =R37 -> 0 | T65: =T37 -> 0
B67: Total Required Draw from SBC | C67: =IF(C68="Yes",IF(C64-C65<24000,24000,C64-C65),0) -> 0 | E67: =IF(E68="Yes",IF(E64-E65<24000,24000,E64-E65),0) -> 0 | G67: =IF(G68="Yes",IF(G64-G65<24000,24000,G64-G65),0) -> 0 | I67: =IF(I68="Yes",IF(I64-I65<24000,24000,I64-I65),0) -> 0 | N67: =IF(N68="Yes",IF(N64-N65<24000,24000,N64-N65),0) -> 0 | P67: =IF(P68="Yes",IF(P64-P65<24000,24000,P64-P65),0) -> 0 | R67: =IF(R68="Yes",IF(R64-R65<24000,24000,R64-R65),0) -> 0 | T67: =IF(T68="Yes",IF(T64-T65<24000,24000,T64-T65),0) -> 0
B68: Include Required Draw in CF?
B71: Liquidity Review
C73: Amount | D73: As of: | G73: Amount | H73: As of:
B74: Operating Company Liquidity | C74: 0 | F74: Affiliate 1 | G74: 0
B75: Owner/Guarantor 1 | C75: =C$27 -> 0 | F75: Affiliate 2 | G75: 0
B76: Owner/Guarantor 2 | C76: =E$27 -> 0 | F76: Affiliate 3 | G76: 0
B77: Owner/Guarantor 3 | C77: =G$27 -> 0 | F77: Affiliate 4 | G77: 0
B78: Owner/Guarantor 4 | C78: =I$27 -> 0 | F78: Affiliate 5 | G78: 0
B80: Owner/Guarantor 5 | C80: =C$27 -> 0
B81: Owner/Guarantor 6 | C81: =E$27 -> 0
B82: Owner/Guarantor 7 | C82: =G$27 -> 0
B83: Owner/Guarantor 8 | C83: =I$27 -> 0
B84: Expand / Collapse Additional Owners
C85: Total Available Liquidity | D85: =SUM(C74:C78,G74:G78) -> 0 | E85: Expected Injection | F85: ='1. Project Structure'!D45 -> 0 | G85: Remaining Available | H85: =D85-F85 -> 0

Sheet 5.Collateral
B2: Collateral Analysis
B3: Collateral Summary
B4: Collateral | C4: Prop Type | D4: Valuation Method | E4: Address | G4: Gross Value | H4: Liquidation Value | I4: Discounted Value | J4: Senior Liens | K4: Liquidation Value
B5: Primary Real Estate | E5: 9000 houston houston tx, 55994 | G5: 0 | H5: 0.85 | I5: =G5*H5 -> 0 | J5: 0 | K5: =IF(I5-J5<0,0,I5-J5) -> 0
B6: Secondary Real Estate | G6: 0 | H6: 0.85 | I6: =G6*H6 -> 0 | J6: 0 | K6: =IF(I6-J6<0,0,I6-J6) -> 0
B7: Secondary Real Estate | G7: 0 | H7: 0.85 | I7: =G7*H7 -> 0 | J7: 0 | K7: =IF(I7-J7<0,0,I7-J7) -> 0
B8: Accounts Receivable | E8: =IF(G8=0," ","") | G8: 0 | H8: 0.1 | I8: =G8*H8 -> 0 | J8: 0 | K8: =IF(I8-J8<0,0,I8-J8) -> 0
B9: Machinery & Equipment | E9: =IF(G9=0," ","") | G9: 0 | H9: 0.5 | I9: =G9*H9 -> 0 | J9: 0 | K9: =IF(I9-J9<0,0,I9-J9) -> 0
B10: Inventory | E10: =IF(G10=0," ","") | G10: 0 | H10: 0.1 | I10: =G10*H10 -> 0 | J10: 0 | K10: =IF(I10-J10<0,0,I10-J10) -> 0
B11: FF&E | E11: =IF(G11=0," ","") | G11: 0 | H11: 0.1 | I11: =G11*H11 -> 0 | J11: 0 | K11: =IF(I11-J11<0,0,I11-J11) -> 0
B12: Lease Hold Improvements | E12: =IF(G12=0," ","") | G12: 0 | H12: 0.05 | I12: =G12*H12 -> 0 | J12: 0 | K12: =IF(I12-J12<0,0,I12-J12) -> 0
B13: Miscellaneous | E13: =IF(G13=0," ","") | G13: 0 | H13: 0 | I13: =G13*H13 -> 0 | J13: 0 | K13: =IF(I13-J13<0,0,I13-J13) -> 0
F14: Totals | I14: =SUM(I5:I13) -> 0 | J14: =SUM(J5:J13) -> 0 | K14: =SUM(K5:K13) -> 0
B16: Loan Amount | C16: ='2. Sources and Uses'!C22 -> 0 | E16: Gross LTV | G16: =IFERROR((C16+J14)/G14,0) -> 0 | H16: Net LTV | J16: Net LTV | K16: =IFERROR((J14+C16)/I14,0) -> 0
B17: Discounted Collateral Value | C17: =K14 -> 0 | E17: Gross Coverage | G17: =IFERROR(G14/(C16+J14),0) -> 0 | H17: Net Coverage | J17: Net Coverage | K17: =IFERROR(I14/(J14+C16),0) -> 0
B18: Gross Exposure Amount | C18: =IF(C16-C17<0,0,C16-C17) -> 0
B19: SBA Gty % | C19: ='1. Project Structure'!J12 -> 0.75 | E19: Life Insurance Requirement | F19: Life Insurance Required | G19: =C16-(K5+K6+K7) -> 0
B20: SBA Guarantee Amount | C20: =IF(C18>0,C19*C18,0) -> 0
B21: Maximum Exposure | C21: =IF(C20>0,C18-C20,0) -> 0

Sheet Charts
B3: Loan Request | I3: Loan Request | N3: Loan Request | T3: Loan Request
C5: ='2. Sources and Uses'!C4 -> T Bank Loan | D5: ='2. Sources and Uses'!D4 -> Borrower | E5: ='2. Sources and Uses'!E4 -> Seller Note | F5: ='2. Sources and Uses'!F4 -> 3rd Party | G5: ='2. Sources and Uses'!G4 -> Total | J5: =C5 -> T Bank Loan | K5: =D5 -> Borrower | L5: =G5 -> Total | O5: =C5 -> T Bank Loan | P5: =D5 -> Borrower | Q5: =E5 -> Seller Note | R5: =G5 -> Total | U5: =C5 -> T Bank Loan | V5: =D5 -> Borrower | W5: =F5 -> 3rd Party | X5: =G5 -> Total
B6: ='2. Sources and Uses'!B6 -> Real Estate Acquisition | C6: ='2. Sources and Uses'!C6 -> 0 | D6: ='2. Sources and Uses'!D6 -> 0 | E6: ='2. Sources and Uses'!E6 -> 0 | F6: ='2. Sources and Uses'!F6 -> 0 | G6: ='2. Sources and Uses'!G6 -> 0 | I6: =B6 -> Real Estate Acquisition | J6: =C6 -> 0 | K6: =D6 -> 0 | L6: =G6 -> 0 | N6: =B6 -> Real Estate Acquisition | O6: =C6 -> 0 | P6: =D6 -> 0 | Q6: =E6 -> 0 | R6: =G6 -> 0 | T6: =B6 -> Real Estate Acquisition | U6: =C6 -> 0 | V6: =D6 -> 0 | W6: =F6 -> 0 | X6: =G6 -> 0
B7: ='2. Sources and Uses'!B7 -> Debt Refi - CRE | C7: ='2. Sources and Uses'!C7 -> 0 | D7: ='2. Sources and Uses'!D7 -> 0 | E7: ='2. Sources and Uses'!E7 -> 0 | F7: ='2. Sources and Uses'!F7 -> 0 | G7: ='2. Sources and Uses'!G7 -> 0 | I7: =B7 -> Debt Refi - CRE | J7: =C7 -> 0 | K7: =D7 -> 0 | L7: =G7 -> 0 | N7: =B7 -> Debt Refi - CRE | O7: =C7 -> 0 | P7: =D7 -> 0 | Q7: =E7 -> 0 | R7: =G7 -> 0 | T7: =B7 -> Debt Refi - CRE | U7: =C7 -> 0 | V7: =D7 -> 0 | W7: =F7 -> 0 | X7: =G7 -> 0
B8: ='2. Sources and Uses'!B8 -> Debt Refi - Non-CRE | C8: ='2. Sources and Uses'!C8 -> 0 | D8: ='2. Sources and Uses'!D8 -> 0 | E8: ='2. Sources and Uses'!E8 -> 0 | F8: ='2. Sources and Uses'!F8 -> 0 | G8: ='2. Sources and Uses'!G8 -> 0 | I8: =B8 -> Debt Refi - Non-CRE | J8: =C8 -> 0 | K8: =D8 -> 0 | L8: =G8 -> 0 | N8: =B8 -> Debt Refi - Non-CRE | O8: =C8 -> 0 | P8: =D8 -> 0 | Q8: =E8 -> 0 | R8: =G8 -> 0 | T8: =B8 -> Debt Refi - Non-CRE | U8: =C8 -> 0 | V8: =D8 -> 0 | W8: =F8 -> 0 | X8: =G8 -> 0
B9: ='2. Sources and Uses'!B9 -> Machinery & Equipment | C9: ='2. Sources and Uses'!C9 -> 0 | D9: ='2. Sources and Uses'!D9 -> 0 | E9: ='2. Sources and Uses'!E9 -> 0 | F9: ='2. Sources and Uses'!F9 -> 0 | G9: ='2. Sources and Uses'!G9 -> 0 | I9: =B9 -> Machinery & Equipment | J9: =C9 -> 0 | K9: =D9 -> 0 | L9: =G9 -> 0 | N9: =B9 -> Machinery & Equipment | O9: =C9 -> 0 | P9: =D9 -> 0 | Q9: =E9 -> 0 | R9: =G9 -> 0 | T9: =B9 -> Machinery & Equipment | U9: =C9 -> 0 | V9: =D9 -> 0 | W9: =F9 -> 0 | X9: =G9 -> 0
B10: ='2. Sources and Uses'!B10 -> Furniture & Fixtures (TIs) | C10: ='2. Sources and Uses'!C10 -> 0 | D10: ='2. Sources and Uses'!D10 -> 0 | E10: ='2. Sources and Uses'!E10 -> 0 | F10: ='2. Sources and Uses'!F10 -> 0 | G10: ='2. Sources and Uses'!G10 -> 0 | I10: =B10 -> Furniture & Fixtures (TIs) | J10: =C10 -> 0 | K10: =D10 -> 0 | L10: =G10 -> 0 | N10: =B10 -> Furniture & Fixtures (TIs) | O10: =C10 -> 0 | P10: =D10 -> 0 | Q10: =E10 -> 0 | R10: =G10 -> 0 | T10: =B10 -> Furniture & Fixtures (TIs) | U10: =C10 -> 0 | V10: =D10 -> 0 | W10: =F10 -> 0 | X10: =G10 -> 0
B11: ='2. Sources and Uses'!B11 -> Inventory | C11: ='2. Sources and Uses'!C11 -> 0 | D11: ='2. Sources and Uses'!D11 -> 0 | E11: ='2. Sources and Uses'!E11 -> 0 | F11: ='2. Sources and Uses'!F11 -> 0 | G11: ='2. Sources and Uses'!G11 -> 0 | I11: =B11 -> Inventory | J11: =C11 -> 0 | K11: =D11 -> 0 | L11: =G11 -> 0 | N11: =B11 -> Inventory | O11: =C11 -> 0 | P11: =D11 -> 0 | Q11: =E11 -> 0 | R11: =G11 -> 0 | T11: =B11 -> Inventory | U11: =C11 -> 0 | V11: =D11 -> 0 | W11: =F11 -> 0 | X11: =G11 -> 0
B12: ='2. Sources and Uses'!B12 -> Working Capital | C12: ='2. Sources and Uses'!C12 -> 0 | D12: ='2. Sources and Uses'!D12 -> 0 | E12: ='2. Sources and Uses'!E12 -> 0 | F12: ='2. Sources and Uses'!F12 -> 0 | G12: ='2. Sources and Uses'!G12 -> 0 | I12: =B12 -> Working Capital | J12: =C12 -> 0 | K12: =D12 -> 0 | L12: =G12 -> 0 | N12: =B12 -> Working Capital | O12: =C12 -> 0 | P12: =D12 -> 0 | Q12: =E12 -> 0 | R12: =G12 -> 0 | T12: =B12 -> Working Capital | U12: =C12 -> 0 | V12: =D12 -> 0 | W12: =F12 -> 0 | X12: =G12 -> 0
B13: ='2. Sources and Uses'!B13 -> Working Capital - Pre Opening | C13: ='2. Sources and Uses'!C13 -> 0 | D13: ='2. Sources and Uses'!D13 -> 0 | E13: ='2. Sources and Uses'!E13 -> 0 | F13: ='2. Sources and Uses'!F13 -> 0 | G13: ='2. Sources and Uses'!G13 -> 0 | I13: =B13 -> Working Capital - Pre Opening | J13: =C13 -> 0 | K13: =D13 -> 0 | L13: =G13 -> 0 | N13: =B13 -> Working Capital - Pre Opening | O13: =C13 -> 0 | P13: =D13 -> 0 | Q13: =E13 -> 0 | R13: =G13 -> 0 | T13: =B13 -> Working Capital - Pre Opening | U13: =C13 -> 0 | V13: =D13 -> 0 | W13: =F13 -> 0 | X13: =G13 -> 0
B14: ='2. Sources and Uses'!B14 -> Business Acquisition | C14: ='2. Sources and Uses'!C14 -> 0 | D14: ='2. Sources and Uses'!D14 -> 0 | E14: ='2. Sources and Uses'!E14 -> 0 | F14: ='2. Sources and Uses'!F14 -> 0 | G14: ='2. Sources and Uses'!G14 -> 0 | I14: =B14 -> Business Acquisition | J14: =C14 -> 0 | K14: =D14 -> 0 | L14: =G14 -> 0 | N14: =B14 -> Business Acquisition | O14: =C14 -> 0 | P14: =D14 -> 0 | Q14: =E14 -> 0 | R14: =G14 -> 0 | T14: =B14 -> Business Acquisition | U14: =C14 -> 0 | V14: =D14 -> 0 | W14: =F14 -> 0 | X14: =G14 -> 0
B15: ='2. Sources and Uses'!B15 -> Franchise Fees | C15: ='2. Sources and Uses'!C15 -> 0 | D15: ='2. Sources and Uses'!D15 -> 0 | E15: ='2. Sources and Uses'!E15 -> 0 | F15: ='2. Sources and Uses'!F15 -> 0 | G15: ='2. Sources and Uses'!G15 -> 0 | I15: =B15 -> Franchise Fees | J15: =C15 -> 0 | K15: =D15 -> 0 | L15: =G15 -> 0 | N15: =B15 -> Franchise Fees | O15: =C15 -> 0 | P15: =D15 -> 0 | Q15: =E15 -> 0 | R15: =G15 -> 0 | T15: =B15 -> Franchise Fees | U15: =C15 -> 0 | V15: =D15 -> 0 | W15: =F15 -> 0 | X15: =G15 -> 0
B16: ='2. Sources and Uses'!B16 -> Construction Hard Costs | C16: ='2. Sources and Uses'!C16 -> 0 | D16: ='2. Sources and Uses'!D16 -> 0 | E16: ='2. Sources and Uses'!E16 -> 0 | F16: ='2. Sources and Uses'!F16 -> 0 | G16: ='2. Sources and Uses'!G16 -> 0 | I16: =B16 -> Construction Hard Costs | J16: =C16 -> 0 | K16: =D16 -> 0 | L16: =G16 -> 0 | N16: =B16 -> Construction Hard Costs | O16: =C16 -> 0 | P16: =D16 -> 0 | Q16: =E16 -> 0 | R16: =G16 -> 0 | T16: =B16 -> Construction Hard Costs | U16: =C16 -> 0 | V16: =D16 -> 0 | W16: =F16 -> 0 | X16: =G16 -> 0
B17: ='2. Sources and Uses'!B17 -> Interim Interest Reserve | C17: ='2. Sources and Uses'!C17 -> 0 | D17: ='2. Sources and Uses'!D17 -> 0 | E17: ='2. Sources and Uses'!E17 -> 0 | F17: ='2. Sources and Uses'!F17 -> 0 | G17: ='2. Sources and Uses'!G17 -> 0 | I17: =B17 -> Interim Interest Reserve | J17: =C17 -> 0 | K17: =D17 -> 0 | L17: =G17 -> 0 | N17: =B17 -> Interim Interest Reserve | O17: =C17 -> 0 | P17: =D17 -> 0 | Q17: =E17 -> 0 | R17: =G17 -> 0 | T17: =B17 -> Interim Interest Reserve | U17: =C17 -> 0 | V17: =D17 -> 0 | W17: =F17 -> 0 | X17: =G17 -> 0
... B21: ='2. Sources and Uses'!B21 -> SBA Gty Fee | C21: ='2. Sources and Uses'!C21 -> 0 | D21: ='2. Sources and Uses'!D21 -> 0 | E21: ='2. Sources and Uses'!E21 | F21: ='2. Sources and Uses'!F21 | G21: ='2. Sources and Uses'!G21 -> 0 | I21: =B21 -> SBA Gty Fee | J21: =C21 -> 0 | K21: =D21 -> 0 | L21: =G21 -> 0 | N21: =B21 -> SBA Gty Fee | O21: =C21 -> 0 | P21: =D21 -> 0 | Q21: =E21 | R21: =G21 -> 0 | T21: =B21 -> SBA Gty Fee | U21: =C21 -> 0 | V21: =D21 -> 0 | W21: =F21 | X21: =G21 -> 0
B22: Project Total | C22: ='2. Sources and Uses'!C22 -> 0 | D22: ='2. Sources and Uses'!D22 -> 0 | E22: ='2. Sources and Uses'!E22 -> 0 | F22: ='2. Sources and Uses'!F22 -> 0 | G22: ='2. Sources and Uses'!G22 -> 0 | I22: =B22 -> Project Total | J22: =C22 -> 0 | K22: =D22 -> 0 | L22: =G22 -> 0 | N22: =B22 -> Project Total | O22: =C22 -> 0 | P22: =D22 -> 0 | Q22: =E22 -> 0 | R22: =G22 -> 0 | T22: =B22 -> Project Total | U22: =C22 -> 0 | V22: =D22 -> 0 | W22: =F22 -> 0 | X22: =G22 -> 0
B23: Percentages | C23: ='2. Sources and Uses'!C23 -> 0 | D23: ='2. Sources and Uses'!D23 -> 0 | E23: ='2. Sources and Uses'!E23 -> 0 | F23: ='2. Sources and Uses'!F23 -> 0 | G23: ='2. Sources and Uses'!G23 -> 0 | I23: =B23 -> Percentages | J23: =C23 -> 0 | K23: =D23 -> 0 | L23: =G23 -> 0 | N23: =B23 -> Percentages | O23: =C23 -> 0 | P23: =D23 -> 0 | Q23: =E23 -> 0 | R23: =G23 -> 0 | T23: =B23 -> Percentages | U23: =C23 -> 0 | V23: =D23 -> 0 | W23: =F23 -> 0 | X23: =G23 -> 0
B26: Closing & 3rd Party Costs
B27: (Estimated)
B28: ='2. Sources and Uses'!B39 -> Loan Packaging Fee | C28: ='2. Sources and Uses'!C39 -> 2500 | D28: ='2. Sources and Uses'!D39 -> 1 | E28: ='2. Sources and Uses'!E39 -> 2500
B29: ='2. Sources and Uses'!B40 -> Title Insurance | C29: ='2. Sources and Uses'!C40 -> 0 | D29: ='2. Sources and Uses'!D40 -> 0 | E29: ='2. Sources and Uses'!E40 -> 0
B30: ='2. Sources and Uses'!B41 -> Real Estate Tax Fee | C30: ='2. Sources and Uses'!C41 -> 0 | D30: ='2. Sources and Uses'!D41 -> 0 | E30: ='2. Sources and Uses'!E41 -> 0
B31: ='2. Sources and Uses'!B42 -> Survey Charges | C31: ='2. Sources and Uses'!C42 -> 3000 | D31: ='2. Sources and Uses'!D42 -> 0 | E31: ='2. Sources and Uses'!E42 -> 0
B32: ='2. Sources and Uses'!B43 -> CRE Appraisal | C32: ='2. Sources and Uses'!C43 -> 3500 | D32: ='2. Sources and Uses'!D43 -> 0 | E32: ='2. Sources and Uses'!E43 -> 0
B33: ='2. Sources and Uses'!B44 -> Equipment Appraisal | C33: ='2. Sources and Uses'!C44 -> 0 | D33: ='2. Sources and Uses'!D44 -> 0 | E33: ='2. Sources and Uses'!E44 -> 0
B34: ='2. Sources and Uses'!B45 -> Appraisal Review | C34: ='2. Sources and Uses'!C45 -> 0 | D34: ='2. Sources and Uses'!D45 -> 0 | E34: ='2. Sources and Uses'!E45 -> 0
B35: ='2. Sources and Uses'!B46 -> Site Visit | C35: ='2. Sources and Uses'!C46 -> 350 | D35: ='2. Sources and Uses'!D46 -> 0 | E35: ='2. Sources and Uses'!E46 -> 0
B36: ='2. Sources and Uses'!B47 -> Environmental Investigation | C36: ='2. Sources and Uses'!C47 -> 2500 | D36: ='2. Sources and Uses'!D47 -> 0 | E36: ='2. Sources and Uses'!E47 -> 0
B37: ='2. Sources and Uses'!B48 -> Business Valuation | C37: ='2. Sources and Uses'!C48 -> 2500 | D37: ='2. Sources and Uses'!D48 -> 0 | E37: ='2. Sources and Uses'!E48 -> 0
B38: ='2. Sources and Uses'!B49 -> Residential Appr/Valuation | C38: ='2. Sources and Uses'!C49 -> 0 | D38: ='2. Sources and Uses'!D49 -> 0 | E38: ='2. Sources and Uses'!E49 -> 0
B39: ='2. Sources and Uses'!B50 -> Attorney Doc Prep | C39: ='2. Sources and Uses'!C50 -> 6000 | D39: ='2. Sources and Uses'!D50 -> 1 | E39: ='2. Sources and Uses'!E50 -> 6000
... B43: ='2. Sources and Uses'!B54 -> Other: UCCs and Misc Closing | C43: ='2. Sources and Uses'!C54 | D43: ='2. Sources and Uses'!D54 | E43: ='2. Sources and Uses'!E54 -> 800
B44: Total Estimated Closing Costs | E44: ='2. Sources and Uses'!E55 -> 10000
B47: Structure Table
C49: ='1. Project Structure'!C11 -> T Bank Loan | D49: ='1. Project Structure'!E11 -> Seller Note | E49: ='1. Project Structure'!F11 -> 3rd Party
B50: Loan Amount | C50: ='1. Project Structure'!C13 -> 0 | D50: ='1. Project Structure'!E13 -> 0 | E50: ='1. Project Structure'!F13 -> 0
B51: ='1. Project Structure'!B14 -> Base Rate | C51: ='1. Project Structure'!C14 -> 0.075 | D51: ='1. Project Structure'!E14 -> 0.08 | E51: ='1. Project Structure'!F14 -> 0.0624
B52: ='1. Project Structure'!B15 -> Spread | C52: ='1. Project Structure'!C15 -> 0.015 | D52: ='1. Project Structure'!E15 -> 0 | E52: ='1. Project Structure'!F15 -> 0
B53: ='1. Project Structure'!B16 -> Indicative Rate | C53: ='1. Project Structure'!C16 -> 0.09 | D53: ='1. Project Structure'!E16 -> 0.08 | E53: ='1. Project Structure'!F16 -> 0.0624
B54: Adjustment / Fix | C54: Quarterly | D54: Fixed | E54: Fixed
B55: ='1. Project Structure'!B18 -> Term (years) | C55: ='1. Project Structure'!C18 -> 10 | D55: ='1. Project Structure'!E18 -> 10 | E55: ='1. Project Structure'!F18 -> 25
B56: ='1. Project Structure'!B20 -> Estimated Payment | C56: ='1. Project Structure'!C20 -> 0 | D56: ='1. Project Structure'!E20 -> 0 | E56: ='1. Project Structure'!F20 -> 0
B59: Blended Rate Table
B60: Bank Loan with CDC Loan
C61: Loan | D61: Est. Payment | E61: Rate
B62: ='1. Project Structure'!C11 -> T Bank Loan | C62: ='1. Project Structure'!C33 -> 0 | D62: ='1. Project Structure'!C20 -> 0 | E62: ='1. Project Structure'!C16 -> 0.09
B63: ='1. Project Structure'!F11 -> 3rd Party | C63: ='1. Project Structure'!F13 -> 0 | D63: ='1. Project Structure'!F20 -> 0 | E63: ='1. Project Structure'!F16 -> 0.0624
B64: Total/Blend | C64: ='2. Sources and Uses'!E22+'2. Sources and Uses'!F65 -> 0 | D64: ='1. Project Structure'!C20+'1. Project Structure'!F20 -> 0 | E64: =(C62*E62+C63*E63)/C64 -> #DIV/0!
B67: Collateral Analysis
B69: Address | D69: Gross Value | E69: Liquidation Value | F69: Discounted Value | G69: Senior Liens | H69: Liquidation Value
B70: ='5.Collateral'!E5 -> 9000 houston houston tx, 55994 | D70: ='5.Collateral'!G5 -> 0 | E70: ='5.Collateral'!H5 -> 0.85 | F70: ='5.Collateral'!I5 -> 0 | G70: ='5.Collateral'!J5 -> 0 | H70: ='5.Collateral'!K5 -> 0
B71: ='5.Collateral'!E6 | D71: ='5.Collateral'!G6 -> 0 | E71: ='5.Collateral'!H6 -> 0.85 | F71: ='5.Collateral'!I6 -> 0 | G71: ='5.Collateral'!J6 -> 0 | H71: ='5.Collateral'!K6 -> 0
B72: ='5.Collateral'!E7 | D72: ='5.Collateral'!G7 -> 0 | E72: ='5.Collateral'!H7 -> 0.85 | F72: ='5.Collateral'!I7 -> 0 | G72: ='5.Collateral'!J7 -> 0 | H72: ='5.Collateral'!K7 -> 0
B73: ='5.Collateral'!E8 | D73: ='5.Collateral'!G8 -> 0 | E73: ='5.Collateral'!H8 -> 0.1 | F73: ='5.Collateral'!I8 -> 0 | G73: ='5.Collateral'!J8 -> 0 | H73: ='5.Collateral'!K8 -> 0
B74: ='5.Collateral'!E9 | D74: ='5.Collateral'!G9 -> 0 | E74: ='5.Collateral'!H9 -> 0.5 | F74: ='5.Collateral'!I9 -> 0 | G74: ='5.Collateral'!J9 -> 0 | H74: ='5.Collateral'!K9 -> 0
B75: ='5.Collateral'!E10 | D75: ='5.Collateral'!G10 -> 0 | E75: ='5.Collateral'!H10 -> 0.1 | F75: ='5.Collateral'!I10 -> 0 | G75: ='5.Collateral'!J10 -> 0 | H75: ='5.Collateral'!K10 -> 0
B76: ='5.Collateral'!E11 | D76: ='5.Collateral'!G11 -> 0 | E76: ='5.Collateral'!H11 -> 0.1 | F76: ='5.Collateral'!I11 -> 0 | G76: ='5.Collateral'!J11 -> 0 | H76: ='5.Collateral'!K11 -> 0
B77: ='5.Collateral'!E12 | D77: ='5.Collateral'!G12 -> 0 | E77: ='5.Collateral'!H12 -> 0.05 | F77: ='5.Collateral'!I12 -> 0 | G77: ='5.Collateral'!J12 -> 0 | H77: ='5.Collateral'!K12 -> 0
B78: ='5.Collateral'!E13 | D78: ='5.Collateral'!G13 -> 0 | E78: ='5.Collateral'!H13 -> 0 | F78: ='5.Collateral'!I13 -> 0 | G78: ='5.Collateral'!J13 -> 0 | H78: ='5.Collateral'!K13 -> 0
C79: Totals | D79: ='5.Collateral'!G14 | F79: ='5.Collateral'!I14 -> 0 | G79: ='5.Collateral'!J14 -> 0 | H79: ='5.Collateral'!K14 -> 0
B81: Gross LTV | D81: ='5.Collateral'!G16 -> 0 | E81: Net LTV | G81: Net LTV | H81: ='5.Collateral'!K16 -> 0
B82: Gross Coverage | D82: ='5.Collateral'!G17 -> 0 | E82: Net Coverage | G82: Net Coverage | H82: ='5.Collateral'!K17 -> 0
B85: Liquidity Analysis
B87: ='4. PFS '!B74 -> Operating Company Liquidity | C87: ='4. PFS '!C74 -> 0
B88: ='4. PFS '!B75 -> Owner/Guarantor 1 | C88: ='4. PFS '!C75 -> 0
B89: ='4. PFS '!B76 -> Owner/Guarantor 2 | C89: ='4. PFS '!C76 -> 0
B90: ='4. PFS '!B77 -> Owner/Guarantor 3 | C90: ='4. PFS '!C77 -> 0
B91: ='4. PFS '!B78 -> Owner/Guarantor 4 | C91: ='4. PFS '!C78 -> 0
B92: ='4. PFS '!F74 -> Affiliate 1 | C92: ='4. PFS '!G74 -> 0
B93: ='4. PFS '!F75 -> Affiliate 2 | C93: ='4. PFS '!G75 -> 0
B94: ='4. PFS '!F76 -> Affiliate 3 | C94: ='4. PFS '!G76 -> 0
B95: ='4. PFS '!F77 -> Affiliate 4 | C95: ='4. PFS '!G77 -> 0
B96: ='4. PFS '!F78 -> Affiliate 5 | C96: ='4. PFS '!G78 -> 0
B97: ='4. PFS '!C85 -> Total Available Liquidity | C97: ='4. PFS '!D85 -> 0
B98: ='4. PFS '!E85 -> Expected Injection | C98: ='4. PFS '!F85 -> 0
B99: Post Close Liquidity | C99: ='4. PFS '!H85 -> 0
B102: Stand-Alone DSCR
B104: ='3. Financials'!B4 -> {Insert business name which represents PSOR} | G104: Projections
C106: ='3. Financials'!D6 -> 44926 | D106: ='3. Financials'!F6 -> 45291 | E106: ='3. Financials'!H6 -> 45657 | F106: ='3. Financials'!J6 -> 45747 | G106: Year 1 | H106: Year 2
F107: ='3. Financials'!J10
B108: ='3. Financials'!C14 -> Total Revenue | C108: ='3. Financials'!D14 -> 0 | D108: ='3. Financials'!F14 -> 0 | E108: ='3. Financials'!H14 -> 0 | F108: ='3. Financials'!J14 -> 0 | G108: ='3. Financials'!N14 -> 0 | H108: ='3. Financials'!P14 -> 0
B109: ='3. Financials'!C15 -> Total COGS | C109: ='3. Financials'!D15 -> 0 | D109: ='3. Financials'!F15 -> 0 | E109: ='3. Financials'!H15 -> 0 | F109: ='3. Financials'!J15 -> 0 | G109: ='3. Financials'!N15 -> 0 | H109: ='3. Financials'!P15 -> 0
B110: ='3. Financials'!C16 -> Total Gross Margin | C110: ='3. Financials'!D16 -> 0 | D110: ='3. Financials'!F16 -> 0 | E110: ='3. Financials'!H16 -> 0 | F110: ='3. Financials'!J16 -> 0 | G110: ='3. Financials'!N16 -> 0 | H110: ='3. Financials'!P16 -> 0
B111: ='3. Financials'!C30 -> Total Operating Expenses | C111: ='3. Financials'!D30 -> 0 | D111: ='3. Financials'!F30 -> 0 | E111: ='3. Financials'!H30 -> 0 | F111: ='3. Financials'!J30 -> 0 | G111: ='3. Financials'!N30 -> 0 | H111: ='3. Financials'!P30 -> 0
B112: ='3. Financials'!C32 -> Ordinary Income | C112: ='3. Financials'!D32 -> 0 | D112: ='3. Financials'!F32 -> 0 | E112: ='3. Financials'!H32 -> 0 | F112: ='3. Financials'!J32 -> 0 | G112: ='3. Financials'!N32 -> 0 | H112: ='3. Financials'!P32 -> 0
B113: ='3. Financials'!C38 -> Total Other Income (Expenses) | C113: ='3. Financials'!D38 -> 0 | D113: ='3. Financials'!F38 -> 0 | E113: ='3. Financials'!H38 -> 0 | F113: ='3. Financials'!J38 -> 0 | G113: ='3. Financials'!N38 -> 0 | H113: ='3. Financials'!P38 -> 0
B114: ='3. Financials'!C40 -> Net Income Before Taxes | C114: ='3. Financials'!D40 -> 0 | D114: ='3. Financials'!F40 -> 0 | E114: ='3. Financials'!H40 -> 0 | F114: ='3. Financials'!J40 -> 0 | G114: ='3. Financials'!N40 -> 0 | H114: ='3. Financials'!P40 -> 0
B115: ='3. Financials'!C41 -> Income Taxes | C115: ='3. Financials'!D41 -> 0 | D115: ='3. Financials'!F41 -> 0 | E115: ='3. Financials'!H41 -> 0 | F115: ='3. Financials'!J41 -> 0 | G115: ='3. Financials'!N41 -> 0 | H115: ='3. Financials'!P41 -> 0
B116: ='3. Financials'!C43 -> NET INCOME AFTER TAXES | C116: ='3. Financials'!D43 -> 0 | D116: ='3. Financials'!F43 -> 0 | E116: ='3. Financials'!H43 -> 0 | F116: ='3. Financials'!J43 -> 0 | G116: ='3. Financials'!N43 -> 0 | H116: ='3. Financials'!P43 -> 0
B118: Add Backs :
B119: ='3. Financials'!C46 -> + Compensation of Officers | C119: ='3. Financials'!D46 -> 0 | D119: ='3. Financials'!F46 -> 0 | E119: ='3. Financials'!H46 -> 0 | F119: ='3. Financials'!J46 -> 0 | G119: ='3. Financials'!N46 -> 0 | H119: ='3. Financials'!P46 -> 0
B120: ='3. Financials'!C47 -> + Depreciation/Amortization | C120: ='3. Financials'!D47 -> 0 | D120: ='3. Financials'!F47 -> 0 | E120: ='3. Financials'!H47 -> 0 | F120: ='3. Financials'!J47 -> 0 | G120: ='3. Financials'!N47 -> 0 | H120: ='3. Financials'!P47 -> 0
B121: ='3. Financials'!C48 -> + Interest Expense | C121: ='3. Financials'!D48 -> 0 | D121: ='3. Financials'!F48 -> 0 | E121: ='3. Financials'!H48 -> 0 | F121: ='3. Financials'!J48 -> 0 | G121: ='3. Financials'!N48 -> 0 | H121: ='3. Financials'!P48 -> 0
B122: ='3. Financials'!C49 -> + Rent Add Back | C122: ='3. Financials'!D49 -> 0 | D122: ='3. Financials'!F49 -> 0 | E122: ='3. Financials'!H49 -> 0 | F122: ='3. Financials'!J49 -> 0 | G122: ='3. Financials'!N49 -> 0 | H122: ='3. Financials'!P49 -> 0
B123: ='3. Financials'!C50 -> + - Other | C123: ='3. Financials'!D50 -> 0 | D123: ='3. Financials'!F50 -> 0 | E123: ='3. Financials'!H50 -> 0 | F123: ='3. Financials'!J50 -> 0 | G123: ='3. Financials'!N50 -> 0 | H123: ='3. Financials'!P50 -> 0
B124: ='3. Financials'!C51 -> + - Other | C124: ='3. Financials'!D51 -> 0 | D124: ='3. Financials'!F51 -> 0 | E124: ='3. Financials'!H51 -> 0 | F124: ='3. Financials'!J51 -> 0 | G124: ='3. Financials'!N51 -> 0 | H124: ='3. Financials'!P51 -> 0
B125: ='3. Financials'!C52 -> - Estimated Property Tax | C125: ='3. Financials'!D52 -> 0 | D125: ='3. Financials'!F52 -> 0 | E125: ='3. Financials'!H52 -> 0 | F125: ='3. Financials'!J52 -> 0 | G125: ='3. Financials'!N52 -> 0 | H125: ='3. Financials'!P52 -> 0
B126: ='3. Financials'!C53 -> - Required Owner's Draw | C126: ='3. Financials'!D53 -> 0 | D126: ='3. Financials'!F53 -> 0 | E126: ='3. Financials'!H53 -> 0 | F126: ='3. Financials'!J53 -> 0 | G126: ='3. Financials'!N53 -> 0 | H126: ='3. Financials'!P53 -> 0
B128: ='3. Financials'!C55 -> Cash Available | C128: ='3. Financials'!D55 -> 0 | D128: ='3. Financials'!F55 -> 0 | E128: ='3. Financials'!H55 -> 0 | F128: ='3. Financials'!J55 -> 0 | G128: ='3. Financials'!N55 -> 0 | H128: ='3. Financials'!P55 -> 0
B130: ='3. Financials'!C57 -> Existing Debt | C130: ='3. Financials'!D57 -> 0 | D130: ='3. Financials'!F57 -> 0 | E130: ='3. Financials'!H57 -> 0 | F130: ='3. Financials'!J57 -> 0 | G130: ='3. Financials'!N57 -> 0 | H130: ='3. Financials'!P57 -> 0
...

Sheet 6. Affiliates
B2: Affiliate Analysis
B3: Income Statement Spreads
B4: {Insert business name which represents Affiliate 1}
B5: Include in Global? | C5: No
B6: Statement Date | D6: 44926 | F6: =EOMONTH(D6,F7) -> 45291 | H6: =EOMONTH(F6,H7) -> 45657 | J6: =EOMONTH(H6,J7) -> 45747
B7: Months Covered | D7: 12 | F7: 12 | H7: 12 | J7: 3
B8: Statement Type | D8: Tax Returns | F8: Tax Returns | J8: Internal
B9: Revenue Recognition
B10: REVENUE | J10: =(J11/J7)*12 -> 0
B11: Revenue | C11: (Product Line #1) | D11: 0 | E11: =IF(D$20=0,0,D11/D$20) -> 0 | F11: 0 | G11: =IF(F$20=0,0,F11/F$20) -> 0 | H11: 0 | I11: =IF(H$20=0,0,H11/H$20) -> 0 | J11: 0 | K11: =IF(J$20=0,0,J11/J$20) -> 0
B12: COGS | C12: (Product Line #1) | D12: 0 | E12: =IF(D$20=0,0,D12/D$20) -> 0 | F12: 0 | G12: =IF(F$20=0,0,F12/F$20) -> 0 | H12: 0 | I12: =IF(H$20=0,0,H12/H$20) -> 0 | J12: 0 | K12: =IF(J$20=0,0,J12/J$20) -> 0
B13: Gross Margin | C13: (Product Line #1) | D13: =D11-D12 -> 0 | E13: =IF(D$20=0,0,D13/D$20) -> 0 | F13: =F11-F12 -> 0 | G13: =IF(F$20=0,0,F13/F$20) -> 0 | H13: =H11-H12 -> 0 | I13: =IF(H$20=0,0,H13/H$20) -> 0 | J13: =J11-J12 -> 0 | K13: =IF(J$20=0,0,J13/J$20) -> 0
B14: Revenue | C14: (Product Line #2) | D14: 0 | E14: =IF(D$20=0,0,D14/D$20) -> 0 | F14: 0 | G14: =IF(F$20=0,0,F14/F$20) -> 0 | H14: 0 | I14: =IF(H$20=0,0,H14/H$20) -> 0 | J14: 0 | K14: =IF(J$20=0,0,J14/J$20) -> 0
B15: COGS | C15: (Product Line #2) | D15: 0 | E15: =IF(D$20=0,0,D15/D$20) -> 0 | F15: 0 | G15: =IF(F$20=0,0,F15/F$20) -> 0 | H15: 0 | I15: =IF(H$20=0,0,H15/H$20) -> 0 | J15: 0 | K15: =IF(J$20=0,0,J15/J$20) -> 0
B16: Gross Margin | C16: (Product Line #2) | D16: =D14-D15 -> 0 | E16: =IF(D$20=0,0,D16/D$20) -> 0 | F16: =F14-F15 -> 0 | G16: =IF(F$20=0,0,F16/F$20) -> 0 | H16: =H14-H15 -> 0 | I16: =IF(H$20=0,0,H16/H$20) -> 0 | J16: =J14-J15 -> 0 | K16: =IF(J$20=0,0,J16/J$20) -> 0
B17: Revenue | C17: (Product Line #3) | D17: 0 | E17: =IF(D$20=0,0,D17/D$20) -> 0 | F17: 0 | G17: =IF(F$20=0,0,F17/F$20) -> 0 | H17: 0 | I17: =IF(H$20=0,0,H17/H$20) -> 0 | J17: 0 | K17: =IF(J$20=0,0,J17/J$20) -> 0
B18: COGS | C18: (Product Line #3) | D18: 0 | E18: =IF(D$20=0,0,D18/D$20) -> 0 | F18: 0 | G18: =IF(F$20=0,0,F18/F$20) -> 0 | H18: 0 | I18: =IF(H$20=0,0,H18/H$20) -> 0 | J18: 0 | K18: =IF(J$20=0,0,J18/J$20) -> 0
B19: Gross Margin | C19: (Product Line #3) | D19: =D17-D18 -> 0 | E19: =IF(D$20=0,0,D19/D$20) -> 0 | F19: =F17-F18 -> 0 | G19: =IF(F$20=0,0,F19/F$20) -> 0 | H19: =H17-H18 -> 0 | I19: =IF(H$20=0,0,H19/H$20) -> 0 | J19: =J17-J18 -> 0 | K19: =IF(J$20=0,0,J19/J$20) -> 0
B20: Click to expand/collapse | C20: Total Revenue | D20: =D11+D14+D17 -> 0 | E20: =IF(D$20=0,0,D20/D$20) -> 0 | F20: =F11+F14+F17 -> 0 | G20: =IF(F$20=0,0,F20/F$20) -> 0 | H20: =H11+H14+H17 -> 0 | I20: =IF(H$20=0,0,H20/H$20) -> 0 | J20: =J11+J14+J17 -> 0 | K20: =IF(J$20=0,0,J20/J$20) -> 0
C21: Total COGS | D21: =D12+D15+D18 -> 0 | E21: =IF(D$20=0,0,D21/D$20) -> 0 | F21: =F12+F15+F18 -> 0 | G21: =IF(F$20=0,0,F21/F$20) -> 0 | H21: =H12+H15+H18 -> 0 | I21: =IF(H$20=0,0,H21/H$20) -> 0 | J21: =J12+J15+J18 -> 0 | K21: =IF(J$20=0,0,J21/J$20) -> 0
C22: Total Gross Margin | D22: =D20-D21 -> 0 | E22: =IF(D$20=0,0,D22/D$20) -> 0 | F22: =F20-F21 -> 0 | G22: =IF(F$20=0,0,F22/F$20) -> 0 | H22: =H20-H21 -> 0 | I22: =IF(H$20=0,0,H22/H$20) -> 0 | J22: =J20-J21 -> 0 | K22: =IF(J$20=0,0,J22/J$20) -> 0
C24: OPERATING EXPENSES
C25: Officer's Compensation | D25: 0 | E25: =IF(D$20=0,0,D25/D$20) -> 0 | F25: 0 | G25: =IF(F$20=0,0,F25/F$20) -> 0 | H25: 0 | I25: =IF(H$20=0,0,H25/H$20) -> 0 | J25: 0 | K25: =IF(J$20=0,0,J25/J$20) -> 0
C26: Salaries & Wages | D26: 0 | E26: =IF(D$20=0,0,D26/D$20) -> 0 | F26: 0 | G26: =IF(F$20=0,0,F26/F$20) -> 0 | H26: 0 | I26: =IF(H$20=0,0,H26/H$20) -> 0 | J26: 0 | K26: =IF(J$20=0,0,J26/J$20) -> 0
C27: Repairs & Maintenance | D27: 0 | E27: =IF(D$20=0,0,D27/D$20) -> 0 | F27: 0 | G27: =IF(F$20=0,0,F27/F$20) -> 0 | H27: 0 | I27: =IF(H$20=0,0,H27/H$20) -> 0 | J27: 0 | K27: =IF(J$20=0,0,J27/J$20) -> 0
C28: Bad Debts | D28: 0 | E28: =IF(D$20=0,0,D28/D$20) -> 0 | F28: 0 | G28: =IF(F$20=0,0,F28/F$20) -> 0 | H28: 0 | I28: =IF(H$20=0,0,H28/H$20) -> 0 | J28: 0 | K28: =IF(J$20=0,0,J28/J$20) -> 0
C29: Rents | D29: 0 | E29: =IF(D$20=0,0,D29/D$20) -> 0 | F29: 0 | G29: =IF(F$20=0,0,F29/F$20) -> 0 | H29: 0 | I29: =IF(H$20=0,0,H29/H$20) -> 0 | J29: 0 | K29: =IF(J$20=0,0,J29/J$20) -> 0
C30: Taxes & Licenses | D30: 0 | E30: =IF(D$20=0,0,D30/D$20) -> 0 | F30: 0 | G30: =IF(F$20=0,0,F30/F$20) -> 0 | H30: 0 | I30: =IF(H$20=0,0,H30/H$20) -> 0 | J30: 0 | K30: =IF(J$20=0,0,J30/J$20) -> 0
C31: Interest | D31: 0 | E31: =IF(D$20=0,0,D31/D$20) -> 0 | F31: 0 | G31: =IF(F$20=0,0,F31/F$20) -> 0 | H31: 0 | I31: =IF(H$20=0,0,H31/H$20) -> 0 | J31: 0 | K31: =IF(J$20=0,0,J31/J$20) -> 0
C32: Depreciation & Amortization | D32: 0 | E32: =IF(D$20=0,0,D32/D$20) -> 0 | F32: 0 | G32: =IF(F$20=0,0,F32/F$20) -> 0 | H32: 0 | I32: =IF(H$20=0,0,H32/H$20) -> 0 | J32: 0 | K32: =IF(J$20=0,0,J32/J$20) -> 0
C33: Advertising | D33: 0 | E33: =IF(D$20=0,0,D33/D$20) -> 0 | F33: 0 | G33: =IF(F$20=0,0,F33/F$20) -> 0 | H33: 0 | I33: =IF(H$20=0,0,H33/H$20) -> 0 | J33: 0 | K33: =IF(J$20=0,0,J33/J$20) -> 0
C34: Pension, Profit Sharing | D34: 0 | E34: =IF(D$20=0,0,D34/D$20) -> 0 | F34: 0 | G34: =IF(F$20=0,0,F34/F$20) -> 0 | H34: 0 | I34: =IF(H$20=0,0,H34/H$20) -> 0 | J34: 0 | K34: =IF(J$20=0,0,J34/J$20) -> 0
C35: Employee Benefits | D35: 0 | E35: =IF(D$20=0,0,D35/D$20) -> 0 | F35: 0 | G35: =IF(F$20=0,0,F35/F$20) -> 0 | H35: 0 | I35: =IF(H$20=0,0,H35/H$20) -> 0 | J35: 0 | K35: =IF(J$20=0,0,J35/J$20) -> 0
C36: Insurance | D36: 0 | E36: =IF(D$20=0,0,D36/D$20) -> 0 | F36: 0 | G36: =IF(F$20=0,0,F36/F$20) -> 0 | H36: 0 | I36: =IF(H$20=0,0,H36/H$20) -> 0 | J36: 0 | K36: =IF(J$20=0,0,J36/J$20) -> 0
... C46: Other | D46: 0 | E46: =IF(D$20=0,0,D46/D$20) -> 0 | F46: 0 | G46: =IF(F$20=0,0,F46/F$20) -> 0 | H46: 0 | I46: =IF(H$20=0,0,H46/H$20) -> 0 | J46: 0 | K46: =IF(J$20=0,0,J46/J$20) -> 0
B47: Click to expand/collapse | C47: Other | D47: 0 | E47: =IF(D$20=0,0,D47/D$20) -> 0 | F47: 0 | G47: =IF(F$20=0,0,F47/F$20) -> 0 | H47: 0 | I47: =IF(H$20=0,0,H47/H$20) -> 0 | J47: 0 | K47: =IF(J$20=0,0,J47/J$20) -> 0
C48: Other | D48: =0-SUM(D25:D47) -> 0 | E48: =IF(D$20=0,0,D48/D$20) -> 0 | F48: =0-SUM(F25:F47) -> 0 | G48: =IF(F$20=0,0,F48/F$20) -> 0 | H48: =0-SUM(H25:H47) -> 0 | I48: =IF(H$20=0,0,H48/H$20) -> 0 | J48: =0-SUM(J25:J47) -> 0 | K48: =IF(J$20=0,0,J48/J$20) -> 0
C49: Total Operating Expenses | D49: =SUM(D25:D48) -> 0 | E49: =IF(D$20=0,0,D49/D$20) -> 0 | F49: =SUM(F25:F48) -> 0 | G49: =IF(F$20=0,0,F49/F$20) -> 0 | H49: =SUM(H25:H48) -> 0 | I49: =IF(H$20=0,0,H49/H$20) -> 0 | J49: =SUM(J25:J48) -> 0 | K49: =IF(J$20=0,0,J49/J$20) -> 0
C51: Ordinary Income | D51: =D22-D49 -> 0 | E51: =IF(D$20=0,0,D51/D$20) -> 0 | F51: =F22-F49 -> 0 | G51: =IF(F$20=0,0,F51/F$20) -> 0 | H51: =H22-H49 -> 0 | I51: =IF(H$20=0,0,H51/H$20) -> 0 | J51: =J22-J49 -> 0 | K51: =IF(J$20=0,0,J51/J$20) -> 0
C53: Other Income | D53: 0 | E53: =IF(D$20=0,0,D53/D$20) -> 0 | F53: 0 | G53: =IF(F$20=0,0,F53/F$20) -> 0 | H53: 0 | I53: =IF(H$20=0,0,H53/H$20) -> 0 | J53: 0 | K53: =IF(J$20=0,0,J53/J$20) -> 0
C54: Other Income | D54: 0 | E54: =IF(D$20=0,0,D54/D$20) -> 0 | F54: 0 | G54: =IF(F$20=0,0,F54/F$20) -> 0 | H54: 0 | I54: =IF(H$20=0,0,H54/H$20) -> 0 | J54: 0 | K54: =IF(J$20=0,0,J54/J$20) -> 0
C55: Other Expense | D55: 0 | E55: =IF(D$20=0,0,D55/D$20) -> 0 | F55: 0 | G55: =IF(F$20=0,0,F55/F$20) -> 0 | H55: 0 | I55: =IF(H$20=0,0,H55/H$20) -> 0 | J55: 0 | K55: =IF(J$20=0,0,J55/J$20) -> 0
C56: Other Expense | D56: 0 | E56: =IF(D$20=0,0,D56/D$20) -> 0 | F56: 0 | G56: =IF(F$20=0,0,F56/F$20) -> 0 | H56: 0 | I56: =IF(H$20=0,0,H56/H$20) -> 0 | J56: 0 | K56: =IF(J$20=0,0,J56/J$20) -> 0
C57: Total Other Income (Expenses) | D57: =SUM(D53:D56) -> 0 | E57: =IF(D$20=0,0,D57/D$20) -> 0 | F57: =SUM(F53:F56) -> 0 | G57: =IF(F$20=0,0,F57/F$20) -> 0 | H57: =SUM(H53:H56) -> 0 | I57: =IF(H$20=0,0,H57/H$20) -> 0 | J57: =SUM(J53:J56) -> 0 | K57: =IF(J$20=0,0,J57/J$20) -> 0
C59: Net Income Before Taxes | D59: =D22-D49+D57 -> 0 | E59: =IF(D$20=0,0,D59/D$20) -> 0 | F59: =F22-F49+F57 -> 0 | G59: =IF(F$20=0,0,F59/F$20) -> 0 | H59: =H22-H49+H57 -> 0 | I59: =IF(H$20=0,0,H59/H$20) -> 0 | J59: =J22-J49+J57 -> 0 | K59: =IF(J$20=0,0,J59/J$20) -> 0
C60: Income Taxes | D60: 0 | E60: =IF(D$20=0,0,D60/D$20) -> 0 | F60: 0 | G60: =IF(F$20=0,0,F60/F$20) -> 0 | H60: 0 | I60: =IF(H$20=0,0,H60/H$20) -> 0 | J60: 0 | K60: =IF(J$20=0,0,J60/J$20) -> 0
C62: NET INCOME AFTER TAXES | D62: =D59-D60 -> 0 | E62: =IF(D$20=0,0,D62/D$20) -> 0 | F62: =F59-F60 -> 0 | G62: =IF(F$20=0,0,F62/F$20) -> 0 | H62: =H59-H60 -> 0 | I62: =IF(H$20=0,0,H62/H$20) -> 0 | J62: =J59-J60 -> 0 | K62: =IF(J$20=0,0,J62/J$20) -> 0
C64: Add Backs :
C65: + Compensation of Officers | D65: =D25 -> 0 | F65: =F25 -> 0 | H65: =H25 -> 0 | J65: =J25 -> 0
C66: + Depreciation/Amortization | D66: =D32 -> 0 | F66: =F32 -> 0 | H66: =H32 -> 0 | J66: =J32 -> 0
C67: + Interest Expense | D67: =D31 -> 0 | F67: =F31 -> 0 | H67: =H31 -> 0 | J67: =J31 -> 0
C68: + Rent Add Back | D68: 0 | F68: 0 | H68: 0 | J68: 0
C69: + - Other | D69: 0 | F69: 0 | H69: 0 | J69: 0
C70: + - Other | D70: 0 | F70: 0 | H70: 0 | J70: 0
C71: - Estimated Property Tax | D71: 0 | F71: 0 | H71: 0 | J71: 0
C72: - Required Owner's Draw | D72: 0 | F72: 0 | H72: 0 | J72: 0
C74: Cash Available | D74: =D62+SUM(D65:D72) -> 0 | F74: =F62+SUM(F65:F72) -> 0 | H74: =H62+SUM(H65:H72) -> 0 | J74: =J62+SUM(J65:J72) -> 0
C76: Existing Monthly Debt | D76: 0 | F76: 0 | H76: 0 | J76: 0
C77: Existing Debt | D77: =D76*D7 -> 0 | F77: =F76*F7 -> 0 | H77: =H76*H7 -> 0 | J77: =J76*J7 -> 0
C79: DCR | D79: =IFERROR(D74/D77,0) -> 0 | F79: =IFERROR(F74/F77,0) -> 0 | H79: =IFERROR(H74/H77,0) -> 0 | J79: =IFERROR(J74/J77,0) -> 0
B80: Click to expand/collapse (Affiliate 1)
B82: Income Statement Spreads
B83: {Insert business name which represents Affiliate 2}
B84: Include in Global? | C84: No
B85: Statement Date | D85: 44926 | F85: =EOMONTH(D85,F86) -> 45291 | H85: =EOMONTH(F85,H86) -> 45657 | J85: =EOMONTH(H85,J86) -> 45747
B86: Months Covered | D86: 12 | F86: 12 | H86: 12 | J86: 3
B87: Statement Type | D87: Tax Returns | F87: Tax Returns | J87: Internal
B88: Revenue Recognition
B89: REVENUE | J89: =(J90/J86)*12 -> 0
B90: Revenue | C90: (Product Line #1) | D90: 0 | E90: =IF(D$99=0,0,D90/D$99) -> 0 | F90: 0 | G90: =IF(F$99=0,0,F90/F$99) -> 0 | H90: 0 | I90: =IF(H$99=0,0,H90/H$99) -> 0 | J90: 0 | K90: =IF(J$99=0,0,J90/J$99) -> 0
B91: COGS | C91: (Product Line #1) | D91: 0 | E91: =IF(D$99=0,0,D91/D$99) -> 0 | F91: 0 | G91: =IF(F$99=0,0,F91/F$99) -> 0 | H91: 0 | I91: =IF(H$99=0,0,H91/H$99) -> 0 | J91: 0 | K91: =IF(J$99=0,0,J91/J$99) -> 0
B92: Gross Margin | C92: (Product Line #1) | D92: =D90-D91 -> 0 | E92: =IF(D$99=0,0,D92/D$99) -> 0 | F92: =F90-F91 -> 0 | G92: =IF(F$99=0,0,F92/F$99) -> 0 | H92: =H90-H91 -> 0 | I92: =IF(H$99=0,0,H92/H$99) -> 0 | J92: =J90-J91 -> 0 | K92: =IF(J$99=0,0,J92/J$99) -> 0
B93: Revenue | C93: (Product Line #2) | D93: 0 | E93: =IF(D$99=0,0,D93/D$99) -> 0 | F93: 0 | G93: =IF(F$99=0,0,F93/F$99) -> 0 | H93: 0 | I93: =IF(H$99=0,0,H93/H$99) -> 0 | J93: 0 | K93: =IF(J$99=0,0,J93/J$99) -> 0
B94: COGS | C94: (Product Line #2) | D94: 0 | E94: =IF(D$99=0,0,D94/D$99) -> 0 | F94: 0 | G94: =IF(F$99=0,0,F94/F$99) -> 0 | H94: 0 | I94: =IF(H$99=0,0,H94/H$99) -> 0 | J94: 0 | K94: =IF(J$99=0,0,J94/J$99) -> 0
B95: Gross Margin | C95: (Product Line #2) | D95: =D93-D94 -> 0 | E95: =IF(D$99=0,0,D95/D$99) -> 0 | F95: =F93-F94 -> 0 | G95: =IF(F$99=0,0,F95/F$99) -> 0 | H95: =H93-H94 -> 0 | I95: =IF(H$99=0,0,H95/H$99) -> 0 | J95: =J93-J94 -> 0 | K95: =IF(J$99=0,0,J95/J$99) -> 0
B96: Revenue | C96: (Product Line #3) | D96: 0 | E96: =IF(D$99=0,0,D96/D$99) -> 0 | F96: 0 | G96: =IF(F$99=0,0,F96/F$99) -> 0 | H96: 0 | I96: =IF(H$99=0,0,H96/H$99) -> 0 | J96: 0 | K96: =IF(J$99=0,0,J96/J$99) -> 0
B97: COGS | C97: (Product Line #3) | D97: 0 | E97: =IF(D$99=0,0,D97/D$99) -> 0 | F97: 0 | G97: =IF(F$99=0,0,F97/F$99) -> 0 | H97: 0 | I97: =IF(H$99=0,0,H97/H$99) -> 0 | J97: 0 | K97: =IF(J$99=0,0,J97/J$99) -> 0
B98: Gross Margin | C98: (Product Line #3) | D98: =D96-D97 -> 0 | E98: =IF(D$99=0,0,D98/D$99) -> 0 | F98: =F96-F97 -> 0 | G98: =IF(F$99=0,0,F98/F$99) -> 0 | H98: =H96-H97 -> 0 | I98: =IF(H$99=0,0,H98/H$99) -> 0 | J98: =J96-J97 -> 0 | K98: =IF(J$99=0,0,J98/J$99) -> 0
B99: Click to expand/collapse | C99: Total Revenue | D99: =D90+D93+D96 -> 0 | E99: =IF(D$99=0,0,D99/D$99) -> 0 | F99: =F90+F93+F96 -> 0 | G99: =IF(F$99=0,0,F99/F$99) -> 0 | H99: =H90+H93+H96 -> 0 | I99: =IF(H$99=0,0,H99/H$99) -> 0 | J99: =J90+J93+J96 -> 0 | K99: =IF(J$99=0,0,J99/J$99) -> 0
C100: Total COGS | D100: =D91+D94+D97 -> 0 | E100: =IF(D$99=0,0,D100/D$99) -> 0 | F100: =F91+F94+F97 -> 0 | G100: =IF(F$99=0,0,F100/F$99) -> 0 | H100: =H91+H94+H97 -> 0 | I100: =IF(H$99=0,0,H100/H$99) -> 0 | J100: =J91+J94+J97 -> 0 | K100: =IF(J$99=0,0,J100/J$99) -> 0
C101: Total Gross Margin | D101: =D99-D100 -> 0 | E101: =IF(D$99=0,0,D101/D$99) -> 0 | F101: =F99-F100 -> 0 | G101: =IF(F$99=0,0,F101/F$99) -> 0 | H101: =H99-H100 -> 0 | I101: =IF(H$99=0,0,H101/H$99) -> 0 | J101: =J99-J100 -> 0 | K101: =IF(J$99=0,0,J101/J$99) -> 0
C103: OPERATING EXPENSES
C104: Officer's Compensation | D104: 0 | E104: =IF(D$99=0,0,D104/D$99) -> 0 | F104: 0 | G104: =IF(F$99=0,0,F104/F$99) -> 0 | H104: 0 | I104: =IF(H$99=0,0,H104/H$99) -> 0 | J104: 0 | K104: =IF(J$99=0,0,J104/J$99) -> 0
C105: Salaries & Wages | D105: 0 | E105: =IF(D$99=0,0,D105/D$99) -> 0 | F105: 0 | G105: =IF(F$99=0,0,F105/F$99) -> 0 | H105: 0 | I105: =IF(H$99=0,0,H105/H$99) -> 0 | J105: 0 | K105: =IF(J$99=0,0,J105/J$99) -> 0
C106: Repairs & Maintenance | D106: 0 | E106: =IF(D$99=0,0,D106/D$99) -> 0 | F106: 0 | G106: =IF(F$99=0,0,F106/F$99) -> 0 | H106: 0 | I106: =IF(H$99=0,0,H106/H$99) -> 0 | J106: 0 | K106: =IF(J$99=0,0,J106/J$99) -> 0
C107: Bad Debts | D107: 0 | E107: =IF(D$99=0,0,D107/D$99) -> 0 | F107: 0 | G107: =IF(F$99=0,0,F107/F$99) -> 0 | H107: 0 | I107: =IF(H$99=0,0,H107/H$99) -> 0 | J107: 0 | K107: =IF(J$99=0,0,J107/J$99) -> 0
C108: Rents | D108: 0 | E108: =IF(D$99=0,0,D108/D$99) -> 0 | F108: 0 | G108: =IF(F$99=0,0,F108/F$99) -> 0 | H108: 0 | I108: =IF(H$99=0,0,H108/H$99) -> 0 | J108: 0 | K108: =IF(J$99=0,0,J108/J$99) -> 0
C109: Taxes & Licenses | D109: 0 | E109: =IF(D$99=0,0,D109/D$99) -> 0 | F109: 0 | G109: =IF(F$99=0,0,F109/F$99) -> 0 | H109: 0 | I109: =IF(H$99=0,0,H109/H$99) -> 0 | J109: 0 | K109: =IF(J$99=0,0,J109/J$99) -> 0
C110: Interest | D110: 0 | E110: =IF(D$99=0,0,D110/D$99) -> 0 | F110: 0 | G110: =IF(F$99=0,0,F110/F$99) -> 0 | H110: 0 | I110: =IF(H$99=0,0,H110/H$99) -> 0 | J110: 0 | K110: =IF(J$99=0,0,J110/J$99) -> 0
C111: Depreciation & Amortization | D111: 0 | E111: =IF(D$99=0,0,D111/D$99) -> 0 | F111: 0 | G111: =IF(F$99=0,0,F111/F$99) -> 0 | H111: 0 | I111: =IF(H$99=0,0,H111/H$99) -> 0 | J111: 0 | K111: =IF(J$99=0,0,J111/J$99) -> 0
C112: Advertising | D112: 0 | E112: =IF(D$99=0,0,D112/D$99) -> 0 | F112: 0 | G112: =IF(F$99=0,0,F112/F$99) -> 0 | H112: 0 | I112: =IF(H$99=0,0,H112/H$99) -> 0 | J112: 0 | K112: =IF(J$99=0,0,J112/J$99) -> 0
C113: Pension, Profit Sharing | D113: 0 | E113: =IF(D$99=0,0,D113/D$99) -> 0 | F113: 0 | G113: =IF(F$99=0,0,F113/F$99) -> 0 | H113: 0 | I113: =IF(H$99=0,0,H113/H$99) -> 0 | J113: 0 | K113: =IF(J$99=0,0,J113/J$99) -> 0
C114: Employee Benefits | D114: 0 | E114: =IF(D$99=0,0,D114/D$99) -> 0 | F114: 0 | G114: =IF(F$99=0,0,F114/F$99) -> 0 | H114: 0 | I114: =IF(H$99=0,0,H114/H$99) -> 0 | J114: 0 | K114: =IF(J$99=0,0,J114/J$99) -> 0
C115: Insurance | D115: 0 | E115: =IF(D$99=0,0,D115/D$99) -> 0 | F115: 0 | G115: =IF(F$99=0,0,F115/F$99) -> 0 | H115: 0 | I115: =IF(H$99=0,0,H115/H$99) -> 0 | J115: 0 | K115: =IF(J$99=0,0,J115/J$99) -> 0
... C125: Other | D125: 0 | E125: =IF(D$99=0,0,D125/D$99) -> 0 | F125: 0 | G125: =IF(F$99=0,0,F125/F$99) -> 0 | H125: 0 | I125: =IF(H$99=0,0,H125/H$99) -> 0 | J125: 0 | K125: =IF(J$99=0,0,J125/J$99) -> 0
B126: Click to expand/collapse | C126: Other | D126: 0 | E126: =IF(D$99=0,0,D126/D$99) -> 0 | F126: 0 | G126: =IF(F$99=0,0,F126/F$99) -> 0 | H126: 0 | I126: =IF(H$99=0,0,H126/H$99) -> 0 | J126: 0 | K126: =IF(J$99=0,0,J126/J$99) -> 0
C127: Other | D127: =0-SUM(D104:D126) -> 0 | E127: =IF(D$99=0,0,D127/D$99) -> 0 | F127: =0-SUM(F104:F126) -> 0 | G127: =IF(F$99=0,0,F127/F$99) -> 0 | H127: =0-SUM(H104:H126) -> 0 | I127: =IF(H$99=0,0,H127/H$99) -> 0 | J127: =0-SUM(J104:J126) -> 0 | K127: =IF(J$99=0,0,J127/J$99) -> 0
C128: Total Operating Expenses | D128: =SUM(D104:D127) -> 0 | E128: =IF(D$99=0,0,D128/D$99) -> 0 | F128: =SUM(F104:F127) -> 0 | G128: =IF(F$99=0,0,F128/F$99) -> 0 | H128: =SUM(H104:H127) -> 0 | I128: =IF(H$99=0,0,H128/H$99) -> 0 | J128: =SUM(J104:J127) -> 0 | K128: =IF(J$99=0,0,J128/J$99) -> 0
C130: Ordinary Income | D130: =D101-D128 -> 0 | E130: =IF(D$99=0,0,D130/D$99) -> 0 | F130: =F101-F128 -> 0 | G130: =IF(F$99=0,0,F130/F$99) -> 0 | H130: =H101-H128 -> 0 | I130: =IF(H$99=0,0,H130/H$99) -> 0 | J130: =J101-J128 -> 0 | K130: =IF(J$99=0,0,J130/J$99) -> 0
C132: Other Income | D132: 0 | E132: =IF(D$99=0,0,D132/D$99) -> 0 | F132: 0 | G132: =IF(F$99=0,0,F132/F$99) -> 0 | H132: 0 | I132: =IF(H$99=0,0,H132/H$99) -> 0 | J132: 0 | K132: =IF(J$99=0,0,J132/J$99) -> 0
...

Sheet Lists
A1: Version | B1: Loan Type | C1: Basics | D1: Request | E1: UW | F1: BDO
A3: Original | B3: N/A | C3: Yes | D3: New | E3: Andrew Taylor | F3: Audrey Wendel
A4: Mod 1 | B4: SBA 7a | C4: No | D4: Renewal | E4: Antony Parker | F4: Ben Eakin
A5: Mod 2 | B5: SBA Express | C5: N/A | D5: Modification | E5: Brent Ruch | F5: Cameron Brewer
A6: Mod 3 | B6: 504 | E6: Jennifer Dennis | F6: Eric Wadley
A7: Mod 4 | B7: USDA | C7: Disbursement | E7: Jessica Gauden | F7: Glenn Giro
A8: Mod 5 | B8: P&E | E8: Rodney Johnson | F8: Greg Swett
A9: Mod 6 | B9: Conventional | C9: Multi | E9: Rose Haynes-Taylor | F9: Jordan Sayler
A10: Mod 7 | C10: Single | D10: True/False | E10: Connor Shaw | F10: Kandace Moon
A11: Mod 8 | E11: Sheila Simms | F11: Kerry Smith
A12: Mod 9 | D12: True | F12: Kevin Coffman
A13: Mod 10 | D13: False | F13: Mike Ramsay
F14: Patrick Phillips
A15: Entity Types | B15: Loan Program | C15: Risk Rating | D15: Statement Type | E15: Revenue Recognition | F15: Rick McMann
F16: Rod Rodriguez
A17: TBD | B17: N/A | C17: 1 | D17: Tax Returns | E17: Cash | F17: Steve Jones
A18: Sole Prop | B18: PLP | C18: 2 | D18: Audited | E18: Accrual
A19: LLC | B19: GP | C19: 3 | D19: Reviewed | E19: Hybrid
A20: S-Corp | B20: 504 | C20: 4 | D20: Compiled | E20: Other
A21: C-Corp | B21: USDA | C21: 5 | D21: Schedule C | F21: Proforma BS
A22: Prof Corp | C22: 5.5 | D22: Internal
A23: Prof LLC | C23: 6 | D23: Form 10K | F23: New BS
A24: Trust | C24: 7 | D24: Form 10Q | F24: Last Year End
A25: LTD Partnership | C25: 8 | D25: Other | F25: Interim
A26: Partnership | C26: 9
F28: Submission
A29: Rate Adjustment | B29: Lien Position | D29: Property Type | E29: Valuation Method
C30: UCC Lien Type | F30: PLP
A31: Daily | B31: First | D31: C-Store | E31: Cost | F31: Standard
A32: Monthly | B32: Second | C32: Purchase Money UCC | D32: Hotel | E32: Appraisal
A33: Calendar Qtr | B33: Third | C33: Blanket UCC | D33: Industrial | E33: Book Value
A34: Other | B34: Fourth | C34: Security Interest | D34: Medical Office | E34: BPO
B35: Best Available | D35: Mixed-Use | E35: Invoice
D36: Mobile Home Park | E36: Estimated | F36: Construction Type
D37: Multi Family | E37: Tax
A38: Entity Class | B38: PFS RE Type | D38: Office | E38: Other | F38: Wood Frame
D39: Office/Warehouse | E39: Roof Type | F39: Steel Frame
A40: Holding Company/EPC | B40: Single Family | D40: Residential | F40: Concrete Frame
A41: Operating Company | B41: Multi Family | D41: Restaurant | E41: Flat - Built Up | F41: Concrete Tilt Up
A42: Affiliate | B42: Commercial | D42: Retail | E42: Flat - Membrane | F42: Concrete Wall
D43: Self Storage | E43: Flat - Other | F43: Hollow Clay Tile / Adobe
D44: Vacant Land | E44: Pitched - Metal | F44: Steel Frame w/Metal Skin
C45: Borrower/Guarantor | D45: Other | E45: Pitched - Shingle | F45: Reinforced Masonry
E46: Pitched - Other | F46: Unreinforced Masonry
A47: CDC Term | B47: Trend | C47: N/A | E47: Other | F47: Other
C48: None | E48: Not Known | F48: Not Known
A49: 10 | B49: Increasing | C49: Borrower
A50: 20 | B50: Decreasing | C50: Guarantor
A51: 25 | B51: Stable | D51: Guarantee
B52: Un Stable | C52: Recourse | E52: Rate Type | F52: Appraisal Value
A53: Request # | B53: Consistent | D53: N/A
B54: Inconsistent | C54: N/A | D54: Full Unsecured | E54: Fixed | F54: As Is
A55: Request 1 | C55: Full | D55: Full Secured | E55: Variable | F55: As Complete
A56: Request 2 | C56: Non | D56: Lim. Unsecured | F56: As Stablized
C57: Partial | D57: Lim. Secured
D58: Spousal Int.
F59: Origination/Packaging
A60: Facility Type | B60: SBA Initial Rate Set | D60: Checks | E60: X/O
C61: Amortization Basis | F61: Packaging Fee
A62: N/A | B62: Day of SBA/USDA Sub | D62: N/A | E62: x | F62: Origination Fee
A63: Term Loan | B63: 5 Days before Closing | C63: 30/360 | D63: Clear
A64: RLOC | B64: Other | C64: Actual/365 | D64: Not Clear
A65: GLOC | C65: Actual/360
A66: Const
A67: Non Rev Adv | F67: Breakeven
A68: Letter of Credit
F69: =#REF! -> #REF!
A70: Tract Income Level | B70: Coll RE Type | C70: HLTV Max | D70: Branch | E70: BSA Rating | F70: =#REF! -> #REF!
F71: =#REF! -> #REF!
A72: Upper | B72: Primary CRE | C72: 0.65 | D72: 12- SMJ | E72: 1- Low | F72: =#REF! -> #REF!
A73: Moderate | B73: Primary Residence | C73: 0.75 | D73: 14-AMW | E73: 2- Low Medium
A74: Middle | B74: Secondary RE | C74: 0.8 | D74: 15-HSE | E74: 3- Medium | F74: Exception Clearing
A75: Low | C75: 0.85 | D75: 21-SBA | E75: 4- Moderate
D76: 22- Wendel Loans | E76: 5-High | F76: Amber- Rose McCool
D77: 76- Integra | F77: Andrew Taylor
F78: Audrey Wendel
A79: Rate Index | F79: Casey McDonald
F80: Gina Bedsole
A81: WSJ Prime | F81: KT Head
A82: SOFR | F82: Lorenzo Saavedra
A83: 10 Yr Treas | F83: Nick Vu
F84: Rachel Preston

Sheet Version
A1: Version | B1: Release Notes
A2: 2016-10(1) | B2: Initial Roll out
A3: 2016-10(2) | B3: Added Preimum/Discount for Purchased Loans
B4: Added Purchase Price for Purchased Loans
B5: Added Additional Collateral Fields
B6: Temporary COA Section in Narrative, pending comprehensive independent page
A7: 2016-11(3) | B7: Misc Formating Changes
B8: Edit to CAR Formula
B9: Edit to SBA Eligibility section formulas on Debt Sch
A10: 2017-01(4) | B10: Added Notes to collateral page for MF Underwriting
B11: Re-Formatted UOP Page
A12: 2017-01(5) | B12: Formulatic corrections on collateral page
B13: General formatting corrections.
A14: 2017-08(6) | B14: Formulatic corrections on Cash Flow page
B15: General formatting corrections.
A16: 2017-10(7) | B16: Reformatted Narrative.
B17: Corrected Formula on Seller Carry Note
B18: Added Business Valuation Methods
A19: 2017-10(8) | B19: Added LTV and Cap at risk calcualtions for purchased loans.
A20: 2018-01(9) | B20: Added additional Ratios to Ratios page.
B21: Added RMA ratios to Hist IS
B22: Added 3rd year Borr Proj to Projections page
B23: Modified UOP and Construction Budget Worksheet to Reconcile each other
A24: 2018-02(10) | B24: Change to UOP Formulas to match Construction page better
B25: Minor modifications to UOP Formulas to show subtotals and remove
B26: SBA Gty Fee calculation for non 7a Loans
B27: Corrected cell references in Affiliate tabes
B28: Created standard "Exhibit A" tab (baseline is hidden) for LOI and CL
B29: Drafted LOI and CL for SBA and Conv Loan types, to autofill from CM
B30: (Baseline is hidden)
B31: Revised Amortization Schedule to utilize "Score" Format.
B32: Other Misc formulatic corrections
A33: 2018-05(11) | B33: Included appraisal review checklist in workbook
B34: Included Environmental Review Checklist in Workbook
B35: Added Balance at maturity lookup
B36: Reformatted all Holding company and affiliate cash flow pages.
B37: Added Loan Type Codes for Synergy
B38: Added Collateral Type Code and Description for Synergy
B39: Added FHLB Eligibility
A40: 2018-06(12) | B40: Added Amortization Basis 30/360; Actual/365; Actual/360
B41: Separated 912 Eligibility to its own tab
B42: misc formatting changes
A43: 2019-03(13) | B43: Added OFAC/MLA Check to Guarantor Summary
B44: Updated SBA Eligibility for 2019-04 SOP Changes
A45: 2019-10(14) | B45: Added tracking fields for CRA Data
A46: 2019-10(15) | B46: Added Bankers Health Care Loan Type
A47: 2019-11(16) | B47: Added Global Cash Flow Page
A48: 2020-03(17) | B48: Added Program Code for SBA Pacheck Protection Program
A49: 2020-06(18) | B49: Added Personal Resource Test (On Hold)
A50: 2020-10(19) | B50: Updates resulting from SOP Changes
A51: 2021-09(20) | B51: Updated SBA Fee Calculation
B52: Corrected GCF Calculation
A53: 2022-12-(21) | B53: Reformat and re-release
C54: Removed references to purchased loans
C55: Removed Synergy Codes
C56: Removed FHLB Eligibility Indicator
C57: Removed OFAC/MLA Check, now addressed elsewhere
C58: Removed CRA Field, tracked elsewhere
C59: Reformatted Payment Calculations and Stress Testing to separate page from CF
C60: Added BDO tab
A61: 2023-04(21) | B61: Added Various T Bank Calculations
A62: 2023-05(22) | B62: Various Bug Fixes
A63: 2023-06(23) | B63: Additional Bug Fixes. Removed linkages between BDO Sheet and UW Sheets
A64: 2023-06(24) | B64: Added Break Even Analysis and W/C Analysis
A65: 2023-07(24) | B65: Modified Breakeven and WC Sheets
A66: 2023-07(25) | B66: Corrected Breakeven Sheet
A67: 2023-08(26) | B67: Corrected various UW formulas and formatting in BRKEVN, WC, PFS, and COLL, Global CF to include aff debt in all periods, added closing cost tier
A68: 2023-09(27) | B68: Added SBA Gty Fee Adjustment Macro.
A69: 2023-10(28) | B69: Added Close date to BDO Prequal. Updated HLTV on Coll Tab. Added 504 Adjustment Macro. Modified SBA Gty Fee to match new fee structure
A70: 2023-11(29) | B70: Reformatted Debt Schedule, Separated BDO Debt Schedule from UW. Corrected 504 HLTV Calculations
A71: 23-12(30) thru 24-02(32) | B71: Various formating and bug fixes.
A72: 24-02(33) | B72: Updated Scoring Matrix. Corrected Formulation on PMT calcs page for number of months added to note date.
... A83: 25-03(44x) | B83: Chg SBA Fee, Updates to Biz Val, WC Analysis, Breakeven

Sheet Scores
B2: T Bank, N.A. SCORING GRID
B3: Total Score | C3: REPAYMENT | D3: MANAGEMENT | E3: CREDIT | F3: EQUITY | G3: COLLATERAL | H3: Working Capital/Liquidity
B4: =SUM(C4:H4) -> 0
B5: 5 | C5: Pro forma DSC of 1.40x in the most recent year and 1.25x or better for the prior 2 years plus stable/positive trends in the interim. Stable is considered + - 0.05 change in DSC. | D5: 3 or more years ownership in SBC or 3 years as primary responsible employee in SBC or 5 years recent experience in near identical type business as Principal Manager with P&L and HR responsibility. | E5: N/A | F5: 25% cash equity from personal sources Expansions: pro forma tangible D/W of 4:1 or less. | G5: Secured 120% of the loan on a discounted basis with any collateral or 100% secured with 1st lien on RE. 504 1st lien No construction | H5: N/A
B6: 4 | C6: Pro forma DSC of 1.40x or better for most recent years plus 1.25x for the 1 prior year plus stable/positive trends in the interim. Stable is considered + - 0.05 change in DSC. | D6: 2 or more years ownership in SBC or 3 years experience in near identical type business. For startups - this experience, must have been within the last 5 years AND one of the guarantors will devote 100% of time to SBC | E6: FICO Score greater than 750. | F6: 25% cash equity from any source or 20% from personal sources Expansions: pro forma tangible D/W of 5:1 or less. | G6: Secured 100% of the loan on a discounted basis with any collateral or 75% with 1st lien on RE. 504 1st Lien Construction | H6: N/A
B7: 3 | C7: Pro forma DSC of an 1.25x or better in most recent FYE and interim plus stable/positive trends in the interim. Stable is considered + - 0.05 change in DSC. Regardless of DSC declining revenue or profitability trends in the most recent year and/or interim. | D7: 2 years ownership in any industry or 3 years of transferable management experience in any industry, or approved franchise For startups - this experience, must have been within the last 5 years AND one of the guarantors will devote 100% of time to SBC. | E7: FICO Score of 700 to 749. Regardless of any higher FICO score BK between 3 and 5 years in time. Regardless of any higher FICO score expected continuing income of between $5500 and $6000 for every $1000 of CC debt | F7: 20% cash equity from any source or 15% from personal sources Expansions: pro forma tangible D/W of 6:1 or less. | G7: Secured 75% of the loan on a discounted basis with any collateral or 50% with 1st lien on RE. | H7: No or minimal working capital requirement OR Borrower has 1.5X working capital from own liquid resources. Minimal is the lesser of 5% of loan amount or $50K. None is included in loan.
B8: 2 | C8: Pro forma DSC of 1.15x or better in most recent FYE and interim plus positive trends in the interim. Regardless of DSC declining revenue or profitability trends in all periods Projection Based or Start Up with Approved Franchise. | D8: 2 years transferable management experience not specific to this industry or non-approved franchise. For startups - this experience must have been within the last 3 years AND one of the guarantors will 100% of time devoted to SBC | E8: FICO Score 650 to 699 Regardless of any higher FICO score expected continuing income of between $5000 and $5499 for every $1000 of CC debt | F8: 10% cash equity from any source Expansions: pro forma tangible D/W of 8:1 or less. | G8: Secured 50% of the loan on a discounted basis with any collateral or 25% with 1st lien on RE. | H8: Borrower has sufficient documented working Capital to inject from own resources (WC as calculated by U/W). In loan is OK as long as borrower has 1x or greater residual liquidity.
B9: 1 | C9: Projection based or start-up. | D9: Less than 2 years transferable management experience OR reliant on prior owner or franchisor for training. For startups - the experience was over 3 years ago. | E9: FICO Score less than 650 Regardless of any higher FICO score expected continuing income of between $4500 and $4999 for every $1000 of CC debt | F9: Less than 10% injection and/or 50% or more Equity is from Seller note on full standby | G9: < 50% secured with any collateral or less than 25% 1st lien on RE. | H9: All, or substantially all of W/C is included in loan or companion loan and borrower has little or no residual liquidity.
B10: 0 | C10: N/A | D10: Remote management or long distance management with no prior experience of remote management. | E10: BK in the last 3 years. Regardless of any higher FICO score expected continuing income of less than $4500 for every $1000 of CC debt | F10: Any other allowable SBA SOP structure that does not require injection. | G10: No CRE included in collateral or only junior liens on residential. | H10: Working capital included in loan proceeds exceeds 50% of borrower cash injection.
B13: Tool - For Credit (Description - How to Use, What this means needed from Ben). Only Manually input is to enter the credit card debt of the owner. The table will populate with the income based on the PFS of the owner.
B14: ='4. PFS '!B75 -> Owner/Guarantor 1 | D14: ='4. PFS '!B76 -> Owner/Guarantor 2 | F14: ='4. PFS '!B77 -> Owner/Guarantor 3 | H14: ='4. PFS '!B78 -> Owner/Guarantor 4
B15: Income | C15: ='4. PFS '!C$37 -> 0 | D15: Income | E15: ='4. PFS '!E37 -> 0 | F15: Income | G15: ='4. PFS '!G37 -> 0 | H15: Income | I15: ='4. PFS '!I37 -> 0
B16: CC Debt | C16: 0 | D16: CC Debt | E16: 0 | F16: CC Debt | G16: 0 | H16: CC Debt | I16: 0
B17: Income Needed $4,500 | C17: =C16*4.5 -> 0 | D17: Income Needed $4,500 | E17: =E16*4.5 -> 0 | F17: Income Needed $4,500 | G17: =G16*4.5 -> 0 | H17: Income Needed $4,501 | I17: =I16*4.5 -> 0
B18: Income Needed $4,999 | C18: =C16*4.999 -> 0 | D18: Income Needed $4,999 | E18: =E16*4.999 -> 0 | F18: Income Needed $4,999 | G18: =G16*4.999 -> 0 | H18: Income Needed $4,1000 | I18: =I16*4.999 -> 0
B19: Income Needed $5,499 | C19: =C16*5.499 -> 0 | D19: Income Needed $5,499 | E19: =E16*5.499 -> 0 | F19: Income Needed $5,499 | G19: =G16*5.499 -> 0 | H19: Income Needed $5,500 | I19: =I16*5.499 -> 0
B20: Income Needed $6,000+ | C20: =C16*6 -> 0 | D20: Income Needed $6,000+ | E20: =E16*6 -> 0 | F20: Income Needed $6,000+ | G20: =G16*6 -> 0 | H20: Income Needed $6,000+ | I20: =I16*6 -> 0
B21: ='4. PFS '!B80 -> Owner/Guarantor 5 | D21: ='4. PFS '!B81 -> Owner/Guarantor 6 | F21: ='4. PFS '!B82 -> Owner/Guarantor 7 | H21: ='4. PFS '!B83 -> Owner/Guarantor 8
B22: Income | C22: ='4. PFS '!N37 -> 0 | D22: Income | E22: ='4. PFS '!P$37 -> 0 | F22: Income | G22: ='4. PFS '!R$37 -> 0 | H22: Income | I22: ='4. PFS '!T$37 -> 0
B23: CC Debt | C23: 0 | D23: CC Debt | E23: 0 | F23: CC Debt | G23: 0 | H23: CC Debt | I23: 1
B24: Income Needed $4,500 | C24: =C23*4.5 -> 0 | D24: Income Needed $4,500 | E24: =E23*4.5 -> 0 | F24: Income Needed $4,500 | G24: =G23*4.5 -> 0 | H24: Income Needed $4,501 | I24: =I23*4.5 -> 4.5
B25: Income Needed $4,999 | C25: =C23*4.999 -> 0 | D25: Income Needed $4,999 | E25: =E23*4.999 -> 0 | F25: Income Needed $4,999 | G25: =G23*4.999 -> 0 | H25: Income Needed $4,1000 | I25: =I23*4.999 -> 4.999
B26: Income Needed $5,499 | C26: =C23*5.499 -> 0 | D26: Income Needed $5,499 | E26: =E23*5.499 -> 0 | F26: Income Needed $5,499 | G26: =G23*5.499 -> 0 | H26: Income Needed $5,500 | I26: =I23*5.499 -> 5.499
B27: Income Needed $6,000+ | C27: =C23*6 -> 0 | D27: Income Needed $6,000+ | E27: =E23*6 -> 0 | F27: Income Needed $6,000+ | G27: =G23*6 -> 0 | H27: Income Needed $6,000+ | I27: =I23*6 -> 6

Sheet Lists_1
A1: Version | B1: Loan Type | C1: Basics | D1: Request | E1: UW | F1: BDO
A3: Original | B3: N/A | C3: Yes | D3: New | E3: Andrew Taylor | F3: Audrey Wendel
A4: Mod 1 | B4: SBA 7a | C4: No | D4: Renewal | E4: Antony Parker | F4: Ben Eakin
A5: Mod 2 | B5: SBA Express | C5: N/A | D5: Modification | E5: Brent Ruch | F5: Cameron Brewer
A6: Mod 3 | B6: 504 | E6: Jennifer Dennis | F6: Eric Wadley
A7: Mod 4 | B7: USDA | C7: Disbursement | E7: Jessica Gauden | F7: Glenn Giro
A8: Mod 5 | B8: P&E | E8: Rodney Johnson | F8: Greg Swett
A9: Mod 6 | B9: Conventional | C9: Multi | E9: Rose Haynes-Taylor | F9: Jordan Sayler
A10: Mod 7 | C10: Single | D10: True/False | E10: Connor Shaw | F10: Kandace Moon
A11: Mod 8 | E11: Sheila Simms | F11: Kerry Smith
A12: Mod 9 | D12: True | F12: Kevin Coffman
A13: Mod 10 | D13: False | F13: Mike Ramsay
F14: Patrick Phillips
A15: Entity Types | B15: Loan Program | C15: Risk Rating | D15: Statement Type | E15: Revenue Recognition | F15: Rick McMann
F16: Rod Rodriguez
A17: TBD | B17: N/A | C17: 1 | D17: Tax Returns | E17: Cash | F17: Steve Jones
A18: Sole Prop | B18: PLP | C18: 2 | D18: Audited | E18: Accrual
A19: LLC | B19: GP | C19: 3 | D19: Reviewed | E19: Hybrid
A20: S-Corp | B20: 504 | C20: 4 | D20: Compiled | E20: Other
A21: C-Corp | B21: USDA | C21: 5 | D21: Schedule C | F21: Proforma BS
A22: Prof Corp | C22: 5.5 | D22: Internal
A23: Prof LLC | C23: 6 | D23: Form 10K | F23: New BS
A24: Trust | C24: 7 | D24: Form 10Q | F24: Last Year End
A25: LTD Partnership | C25: 8 | D25: Other | F25: Interim
A26: Partnership | C26: 9
F28: Submission
A29: Rate Adjustment | B29: Lien Position | D29: Property Type | E29: Valuation Method
C30: UCC Lien Type | F30: PLP
A31: Daily | B31: First | D31: C-Store | E31: Cost | F31: Standard
A32: Monthly | B32: Second | C32: Purchase Money UCC | D32: Hotel | E32: Appraisal
A33: Calendar Qtr | B33: Third | C33: Blanket UCC | D33: Industrial | E33: Book Value
A34: Other | B34: Fourth | C34: Security Interest | D34: Medical Office | E34: BPO
B35: Best Available | D35: Mixed-Use | E35: Invoice
D36: Mobile Home Park | E36: Estimated | F36: Construction Type
D37: Multi Family | E37: Tax
A38: Entity Class | B38: PFS RE Type | D38: Office | E38: Other | F38: Wood Frame
D39: Office/Warehouse | E39: Roof Type | F39: Steel Frame
A40: Holding Company/EPC | B40: Single Family | D40: Residential | F40: Concrete Frame
A41: Operating Company | B41: Multi Family | D41: Restaurant | E41: Flat - Built Up | F41: Concrete Tilt Up
A42: Affiliate | B42: Commercial | D42: Retail | E42: Flat - Membrane | F42: Concrete Wall
D43: Self Storage | E43: Flat - Other | F43: Hollow Clay Tile / Adobe
D44: Vacant Land | E44: Pitched - Metal | F44: Steel Frame w/Metal Skin
C45: Borrower/Guarantor | D45: Other | E45: Pitched - Shingle | F45: Reinforced Masonry
E46: Pitched - Other | F46: Unreinforced Masonry
A47: CDC Term | B47: Trend | C47: N/A | E47: Other | F47: Other
C48: None | E48: Not Known | F48: Not Known
A49: 10 | B49: Increasing | C49: Borrower
A50: 20 | B50: Decreasing | C50: Guarantor
A51: 25 | B51: Stable | D51: Guarantee
B52: Un Stable | C52: Recourse | E52: Rate Type | F52: Appraisal Value
A53: Request # | B53: Consistent | D53: N/A
B54: Inconsistent | C54: N/A | D54: Full Unsecured | E54: Fixed | F54: As Is
A55: Request 1 | C55: Full | D55: Full Secured | E55: Variable | F55: As Complete
A56: Request 2 | C56: Non | D56: Lim. Unsecured | F56: As Stablized
C57: Partial | D57: Lim. Secured
D58: Spousal Int.
F59: Origination/Packaging
A60: Facility Type | B60: SBA Initial Rate Set | D60: Checks | E60: X/O
C61: Amortization Basis | F61: Packaging Fee
A62: N/A | B62: Day of SBA/USDA Sub | D62: N/A | E62: x | F62: Origination Fee
A63: Term Loan | B63: 5 Days before Closing | C63: 30/360 | D63: Clear
A64: RLOC | B64: Other | C64: Actual/365 | D64: Not Clear
A65: GLOC | C65: Actual/360
A66: Const
A67: Non Rev Adv | F67: Breakeven
A68: Letter of Credit
F69: =#REF! -> #REF!
A70: Tract Income Level | B70: Coll RE Type | C70: HLTV Max | D70: Branch | E70: BSA Rating | F70: =#REF! -> #REF!
F71: =#REF! -> #REF!
A72: Upper | B72: Primary CRE | C72: 0.65 | D72: 12- SMJ | E72: 1- Low | F72: =#REF! -> #REF!
A73: Moderate | B73: Primary Residence | C73: 0.75 | D73: 14-AMW | E73: 2- Low Medium
A74: Middle | B74: Secondary RE | C74: 0.8 | D74: 15-HSE | E74: 3- Medium | F74: Exception Clearing
A75: Low | C75: 0.85 | D75: 21-SBA | E75: 4- Moderate
D76: 22- Wendel Loans | E76: 5-High | F76: Amber- Rose McCool
D77: 76- Integra | F77: Andrew Taylor
F78: Audrey Wendel
A79: Rate Index | F79: Casey McDonald
F80: Gina Bedsole
A81: WSJ Prime | F81: KT Head
A82: SOFR | F82: Lorenzo Saavedra
A83: 10 Yr Treas | F83: Nick Vu
F84: Rachel Preston
